Workbook
Name AwardTypeCategories: 'Dashboard'!$AD$42:$AD$42
Name SetAsideCategories: 'Dashboard'!$AG$42:$AG$42
Name PerformanceStateCategories: 'Dashboard'!$AJ$42:$AJ$42
Name VendorChoices: 'Dashboard'!$AM$1:$AM$1
Name OfficeChoices: 'Dashboard'!$AN$1:$AN$1
Name TypeChoices: 'Dashboard'!$AO$1:$AO$1

Sheet Dashboard
AM1: All | AN1: All | AO1: All
B2: Contract awards & spend | T2: Logo here | AA2: Vendor ID | AB2: =IF(H7="All","All",IF(COUNTIFS(VendorGroups[Filter label],H7)=1,INDEX(VendorGroups[Record ID],MATCH(H7,VendorGroups[Filter label],0)),"Invalid")) -> All
B3: =IF(Transactions!B3="","Buyer / market",Transactions!B3) -> Buyer / market | Q3: =IF(Transactions!G4="","Retrieved: not supplied","Retrieved "&TEXT(Transactions!G4,"mmm d, yyyy")) -> Retrieved: not supplied | AA3: Office ID | AB3: =IF(B10="All","All",IF(COUNTIFS(OfficeGroups[Filter label],B10)=1,INDEX(OfficeGroups[Record ID],MATCH(B10,OfficeGroups[Filter label],0)),"Invalid")) -> All
B4: =IF(Transactions!G3="","Add reviewed records and reporting dates to populate this workbook.",Transactions!G3) -> Add reviewed records and reporting dates to populate this workbook.
B6: Fiscal year | H6: Vendor | AA6: Net obligations | AB6: =IF(Trends!$B$6<>"","",SUMIFS(TransactionsData[Obligations],TransactionsData[Selected],1))
H7: All | AA7: Awards with obligations | AB7: =IF(Trends!$B$6<>"","",SUM(TransactionsData[First selected award]))
AA8: Vendors with obligations | AB8: =IF(Trends!$B$6<>"","",SUM(TransactionsData[First selected vendor]))
B9: Funding office | N9: Current award type | AA9: Transactions | AB9: =IF(Trends!$B$6<>"","",SUM(TransactionsData[Selected]))
B10: All | N10: All
AB11: =IF(OR(Dashboard!$B$7="All",NOT(ISNUMBER(Dashboard!$B$7))),0,IF(AND(COUNTIFS(Trends!$I$26,Dashboard!$B$7)=1,COUNTIFS(Trends!$I$26,Dashboard!$B$7-1)=1),IF(AND(INDEX(Trends!$J$26,MATCH(Dashboard!$B$7,Trends!$I$26,0))=1,INDEX(Trends!$J$26,MATCH(Dashboard!$B$7-1,Trends!$I$26,0))=1),1,0),0)) -> 0
B12: =Trends!$B$6 -> Awaiting source data
AB13: =IF(AB11=1,INDEX(Trends!$D$26,MATCH(Dashboard!$B$7-1,Trends!$I$26,0)),"")
B14: Net obligations | H14: Awards with obligations | N14: Vendors with obligations | T14: Transactions | AB14: =IF(AB11=1,INDEX(Trends!$E$26,MATCH(Dashboard!$B$7-1,Trends!$I$26,0)),"")
B15: =IF(Trends!$B$6<>"","—",TEXT(AB6/1000000,"$0.00")&"M") -> — | H15: =IF(Trends!$B$6<>"","—",AB7) -> — | N15: =IF(Trends!$B$6<>"","—",AB8) -> — | T15: =IF(Trends!$B$6<>"","—",AB9) -> — | AB15: =IF(AB11=1,INDEX(Trends!$F$26,MATCH(Dashboard!$B$7-1,Trends!$I$26,0)),"")
AB16: =IF(AB11=1,INDEX(Trends!$G$26,MATCH(Dashboard!$B$7-1,Trends!$I$26,0)),"")
B17: =IF(OR(Trends!$B$6<>"",AB11<>1),"",IF(AB13>0,TEXT((AB6-AB13)/AB13,"+0.0%;-0.0%;+0.0%")&" vs FY"&(Dashboard!$B$7-1),"")) | H17: =IF(OR(Trends!$B$6<>"",AB11<>1),"",IF(AB7=AB14,"No change vs FY"&(Dashboard!$B$7-1),TEXT(AB7-AB14,"+#,##0;-#,##0;0")&" vs FY"&(Dashboard!$B$7-1))) | N17: =IF(OR(Trends!$B$6<>"",AB11<>1),"",IF(AB8=AB15,"No change vs FY"&(Dashboard!$B$7-1),TEXT(AB8-AB15,"+#,##0;-#,##0;0")&" vs FY"&(Dashboard!$B$7-1))) | T17: =IF(OR(Trends!$B$6<>"",AB11<>1),"",IF(AB9=AB16,"No change vs FY"&(Dashboard!$B$7-1),TEXT(AB9-AB16,"+#,##0;-#,##0;0")&" vs FY"&(Dashboard!$B$7-1)))
B19: =IF(Dashboard!$B$7="All","All covered years",IF(Dashboard!$B$7="","No reporting period","FY"&Dashboard!$B$7)) -> No reporting period | H19: =IF(Dashboard!$B$7="All","All covered years",IF(Dashboard!$B$7="","No reporting period","FY"&Dashboard!$B$7)) -> No reporting period | N19: =IF(Dashboard!$B$7="All","All covered years",IF(Dashboard!$B$7="","No reporting period","FY"&Dashboard!$B$7)) -> No reporting period | T19: =IF(Dashboard!$B$7="All","All covered years",IF(Dashboard!$B$7="","No reporting period","FY"&Dashboard!$B$7)) -> No reporting period
B20: Charts in USD millions
B21: Annual net obligations | N21: Leading vendors | AA21: Category | AB21: Net obligations | AD21: Category | AE21: Net obligations
AA22: =IF(Trends!A26="","",Trends!A26) | AB22: =IF((IF(Trends!$B$6<>"","",Trends!D26))="","",(IF(Trends!$B$6<>"","",Trends!D26))/1000000) | AD22: =IF(Trends!$B$6<>"","",IF(COUNTIFS(VendorGroups[Source actions],">0")>5,"Other vendors","")) | AE22: =IF((IF(Trends!$B$6<>"","",IF(AD22="","",SUMIFS(VendorGroups[Source net],VendorGroups[Source rank],">5"))))="","",(IF(Trends!$B$6<>"","",IF(AD22="","",SUMIFS(VendorGroups[Source net],VendorGroups[Source rank],">5"))))/1000000)
AD23: =IF('Vendors & Buyers'!B12="","",'Vendors & Buyers'!B12) | AE23: =IF((IF(AD23="","",'Vendors & Buyers'!D12))="","",(IF(AD23="","",'Vendors & Buyers'!D12))/1000000)
AD24: =IF('Vendors & Buyers'!B11="","",'Vendors & Buyers'!B11) | AE24: =IF((IF(AD24="","",'Vendors & Buyers'!D11))="","",(IF(AD24="","",'Vendors & Buyers'!D11))/1000000)
AD25: =IF('Vendors & Buyers'!B10="","",'Vendors & Buyers'!B10) | AE25: =IF((IF(AD25="","",'Vendors & Buyers'!D10))="","",(IF(AD25="","",'Vendors & Buyers'!D10))/1000000)
AD26: =IF('Vendors & Buyers'!B9="","",'Vendors & Buyers'!B9) | AE26: =IF((IF(AD26="","",'Vendors & Buyers'!D9))="","",(IF(AD26="","",'Vendors & Buyers'!D9))/1000000)
AD27: =IF('Vendors & Buyers'!B8="","",'Vendors & Buyers'!B8) | AE27: =IF((IF(AD27="","",'Vendors & Buyers'!D8))="","",(IF(AD27="","",'Vendors & Buyers'!D8))/1000000)
B36: Annual and quarterly history use all covered years. Rankings and breakdowns use the selected fiscal year.
B38: Contract awards & spend — breakdowns
B39: ="USD millions | Period: "&IF(B7="All","All covered years",IF(B7="","Not supplied","FY"&B7))&" | Award type: "&N10&CHAR(10)&"Vendor: "&H7&" | Funding office: "&B10 -> USD millions | Period: Not supplied | Award type: All Vendor: All | Funding office: All | AB39: =MAX(1,COUNTIFS(Trends!$K$32:$K$35,">0")) -> 1
B40: Quarterly history · all covered years | N40: Current award types
AA41: Category | AB41: Net obligations | AD41: Category | AE41: Net obligations | AG41: Category | AH41: Net obligations | AJ41: Category | AK41: Net obligations
AA42: =IF(Trends!A32="","",Trends!A32) | AB42: =IF((IF(OR(Trends!$B$6<>"",AA42=""),"",Trends!D32))="","",(IF(OR(Trends!$B$6<>"",AA42=""),"",Trends!D32))/1000000) | AE42: =IF((IF(AD42="","",IF(Trends!$B$6<>"","",SUMIFS(TransactionsData[Obligations],TransactionsData[Current award type],AD42,TransactionsData[Selected],1))))="","",(IF(AD42="","",IF(Trends!$B$6<>"","",SUMIFS(TransactionsData[Obligations],TransactionsData[Current award type],AD42,TransactionsData[Selected],1))))/1000000) | AH42: =IF((IF(AG42="","",IF(Trends!$B$6<>"","",SUMIFS(TransactionsData[Obligations],TransactionsData[Current set-aside],AG42,TransactionsData[Selected],1))))="","",(IF(AG42="","",IF(Trends!$B$6<>"","",SUMIFS(TransactionsData[Obligations],TransactionsData[Current set-aside],AG42,TransactionsData[Selected],1))))/1000000) | AK42: =IF((IF(AJ42="","",IF(Trends!$B$6<>"","",SUMIFS(TransactionsData[Obligations],TransactionsData[Performance state],AJ42,TransactionsData[Selected],1))))="","",(IF(AJ42="","",IF(Trends!$B$6<>"","",SUMIFS(TransactionsData[Obligations],TransactionsData[Performance state],AJ42,TransactionsData[Selected],1))))/1000000)
AA43: =IF(Trends!A33="","",Trends!A33) | AB43: =IF((IF(OR(Trends!$B$6<>"",AA43=""),"",Trends!D33))="","",(IF(OR(Trends!$B$6<>"",AA43=""),"",Trends!D33))/1000000)
AA44: =IF(Trends!A34="","",Trends!A34) | AB44: =IF((IF(OR(Trends!$B$6<>"",AA44=""),"",Trends!D34))="","",(IF(OR(Trends!$B$6<>"",AA44=""),"",Trends!D34))/1000000)
AA45: =IF(Trends!A35="","",Trends!A35) | AB45: =IF((IF(OR(Trends!$B$6<>"",AA45=""),"",Trends!D35))="","",(IF(OR(Trends!$B$6<>"",AA45=""),"",Trends!D35))/1000000)
B58: Current set-asides | N58: Place of performance by state
B76: Current award snapshots; set-asides do not measure small-business participation. Location is place of performance.

Sheet Trends
A2: Trends
A3: ="Buyer: "&IF(Transactions!B3="","Not supplied",Transactions!B3)&" | History: "&IF(Transactions!B4="","Not supplied",TEXT(Transactions!B4,"mmm d, yyyy"))&" through "&IF(Transactions!D4="","Not supplied",TEXT(Transactions!D4,"mmm d, yyyy"))&" | Award type: "&Dashboard!$N$10 -> Buyer: Not supplied | History: Not supplied through Not supplied | Award type: All
A4: ="Vendor: "&Dashboard!H7&CHAR(10)&"Funding office: "&Dashboard!B10 -> Vendor: All Funding office: All
A5: Chart in USD millions; supporting tables in USD.
A6: Report status | B6: =IF(COUNTIF(AwardsData[Input check],"New category: refresh report")>0,"Refresh report for new classifications",IF(COUNTA(TransactionsData[Transaction ID])=0,"Awaiting source data",IF(OR(NOT(ISNUMBER(Transactions!B4)),NOT(ISNUMBER(Transactions!D4)),Transactions!B4>Transactions!D4,NOT(ISNUMBER(Transactions!G4))),"Enter valid coverage and retrieval dates",IF(COUNTIFS(TransactionsData[Input check],"?*")+COUNTIFS(AwardsData[Input check],"?*")+COUNTIFS(VendorGroups[Input check],"?*")+COUNTIFS(OfficeGroups[Input check],"?*")>0,"Review source input checks",IF(OR(Dashboard!$AB$2="Invalid",Dashboard!$AB$3="Invalid",AND(Dashboard!$N$10<>"All",COUNTIFS(TypeChoices,Dashboard!$N$10)<>1)),"Choose valid Dashboard filters",IF(NOT(OR(Dashboard!$B$7="All",COUNTIFS($I$26,Dashboard!$B$7)=1)),"Choose a reporting year",IF(SUMPRODUCT((TransactionsData[Eligible]=1)*(COUNTIFS(VendorGroups[Record ID],TransactionsData[Vendor ID])<>1))+SUMPRODUCT((TransactionsData[Eligible]=1)*(COUNTIFS(OfficeGroups[Record ID],TransactionsData[Funding office ID])<>1))>0,"Add missing vendor or office registry IDs",""))))))) -> Awaiting source data
A23: Four-quarter average begins after four complete consecutive quarters. Negative values retain their sign.
A25: Fiscal year | B25: Positive obligations | C25: Deobligations | D25: Net obligations | E25: Awards with obligations | F25: Vendors with obligations | G25: Transactions | H25: YoY change | I25: Year key | J25: Complete year
A26: =IF(I26="","","FY"&I26) | B26: =IF(I26="","",IF(Trends!$B$6<>"","",SUMIFS(TransactionsData[Positive],TransactionsData[FY],I26,TransactionsData[Dimension match],1))) | C26: =IF(I26="","",IF(Trends!$B$6<>"","",SUMIFS(TransactionsData[Deobligations],TransactionsData[FY],I26,TransactionsData[Dimension match],1))) | D26: =IF(I26="","",IF(Trends!$B$6<>"","",SUMIFS(TransactionsData[Obligations],TransactionsData[FY],I26,TransactionsData[Dimension match],1))) | E26: =IF(I26="","",IF(Trends!$B$6<>"","",SUMIFS(TransactionsData[First annual award],TransactionsData[FY],I26,TransactionsData[Dimension match],1))) | F26: =IF(I26="","",IF(Trends!$B$6<>"","",SUMIFS(TransactionsData[First annual vendor],TransactionsData[FY],I26,TransactionsData[Dimension match],1))) | G26: =IF(I26="","",IF(Trends!$B$6<>"","",COUNTIFS(TransactionsData[FY],I26,TransactionsData[Dimension match],1))) | H26: ="" | J26: =IF(I26="","",IF(AND(Transactions!$B$4<=DATE(I26-1,10,1),Transactions!$D$4>=DATE(I26,9,30)),1,0))
A31: Quarter | B31: From | C31: Through | D31: Net obligations | E31: Deobligations | F31: Transactions | G31: 4-quarter average | H31: Coverage | I31: Year key | J31: Quarter key | K31: Selected order | L31: Net obligations | M31: 4-quarter average
A32: =IF(I32="","","FY"&I32&" Q"&J32) | B32: =IF(I32="","",DATE(I32-IF(J32=1,1,0),CHOOSE(J32,10,1,4,7),1)) | C32: =IF(B32="","",EDATE(B32,3)-1) | D32: =IF(I32="","",IF(Trends!$B$6<>"","",SUMIFS(TransactionsData[Obligations],TransactionsData[FY],I32,TransactionsData[Quarter],J32,TransactionsData[Dimension match],1))) | E32: =IF(I32="","",IF(Trends!$B$6<>"","",SUMIFS(TransactionsData[Deobligations],TransactionsData[FY],I32,TransactionsData[Quarter],J32,TransactionsData[Dimension match],1))) | F32: =IF(I32="","",IF(Trends!$B$6<>"","",COUNTIFS(TransactionsData[FY],I32,TransactionsData[Quarter],J32,TransactionsData[Dimension match],1))) | H32: =IF(I32="","",IF(AND(B32>=Transactions!$B$4,C32<=Transactions!$D$4),"Complete","Partial")) | K32: =IF(OR(I32="",AND(Dashboard!$B$7<>"All",I32<>Dashboard!$B$7)),0,IF(Dashboard!$B$7="All",ROW()-31,J32)) -> 0 | L32: =IF(OR(Trends!$B$6<>"",I32=""),"",D32/1000000)
A33: =IF(I33="","","FY"&I33&" Q"&J33) | B33: =IF(I33="","",DATE(I33-IF(J33=1,1,0),CHOOSE(J33,10,1,4,7),1)) | C33: =IF(B33="","",EDATE(B33,3)-1) | D33: =IF(I33="","",IF(Trends!$B$6<>"","",SUMIFS(TransactionsData[Obligations],TransactionsData[FY],I33,TransactionsData[Quarter],J33,TransactionsData[Dimension match],1))) | E33: =IF(I33="","",IF(Trends!$B$6<>"","",SUMIFS(TransactionsData[Deobligations],TransactionsData[FY],I33,TransactionsData[Quarter],J33,TransactionsData[Dimension match],1))) | F33: =IF(I33="","",IF(Trends!$B$6<>"","",COUNTIFS(TransactionsData[FY],I33,TransactionsData[Quarter],J33,TransactionsData[Dimension match],1))) | H33: =IF(I33="","",IF(AND(B33>=Transactions!$B$4,C33<=Transactions!$D$4),"Complete","Partial")) | K33: =IF(OR(I33="",AND(Dashboard!$B$7<>"All",I33<>Dashboard!$B$7)),0,IF(Dashboard!$B$7="All",ROW()-31,J33)) -> 0 | L33: =IF(OR(Trends!$B$6<>"",I33=""),"",D33/1000000)
A34: =IF(I34="","","FY"&I34&" Q"&J34) | B34: =IF(I34="","",DATE(I34-IF(J34=1,1,0),CHOOSE(J34,10,1,4,7),1)) | C34: =IF(B34="","",EDATE(B34,3)-1) | D34: =IF(I34="","",IF(Trends!$B$6<>"","",SUMIFS(TransactionsData[Obligations],TransactionsData[FY],I34,TransactionsData[Quarter],J34,TransactionsData[Dimension match],1))) | E34: =IF(I34="","",IF(Trends!$B$6<>"","",SUMIFS(TransactionsData[Deobligations],TransactionsData[FY],I34,TransactionsData[Quarter],J34,TransactionsData[Dimension match],1))) | F34: =IF(I34="","",IF(Trends!$B$6<>"","",COUNTIFS(TransactionsData[FY],I34,TransactionsData[Quarter],J34,TransactionsData[Dimension match],1))) | H34: =IF(I34="","",IF(AND(B34>=Transactions!$B$4,C34<=Transactions!$D$4),"Complete","Partial")) | K34: =IF(OR(I34="",AND(Dashboard!$B$7<>"All",I34<>Dashboard!$B$7)),0,IF(Dashboard!$B$7="All",ROW()-31,J34)) -> 0 | L34: =IF(OR(Trends!$B$6<>"",I34=""),"",D34/1000000)
A35: =IF(I35="","","FY"&I35&" Q"&J35) | B35: =IF(I35="","",DATE(I35-IF(J35=1,1,0),CHOOSE(J35,10,1,4,7),1)) | C35: =IF(B35="","",EDATE(B35,3)-1) | D35: =IF(I35="","",IF(Trends!$B$6<>"","",SUMIFS(TransactionsData[Obligations],TransactionsData[FY],I35,TransactionsData[Quarter],J35,TransactionsData[Dimension match],1))) | E35: =IF(I35="","",IF(Trends!$B$6<>"","",SUMIFS(TransactionsData[Deobligations],TransactionsData[FY],I35,TransactionsData[Quarter],J35,TransactionsData[Dimension match],1))) | F35: =IF(I35="","",IF(Trends!$B$6<>"","",COUNTIFS(TransactionsData[FY],I35,TransactionsData[Quarter],J35,TransactionsData[Dimension match],1))) | G35: =IF(AND(Trends!$B$6="",COUNTIFS(H32:H35,"Complete")=4),SUM(D32:D35)/4,"") | H35: =IF(I35="","",IF(AND(B35>=Transactions!$B$4,C35<=Transactions!$D$4),"Complete","Partial")) | K35: =IF(OR(I35="",AND(Dashboard!$B$7<>"All",I35<>Dashboard!$B$7)),0,IF(Dashboard!$B$7="All",ROW()-31,J35)) -> 0 | L35: =IF(OR(Trends!$B$6<>"",I35=""),"",D35/1000000) | M35: =IF(G35="","",G35/1000000)

Sheet Vendors & Buyers
A2: Vendors & Buyers
A3: ="Buyer: "&IF(Transactions!B3="","Not supplied",Transactions!B3)&" | Period: "&IF(Dashboard!$B$7="All","All covered years",IF(Dashboard!$B$7="","Not supplied","FY"&Dashboard!$B$7))&" | Award type: "&Dashboard!$N$10 -> Buyer: Not supplied | Period: Not supplied | Award type: All
A4: ="Vendor: "&Dashboard!H7 -> Vendor: All
A5: ="Funding office: "&Dashboard!B10 -> Funding office: All
A6: Rankings follow the filters above. Award counts include nonzero obligation or deobligation actions.
A7: Rank | B7: Vendor | C7: UEI | D7: Net obligations | E7: Deobligations | F7: Awards with obligations | G7: Transactions | H7: Record ID | I7: Source name | J7: Source UEI | K7: Source URL | L7: Filter label | M7: Source net | N7: Source deobligations | O7: Source awards | P7: Source actions | Q7: Source rank | R7: Input check
A8: =IF(Trends!$B$6<>"","",IF(COUNTIFS(VendorGroups[Source rank],1)=1,1,"")) | B8: =IF(Trends!$B$6<>"","",IF(COUNTIFS(VendorGroups[Source rank],1)=1,IF(INDEX(VendorGroups[Source URL],MATCH(1,VendorGroups[Source rank],0))="",INDEX(VendorGroups[Source name],MATCH(1,VendorGroups[Source rank],0)),HYPERLINK(INDEX(VendorGroups[Source URL],MATCH(1,VendorGroups[Source rank],0)),INDEX(VendorGroups[Source name],MATCH(1,VendorGroups[Source rank],0)))),"")) | C8: =IF(Trends!$B$6<>"","",IF(COUNTIFS(VendorGroups[Source rank],1)=1,IF(INDEX(VendorGroups[Source UEI],MATCH(1,VendorGroups[Source rank],0))="","Not supplied",INDEX(VendorGroups[Source UEI],MATCH(1,VendorGroups[Source rank],0))),"")) | D8: =IF(Trends!$B$6<>"","",IF(COUNTIFS(VendorGroups[Source rank],1)=1,INDEX(VendorGroups[Source net],MATCH(1,VendorGroups[Source rank],0)),"")) | E8: =IF(Trends!$B$6<>"","",IF(COUNTIFS(VendorGroups[Source rank],1)=1,INDEX(VendorGroups[Source deobligations],MATCH(1,VendorGroups[Source rank],0)),"")) | F8: =IF(Trends!$B$6<>"","",IF(COUNTIFS(VendorGroups[Source rank],1)=1,INDEX(VendorGroups[Source awards],MATCH(1,VendorGroups[Source rank],0)),"")) | G8: =IF(Trends!$B$6<>"","",IF(COUNTIFS(VendorGroups[Source rank],1)=1,INDEX(VendorGroups[Source actions],MATCH(1,VendorGroups[Source rank],0)),"")) | L8: =IF(H8="","",I8&IF(J8="",""," ["&J8&"]")) | M8: =IF(H8="","",SUMIFS(TransactionsData[Obligations],TransactionsData[Vendor ID],H8,TransactionsData[Selected],1)) | N8: =IF(H8="","",SUMIFS(TransactionsData[Deobligations],TransactionsData[Vendor ID],H8,TransactionsData[Selected],1)) | O8: =IF(H8="","",SUMIFS(TransactionsData[First vendor award],TransactionsData[Vendor ID],H8)) | P8: =IF(H8="","",COUNTIFS(TransactionsData[Vendor ID],H8,TransactionsData[Selected],1)) | Q8: =IF(OR(H8="",P8=0),"",COUNTIFS(VendorGroups[Source net],">"&M8,VendorGroups[Source actions],">0")+COUNTIFS(VendorGroups[Source net],M8,VendorGroups[Record ID],"<"&H8,VendorGroups[Source actions],">0")+1) | R8: =IF(H8="",IF(COUNTA(I8:K8)>0,"Missing record ID",""),IF(COUNTIFS(VendorGroups[Record ID],H8)<>1,"Duplicate record ID",IF(I8="","Add name","")))
A9: =IF(Trends!$B$6<>"","",IF(COUNTIFS(VendorGroups[Source rank],2)=1,2,"")) | B9: =IF(Trends!$B$6<>"","",IF(COUNTIFS(VendorGroups[Source rank],2)=1,IF(INDEX(VendorGroups[Source URL],MATCH(2,VendorGroups[Source rank],0))="",INDEX(VendorGroups[Source name],MATCH(2,VendorGroups[Source rank],0)),HYPERLINK(INDEX(VendorGroups[Source URL],MATCH(2,VendorGroups[Source rank],0)),INDEX(VendorGroups[Source name],MATCH(2,VendorGroups[Source rank],0)))),"")) | C9: =IF(Trends!$B$6<>"","",IF(COUNTIFS(VendorGroups[Source rank],2)=1,IF(INDEX(VendorGroups[Source UEI],MATCH(2,VendorGroups[Source rank],0))="","Not supplied",INDEX(VendorGroups[Source UEI],MATCH(2,VendorGroups[Source rank],0))),"")) | D9: =IF(Trends!$B$6<>"","",IF(COUNTIFS(VendorGroups[Source rank],2)=1,INDEX(VendorGroups[Source net],MATCH(2,VendorGroups[Source rank],0)),"")) | E9: =IF(Trends!$B$6<>"","",IF(COUNTIFS(VendorGroups[Source rank],2)=1,INDEX(VendorGroups[Source deobligations],MATCH(2,VendorGroups[Source rank],0)),"")) | F9: =IF(Trends!$B$6<>"","",IF(COUNTIFS(VendorGroups[Source rank],2)=1,INDEX(VendorGroups[Source awards],MATCH(2,VendorGroups[Source rank],0)),"")) | G9: =IF(Trends!$B$6<>"","",IF(COUNTIFS(VendorGroups[Source rank],2)=1,INDEX(VendorGroups[Source actions],MATCH(2,VendorGroups[Source rank],0)),"")) | L9: =IF(H9="","",I9&IF(J9="",""," ["&J9&"]")) | M9: =IF(H9="","",SUMIFS(TransactionsData[Obligations],TransactionsData[Vendor ID],H9,TransactionsData[Selected],1)) | N9: =IF(H9="","",SUMIFS(TransactionsData[Deobligations],TransactionsData[Vendor ID],H9,TransactionsData[Selected],1)) | O9: =IF(H9="","",SUMIFS(TransactionsData[First vendor award],TransactionsData[Vendor ID],H9)) | P9: =IF(H9="","",COUNTIFS(TransactionsData[Vendor ID],H9,TransactionsData[Selected],1)) | Q9: =IF(OR(H9="",P9=0),"",COUNTIFS(VendorGroups[Source net],">"&M9,VendorGroups[Source actions],">0")+COUNTIFS(VendorGroups[Source net],M9,VendorGroups[Record ID],"<"&H9,VendorGroups[Source actions],">0")+1) | R9: =IF(H9="",IF(COUNTA(I9:K9)>0,"Missing record ID",""),IF(COUNTIFS(VendorGroups[Record ID],H9)<>1,"Duplicate record ID",IF(I9="","Add name","")))
A10: =IF(Trends!$B$6<>"","",IF(COUNTIFS(VendorGroups[Source rank],3)=1,3,"")) | B10: =IF(Trends!$B$6<>"","",IF(COUNTIFS(VendorGroups[Source rank],3)=1,IF(INDEX(VendorGroups[Source URL],MATCH(3,VendorGroups[Source rank],0))="",INDEX(VendorGroups[Source name],MATCH(3,VendorGroups[Source rank],0)),HYPERLINK(INDEX(VendorGroups[Source URL],MATCH(3,VendorGroups[Source rank],0)),INDEX(VendorGroups[Source name],MATCH(3,VendorGroups[Source rank],0)))),"")) | C10: =IF(Trends!$B$6<>"","",IF(COUNTIFS(VendorGroups[Source rank],3)=1,IF(INDEX(VendorGroups[Source UEI],MATCH(3,VendorGroups[Source rank],0))="","Not supplied",INDEX(VendorGroups[Source UEI],MATCH(3,VendorGroups[Source rank],0))),"")) | D10: =IF(Trends!$B$6<>"","",IF(COUNTIFS(VendorGroups[Source rank],3)=1,INDEX(VendorGroups[Source net],MATCH(3,VendorGroups[Source rank],0)),"")) | E10: =IF(Trends!$B$6<>"","",IF(COUNTIFS(VendorGroups[Source rank],3)=1,INDEX(VendorGroups[Source deobligations],MATCH(3,VendorGroups[Source rank],0)),"")) | F10: =IF(Trends!$B$6<>"","",IF(COUNTIFS(VendorGroups[Source rank],3)=1,INDEX(VendorGroups[Source awards],MATCH(3,VendorGroups[Source rank],0)),"")) | G10: =IF(Trends!$B$6<>"","",IF(COUNTIFS(VendorGroups[Source rank],3)=1,INDEX(VendorGroups[Source actions],MATCH(3,VendorGroups[Source rank],0)),"")) | L10: =IF(H10="","",I10&IF(J10="",""," ["&J10&"]")) | M10: =IF(H10="","",SUMIFS(TransactionsData[Obligations],TransactionsData[Vendor ID],H10,TransactionsData[Selected],1)) | N10: =IF(H10="","",SUMIFS(TransactionsData[Deobligations],TransactionsData[Vendor ID],H10,TransactionsData[Selected],1)) | O10: =IF(H10="","",SUMIFS(TransactionsData[First vendor award],TransactionsData[Vendor ID],H10)) | P10: =IF(H10="","",COUNTIFS(TransactionsData[Vendor ID],H10,TransactionsData[Selected],1)) | Q10: =IF(OR(H10="",P10=0),"",COUNTIFS(VendorGroups[Source net],">"&M10,VendorGroups[Source actions],">0")+COUNTIFS(VendorGroups[Source net],M10,VendorGroups[Record ID],"<"&H10,VendorGroups[Source actions],">0")+1) | R10: =IF(H10="",IF(COUNTA(I10:K10)>0,"Missing record ID",""),IF(COUNTIFS(VendorGroups[Record ID],H10)<>1,"Duplicate record ID",IF(I10="","Add name","")))
A11: =IF(Trends!$B$6<>"","",IF(COUNTIFS(VendorGroups[Source rank],4)=1,4,"")) | B11: =IF(Trends!$B$6<>"","",IF(COUNTIFS(VendorGroups[Source rank],4)=1,IF(INDEX(VendorGroups[Source URL],MATCH(4,VendorGroups[Source rank],0))="",INDEX(VendorGroups[Source name],MATCH(4,VendorGroups[Source rank],0)),HYPERLINK(INDEX(VendorGroups[Source URL],MATCH(4,VendorGroups[Source rank],0)),INDEX(VendorGroups[Source name],MATCH(4,VendorGroups[Source rank],0)))),"")) | C11: =IF(Trends!$B$6<>"","",IF(COUNTIFS(VendorGroups[Source rank],4)=1,IF(INDEX(VendorGroups[Source UEI],MATCH(4,VendorGroups[Source rank],0))="","Not supplied",INDEX(VendorGroups[Source UEI],MATCH(4,VendorGroups[Source rank],0))),"")) | D11: =IF(Trends!$B$6<>"","",IF(COUNTIFS(VendorGroups[Source rank],4)=1,INDEX(VendorGroups[Source net],MATCH(4,VendorGroups[Source rank],0)),"")) | E11: =IF(Trends!$B$6<>"","",IF(COUNTIFS(VendorGroups[Source rank],4)=1,INDEX(VendorGroups[Source deobligations],MATCH(4,VendorGroups[Source rank],0)),"")) | F11: =IF(Trends!$B$6<>"","",IF(COUNTIFS(VendorGroups[Source rank],4)=1,INDEX(VendorGroups[Source awards],MATCH(4,VendorGroups[Source rank],0)),"")) | G11: =IF(Trends!$B$6<>"","",IF(COUNTIFS(VendorGroups[Source rank],4)=1,INDEX(VendorGroups[Source actions],MATCH(4,VendorGroups[Source rank],0)),"")) | L11: =IF(H11="","",I11&IF(J11="",""," ["&J11&"]")) | M11: =IF(H11="","",SUMIFS(TransactionsData[Obligations],TransactionsData[Vendor ID],H11,TransactionsData[Selected],1)) | N11: =IF(H11="","",SUMIFS(TransactionsData[Deobligations],TransactionsData[Vendor ID],H11,TransactionsData[Selected],1)) | O11: =IF(H11="","",SUMIFS(TransactionsData[First vendor award],TransactionsData[Vendor ID],H11)) | P11: =IF(H11="","",COUNTIFS(TransactionsData[Vendor ID],H11,TransactionsData[Selected],1)) | Q11: =IF(OR(H11="",P11=0),"",COUNTIFS(VendorGroups[Source net],">"&M11,VendorGroups[Source actions],">0")+COUNTIFS(VendorGroups[Source net],M11,VendorGroups[Record ID],"<"&H11,VendorGroups[Source actions],">0")+1) | R11: =IF(H11="",IF(COUNTA(I11:K11)>0,"Missing record ID",""),IF(COUNTIFS(VendorGroups[Record ID],H11)<>1,"Duplicate record ID",IF(I11="","Add name","")))
A12: =IF(Trends!$B$6<>"","",IF(COUNTIFS(VendorGroups[Source rank],5)=1,5,"")) | B12: =IF(Trends!$B$6<>"","",IF(COUNTIFS(VendorGroups[Source rank],5)=1,IF(INDEX(VendorGroups[Source URL],MATCH(5,VendorGroups[Source rank],0))="",INDEX(VendorGroups[Source name],MATCH(5,VendorGroups[Source rank],0)),HYPERLINK(INDEX(VendorGroups[Source URL],MATCH(5,VendorGroups[Source rank],0)),INDEX(VendorGroups[Source name],MATCH(5,VendorGroups[Source rank],0)))),"")) | C12: =IF(Trends!$B$6<>"","",IF(COUNTIFS(VendorGroups[Source rank],5)=1,IF(INDEX(VendorGroups[Source UEI],MATCH(5,VendorGroups[Source rank],0))="","Not supplied",INDEX(VendorGroups[Source UEI],MATCH(5,VendorGroups[Source rank],0))),"")) | D12: =IF(Trends!$B$6<>"","",IF(COUNTIFS(VendorGroups[Source rank],5)=1,INDEX(VendorGroups[Source net],MATCH(5,VendorGroups[Source rank],0)),"")) | E12: =IF(Trends!$B$6<>"","",IF(COUNTIFS(VendorGroups[Source rank],5)=1,INDEX(VendorGroups[Source deobligations],MATCH(5,VendorGroups[Source rank],0)),"")) | F12: =IF(Trends!$B$6<>"","",IF(COUNTIFS(VendorGroups[Source rank],5)=1,INDEX(VendorGroups[Source awards],MATCH(5,VendorGroups[Source rank],0)),"")) | G12: =IF(Trends!$B$6<>"","",IF(COUNTIFS(VendorGroups[Source rank],5)=1,INDEX(VendorGroups[Source actions],MATCH(5,VendorGroups[Source rank],0)),"")) | L12: =IF(H12="","",I12&IF(J12="",""," ["&J12&"]")) | M12: =IF(H12="","",SUMIFS(TransactionsData[Obligations],TransactionsData[Vendor ID],H12,TransactionsData[Selected],1)) | N12: =IF(H12="","",SUMIFS(TransactionsData[Deobligations],TransactionsData[Vendor ID],H12,TransactionsData[Selected],1)) | O12: =IF(H12="","",SUMIFS(TransactionsData[First vendor award],TransactionsData[Vendor ID],H12)) | P12: =IF(H12="","",COUNTIFS(TransactionsData[Vendor ID],H12,TransactionsData[Selected],1)) | Q12: =IF(OR(H12="",P12=0),"",COUNTIFS(VendorGroups[Source net],">"&M12,VendorGroups[Source actions],">0")+COUNTIFS(VendorGroups[Source net],M12,VendorGroups[Record ID],"<"&H12,VendorGroups[Source actions],">0")+1) | R12: =IF(H12="",IF(COUNTA(I12:K12)>0,"Missing record ID",""),IF(COUNTIFS(VendorGroups[Record ID],H12)<>1,"Duplicate record ID",IF(I12="","Add name","")))
A13: =IF(Trends!$B$6<>"","",IF(COUNTIFS(VendorGroups[Source rank],6)=1,6,"")) | B13: =IF(Trends!$B$6<>"","",IF(COUNTIFS(VendorGroups[Source rank],6)=1,IF(INDEX(VendorGroups[Source URL],MATCH(6,VendorGroups[Source rank],0))="",INDEX(VendorGroups[Source name],MATCH(6,VendorGroups[Source rank],0)),HYPERLINK(INDEX(VendorGroups[Source URL],MATCH(6,VendorGroups[Source rank],0)),INDEX(VendorGroups[Source name],MATCH(6,VendorGroups[Source rank],0)))),"")) | C13: =IF(Trends!$B$6<>"","",IF(COUNTIFS(VendorGroups[Source rank],6)=1,IF(INDEX(VendorGroups[Source UEI],MATCH(6,VendorGroups[Source rank],0))="","Not supplied",INDEX(VendorGroups[Source UEI],MATCH(6,VendorGroups[Source rank],0))),"")) | D13: =IF(Trends!$B$6<>"","",IF(COUNTIFS(VendorGroups[Source rank],6)=1,INDEX(VendorGroups[Source net],MATCH(6,VendorGroups[Source rank],0)),"")) | E13: =IF(Trends!$B$6<>"","",IF(COUNTIFS(VendorGroups[Source rank],6)=1,INDEX(VendorGroups[Source deobligations],MATCH(6,VendorGroups[Source rank],0)),"")) | F13: =IF(Trends!$B$6<>"","",IF(COUNTIFS(VendorGroups[Source rank],6)=1,INDEX(VendorGroups[Source awards],MATCH(6,VendorGroups[Source rank],0)),"")) | G13: =IF(Trends!$B$6<>"","",IF(COUNTIFS(VendorGroups[Source rank],6)=1,INDEX(VendorGroups[Source actions],MATCH(6,VendorGroups[Source rank],0)),"")) | L13: =IF(H13="","",I13&IF(J13="",""," ["&J13&"]")) | M13: =IF(H13="","",SUMIFS(TransactionsData[Obligations],TransactionsData[Vendor ID],H13,TransactionsData[Selected],1)) | N13: =IF(H13="","",SUMIFS(TransactionsData[Deobligations],TransactionsData[Vendor ID],H13,TransactionsData[Selected],1)) | O13: =IF(H13="","",SUMIFS(TransactionsData[First vendor award],TransactionsData[Vendor ID],H13)) | P13: =IF(H13="","",COUNTIFS(TransactionsData[Vendor ID],H13,TransactionsData[Selected],1)) | Q13: =IF(OR(H13="",P13=0),"",COUNTIFS(VendorGroups[Source net],">"&M13,VendorGroups[Source actions],">0")+COUNTIFS(VendorGroups[Source net],M13,VendorGroups[Record ID],"<"&H13,VendorGroups[Source actions],">0")+1) | R13: =IF(H13="",IF(COUNTA(I13:K13)>0,"Missing record ID",""),IF(COUNTIFS(VendorGroups[Record ID],H13)<>1,"Duplicate record ID",IF(I13="","Add name","")))
A14: =IF(Trends!$B$6<>"","",IF(COUNTIFS(VendorGroups[Source rank],7)=1,7,"")) | B14: =IF(Trends!$B$6<>"","",IF(COUNTIFS(VendorGroups[Source rank],7)=1,IF(INDEX(VendorGroups[Source URL],MATCH(7,VendorGroups[Source rank],0))="",INDEX(VendorGroups[Source name],MATCH(7,VendorGroups[Source rank],0)),HYPERLINK(INDEX(VendorGroups[Source URL],MATCH(7,VendorGroups[Source rank],0)),INDEX(VendorGroups[Source name],MATCH(7,VendorGroups[Source rank],0)))),"")) | C14: =IF(Trends!$B$6<>"","",IF(COUNTIFS(VendorGroups[Source rank],7)=1,IF(INDEX(VendorGroups[Source UEI],MATCH(7,VendorGroups[Source rank],0))="","Not supplied",INDEX(VendorGroups[Source UEI],MATCH(7,VendorGroups[Source rank],0))),"")) | D14: =IF(Trends!$B$6<>"","",IF(COUNTIFS(VendorGroups[Source rank],7)=1,INDEX(VendorGroups[Source net],MATCH(7,VendorGroups[Source rank],0)),"")) | E14: =IF(Trends!$B$6<>"","",IF(COUNTIFS(VendorGroups[Source rank],7)=1,INDEX(VendorGroups[Source deobligations],MATCH(7,VendorGroups[Source rank],0)),"")) | F14: =IF(Trends!$B$6<>"","",IF(COUNTIFS(VendorGroups[Source rank],7)=1,INDEX(VendorGroups[Source awards],MATCH(7,VendorGroups[Source rank],0)),"")) | G14: =IF(Trends!$B$6<>"","",IF(COUNTIFS(VendorGroups[Source rank],7)=1,INDEX(VendorGroups[Source actions],MATCH(7,VendorGroups[Source rank],0)),"")) | L14: =IF(H14="","",I14&IF(J14="",""," ["&J14&"]")) | M14: =IF(H14="","",SUMIFS(TransactionsData[Obligations],TransactionsData[Vendor ID],H14,TransactionsData[Selected],1)) | N14: =IF(H14="","",SUMIFS(TransactionsData[Deobligations],TransactionsData[Vendor ID],H14,TransactionsData[Selected],1)) | O14: =IF(H14="","",SUMIFS(TransactionsData[First vendor award],TransactionsData[Vendor ID],H14)) | P14: =IF(H14="","",COUNTIFS(TransactionsData[Vendor ID],H14,TransactionsData[Selected],1)) | Q14: =IF(OR(H14="",P14=0),"",COUNTIFS(VendorGroups[Source net],">"&M14,VendorGroups[Source actions],">0")+COUNTIFS(VendorGroups[Source net],M14,VendorGroups[Record ID],"<"&H14,VendorGroups[Source actions],">0")+1) | R14: =IF(H14="",IF(COUNTA(I14:K14)>0,"Missing record ID",""),IF(COUNTIFS(VendorGroups[Record ID],H14)<>1,"Duplicate record ID",IF(I14="","Add name","")))
A15: =IF(Trends!$B$6<>"","",IF(COUNTIFS(VendorGroups[Source rank],8)=1,8,"")) | B15: =IF(Trends!$B$6<>"","",IF(COUNTIFS(VendorGroups[Source rank],8)=1,IF(INDEX(VendorGroups[Source URL],MATCH(8,VendorGroups[Source rank],0))="",INDEX(VendorGroups[Source name],MATCH(8,VendorGroups[Source rank],0)),HYPERLINK(INDEX(VendorGroups[Source URL],MATCH(8,VendorGroups[Source rank],0)),INDEX(VendorGroups[Source name],MATCH(8,VendorGroups[Source rank],0)))),"")) | C15: =IF(Trends!$B$6<>"","",IF(COUNTIFS(VendorGroups[Source rank],8)=1,IF(INDEX(VendorGroups[Source UEI],MATCH(8,VendorGroups[Source rank],0))="","Not supplied",INDEX(VendorGroups[Source UEI],MATCH(8,VendorGroups[Source rank],0))),"")) | D15: =IF(Trends!$B$6<>"","",IF(COUNTIFS(VendorGroups[Source rank],8)=1,INDEX(VendorGroups[Source net],MATCH(8,VendorGroups[Source rank],0)),"")) | E15: =IF(Trends!$B$6<>"","",IF(COUNTIFS(VendorGroups[Source rank],8)=1,INDEX(VendorGroups[Source deobligations],MATCH(8,VendorGroups[Source rank],0)),"")) | F15: =IF(Trends!$B$6<>"","",IF(COUNTIFS(VendorGroups[Source rank],8)=1,INDEX(VendorGroups[Source awards],MATCH(8,VendorGroups[Source rank],0)),"")) | G15: =IF(Trends!$B$6<>"","",IF(COUNTIFS(VendorGroups[Source rank],8)=1,INDEX(VendorGroups[Source actions],MATCH(8,VendorGroups[Source rank],0)),"")) | L15: =IF(H15="","",I15&IF(J15="",""," ["&J15&"]")) | M15: =IF(H15="","",SUMIFS(TransactionsData[Obligations],TransactionsData[Vendor ID],H15,TransactionsData[Selected],1)) | N15: =IF(H15="","",SUMIFS(TransactionsData[Deobligations],TransactionsData[Vendor ID],H15,TransactionsData[Selected],1)) | O15: =IF(H15="","",SUMIFS(TransactionsData[First vendor award],TransactionsData[Vendor ID],H15)) | P15: =IF(H15="","",COUNTIFS(TransactionsData[Vendor ID],H15,TransactionsData[Selected],1)) | Q15: =IF(OR(H15="",P15=0),"",COUNTIFS(VendorGroups[Source net],">"&M15,VendorGroups[Source actions],">0")+COUNTIFS(VendorGroups[Source net],M15,VendorGroups[Record ID],"<"&H15,VendorGroups[Source actions],">0")+1) | R15: =IF(H15="",IF(COUNTA(I15:K15)>0,"Missing record ID",""),IF(COUNTIFS(VendorGroups[Record ID],H15)<>1,"Duplicate record ID",IF(I15="","Add name","")))
A16: =IF(Trends!$B$6<>"","",IF(COUNTIFS(VendorGroups[Source rank],9)=1,9,"")) | B16: =IF(Trends!$B$6<>"","",IF(COUNTIFS(VendorGroups[Source rank],9)=1,IF(INDEX(VendorGroups[Source URL],MATCH(9,VendorGroups[Source rank],0))="",INDEX(VendorGroups[Source name],MATCH(9,VendorGroups[Source rank],0)),HYPERLINK(INDEX(VendorGroups[Source URL],MATCH(9,VendorGroups[Source rank],0)),INDEX(VendorGroups[Source name],MATCH(9,VendorGroups[Source rank],0)))),"")) | C16: =IF(Trends!$B$6<>"","",IF(COUNTIFS(VendorGroups[Source rank],9)=1,IF(INDEX(VendorGroups[Source UEI],MATCH(9,VendorGroups[Source rank],0))="","Not supplied",INDEX(VendorGroups[Source UEI],MATCH(9,VendorGroups[Source rank],0))),"")) | D16: =IF(Trends!$B$6<>"","",IF(COUNTIFS(VendorGroups[Source rank],9)=1,INDEX(VendorGroups[Source net],MATCH(9,VendorGroups[Source rank],0)),"")) | E16: =IF(Trends!$B$6<>"","",IF(COUNTIFS(VendorGroups[Source rank],9)=1,INDEX(VendorGroups[Source deobligations],MATCH(9,VendorGroups[Source rank],0)),"")) | F16: =IF(Trends!$B$6<>"","",IF(COUNTIFS(VendorGroups[Source rank],9)=1,INDEX(VendorGroups[Source awards],MATCH(9,VendorGroups[Source rank],0)),"")) | G16: =IF(Trends!$B$6<>"","",IF(COUNTIFS(VendorGroups[Source rank],9)=1,INDEX(VendorGroups[Source actions],MATCH(9,VendorGroups[Source rank],0)),"")) | L16: =IF(H16="","",I16&IF(J16="",""," ["&J16&"]")) | M16: =IF(H16="","",SUMIFS(TransactionsData[Obligations],TransactionsData[Vendor ID],H16,TransactionsData[Selected],1)) | N16: =IF(H16="","",SUMIFS(TransactionsData[Deobligations],TransactionsData[Vendor ID],H16,TransactionsData[Selected],1)) | O16: =IF(H16="","",SUMIFS(TransactionsData[First vendor award],TransactionsData[Vendor ID],H16)) | P16: =IF(H16="","",COUNTIFS(TransactionsData[Vendor ID],H16,TransactionsData[Selected],1)) | Q16: =IF(OR(H16="",P16=0),"",COUNTIFS(VendorGroups[Source net],">"&M16,VendorGroups[Source actions],">0")+COUNTIFS(VendorGroups[Source net],M16,VendorGroups[Record ID],"<"&H16,VendorGroups[Source actions],">0")+1) | R16: =IF(H16="",IF(COUNTA(I16:K16)>0,"Missing record ID",""),IF(COUNTIFS(VendorGroups[Record ID],H16)<>1,"Duplicate record ID",IF(I16="","Add name","")))
A17: =IF(Trends!$B$6<>"","",IF(COUNTIFS(VendorGroups[Source rank],10)=1,10,"")) | B17: =IF(Trends!$B$6<>"","",IF(COUNTIFS(VendorGroups[Source rank],10)=1,IF(INDEX(VendorGroups[Source URL],MATCH(10,VendorGroups[Source rank],0))="",INDEX(VendorGroups[Source name],MATCH(10,VendorGroups[Source rank],0)),HYPERLINK(INDEX(VendorGroups[Source URL],MATCH(10,VendorGroups[Source rank],0)),INDEX(VendorGroups[Source name],MATCH(10,VendorGroups[Source rank],0)))),"")) | C17: =IF(Trends!$B$6<>"","",IF(COUNTIFS(VendorGroups[Source rank],10)=1,IF(INDEX(VendorGroups[Source UEI],MATCH(10,VendorGroups[Source rank],0))="","Not supplied",INDEX(VendorGroups[Source UEI],MATCH(10,VendorGroups[Source rank],0))),"")) | D17: =IF(Trends!$B$6<>"","",IF(COUNTIFS(VendorGroups[Source rank],10)=1,INDEX(VendorGroups[Source net],MATCH(10,VendorGroups[Source rank],0)),"")) | E17: =IF(Trends!$B$6<>"","",IF(COUNTIFS(VendorGroups[Source rank],10)=1,INDEX(VendorGroups[Source deobligations],MATCH(10,VendorGroups[Source rank],0)),"")) | F17: =IF(Trends!$B$6<>"","",IF(COUNTIFS(VendorGroups[Source rank],10)=1,INDEX(VendorGroups[Source awards],MATCH(10,VendorGroups[Source rank],0)),"")) | G17: =IF(Trends!$B$6<>"","",IF(COUNTIFS(VendorGroups[Source rank],10)=1,INDEX(VendorGroups[Source actions],MATCH(10,VendorGroups[Source rank],0)),"")) | L17: =IF(H17="","",I17&IF(J17="",""," ["&J17&"]")) | M17: =IF(H17="","",SUMIFS(TransactionsData[Obligations],TransactionsData[Vendor ID],H17,TransactionsData[Selected],1)) | N17: =IF(H17="","",SUMIFS(TransactionsData[Deobligations],TransactionsData[Vendor ID],H17,TransactionsData[Selected],1)) | O17: =IF(H17="","",SUMIFS(TransactionsData[First vendor award],TransactionsData[Vendor ID],H17)) | P17: =IF(H17="","",COUNTIFS(TransactionsData[Vendor ID],H17,TransactionsData[Selected],1)) | Q17: =IF(OR(H17="",P17=0),"",COUNTIFS(VendorGroups[Source net],">"&M17,VendorGroups[Source actions],">0")+COUNTIFS(VendorGroups[Source net],M17,VendorGroups[Record ID],"<"&H17,VendorGroups[Source actions],">0")+1) | R17: =IF(H17="",IF(COUNTA(I17:K17)>0,"Missing record ID",""),IF(COUNTIFS(VendorGroups[Record ID],H17)<>1,"Duplicate record ID",IF(I17="","Add name","")))
A18: =IF(Trends!$B$6<>"","",IF(COUNTIFS(VendorGroups[Source rank],11)=1,11,"")) | B18: =IF(Trends!$B$6<>"","",IF(COUNTIFS(VendorGroups[Source rank],11)=1,IF(INDEX(VendorGroups[Source URL],MATCH(11,VendorGroups[Source rank],0))="",INDEX(VendorGroups[Source name],MATCH(11,VendorGroups[Source rank],0)),HYPERLINK(INDEX(VendorGroups[Source URL],MATCH(11,VendorGroups[Source rank],0)),INDEX(VendorGroups[Source name],MATCH(11,VendorGroups[Source rank],0)))),"")) | C18: =IF(Trends!$B$6<>"","",IF(COUNTIFS(VendorGroups[Source rank],11)=1,IF(INDEX(VendorGroups[Source UEI],MATCH(11,VendorGroups[Source rank],0))="","Not supplied",INDEX(VendorGroups[Source UEI],MATCH(11,VendorGroups[Source rank],0))),"")) | D18: =IF(Trends!$B$6<>"","",IF(COUNTIFS(VendorGroups[Source rank],11)=1,INDEX(VendorGroups[Source net],MATCH(11,VendorGroups[Source rank],0)),"")) | E18: =IF(Trends!$B$6<>"","",IF(COUNTIFS(VendorGroups[Source rank],11)=1,INDEX(VendorGroups[Source deobligations],MATCH(11,VendorGroups[Source rank],0)),"")) | F18: =IF(Trends!$B$6<>"","",IF(COUNTIFS(VendorGroups[Source rank],11)=1,INDEX(VendorGroups[Source awards],MATCH(11,VendorGroups[Source rank],0)),"")) | G18: =IF(Trends!$B$6<>"","",IF(COUNTIFS(VendorGroups[Source rank],11)=1,INDEX(VendorGroups[Source actions],MATCH(11,VendorGroups[Source rank],0)),"")) | L18: =IF(H18="","",I18&IF(J18="",""," ["&J18&"]")) | M18: =IF(H18="","",SUMIFS(TransactionsData[Obligations],TransactionsData[Vendor ID],H18,TransactionsData[Selected],1)) | N18: =IF(H18="","",SUMIFS(TransactionsData[Deobligations],TransactionsData[Vendor ID],H18,TransactionsData[Selected],1)) | O18: =IF(H18="","",SUMIFS(TransactionsData[First vendor award],TransactionsData[Vendor ID],H18)) | P18: =IF(H18="","",COUNTIFS(TransactionsData[Vendor ID],H18,TransactionsData[Selected],1)) | Q18: =IF(OR(H18="",P18=0),"",COUNTIFS(VendorGroups[Source net],">"&M18,VendorGroups[Source actions],">0")+COUNTIFS(VendorGroups[Source net],M18,VendorGroups[Record ID],"<"&H18,VendorGroups[Source actions],">0")+1) | R18: =IF(H18="",IF(COUNTA(I18:K18)>0,"Missing record ID",""),IF(COUNTIFS(VendorGroups[Record ID],H18)<>1,"Duplicate record ID",IF(I18="","Add name","")))
A19: =IF(Trends!$B$6<>"","",IF(COUNTIFS(VendorGroups[Source rank],12)=1,12,"")) | B19: =IF(Trends!$B$6<>"","",IF(COUNTIFS(VendorGroups[Source rank],12)=1,IF(INDEX(VendorGroups[Source URL],MATCH(12,VendorGroups[Source rank],0))="",INDEX(VendorGroups[Source name],MATCH(12,VendorGroups[Source rank],0)),HYPERLINK(INDEX(VendorGroups[Source URL],MATCH(12,VendorGroups[Source rank],0)),INDEX(VendorGroups[Source name],MATCH(12,VendorGroups[Source rank],0)))),"")) | C19: =IF(Trends!$B$6<>"","",IF(COUNTIFS(VendorGroups[Source rank],12)=1,IF(INDEX(VendorGroups[Source UEI],MATCH(12,VendorGroups[Source rank],0))="","Not supplied",INDEX(VendorGroups[Source UEI],MATCH(12,VendorGroups[Source rank],0))),"")) | D19: =IF(Trends!$B$6<>"","",IF(COUNTIFS(VendorGroups[Source rank],12)=1,INDEX(VendorGroups[Source net],MATCH(12,VendorGroups[Source rank],0)),"")) | E19: =IF(Trends!$B$6<>"","",IF(COUNTIFS(VendorGroups[Source rank],12)=1,INDEX(VendorGroups[Source deobligations],MATCH(12,VendorGroups[Source rank],0)),"")) | F19: =IF(Trends!$B$6<>"","",IF(COUNTIFS(VendorGroups[Source rank],12)=1,INDEX(VendorGroups[Source awards],MATCH(12,VendorGroups[Source rank],0)),"")) | G19: =IF(Trends!$B$6<>"","",IF(COUNTIFS(VendorGroups[Source rank],12)=1,INDEX(VendorGroups[Source actions],MATCH(12,VendorGroups[Source rank],0)),"")) | L19: =IF(H19="","",I19&IF(J19="",""," ["&J19&"]")) | M19: =IF(H19="","",SUMIFS(TransactionsData[Obligations],TransactionsData[Vendor ID],H19,TransactionsData[Selected],1)) | N19: =IF(H19="","",SUMIFS(TransactionsData[Deobligations],TransactionsData[Vendor ID],H19,TransactionsData[Selected],1)) | O19: =IF(H19="","",SUMIFS(TransactionsData[First vendor award],TransactionsData[Vendor ID],H19)) | P19: =IF(H19="","",COUNTIFS(TransactionsData[Vendor ID],H19,TransactionsData[Selected],1)) | Q19: =IF(OR(H19="",P19=0),"",COUNTIFS(VendorGroups[Source net],">"&M19,VendorGroups[Source actions],">0")+COUNTIFS(VendorGroups[Source net],M19,VendorGroups[Record ID],"<"&H19,VendorGroups[Source actions],">0")+1) | R19: =IF(H19="",IF(COUNTA(I19:K19)>0,"Missing record ID",""),IF(COUNTIFS(VendorGroups[Record ID],H19)<>1,"Duplicate record ID",IF(I19="","Add name","")))
A24: Rank | B24: Funding office | C24: Office code | D24: Net obligations | E24: Deobligations | F24: Awards with obligations | G24: Transactions | H24: Record ID | I24: Source name | J24: Source UEI | K24: Source URL | L24: Filter label | M24: Source net | N24: Source deobligations | O24: Source awards | P24: Source actions | Q24: Source rank | R24: Input check
A25: =IF(Trends!$B$6<>"","",IF(COUNTIFS(OfficeGroups[Source rank],1)=1,1,"")) | B25: =IF(Trends!$B$6<>"","",IF(COUNTIFS(OfficeGroups[Source rank],1)=1,IF(INDEX(OfficeGroups[Source URL],MATCH(1,OfficeGroups[Source rank],0))="",INDEX(OfficeGroups[Source name],MATCH(1,OfficeGroups[Source rank],0)),HYPERLINK(INDEX(OfficeGroups[Source URL],MATCH(1,OfficeGroups[Source rank],0)),INDEX(OfficeGroups[Source name],MATCH(1,OfficeGroups[Source rank],0)))),"")) | C25: =IF(Trends!$B$6<>"","",IF(COUNTIFS(OfficeGroups[Source rank],1)=1,IF(INDEX(OfficeGroups[Source UEI],MATCH(1,OfficeGroups[Source rank],0))="","Not supplied",INDEX(OfficeGroups[Source UEI],MATCH(1,OfficeGroups[Source rank],0))),"")) | D25: =IF(Trends!$B$6<>"","",IF(COUNTIFS(OfficeGroups[Source rank],1)=1,INDEX(OfficeGroups[Source net],MATCH(1,OfficeGroups[Source rank],0)),"")) | E25: =IF(Trends!$B$6<>"","",IF(COUNTIFS(OfficeGroups[Source rank],1)=1,INDEX(OfficeGroups[Source deobligations],MATCH(1,OfficeGroups[Source rank],0)),"")) | F25: =IF(Trends!$B$6<>"","",IF(COUNTIFS(OfficeGroups[Source rank],1)=1,INDEX(OfficeGroups[Source awards],MATCH(1,OfficeGroups[Source rank],0)),"")) | G25: =IF(Trends!$B$6<>"","",IF(COUNTIFS(OfficeGroups[Source rank],1)=1,INDEX(OfficeGroups[Source actions],MATCH(1,OfficeGroups[Source rank],0)),"")) | L25: =IF(H25="","",I25&IF(J25="",""," ["&J25&"]")) | M25: =IF(H25="","",SUMIFS(TransactionsData[Obligations],TransactionsData[Funding office ID],H25,TransactionsData[Selected],1)) | N25: =IF(H25="","",SUMIFS(TransactionsData[Deobligations],TransactionsData[Funding office ID],H25,TransactionsData[Selected],1)) | O25: =IF(H25="","",SUMIFS(TransactionsData[First office award],TransactionsData[Funding office ID],H25)) | P25: =IF(H25="","",COUNTIFS(TransactionsData[Funding office ID],H25,TransactionsData[Selected],1)) | Q25: =IF(OR(H25="",P25=0),"",COUNTIFS(OfficeGroups[Source net],">"&M25,OfficeGroups[Source actions],">0")+COUNTIFS(OfficeGroups[Source net],M25,OfficeGroups[Record ID],"<"&H25,OfficeGroups[Source actions],">0")+1) | R25: =IF(H25="",IF(COUNTA(I25:K25)>0,"Missing record ID",""),IF(COUNTIFS(OfficeGroups[Record ID],H25)<>1,"Duplicate record ID",IF(I25="","Add name","")))
A26: =IF(Trends!$B$6<>"","",IF(COUNTIFS(OfficeGroups[Source rank],2)=1,2,"")) | B26: =IF(Trends!$B$6<>"","",IF(COUNTIFS(OfficeGroups[Source rank],2)=1,IF(INDEX(OfficeGroups[Source URL],MATCH(2,OfficeGroups[Source rank],0))="",INDEX(OfficeGroups[Source name],MATCH(2,OfficeGroups[Source rank],0)),HYPERLINK(INDEX(OfficeGroups[Source URL],MATCH(2,OfficeGroups[Source rank],0)),INDEX(OfficeGroups[Source name],MATCH(2,OfficeGroups[Source rank],0)))),"")) | C26: =IF(Trends!$B$6<>"","",IF(COUNTIFS(OfficeGroups[Source rank],2)=1,IF(INDEX(OfficeGroups[Source UEI],MATCH(2,OfficeGroups[Source rank],0))="","Not supplied",INDEX(OfficeGroups[Source UEI],MATCH(2,OfficeGroups[Source rank],0))),"")) | D26: =IF(Trends!$B$6<>"","",IF(COUNTIFS(OfficeGroups[Source rank],2)=1,INDEX(OfficeGroups[Source net],MATCH(2,OfficeGroups[Source rank],0)),"")) | E26: =IF(Trends!$B$6<>"","",IF(COUNTIFS(OfficeGroups[Source rank],2)=1,INDEX(OfficeGroups[Source deobligations],MATCH(2,OfficeGroups[Source rank],0)),"")) | F26: =IF(Trends!$B$6<>"","",IF(COUNTIFS(OfficeGroups[Source rank],2)=1,INDEX(OfficeGroups[Source awards],MATCH(2,OfficeGroups[Source rank],0)),"")) | G26: =IF(Trends!$B$6<>"","",IF(COUNTIFS(OfficeGroups[Source rank],2)=1,INDEX(OfficeGroups[Source actions],MATCH(2,OfficeGroups[Source rank],0)),"")) | L26: =IF(H26="","",I26&IF(J26="",""," ["&J26&"]")) | M26: =IF(H26="","",SUMIFS(TransactionsData[Obligations],TransactionsData[Funding office ID],H26,TransactionsData[Selected],1)) | N26: =IF(H26="","",SUMIFS(TransactionsData[Deobligations],TransactionsData[Funding office ID],H26,TransactionsData[Selected],1)) | O26: =IF(H26="","",SUMIFS(TransactionsData[First office award],TransactionsData[Funding office ID],H26)) | P26: =IF(H26="","",COUNTIFS(TransactionsData[Funding office ID],H26,TransactionsData[Selected],1)) | Q26: =IF(OR(H26="",P26=0),"",COUNTIFS(OfficeGroups[Source net],">"&M26,OfficeGroups[Source actions],">0")+COUNTIFS(OfficeGroups[Source net],M26,OfficeGroups[Record ID],"<"&H26,OfficeGroups[Source actions],">0")+1) | R26: =IF(H26="",IF(COUNTA(I26:K26)>0,"Missing record ID",""),IF(COUNTIFS(OfficeGroups[Record ID],H26)<>1,"Duplicate record ID",IF(I26="","Add name","")))
A27: =IF(Trends!$B$6<>"","",IF(COUNTIFS(OfficeGroups[Source rank],3)=1,3,"")) | B27: =IF(Trends!$B$6<>"","",IF(COUNTIFS(OfficeGroups[Source rank],3)=1,IF(INDEX(OfficeGroups[Source URL],MATCH(3,OfficeGroups[Source rank],0))="",INDEX(OfficeGroups[Source name],MATCH(3,OfficeGroups[Source rank],0)),HYPERLINK(INDEX(OfficeGroups[Source URL],MATCH(3,OfficeGroups[Source rank],0)),INDEX(OfficeGroups[Source name],MATCH(3,OfficeGroups[Source rank],0)))),"")) | C27: =IF(Trends!$B$6<>"","",IF(COUNTIFS(OfficeGroups[Source rank],3)=1,IF(INDEX(OfficeGroups[Source UEI],MATCH(3,OfficeGroups[Source rank],0))="","Not supplied",INDEX(OfficeGroups[Source UEI],MATCH(3,OfficeGroups[Source rank],0))),"")) | D27: =IF(Trends!$B$6<>"","",IF(COUNTIFS(OfficeGroups[Source rank],3)=1,INDEX(OfficeGroups[Source net],MATCH(3,OfficeGroups[Source rank],0)),"")) | E27: =IF(Trends!$B$6<>"","",IF(COUNTIFS(OfficeGroups[Source rank],3)=1,INDEX(OfficeGroups[Source deobligations],MATCH(3,OfficeGroups[Source rank],0)),"")) | F27: =IF(Trends!$B$6<>"","",IF(COUNTIFS(OfficeGroups[Source rank],3)=1,INDEX(OfficeGroups[Source awards],MATCH(3,OfficeGroups[Source rank],0)),"")) | G27: =IF(Trends!$B$6<>"","",IF(COUNTIFS(OfficeGroups[Source rank],3)=1,INDEX(OfficeGroups[Source actions],MATCH(3,OfficeGroups[Source rank],0)),"")) | L27: =IF(H27="","",I27&IF(J27="",""," ["&J27&"]")) | M27: =IF(H27="","",SUMIFS(TransactionsData[Obligations],TransactionsData[Funding office ID],H27,TransactionsData[Selected],1)) | N27: =IF(H27="","",SUMIFS(TransactionsData[Deobligations],TransactionsData[Funding office ID],H27,TransactionsData[Selected],1)) | O27: =IF(H27="","",SUMIFS(TransactionsData[First office award],TransactionsData[Funding office ID],H27)) | P27: =IF(H27="","",COUNTIFS(TransactionsData[Funding office ID],H27,TransactionsData[Selected],1)) | Q27: =IF(OR(H27="",P27=0),"",COUNTIFS(OfficeGroups[Source net],">"&M27,OfficeGroups[Source actions],">0")+COUNTIFS(OfficeGroups[Source net],M27,OfficeGroups[Record ID],"<"&H27,OfficeGroups[Source actions],">0")+1) | R27: =IF(H27="",IF(COUNTA(I27:K27)>0,"Missing record ID",""),IF(COUNTIFS(OfficeGroups[Record ID],H27)<>1,"Duplicate record ID",IF(I27="","Add name","")))
A28: =IF(Trends!$B$6<>"","",IF(COUNTIFS(OfficeGroups[Source rank],4)=1,4,"")) | B28: =IF(Trends!$B$6<>"","",IF(COUNTIFS(OfficeGroups[Source rank],4)=1,IF(INDEX(OfficeGroups[Source URL],MATCH(4,OfficeGroups[Source rank],0))="",INDEX(OfficeGroups[Source name],MATCH(4,OfficeGroups[Source rank],0)),HYPERLINK(INDEX(OfficeGroups[Source URL],MATCH(4,OfficeGroups[Source rank],0)),INDEX(OfficeGroups[Source name],MATCH(4,OfficeGroups[Source rank],0)))),"")) | C28: =IF(Trends!$B$6<>"","",IF(COUNTIFS(OfficeGroups[Source rank],4)=1,IF(INDEX(OfficeGroups[Source UEI],MATCH(4,OfficeGroups[Source rank],0))="","Not supplied",INDEX(OfficeGroups[Source UEI],MATCH(4,OfficeGroups[Source rank],0))),"")) | D28: =IF(Trends!$B$6<>"","",IF(COUNTIFS(OfficeGroups[Source rank],4)=1,INDEX(OfficeGroups[Source net],MATCH(4,OfficeGroups[Source rank],0)),"")) | E28: =IF(Trends!$B$6<>"","",IF(COUNTIFS(OfficeGroups[Source rank],4)=1,INDEX(OfficeGroups[Source deobligations],MATCH(4,OfficeGroups[Source rank],0)),"")) | F28: =IF(Trends!$B$6<>"","",IF(COUNTIFS(OfficeGroups[Source rank],4)=1,INDEX(OfficeGroups[Source awards],MATCH(4,OfficeGroups[Source rank],0)),"")) | G28: =IF(Trends!$B$6<>"","",IF(COUNTIFS(OfficeGroups[Source rank],4)=1,INDEX(OfficeGroups[Source actions],MATCH(4,OfficeGroups[Source rank],0)),"")) | L28: =IF(H28="","",I28&IF(J28="",""," ["&J28&"]")) | M28: =IF(H28="","",SUMIFS(TransactionsData[Obligations],TransactionsData[Funding office ID],H28,TransactionsData[Selected],1)) | N28: =IF(H28="","",SUMIFS(TransactionsData[Deobligations],TransactionsData[Funding office ID],H28,TransactionsData[Selected],1)) | O28: =IF(H28="","",SUMIFS(TransactionsData[First office award],TransactionsData[Funding office ID],H28)) | P28: =IF(H28="","",COUNTIFS(TransactionsData[Funding office ID],H28,TransactionsData[Selected],1)) | Q28: =IF(OR(H28="",P28=0),"",COUNTIFS(OfficeGroups[Source net],">"&M28,OfficeGroups[Source actions],">0")+COUNTIFS(OfficeGroups[Source net],M28,OfficeGroups[Record ID],"<"&H28,OfficeGroups[Source actions],">0")+1) | R28: =IF(H28="",IF(COUNTA(I28:K28)>0,"Missing record ID",""),IF(COUNTIFS(OfficeGroups[Record ID],H28)<>1,"Duplicate record ID",IF(I28="","Add name","")))
A29: =IF(Trends!$B$6<>"","",IF(COUNTIFS(OfficeGroups[Source rank],5)=1,5,"")) | B29: =IF(Trends!$B$6<>"","",IF(COUNTIFS(OfficeGroups[Source rank],5)=1,IF(INDEX(OfficeGroups[Source URL],MATCH(5,OfficeGroups[Source rank],0))="",INDEX(OfficeGroups[Source name],MATCH(5,OfficeGroups[Source rank],0)),HYPERLINK(INDEX(OfficeGroups[Source URL],MATCH(5,OfficeGroups[Source rank],0)),INDEX(OfficeGroups[Source name],MATCH(5,OfficeGroups[Source rank],0)))),"")) | C29: =IF(Trends!$B$6<>"","",IF(COUNTIFS(OfficeGroups[Source rank],5)=1,IF(INDEX(OfficeGroups[Source UEI],MATCH(5,OfficeGroups[Source rank],0))="","Not supplied",INDEX(OfficeGroups[Source UEI],MATCH(5,OfficeGroups[Source rank],0))),"")) | D29: =IF(Trends!$B$6<>"","",IF(COUNTIFS(OfficeGroups[Source rank],5)=1,INDEX(OfficeGroups[Source net],MATCH(5,OfficeGroups[Source rank],0)),"")) | E29: =IF(Trends!$B$6<>"","",IF(COUNTIFS(OfficeGroups[Source rank],5)=1,INDEX(OfficeGroups[Source deobligations],MATCH(5,OfficeGroups[Source rank],0)),"")) | F29: =IF(Trends!$B$6<>"","",IF(COUNTIFS(OfficeGroups[Source rank],5)=1,INDEX(OfficeGroups[Source awards],MATCH(5,OfficeGroups[Source rank],0)),"")) | G29: =IF(Trends!$B$6<>"","",IF(COUNTIFS(OfficeGroups[Source rank],5)=1,INDEX(OfficeGroups[Source actions],MATCH(5,OfficeGroups[Source rank],0)),"")) | L29: =IF(H29="","",I29&IF(J29="",""," ["&J29&"]")) | M29: =IF(H29="","",SUMIFS(TransactionsData[Obligations],TransactionsData[Funding office ID],H29,TransactionsData[Selected],1)) | N29: =IF(H29="","",SUMIFS(TransactionsData[Deobligations],TransactionsData[Funding office ID],H29,TransactionsData[Selected],1)) | O29: =IF(H29="","",SUMIFS(TransactionsData[First office award],TransactionsData[Funding office ID],H29)) | P29: =IF(H29="","",COUNTIFS(TransactionsData[Funding office ID],H29,TransactionsData[Selected],1)) | Q29: =IF(OR(H29="",P29=0),"",COUNTIFS(OfficeGroups[Source net],">"&M29,OfficeGroups[Source actions],">0")+COUNTIFS(OfficeGroups[Source net],M29,OfficeGroups[Record ID],"<"&H29,OfficeGroups[Source actions],">0")+1) | R29: =IF(H29="",IF(COUNTA(I29:K29)>0,"Missing record ID",""),IF(COUNTIFS(OfficeGroups[Record ID],H29)<>1,"Duplicate record ID",IF(I29="","Add name","")))
A30: =IF(Trends!$B$6<>"","",IF(COUNTIFS(OfficeGroups[Source rank],6)=1,6,"")) | B30: =IF(Trends!$B$6<>"","",IF(COUNTIFS(OfficeGroups[Source rank],6)=1,IF(INDEX(OfficeGroups[Source URL],MATCH(6,OfficeGroups[Source rank],0))="",INDEX(OfficeGroups[Source name],MATCH(6,OfficeGroups[Source rank],0)),HYPERLINK(INDEX(OfficeGroups[Source URL],MATCH(6,OfficeGroups[Source rank],0)),INDEX(OfficeGroups[Source name],MATCH(6,OfficeGroups[Source rank],0)))),"")) | C30: =IF(Trends!$B$6<>"","",IF(COUNTIFS(OfficeGroups[Source rank],6)=1,IF(INDEX(OfficeGroups[Source UEI],MATCH(6,OfficeGroups[Source rank],0))="","Not supplied",INDEX(OfficeGroups[Source UEI],MATCH(6,OfficeGroups[Source rank],0))),"")) | D30: =IF(Trends!$B$6<>"","",IF(COUNTIFS(OfficeGroups[Source rank],6)=1,INDEX(OfficeGroups[Source net],MATCH(6,OfficeGroups[Source rank],0)),"")) | E30: =IF(Trends!$B$6<>"","",IF(COUNTIFS(OfficeGroups[Source rank],6)=1,INDEX(OfficeGroups[Source deobligations],MATCH(6,OfficeGroups[Source rank],0)),"")) | F30: =IF(Trends!$B$6<>"","",IF(COUNTIFS(OfficeGroups[Source rank],6)=1,INDEX(OfficeGroups[Source awards],MATCH(6,OfficeGroups[Source rank],0)),"")) | G30: =IF(Trends!$B$6<>"","",IF(COUNTIFS(OfficeGroups[Source rank],6)=1,INDEX(OfficeGroups[Source actions],MATCH(6,OfficeGroups[Source rank],0)),"")) | L30: =IF(H30="","",I30&IF(J30="",""," ["&J30&"]")) | M30: =IF(H30="","",SUMIFS(TransactionsData[Obligations],TransactionsData[Funding office ID],H30,TransactionsData[Selected],1)) | N30: =IF(H30="","",SUMIFS(TransactionsData[Deobligations],TransactionsData[Funding office ID],H30,TransactionsData[Selected],1)) | O30: =IF(H30="","",SUMIFS(TransactionsData[First office award],TransactionsData[Funding office ID],H30)) | P30: =IF(H30="","",COUNTIFS(TransactionsData[Funding office ID],H30,TransactionsData[Selected],1)) | Q30: =IF(OR(H30="",P30=0),"",COUNTIFS(OfficeGroups[Source net],">"&M30,OfficeGroups[Source actions],">0")+COUNTIFS(OfficeGroups[Source net],M30,OfficeGroups[Record ID],"<"&H30,OfficeGroups[Source actions],">0")+1) | R30: =IF(H30="",IF(COUNTA(I30:K30)>0,"Missing record ID",""),IF(COUNTIFS(OfficeGroups[Record ID],H30)<>1,"Duplicate record ID",IF(I30="","Add name","")))
A31: =IF(Trends!$B$6<>"","",IF(COUNTIFS(OfficeGroups[Source rank],7)=1,7,"")) | B31: =IF(Trends!$B$6<>"","",IF(COUNTIFS(OfficeGroups[Source rank],7)=1,IF(INDEX(OfficeGroups[Source URL],MATCH(7,OfficeGroups[Source rank],0))="",INDEX(OfficeGroups[Source name],MATCH(7,OfficeGroups[Source rank],0)),HYPERLINK(INDEX(OfficeGroups[Source URL],MATCH(7,OfficeGroups[Source rank],0)),INDEX(OfficeGroups[Source name],MATCH(7,OfficeGroups[Source rank],0)))),"")) | C31: =IF(Trends!$B$6<>"","",IF(COUNTIFS(OfficeGroups[Source rank],7)=1,IF(INDEX(OfficeGroups[Source UEI],MATCH(7,OfficeGroups[Source rank],0))="","Not supplied",INDEX(OfficeGroups[Source UEI],MATCH(7,OfficeGroups[Source rank],0))),"")) | D31: =IF(Trends!$B$6<>"","",IF(COUNTIFS(OfficeGroups[Source rank],7)=1,INDEX(OfficeGroups[Source net],MATCH(7,OfficeGroups[Source rank],0)),"")) | E31: =IF(Trends!$B$6<>"","",IF(COUNTIFS(OfficeGroups[Source rank],7)=1,INDEX(OfficeGroups[Source deobligations],MATCH(7,OfficeGroups[Source rank],0)),"")) | F31: =IF(Trends!$B$6<>"","",IF(COUNTIFS(OfficeGroups[Source rank],7)=1,INDEX(OfficeGroups[Source awards],MATCH(7,OfficeGroups[Source rank],0)),"")) | G31: =IF(Trends!$B$6<>"","",IF(COUNTIFS(OfficeGroups[Source rank],7)=1,INDEX(OfficeGroups[Source actions],MATCH(7,OfficeGroups[Source rank],0)),"")) | L31: =IF(H31="","",I31&IF(J31="",""," ["&J31&"]")) | M31: =IF(H31="","",SUMIFS(TransactionsData[Obligations],TransactionsData[Funding office ID],H31,TransactionsData[Selected],1)) | N31: =IF(H31="","",SUMIFS(TransactionsData[Deobligations],TransactionsData[Funding office ID],H31,TransactionsData[Selected],1)) | O31: =IF(H31="","",SUMIFS(TransactionsData[First office award],TransactionsData[Funding office ID],H31)) | P31: =IF(H31="","",COUNTIFS(TransactionsData[Funding office ID],H31,TransactionsData[Selected],1)) | Q31: =IF(OR(H31="",P31=0),"",COUNTIFS(OfficeGroups[Source net],">"&M31,OfficeGroups[Source actions],">0")+COUNTIFS(OfficeGroups[Source net],M31,OfficeGroups[Record ID],"<"&H31,OfficeGroups[Source actions],">0")+1) | R31: =IF(H31="",IF(COUNTA(I31:K31)>0,"Missing record ID",""),IF(COUNTIFS(OfficeGroups[Record ID],H31)<>1,"Duplicate record ID",IF(I31="","Add name","")))
A32: =IF(Trends!$B$6<>"","",IF(COUNTIFS(OfficeGroups[Source rank],8)=1,8,"")) | B32: =IF(Trends!$B$6<>"","",IF(COUNTIFS(OfficeGroups[Source rank],8)=1,IF(INDEX(OfficeGroups[Source URL],MATCH(8,OfficeGroups[Source rank],0))="",INDEX(OfficeGroups[Source name],MATCH(8,OfficeGroups[Source rank],0)),HYPERLINK(INDEX(OfficeGroups[Source URL],MATCH(8,OfficeGroups[Source rank],0)),INDEX(OfficeGroups[Source name],MATCH(8,OfficeGroups[Source rank],0)))),"")) | C32: =IF(Trends!$B$6<>"","",IF(COUNTIFS(OfficeGroups[Source rank],8)=1,IF(INDEX(OfficeGroups[Source UEI],MATCH(8,OfficeGroups[Source rank],0))="","Not supplied",INDEX(OfficeGroups[Source UEI],MATCH(8,OfficeGroups[Source rank],0))),"")) | D32: =IF(Trends!$B$6<>"","",IF(COUNTIFS(OfficeGroups[Source rank],8)=1,INDEX(OfficeGroups[Source net],MATCH(8,OfficeGroups[Source rank],0)),"")) | E32: =IF(Trends!$B$6<>"","",IF(COUNTIFS(OfficeGroups[Source rank],8)=1,INDEX(OfficeGroups[Source deobligations],MATCH(8,OfficeGroups[Source rank],0)),"")) | F32: =IF(Trends!$B$6<>"","",IF(COUNTIFS(OfficeGroups[Source rank],8)=1,INDEX(OfficeGroups[Source awards],MATCH(8,OfficeGroups[Source rank],0)),"")) | G32: =IF(Trends!$B$6<>"","",IF(COUNTIFS(OfficeGroups[Source rank],8)=1,INDEX(OfficeGroups[Source actions],MATCH(8,OfficeGroups[Source rank],0)),"")) | L32: =IF(H32="","",I32&IF(J32="",""," ["&J32&"]")) | M32: =IF(H32="","",SUMIFS(TransactionsData[Obligations],TransactionsData[Funding office ID],H32,TransactionsData[Selected],1)) | N32: =IF(H32="","",SUMIFS(TransactionsData[Deobligations],TransactionsData[Funding office ID],H32,TransactionsData[Selected],1)) | O32: =IF(H32="","",SUMIFS(TransactionsData[First office award],TransactionsData[Funding office ID],H32)) | P32: =IF(H32="","",COUNTIFS(TransactionsData[Funding office ID],H32,TransactionsData[Selected],1)) | Q32: =IF(OR(H32="",P32=0),"",COUNTIFS(OfficeGroups[Source net],">"&M32,OfficeGroups[Source actions],">0")+COUNTIFS(OfficeGroups[Source net],M32,OfficeGroups[Record ID],"<"&H32,OfficeGroups[Source actions],">0")+1) | R32: =IF(H32="",IF(COUNTA(I32:K32)>0,"Missing record ID",""),IF(COUNTIFS(OfficeGroups[Record ID],H32)<>1,"Duplicate record ID",IF(I32="","Add name","")))
A33: =IF(Trends!$B$6<>"","",IF(COUNTIFS(OfficeGroups[Source rank],9)=1,9,"")) | B33: =IF(Trends!$B$6<>"","",IF(COUNTIFS(OfficeGroups[Source rank],9)=1,IF(INDEX(OfficeGroups[Source URL],MATCH(9,OfficeGroups[Source rank],0))="",INDEX(OfficeGroups[Source name],MATCH(9,OfficeGroups[Source rank],0)),HYPERLINK(INDEX(OfficeGroups[Source URL],MATCH(9,OfficeGroups[Source rank],0)),INDEX(OfficeGroups[Source name],MATCH(9,OfficeGroups[Source rank],0)))),"")) | C33: =IF(Trends!$B$6<>"","",IF(COUNTIFS(OfficeGroups[Source rank],9)=1,IF(INDEX(OfficeGroups[Source UEI],MATCH(9,OfficeGroups[Source rank],0))="","Not supplied",INDEX(OfficeGroups[Source UEI],MATCH(9,OfficeGroups[Source rank],0))),"")) | D33: =IF(Trends!$B$6<>"","",IF(COUNTIFS(OfficeGroups[Source rank],9)=1,INDEX(OfficeGroups[Source net],MATCH(9,OfficeGroups[Source rank],0)),"")) | E33: =IF(Trends!$B$6<>"","",IF(COUNTIFS(OfficeGroups[Source rank],9)=1,INDEX(OfficeGroups[Source deobligations],MATCH(9,OfficeGroups[Source rank],0)),"")) | F33: =IF(Trends!$B$6<>"","",IF(COUNTIFS(OfficeGroups[Source rank],9)=1,INDEX(OfficeGroups[Source awards],MATCH(9,OfficeGroups[Source rank],0)),"")) | G33: =IF(Trends!$B$6<>"","",IF(COUNTIFS(OfficeGroups[Source rank],9)=1,INDEX(OfficeGroups[Source actions],MATCH(9,OfficeGroups[Source rank],0)),"")) | L33: =IF(H33="","",I33&IF(J33="",""," ["&J33&"]")) | M33: =IF(H33="","",SUMIFS(TransactionsData[Obligations],TransactionsData[Funding office ID],H33,TransactionsData[Selected],1)) | N33: =IF(H33="","",SUMIFS(TransactionsData[Deobligations],TransactionsData[Funding office ID],H33,TransactionsData[Selected],1)) | O33: =IF(H33="","",SUMIFS(TransactionsData[First office award],TransactionsData[Funding office ID],H33)) | P33: =IF(H33="","",COUNTIFS(TransactionsData[Funding office ID],H33,TransactionsData[Selected],1)) | Q33: =IF(OR(H33="",P33=0),"",COUNTIFS(OfficeGroups[Source net],">"&M33,OfficeGroups[Source actions],">0")+COUNTIFS(OfficeGroups[Source net],M33,OfficeGroups[Record ID],"<"&H33,OfficeGroups[Source actions],">0")+1) | R33: =IF(H33="",IF(COUNTA(I33:K33)>0,"Missing record ID",""),IF(COUNTIFS(OfficeGroups[Record ID],H33)<>1,"Duplicate record ID",IF(I33="","Add name","")))
A34: =IF(Trends!$B$6<>"","",IF(COUNTIFS(OfficeGroups[Source rank],10)=1,10,"")) | B34: =IF(Trends!$B$6<>"","",IF(COUNTIFS(OfficeGroups[Source rank],10)=1,IF(INDEX(OfficeGroups[Source URL],MATCH(10,OfficeGroups[Source rank],0))="",INDEX(OfficeGroups[Source name],MATCH(10,OfficeGroups[Source rank],0)),HYPERLINK(INDEX(OfficeGroups[Source URL],MATCH(10,OfficeGroups[Source rank],0)),INDEX(OfficeGroups[Source name],MATCH(10,OfficeGroups[Source rank],0)))),"")) | C34: =IF(Trends!$B$6<>"","",IF(COUNTIFS(OfficeGroups[Source rank],10)=1,IF(INDEX(OfficeGroups[Source UEI],MATCH(10,OfficeGroups[Source rank],0))="","Not supplied",INDEX(OfficeGroups[Source UEI],MATCH(10,OfficeGroups[Source rank],0))),"")) | D34: =IF(Trends!$B$6<>"","",IF(COUNTIFS(OfficeGroups[Source rank],10)=1,INDEX(OfficeGroups[Source net],MATCH(10,OfficeGroups[Source rank],0)),"")) | E34: =IF(Trends!$B$6<>"","",IF(COUNTIFS(OfficeGroups[Source rank],10)=1,INDEX(OfficeGroups[Source deobligations],MATCH(10,OfficeGroups[Source rank],0)),"")) | F34: =IF(Trends!$B$6<>"","",IF(COUNTIFS(OfficeGroups[Source rank],10)=1,INDEX(OfficeGroups[Source awards],MATCH(10,OfficeGroups[Source rank],0)),"")) | G34: =IF(Trends!$B$6<>"","",IF(COUNTIFS(OfficeGroups[Source rank],10)=1,INDEX(OfficeGroups[Source actions],MATCH(10,OfficeGroups[Source rank],0)),"")) | L34: =IF(H34="","",I34&IF(J34="",""," ["&J34&"]")) | M34: =IF(H34="","",SUMIFS(TransactionsData[Obligations],TransactionsData[Funding office ID],H34,TransactionsData[Selected],1)) | N34: =IF(H34="","",SUMIFS(TransactionsData[Deobligations],TransactionsData[Funding office ID],H34,TransactionsData[Selected],1)) | O34: =IF(H34="","",SUMIFS(TransactionsData[First office award],TransactionsData[Funding office ID],H34)) | P34: =IF(H34="","",COUNTIFS(TransactionsData[Funding office ID],H34,TransactionsData[Selected],1)) | Q34: =IF(OR(H34="",P34=0),"",COUNTIFS(OfficeGroups[Source net],">"&M34,OfficeGroups[Source actions],">0")+COUNTIFS(OfficeGroups[Source net],M34,OfficeGroups[Record ID],"<"&H34,OfficeGroups[Source actions],">0")+1) | R34: =IF(H34="",IF(COUNTA(I34:K34)>0,"Missing record ID",""),IF(COUNTIFS(OfficeGroups[Record ID],H34)<>1,"Duplicate record ID",IF(I34="","Add name","")))

Sheet Awards
A2: Awards
B3: ="Buyer: "&IF(Transactions!B3="","Not supplied",Transactions!B3)&" | Amount period: "&IF(Dashboard!$B$7="All","All covered years",IF(Dashboard!$B$7="","Not supplied","FY"&Dashboard!$B$7))&" | Award-type filter: "&Dashboard!$N$10 -> Buyer: Not supplied | Amount period: Not supplied | Award-type filter: All | H3: ="Buyer: "&IF(Transactions!B3="","Not supplied",Transactions!B3)&" | Amount period: "&IF(Dashboard!$B$7="All","All covered years",IF(Dashboard!$B$7="","Not supplied","FY"&Dashboard!$B$7))&" | Award-type filter: "&Dashboard!$N$10 -> Buyer: Not supplied | Amount period: Not supplied | Award-type filter: All
B4: ="Amount filter — vendor: "&Dashboard!H7 -> Amount filter — vendor: All | H4: ="Amount filter — vendor: "&Dashboard!H7 -> Amount filter — vendor: All
B5: ="Amount filter — funding office: "&Dashboard!B10 -> Amount filter — funding office: All | H5: ="Amount filter — funding office: "&Dashboard!B10 -> Amount filter — funding office: All
B6: All source awards are listed. Only amounts follow the filters; covered amounts span all covered dates. | H6: ="All source awards are listed. Current snapshots are unfiltered; retrieved "&IF(Transactions!G4="","Not supplied",TEXT(Transactions!G4,"mmm d, yyyy")) -> All source awards are listed. Current snapshots are unfiltered; retrieved Not supplied
A7: Award reference | B7: Vendor | C7: UEI | D7: Period obligations | E7: Covered obligations | F7: Current award type | G7: Current set-aside | H7: Performance state | I7: Current obligations | J7: Potential ceiling | K7: Award date | L7: Completion date | M7: Place of performance | N7: Parent vehicle | O7: PSC | P7: NAICS | Q7: Retrieved | R7: Award ID | S7: Original award reference | T7: Original vendor name | U7: Source URL | V7: Vendor URL | W7: Input check | X7: Period actions | Y7: Covered actions
A8: =IF(S8="","",IF(U8="",S8,HYPERLINK(U8,S8))) | B8: =IF(T8="","",IF(V8="",T8,HYPERLINK(V8,T8))) | D8: =IF(R8="","",IF(Trends!$B$6<>"","",SUMIFS(TransactionsData[Obligations],TransactionsData[Award ID],R8,TransactionsData[Selected],1))) | E8: =IF(R8="","",IF(Trends!$B$6<>"","",SUMIFS(TransactionsData[Obligations],TransactionsData[Award ID],R8,TransactionsData[Dimension match],1))) | W8: =IF(R8="",IF(COUNTA(C8,F8:V8)>0,"Missing award ID",""),IF(COUNTIFS(AwardsData[Award ID],R8)<>1,"Duplicate award ID",IF(OR(S8="",T8="",F8=""),"Add reference, vendor and award type",IF(OR(AND(I8<>"",NOT(ISNUMBER(I8))),AND(J8<>"",NOT(ISNUMBER(J8)))),"Use numeric snapshot amounts",IF(OR(COUNTIF(AwardTypeCategories,F8)<>1,COUNTIF(SetAsideCategories,G8)<>1,COUNTIF(PerformanceStateCategories,H8)<>1),"New category: refresh report",""))))) | X8: =IF(R8="","",COUNTIFS(TransactionsData[Award ID],R8,TransactionsData[Selected],1)) | Y8: =IF(R8="","",COUNTIFS(TransactionsData[Award ID],R8,TransactionsData[Dimension match],1))
A9: =IF(S9="","",IF(U9="",S9,HYPERLINK(U9,S9))) | B9: =IF(T9="","",IF(V9="",T9,HYPERLINK(V9,T9))) | D9: =IF(R9="","",IF(Trends!$B$6<>"","",SUMIFS(TransactionsData[Obligations],TransactionsData[Award ID],R9,TransactionsData[Selected],1))) | E9: =IF(R9="","",IF(Trends!$B$6<>"","",SUMIFS(TransactionsData[Obligations],TransactionsData[Award ID],R9,TransactionsData[Dimension match],1))) | W9: =IF(R9="",IF(COUNTA(C9,F9:V9)>0,"Missing award ID",""),IF(COUNTIFS(AwardsData[Award ID],R9)<>1,"Duplicate award ID",IF(OR(S9="",T9="",F9=""),"Add reference, vendor and award type",IF(OR(AND(I9<>"",NOT(ISNUMBER(I9))),AND(J9<>"",NOT(ISNUMBER(J9)))),"Use numeric snapshot amounts",IF(OR(COUNTIF(AwardTypeCategories,F9)<>1,COUNTIF(SetAsideCategories,G9)<>1,COUNTIF(PerformanceStateCategories,H9)<>1),"New category: refresh report",""))))) | X9: =IF(R9="","",COUNTIFS(TransactionsData[Award ID],R9,TransactionsData[Selected],1)) | Y9: =IF(R9="","",COUNTIFS(TransactionsData[Award ID],R9,TransactionsData[Dimension match],1))
A10: =IF(S10="","",IF(U10="",S10,HYPERLINK(U10,S10))) | B10: =IF(T10="","",IF(V10="",T10,HYPERLINK(V10,T10))) | D10: =IF(R10="","",IF(Trends!$B$6<>"","",SUMIFS(TransactionsData[Obligations],TransactionsData[Award ID],R10,TransactionsData[Selected],1))) | E10: =IF(R10="","",IF(Trends!$B$6<>"","",SUMIFS(TransactionsData[Obligations],TransactionsData[Award ID],R10,TransactionsData[Dimension match],1))) | W10: =IF(R10="",IF(COUNTA(C10,F10:V10)>0,"Missing award ID",""),IF(COUNTIFS(AwardsData[Award ID],R10)<>1,"Duplicate award ID",IF(OR(S10="",T10="",F10=""),"Add reference, vendor and award type",IF(OR(AND(I10<>"",NOT(ISNUMBER(I10))),AND(J10<>"",NOT(ISNUMBER(J10)))),"Use numeric snapshot amounts",IF(OR(COUNTIF(AwardTypeCategories,F10)<>1,COUNTIF(SetAsideCategories,G10)<>1,COUNTIF(PerformanceStateCategories,H10)<>1),"New category: refresh report",""))))) | X10: =IF(R10="","",COUNTIFS(TransactionsData[Award ID],R10,TransactionsData[Selected],1)) | Y10: =IF(R10="","",COUNTIFS(TransactionsData[Award ID],R10,TransactionsData[Dimension match],1))
A11: =IF(S11="","",IF(U11="",S11,HYPERLINK(U11,S11))) | B11: =IF(T11="","",IF(V11="",T11,HYPERLINK(V11,T11))) | D11: =IF(R11="","",IF(Trends!$B$6<>"","",SUMIFS(TransactionsData[Obligations],TransactionsData[Award ID],R11,TransactionsData[Selected],1))) | E11: =IF(R11="","",IF(Trends!$B$6<>"","",SUMIFS(TransactionsData[Obligations],TransactionsData[Award ID],R11,TransactionsData[Dimension match],1))) | W11: =IF(R11="",IF(COUNTA(C11,F11:V11)>0,"Missing award ID",""),IF(COUNTIFS(AwardsData[Award ID],R11)<>1,"Duplicate award ID",IF(OR(S11="",T11="",F11=""),"Add reference, vendor and award type",IF(OR(AND(I11<>"",NOT(ISNUMBER(I11))),AND(J11<>"",NOT(ISNUMBER(J11)))),"Use numeric snapshot amounts",IF(OR(COUNTIF(AwardTypeCategories,F11)<>1,COUNTIF(SetAsideCategories,G11)<>1,COUNTIF(PerformanceStateCategories,H11)<>1),"New category: refresh report",""))))) | X11: =IF(R11="","",COUNTIFS(TransactionsData[Award ID],R11,TransactionsData[Selected],1)) | Y11: =IF(R11="","",COUNTIFS(TransactionsData[Award ID],R11,TransactionsData[Dimension match],1))
A12: =IF(S12="","",IF(U12="",S12,HYPERLINK(U12,S12))) | B12: =IF(T12="","",IF(V12="",T12,HYPERLINK(V12,T12))) | D12: =IF(R12="","",IF(Trends!$B$6<>"","",SUMIFS(TransactionsData[Obligations],TransactionsData[Award ID],R12,TransactionsData[Selected],1))) | E12: =IF(R12="","",IF(Trends!$B$6<>"","",SUMIFS(TransactionsData[Obligations],TransactionsData[Award ID],R12,TransactionsData[Dimension match],1))) | W12: =IF(R12="",IF(COUNTA(C12,F12:V12)>0,"Missing award ID",""),IF(COUNTIFS(AwardsData[Award ID],R12)<>1,"Duplicate award ID",IF(OR(S12="",T12="",F12=""),"Add reference, vendor and award type",IF(OR(AND(I12<>"",NOT(ISNUMBER(I12))),AND(J12<>"",NOT(ISNUMBER(J12)))),"Use numeric snapshot amounts",IF(OR(COUNTIF(AwardTypeCategories,F12)<>1,COUNTIF(SetAsideCategories,G12)<>1,COUNTIF(PerformanceStateCategories,H12)<>1),"New category: refresh report",""))))) | X12: =IF(R12="","",COUNTIFS(TransactionsData[Award ID],R12,TransactionsData[Selected],1)) | Y12: =IF(R12="","",COUNTIFS(TransactionsData[Award ID],R12,TransactionsData[Dimension match],1))
A13: =IF(S13="","",IF(U13="",S13,HYPERLINK(U13,S13))) | B13: =IF(T13="","",IF(V13="",T13,HYPERLINK(V13,T13))) | D13: =IF(R13="","",IF(Trends!$B$6<>"","",SUMIFS(TransactionsData[Obligations],TransactionsData[Award ID],R13,TransactionsData[Selected],1))) | E13: =IF(R13="","",IF(Trends!$B$6<>"","",SUMIFS(TransactionsData[Obligations],TransactionsData[Award ID],R13,TransactionsData[Dimension match],1))) | W13: =IF(R13="",IF(COUNTA(C13,F13:V13)>0,"Missing award ID",""),IF(COUNTIFS(AwardsData[Award ID],R13)<>1,"Duplicate award ID",IF(OR(S13="",T13="",F13=""),"Add reference, vendor and award type",IF(OR(AND(I13<>"",NOT(ISNUMBER(I13))),AND(J13<>"",NOT(ISNUMBER(J13)))),"Use numeric snapshot amounts",IF(OR(COUNTIF(AwardTypeCategories,F13)<>1,COUNTIF(SetAsideCategories,G13)<>1,COUNTIF(PerformanceStateCategories,H13)<>1),"New category: refresh report",""))))) | X13: =IF(R13="","",COUNTIFS(TransactionsData[Award ID],R13,TransactionsData[Selected],1)) | Y13: =IF(R13="","",COUNTIFS(TransactionsData[Award ID],R13,TransactionsData[Dimension match],1))
A14: =IF(S14="","",IF(U14="",S14,HYPERLINK(U14,S14))) | B14: =IF(T14="","",IF(V14="",T14,HYPERLINK(V14,T14))) | D14: =IF(R14="","",IF(Trends!$B$6<>"","",SUMIFS(TransactionsData[Obligations],TransactionsData[Award ID],R14,TransactionsData[Selected],1))) | E14: =IF(R14="","",IF(Trends!$B$6<>"","",SUMIFS(TransactionsData[Obligations],TransactionsData[Award ID],R14,TransactionsData[Dimension match],1))) | W14: =IF(R14="",IF(COUNTA(C14,F14:V14)>0,"Missing award ID",""),IF(COUNTIFS(AwardsData[Award ID],R14)<>1,"Duplicate award ID",IF(OR(S14="",T14="",F14=""),"Add reference, vendor and award type",IF(OR(AND(I14<>"",NOT(ISNUMBER(I14))),AND(J14<>"",NOT(ISNUMBER(J14)))),"Use numeric snapshot amounts",IF(OR(COUNTIF(AwardTypeCategories,F14)<>1,COUNTIF(SetAsideCategories,G14)<>1,COUNTIF(PerformanceStateCategories,H14)<>1),"New category: refresh report",""))))) | X14: =IF(R14="","",COUNTIFS(TransactionsData[Award ID],R14,TransactionsData[Selected],1)) | Y14: =IF(R14="","",COUNTIFS(TransactionsData[Award ID],R14,TransactionsData[Dimension match],1))
A15: =IF(S15="","",IF(U15="",S15,HYPERLINK(U15,S15))) | B15: =IF(T15="","",IF(V15="",T15,HYPERLINK(V15,T15))) | D15: =IF(R15="","",IF(Trends!$B$6<>"","",SUMIFS(TransactionsData[Obligations],TransactionsData[Award ID],R15,TransactionsData[Selected],1))) | E15: =IF(R15="","",IF(Trends!$B$6<>"","",SUMIFS(TransactionsData[Obligations],TransactionsData[Award ID],R15,TransactionsData[Dimension match],1))) | W15: =IF(R15="",IF(COUNTA(C15,F15:V15)>0,"Missing award ID",""),IF(COUNTIFS(AwardsData[Award ID],R15)<>1,"Duplicate award ID",IF(OR(S15="",T15="",F15=""),"Add reference, vendor and award type",IF(OR(AND(I15<>"",NOT(ISNUMBER(I15))),AND(J15<>"",NOT(ISNUMBER(J15)))),"Use numeric snapshot amounts",IF(OR(COUNTIF(AwardTypeCategories,F15)<>1,COUNTIF(SetAsideCategories,G15)<>1,COUNTIF(PerformanceStateCategories,H15)<>1),"New category: refresh report",""))))) | X15: =IF(R15="","",COUNTIFS(TransactionsData[Award ID],R15,TransactionsData[Selected],1)) | Y15: =IF(R15="","",COUNTIFS(TransactionsData[Award ID],R15,TransactionsData[Dimension match],1))
A16: =IF(S16="","",IF(U16="",S16,HYPERLINK(U16,S16))) | B16: =IF(T16="","",IF(V16="",T16,HYPERLINK(V16,T16))) | D16: =IF(R16="","",IF(Trends!$B$6<>"","",SUMIFS(TransactionsData[Obligations],TransactionsData[Award ID],R16,TransactionsData[Selected],1))) | E16: =IF(R16="","",IF(Trends!$B$6<>"","",SUMIFS(TransactionsData[Obligations],TransactionsData[Award ID],R16,TransactionsData[Dimension match],1))) | W16: =IF(R16="",IF(COUNTA(C16,F16:V16)>0,"Missing award ID",""),IF(COUNTIFS(AwardsData[Award ID],R16)<>1,"Duplicate award ID",IF(OR(S16="",T16="",F16=""),"Add reference, vendor and award type",IF(OR(AND(I16<>"",NOT(ISNUMBER(I16))),AND(J16<>"",NOT(ISNUMBER(J16)))),"Use numeric snapshot amounts",IF(OR(COUNTIF(AwardTypeCategories,F16)<>1,COUNTIF(SetAsideCategories,G16)<>1,COUNTIF(PerformanceStateCategories,H16)<>1),"New category: refresh report",""))))) | X16: =IF(R16="","",COUNTIFS(TransactionsData[Award ID],R16,TransactionsData[Selected],1)) | Y16: =IF(R16="","",COUNTIFS(TransactionsData[Award ID],R16,TransactionsData[Dimension match],1))
A17: =IF(S17="","",IF(U17="",S17,HYPERLINK(U17,S17))) | B17: =IF(T17="","",IF(V17="",T17,HYPERLINK(V17,T17))) | D17: =IF(R17="","",IF(Trends!$B$6<>"","",SUMIFS(TransactionsData[Obligations],TransactionsData[Award ID],R17,TransactionsData[Selected],1))) | E17: =IF(R17="","",IF(Trends!$B$6<>"","",SUMIFS(TransactionsData[Obligations],TransactionsData[Award ID],R17,TransactionsData[Dimension match],1))) | W17: =IF(R17="",IF(COUNTA(C17,F17:V17)>0,"Missing award ID",""),IF(COUNTIFS(AwardsData[Award ID],R17)<>1,"Duplicate award ID",IF(OR(S17="",T17="",F17=""),"Add reference, vendor and award type",IF(OR(AND(I17<>"",NOT(ISNUMBER(I17))),AND(J17<>"",NOT(ISNUMBER(J17)))),"Use numeric snapshot amounts",IF(OR(COUNTIF(AwardTypeCategories,F17)<>1,COUNTIF(SetAsideCategories,G17)<>1,COUNTIF(PerformanceStateCategories,H17)<>1),"New category: refresh report",""))))) | X17: =IF(R17="","",COUNTIFS(TransactionsData[Award ID],R17,TransactionsData[Selected],1)) | Y17: =IF(R17="","",COUNTIFS(TransactionsData[Award ID],R17,TransactionsData[Dimension match],1))
A18: =IF(S18="","",IF(U18="",S18,HYPERLINK(U18,S18))) | B18: =IF(T18="","",IF(V18="",T18,HYPERLINK(V18,T18))) | D18: =IF(R18="","",IF(Trends!$B$6<>"","",SUMIFS(TransactionsData[Obligations],TransactionsData[Award ID],R18,TransactionsData[Selected],1))) | E18: =IF(R18="","",IF(Trends!$B$6<>"","",SUMIFS(TransactionsData[Obligations],TransactionsData[Award ID],R18,TransactionsData[Dimension match],1))) | W18: =IF(R18="",IF(COUNTA(C18,F18:V18)>0,"Missing award ID",""),IF(COUNTIFS(AwardsData[Award ID],R18)<>1,"Duplicate award ID",IF(OR(S18="",T18="",F18=""),"Add reference, vendor and award type",IF(OR(AND(I18<>"",NOT(ISNUMBER(I18))),AND(J18<>"",NOT(ISNUMBER(J18)))),"Use numeric snapshot amounts",IF(OR(COUNTIF(AwardTypeCategories,F18)<>1,COUNTIF(SetAsideCategories,G18)<>1,COUNTIF(PerformanceStateCategories,H18)<>1),"New category: refresh report",""))))) | X18: =IF(R18="","",COUNTIFS(TransactionsData[Award ID],R18,TransactionsData[Selected],1)) | Y18: =IF(R18="","",COUNTIFS(TransactionsData[Award ID],R18,TransactionsData[Dimension match],1))
A19: =IF(S19="","",IF(U19="",S19,HYPERLINK(U19,S19))) | B19: =IF(T19="","",IF(V19="",T19,HYPERLINK(V19,T19))) | D19: =IF(R19="","",IF(Trends!$B$6<>"","",SUMIFS(TransactionsData[Obligations],TransactionsData[Award ID],R19,TransactionsData[Selected],1))) | E19: =IF(R19="","",IF(Trends!$B$6<>"","",SUMIFS(TransactionsData[Obligations],TransactionsData[Award ID],R19,TransactionsData[Dimension match],1))) | W19: =IF(R19="",IF(COUNTA(C19,F19:V19)>0,"Missing award ID",""),IF(COUNTIFS(AwardsData[Award ID],R19)<>1,"Duplicate award ID",IF(OR(S19="",T19="",F19=""),"Add reference, vendor and award type",IF(OR(AND(I19<>"",NOT(ISNUMBER(I19))),AND(J19<>"",NOT(ISNUMBER(J19)))),"Use numeric snapshot amounts",IF(OR(COUNTIF(AwardTypeCategories,F19)<>1,COUNTIF(SetAsideCategories,G19)<>1,COUNTIF(PerformanceStateCategories,H19)<>1),"New category: refresh report",""))))) | X19: =IF(R19="","",COUNTIFS(TransactionsData[Award ID],R19,TransactionsData[Selected],1)) | Y19: =IF(R19="","",COUNTIFS(TransactionsData[Award ID],R19,TransactionsData[Dimension match],1))
... A22: =IF(S22="","",IF(U22="",S22,HYPERLINK(U22,S22))) | B22: =IF(T22="","",IF(V22="",T22,HYPERLINK(V22,T22))) | D22: =IF(R22="","",IF(Trends!$B$6<>"","",SUMIFS(TransactionsData[Obligations],TransactionsData[Award ID],R22,TransactionsData[Selected],1))) | E22: =IF(R22="","",IF(Trends!$B$6<>"","",SUMIFS(TransactionsData[Obligations],TransactionsData[Award ID],R22,TransactionsData[Dimension match],1))) | W22: =IF(R22="",IF(COUNTA(C22,F22:V22)>0,"Missing award ID",""),IF(COUNTIFS(AwardsData[Award ID],R22)<>1,"Duplicate award ID",IF(OR(S22="",T22="",F22=""),"Add reference, vendor and award type",IF(OR(AND(I22<>"",NOT(ISNUMBER(I22))),AND(J22<>"",NOT(ISNUMBER(J22)))),"Use numeric snapshot amounts",IF(OR(COUNTIF(AwardTypeCategories,F22)<>1,COUNTIF(SetAsideCategories,G22)<>1,COUNTIF(PerformanceStateCategories,H22)<>1),"New category: refresh report",""))))) | X22: =IF(R22="","",COUNTIFS(TransactionsData[Award ID],R22,TransactionsData[Selected],1)) | Y22: =IF(R22="","",COUNTIFS(TransactionsData[Award ID],R22,TransactionsData[Dimension match],1))

Sheet Transactions
A2: Transactions
A3: Buyer | F3: Scope
A4: From | C4: Through | F4: Retrieved
A6: Add the buyer, work scope, reporting dates and reviewed source records.
A7: Net obligations include deobligations. They are not cash payments, award ceilings or vendor revenue.
A9: Included | B9: =SUM(TransactionsData[Eligible]) -> 0 | C9: Excluded actions | D9: =COUNTIFS(TransactionsData[Inclusion],"Exclude") -> 0 | F9: Excluded dollars | G9: =SUMIFS(TransactionsData[Obligations],TransactionsData[Inclusion],"Exclude") -> 0
A10: Row total | B10: =IF(COUNTA(TransactionsData[Transaction ID])=0,"",SUMIFS(TransactionsData[Obligations],TransactionsData[Eligible],1)) | C10: Search aggregate | F10: Difference | G10: =IF(D10="","",B10-D10)
A12: Record exclusions and source reconciliation here. Keep excluded rows in the ledger.
A14: Blue: report settings. Green: source inputs. Gray: calculations. Expand grouped columns for IDs and calculation steps.
A15: ="Source ledger: "&IF(Transactions!B3="","Not supplied",Transactions!B3)&" | "&IF(Transactions!B4="","Not supplied",TEXT(Transactions!B4,"mmm d, yyyy"))&" through "&IF(Transactions!D4="","Not supplied",TEXT(Transactions!D4,"mmm d, yyyy"))&CHAR(10)&"All retrieved rows are retained. Dashboard filters do not narrow this table; its own filters control visible rows." -> Source ledger: Not supplied | Not supplied through Not supplied All retrieved rows are retained. Dashboard filters do not narrow this table; its own filters control visible rows.
A16: Date | B16: Award reference | C16: Vendor | D16: UEI | E16: Funding office | F16: Obligations | G16: Inclusion | H16: Exclusion reason | I16: Transaction ID | J16: Award ID | K16: Vendor ID | L16: Funding office ID | M16: Original award reference | N16: Original vendor name | O16: Original office name | P16: Award URL | Q16: Vendor URL | R16: Office URL | S16: FY | T16: Quarter | U16: Input check | V16: Eligible | W16: Current award type | X16: Current set-aside | Y16: Performance state | Z16: Dimension match | AA16: Selected | AB16: Nonzero | AC16: First selected award | AD16: First selected vendor | AE16: First annual award | AF16: First annual vendor | AG16: First office award | AH16: First vendor award | AI16: Positive | AJ16: Deobligations
B17: =IF(M17="","",IF(P17="",M17,HYPERLINK(P17,M17))) | C17: =IF(N17="","",IF(Q17="",N17,HYPERLINK(Q17,N17))) | E17: =IF(O17="","",IF(R17="",O17,HYPERLINK(R17,O17))) | S17: =IF(ISNUMBER(A17),YEAR(A17)+IF(MONTH(A17)>=10,1,0),"") | T17: =IF(ISNUMBER(A17),INT(MOD(MONTH(A17)-10,12)/3)+1,"") | U17: =IF(AND(I17<>"",D17<>"",OR(COUNTIFS(TransactionsData[Vendor ID],K17,TransactionsData[UEI],"<>"&D17,TransactionsData[UEI],"?*")>0,COUNTIFS(VendorGroups[Record ID],K17,VendorGroups[Source UEI],"<>"&D17,VendorGroups[Source UEI],"?*")>0)),"Conflicting vendor UEIs",IF(I17="",IF(COUNTA(A17,D17,F17:R17)>0,"Missing transaction ID",""),IF(COUNTIFS(TransactionsData[Transaction ID],I17)<>1,"Duplicate transaction ID",IF(OR(NOT(ISNUMBER(A17)),A17<1,A17>DATE(2099,1,1)),"Use a valid date",IF(OR(A17<$B$4,A17>$D$4),"Outside coverage",IF(NOT(ISNUMBER(F17)),"Missing or invalid amount",IF(OR(K17="",L17="",N17=""),"Add vendor and office identities",IF(G17="Exclude",IF(OR(F17<>0,H17=""),"Review nonzero or unexplained exclusion",""),IF(G17<>"Include","Choose Include or Exclude",IF(COUNTIFS(AwardsData[Award ID],J17)<>1,"Award link needs review",IF(INDEX(AwardsData[Input check],MATCH(J17,AwardsData[Award ID],0))<>"","Check award inputs",""))))))))))) | V17: =IF(AND(I17<>"",U17="",G17="Include"),1,0) -> 0 | W17: =IF(I17="","",IF(COUNTIFS(AwardsData[Award ID],J17)=1,INDEX(AwardsData[Current award type],MATCH(J17,AwardsData[Award ID],0)),"Unlinked")) | X17: =IF(I17="","",IF(COUNTIFS(AwardsData[Award ID],J17)=1,INDEX(AwardsData[Current set-aside],MATCH(J17,AwardsData[Award ID],0)),"Unlinked")) | Y17: =IF(I17="","",IF(COUNTIFS(AwardsData[Award ID],J17)=1,INDEX(AwardsData[Performance state],MATCH(J17,AwardsData[Award ID],0)),"Unlinked")) | Z17: =IF(AND(V17=1,OR(Dashboard!$AB$2="All",K17=Dashboard!$AB$2),OR(Dashboard!$AB$3="All",L17=Dashboard!$AB$3),OR(Dashboard!$N$10="All",W17=Dashboard!$N$10)),1,0) -> 0 | AA17: =IF(AND(Z17=1,OR(Dashboard!$B$7="All",S17=Dashboard!$B$7)),1,0) -> 0 | AB17: =IF(AND(V17=1,F17<>0),1,0) -> 0 | AC17: =IF(AND(AA17=1,AB17=1),IF(COUNTIFS($J$17:J17,J17,$AA$17:AA17,1,$AB$17:AB17,1)=1,1,0),0) -> 0 | AD17: =IF(AND(AA17=1,AB17=1),IF(COUNTIFS($K$17:K17,K17,$AA$17:AA17,1,$AB$17:AB17,1)=1,1,0),0) -> 0 | AE17: =IF(AND(Z17=1,AB17=1),IF(COUNTIFS($J$17:J17,J17,$S$17:S17,S17,$Z$17:Z17,1,$AB$17:AB17,1)=1,1,0),0) -> 0 | AF17: =IF(AND(Z17=1,AB17=1),IF(COUNTIFS($K$17:K17,K17,$S$17:S17,S17,$Z$17:Z17,1,$AB$17:AB17,1)=1,1,0),0) -> 0 | AG17: =IF(AND(AA17=1,AB17=1),IF(COUNTIFS($J$17:J17,J17,$L$17:L17,L17,$AA$17:AA17,1,$AB$17:AB17,1)=1,1,0),0) -> 0 | AH17: =IF(AND(AA17=1,AB17=1),IF(COUNTIFS($J$17:J17,J17,$K$17:K17,K17,$AA$17:AA17,1,$AB$17:AB17,1)=1,1,0),0) -> 0 | AI17: =IF(V17=1,MAX(F17,0),0) -> 0 | AJ17: =IF(V17=1,MIN(F17,0),0) -> 0
B18: =IF(M18="","",IF(P18="",M18,HYPERLINK(P18,M18))) | C18: =IF(N18="","",IF(Q18="",N18,HYPERLINK(Q18,N18))) | E18: =IF(O18="","",IF(R18="",O18,HYPERLINK(R18,O18))) | S18: =IF(ISNUMBER(A18),YEAR(A18)+IF(MONTH(A18)>=10,1,0),"") | T18: =IF(ISNUMBER(A18),INT(MOD(MONTH(A18)-10,12)/3)+1,"") | U18: =IF(AND(I18<>"",D18<>"",OR(COUNTIFS(TransactionsData[Vendor ID],K18,TransactionsData[UEI],"<>"&D18,TransactionsData[UEI],"?*")>0,COUNTIFS(VendorGroups[Record ID],K18,VendorGroups[Source UEI],"<>"&D18,VendorGroups[Source UEI],"?*")>0)),"Conflicting vendor UEIs",IF(I18="",IF(COUNTA(A18,D18,F18:R18)>0,"Missing transaction ID",""),IF(COUNTIFS(TransactionsData[Transaction ID],I18)<>1,"Duplicate transaction ID",IF(OR(NOT(ISNUMBER(A18)),A18<1,A18>DATE(2099,1,1)),"Use a valid date",IF(OR(A18<$B$4,A18>$D$4),"Outside coverage",IF(NOT(ISNUMBER(F18)),"Missing or invalid amount",IF(OR(K18="",L18="",N18=""),"Add vendor and office identities",IF(G18="Exclude",IF(OR(F18<>0,H18=""),"Review nonzero or unexplained exclusion",""),IF(G18<>"Include","Choose Include or Exclude",IF(COUNTIFS(AwardsData[Award ID],J18)<>1,"Award link needs review",IF(INDEX(AwardsData[Input check],MATCH(J18,AwardsData[Award ID],0))<>"","Check award inputs",""))))))))))) | V18: =IF(AND(I18<>"",U18="",G18="Include"),1,0) -> 0 | W18: =IF(I18="","",IF(COUNTIFS(AwardsData[Award ID],J18)=1,INDEX(AwardsData[Current award type],MATCH(J18,AwardsData[Award ID],0)),"Unlinked")) | X18: =IF(I18="","",IF(COUNTIFS(AwardsData[Award ID],J18)=1,INDEX(AwardsData[Current set-aside],MATCH(J18,AwardsData[Award ID],0)),"Unlinked")) | Y18: =IF(I18="","",IF(COUNTIFS(AwardsData[Award ID],J18)=1,INDEX(AwardsData[Performance state],MATCH(J18,AwardsData[Award ID],0)),"Unlinked")) | Z18: =IF(AND(V18=1,OR(Dashboard!$AB$2="All",K18=Dashboard!$AB$2),OR(Dashboard!$AB$3="All",L18=Dashboard!$AB$3),OR(Dashboard!$N$10="All",W18=Dashboard!$N$10)),1,0) -> 0 | AA18: =IF(AND(Z18=1,OR(Dashboard!$B$7="All",S18=Dashboard!$B$7)),1,0) -> 0 | AB18: =IF(AND(V18=1,F18<>0),1,0) -> 0 | AC18: =IF(AND(AA18=1,AB18=1),IF(COUNTIFS($J$17:J18,J18,$AA$17:AA18,1,$AB$17:AB18,1)=1,1,0),0) -> 0 | AD18: =IF(AND(AA18=1,AB18=1),IF(COUNTIFS($K$17:K18,K18,$AA$17:AA18,1,$AB$17:AB18,1)=1,1,0),0) -> 0 | AE18: =IF(AND(Z18=1,AB18=1),IF(COUNTIFS($J$17:J18,J18,$S$17:S18,S18,$Z$17:Z18,1,$AB$17:AB18,1)=1,1,0),0) -> 0 | AF18: =IF(AND(Z18=1,AB18=1),IF(COUNTIFS($K$17:K18,K18,$S$17:S18,S18,$Z$17:Z18,1,$AB$17:AB18,1)=1,1,0),0) -> 0 | AG18: =IF(AND(AA18=1,AB18=1),IF(COUNTIFS($J$17:J18,J18,$L$17:L18,L18,$AA$17:AA18,1,$AB$17:AB18,1)=1,1,0),0) -> 0 | AH18: =IF(AND(AA18=1,AB18=1),IF(COUNTIFS($J$17:J18,J18,$K$17:K18,K18,$AA$17:AA18,1,$AB$17:AB18,1)=1,1,0),0) -> 0 | AI18: =IF(V18=1,MAX(F18,0),0) -> 0 | AJ18: =IF(V18=1,MIN(F18,0),0) -> 0
B19: =IF(M19="","",IF(P19="",M19,HYPERLINK(P19,M19))) | C19: =IF(N19="","",IF(Q19="",N19,HYPERLINK(Q19,N19))) | E19: =IF(O19="","",IF(R19="",O19,HYPERLINK(R19,O19))) | S19: =IF(ISNUMBER(A19),YEAR(A19)+IF(MONTH(A19)>=10,1,0),"") | T19: =IF(ISNUMBER(A19),INT(MOD(MONTH(A19)-10,12)/3)+1,"") | U19: =IF(AND(I19<>"",D19<>"",OR(COUNTIFS(TransactionsData[Vendor ID],K19,TransactionsData[UEI],"<>"&D19,TransactionsData[UEI],"?*")>0,COUNTIFS(VendorGroups[Record ID],K19,VendorGroups[Source UEI],"<>"&D19,VendorGroups[Source UEI],"?*")>0)),"Conflicting vendor UEIs",IF(I19="",IF(COUNTA(A19,D19,F19:R19)>0,"Missing transaction ID",""),IF(COUNTIFS(TransactionsData[Transaction ID],I19)<>1,"Duplicate transaction ID",IF(OR(NOT(ISNUMBER(A19)),A19<1,A19>DATE(2099,1,1)),"Use a valid date",IF(OR(A19<$B$4,A19>$D$4),"Outside coverage",IF(NOT(ISNUMBER(F19)),"Missing or invalid amount",IF(OR(K19="",L19="",N19=""),"Add vendor and office identities",IF(G19="Exclude",IF(OR(F19<>0,H19=""),"Review nonzero or unexplained exclusion",""),IF(G19<>"Include","Choose Include or Exclude",IF(COUNTIFS(AwardsData[Award ID],J19)<>1,"Award link needs review",IF(INDEX(AwardsData[Input check],MATCH(J19,AwardsData[Award ID],0))<>"","Check award inputs",""))))))))))) | V19: =IF(AND(I19<>"",U19="",G19="Include"),1,0) -> 0 | W19: =IF(I19="","",IF(COUNTIFS(AwardsData[Award ID],J19)=1,INDEX(AwardsData[Current award type],MATCH(J19,AwardsData[Award ID],0)),"Unlinked")) | X19: =IF(I19="","",IF(COUNTIFS(AwardsData[Award ID],J19)=1,INDEX(AwardsData[Current set-aside],MATCH(J19,AwardsData[Award ID],0)),"Unlinked")) | Y19: =IF(I19="","",IF(COUNTIFS(AwardsData[Award ID],J19)=1,INDEX(AwardsData[Performance state],MATCH(J19,AwardsData[Award ID],0)),"Unlinked")) | Z19: =IF(AND(V19=1,OR(Dashboard!$AB$2="All",K19=Dashboard!$AB$2),OR(Dashboard!$AB$3="All",L19=Dashboard!$AB$3),OR(Dashboard!$N$10="All",W19=Dashboard!$N$10)),1,0) -> 0 | AA19: =IF(AND(Z19=1,OR(Dashboard!$B$7="All",S19=Dashboard!$B$7)),1,0) -> 0 | AB19: =IF(AND(V19=1,F19<>0),1,0) -> 0 | AC19: =IF(AND(AA19=1,AB19=1),IF(COUNTIFS($J$17:J19,J19,$AA$17:AA19,1,$AB$17:AB19,1)=1,1,0),0) -> 0 | AD19: =IF(AND(AA19=1,AB19=1),IF(COUNTIFS($K$17:K19,K19,$AA$17:AA19,1,$AB$17:AB19,1)=1,1,0),0) -> 0 | AE19: =IF(AND(Z19=1,AB19=1),IF(COUNTIFS($J$17:J19,J19,$S$17:S19,S19,$Z$17:Z19,1,$AB$17:AB19,1)=1,1,0),0) -> 0 | AF19: =IF(AND(Z19=1,AB19=1),IF(COUNTIFS($K$17:K19,K19,$S$17:S19,S19,$Z$17:Z19,1,$AB$17:AB19,1)=1,1,0),0) -> 0 | AG19: =IF(AND(AA19=1,AB19=1),IF(COUNTIFS($J$17:J19,J19,$L$17:L19,L19,$AA$17:AA19,1,$AB$17:AB19,1)=1,1,0),0) -> 0 | AH19: =IF(AND(AA19=1,AB19=1),IF(COUNTIFS($J$17:J19,J19,$K$17:K19,K19,$AA$17:AA19,1,$AB$17:AB19,1)=1,1,0),0) -> 0 | AI19: =IF(V19=1,MAX(F19,0),0) -> 0 | AJ19: =IF(V19=1,MIN(F19,0),0) -> 0
B20: =IF(M20="","",IF(P20="",M20,HYPERLINK(P20,M20))) | C20: =IF(N20="","",IF(Q20="",N20,HYPERLINK(Q20,N20))) | E20: =IF(O20="","",IF(R20="",O20,HYPERLINK(R20,O20))) | S20: =IF(ISNUMBER(A20),YEAR(A20)+IF(MONTH(A20)>=10,1,0),"") | T20: =IF(ISNUMBER(A20),INT(MOD(MONTH(A20)-10,12)/3)+1,"") | U20: =IF(AND(I20<>"",D20<>"",OR(COUNTIFS(TransactionsData[Vendor ID],K20,TransactionsData[UEI],"<>"&D20,TransactionsData[UEI],"?*")>0,COUNTIFS(VendorGroups[Record ID],K20,VendorGroups[Source UEI],"<>"&D20,VendorGroups[Source UEI],"?*")>0)),"Conflicting vendor UEIs",IF(I20="",IF(COUNTA(A20,D20,F20:R20)>0,"Missing transaction ID",""),IF(COUNTIFS(TransactionsData[Transaction ID],I20)<>1,"Duplicate transaction ID",IF(OR(NOT(ISNUMBER(A20)),A20<1,A20>DATE(2099,1,1)),"Use a valid date",IF(OR(A20<$B$4,A20>$D$4),"Outside coverage",IF(NOT(ISNUMBER(F20)),"Missing or invalid amount",IF(OR(K20="",L20="",N20=""),"Add vendor and office identities",IF(G20="Exclude",IF(OR(F20<>0,H20=""),"Review nonzero or unexplained exclusion",""),IF(G20<>"Include","Choose Include or Exclude",IF(COUNTIFS(AwardsData[Award ID],J20)<>1,"Award link needs review",IF(INDEX(AwardsData[Input check],MATCH(J20,AwardsData[Award ID],0))<>"","Check award inputs",""))))))))))) | V20: =IF(AND(I20<>"",U20="",G20="Include"),1,0) -> 0 | W20: =IF(I20="","",IF(COUNTIFS(AwardsData[Award ID],J20)=1,INDEX(AwardsData[Current award type],MATCH(J20,AwardsData[Award ID],0)),"Unlinked")) | X20: =IF(I20="","",IF(COUNTIFS(AwardsData[Award ID],J20)=1,INDEX(AwardsData[Current set-aside],MATCH(J20,AwardsData[Award ID],0)),"Unlinked")) | Y20: =IF(I20="","",IF(COUNTIFS(AwardsData[Award ID],J20)=1,INDEX(AwardsData[Performance state],MATCH(J20,AwardsData[Award ID],0)),"Unlinked")) | Z20: =IF(AND(V20=1,OR(Dashboard!$AB$2="All",K20=Dashboard!$AB$2),OR(Dashboard!$AB$3="All",L20=Dashboard!$AB$3),OR(Dashboard!$N$10="All",W20=Dashboard!$N$10)),1,0) -> 0 | AA20: =IF(AND(Z20=1,OR(Dashboard!$B$7="All",S20=Dashboard!$B$7)),1,0) -> 0 | AB20: =IF(AND(V20=1,F20<>0),1,0) -> 0 | AC20: =IF(AND(AA20=1,AB20=1),IF(COUNTIFS($J$17:J20,J20,$AA$17:AA20,1,$AB$17:AB20,1)=1,1,0),0) -> 0 | AD20: =IF(AND(AA20=1,AB20=1),IF(COUNTIFS($K$17:K20,K20,$AA$17:AA20,1,$AB$17:AB20,1)=1,1,0),0) -> 0 | AE20: =IF(AND(Z20=1,AB20=1),IF(COUNTIFS($J$17:J20,J20,$S$17:S20,S20,$Z$17:Z20,1,$AB$17:AB20,1)=1,1,0),0) -> 0 | AF20: =IF(AND(Z20=1,AB20=1),IF(COUNTIFS($K$17:K20,K20,$S$17:S20,S20,$Z$17:Z20,1,$AB$17:AB20,1)=1,1,0),0) -> 0 | AG20: =IF(AND(AA20=1,AB20=1),IF(COUNTIFS($J$17:J20,J20,$L$17:L20,L20,$AA$17:AA20,1,$AB$17:AB20,1)=1,1,0),0) -> 0 | AH20: =IF(AND(AA20=1,AB20=1),IF(COUNTIFS($J$17:J20,J20,$K$17:K20,K20,$AA$17:AA20,1,$AB$17:AB20,1)=1,1,0),0) -> 0 | AI20: =IF(V20=1,MAX(F20,0),0) -> 0 | AJ20: =IF(V20=1,MIN(F20,0),0) -> 0
B21: =IF(M21="","",IF(P21="",M21,HYPERLINK(P21,M21))) | C21: =IF(N21="","",IF(Q21="",N21,HYPERLINK(Q21,N21))) | E21: =IF(O21="","",IF(R21="",O21,HYPERLINK(R21,O21))) | S21: =IF(ISNUMBER(A21),YEAR(A21)+IF(MONTH(A21)>=10,1,0),"") | T21: =IF(ISNUMBER(A21),INT(MOD(MONTH(A21)-10,12)/3)+1,"") | U21: =IF(AND(I21<>"",D21<>"",OR(COUNTIFS(TransactionsData[Vendor ID],K21,TransactionsData[UEI],"<>"&D21,TransactionsData[UEI],"?*")>0,COUNTIFS(VendorGroups[Record ID],K21,VendorGroups[Source UEI],"<>"&D21,VendorGroups[Source UEI],"?*")>0)),"Conflicting vendor UEIs",IF(I21="",IF(COUNTA(A21,D21,F21:R21)>0,"Missing transaction ID",""),IF(COUNTIFS(TransactionsData[Transaction ID],I21)<>1,"Duplicate transaction ID",IF(OR(NOT(ISNUMBER(A21)),A21<1,A21>DATE(2099,1,1)),"Use a valid date",IF(OR(A21<$B$4,A21>$D$4),"Outside coverage",IF(NOT(ISNUMBER(F21)),"Missing or invalid amount",IF(OR(K21="",L21="",N21=""),"Add vendor and office identities",IF(G21="Exclude",IF(OR(F21<>0,H21=""),"Review nonzero or unexplained exclusion",""),IF(G21<>"Include","Choose Include or Exclude",IF(COUNTIFS(AwardsData[Award ID],J21)<>1,"Award link needs review",IF(INDEX(AwardsData[Input check],MATCH(J21,AwardsData[Award ID],0))<>"","Check award inputs",""))))))))))) | V21: =IF(AND(I21<>"",U21="",G21="Include"),1,0) -> 0 | W21: =IF(I21="","",IF(COUNTIFS(AwardsData[Award ID],J21)=1,INDEX(AwardsData[Current award type],MATCH(J21,AwardsData[Award ID],0)),"Unlinked")) | X21: =IF(I21="","",IF(COUNTIFS(AwardsData[Award ID],J21)=1,INDEX(AwardsData[Current set-aside],MATCH(J21,AwardsData[Award ID],0)),"Unlinked")) | Y21: =IF(I21="","",IF(COUNTIFS(AwardsData[Award ID],J21)=1,INDEX(AwardsData[Performance state],MATCH(J21,AwardsData[Award ID],0)),"Unlinked")) | Z21: =IF(AND(V21=1,OR(Dashboard!$AB$2="All",K21=Dashboard!$AB$2),OR(Dashboard!$AB$3="All",L21=Dashboard!$AB$3),OR(Dashboard!$N$10="All",W21=Dashboard!$N$10)),1,0) -> 0 | AA21: =IF(AND(Z21=1,OR(Dashboard!$B$7="All",S21=Dashboard!$B$7)),1,0) -> 0 | AB21: =IF(AND(V21=1,F21<>0),1,0) -> 0 | AC21: =IF(AND(AA21=1,AB21=1),IF(COUNTIFS($J$17:J21,J21,$AA$17:AA21,1,$AB$17:AB21,1)=1,1,0),0) -> 0 | AD21: =IF(AND(AA21=1,AB21=1),IF(COUNTIFS($K$17:K21,K21,$AA$17:AA21,1,$AB$17:AB21,1)=1,1,0),0) -> 0 | AE21: =IF(AND(Z21=1,AB21=1),IF(COUNTIFS($J$17:J21,J21,$S$17:S21,S21,$Z$17:Z21,1,$AB$17:AB21,1)=1,1,0),0) -> 0 | AF21: =IF(AND(Z21=1,AB21=1),IF(COUNTIFS($K$17:K21,K21,$S$17:S21,S21,$Z$17:Z21,1,$AB$17:AB21,1)=1,1,0),0) -> 0 | AG21: =IF(AND(AA21=1,AB21=1),IF(COUNTIFS($J$17:J21,J21,$L$17:L21,L21,$AA$17:AA21,1,$AB$17:AB21,1)=1,1,0),0) -> 0 | AH21: =IF(AND(AA21=1,AB21=1),IF(COUNTIFS($J$17:J21,J21,$K$17:K21,K21,$AA$17:AA21,1,$AB$17:AB21,1)=1,1,0),0) -> 0 | AI21: =IF(V21=1,MAX(F21,0),0) -> 0 | AJ21: =IF(V21=1,MIN(F21,0),0) -> 0
B22: =IF(M22="","",IF(P22="",M22,HYPERLINK(P22,M22))) | C22: =IF(N22="","",IF(Q22="",N22,HYPERLINK(Q22,N22))) | E22: =IF(O22="","",IF(R22="",O22,HYPERLINK(R22,O22))) | S22: =IF(ISNUMBER(A22),YEAR(A22)+IF(MONTH(A22)>=10,1,0),"") | T22: =IF(ISNUMBER(A22),INT(MOD(MONTH(A22)-10,12)/3)+1,"") | U22: =IF(AND(I22<>"",D22<>"",OR(COUNTIFS(TransactionsData[Vendor ID],K22,TransactionsData[UEI],"<>"&D22,TransactionsData[UEI],"?*")>0,COUNTIFS(VendorGroups[Record ID],K22,VendorGroups[Source UEI],"<>"&D22,VendorGroups[Source UEI],"?*")>0)),"Conflicting vendor UEIs",IF(I22="",IF(COUNTA(A22,D22,F22:R22)>0,"Missing transaction ID",""),IF(COUNTIFS(TransactionsData[Transaction ID],I22)<>1,"Duplicate transaction ID",IF(OR(NOT(ISNUMBER(A22)),A22<1,A22>DATE(2099,1,1)),"Use a valid date",IF(OR(A22<$B$4,A22>$D$4),"Outside coverage",IF(NOT(ISNUMBER(F22)),"Missing or invalid amount",IF(OR(K22="",L22="",N22=""),"Add vendor and office identities",IF(G22="Exclude",IF(OR(F22<>0,H22=""),"Review nonzero or unexplained exclusion",""),IF(G22<>"Include","Choose Include or Exclude",IF(COUNTIFS(AwardsData[Award ID],J22)<>1,"Award link needs review",IF(INDEX(AwardsData[Input check],MATCH(J22,AwardsData[Award ID],0))<>"","Check award inputs",""))))))))))) | V22: =IF(AND(I22<>"",U22="",G22="Include"),1,0) -> 0 | W22: =IF(I22="","",IF(COUNTIFS(AwardsData[Award ID],J22)=1,INDEX(AwardsData[Current award type],MATCH(J22,AwardsData[Award ID],0)),"Unlinked")) | X22: =IF(I22="","",IF(COUNTIFS(AwardsData[Award ID],J22)=1,INDEX(AwardsData[Current set-aside],MATCH(J22,AwardsData[Award ID],0)),"Unlinked")) | Y22: =IF(I22="","",IF(COUNTIFS(AwardsData[Award ID],J22)=1,INDEX(AwardsData[Performance state],MATCH(J22,AwardsData[Award ID],0)),"Unlinked")) | Z22: =IF(AND(V22=1,OR(Dashboard!$AB$2="All",K22=Dashboard!$AB$2),OR(Dashboard!$AB$3="All",L22=Dashboard!$AB$3),OR(Dashboard!$N$10="All",W22=Dashboard!$N$10)),1,0) -> 0 | AA22: =IF(AND(Z22=1,OR(Dashboard!$B$7="All",S22=Dashboard!$B$7)),1,0) -> 0 | AB22: =IF(AND(V22=1,F22<>0),1,0) -> 0 | AC22: =IF(AND(AA22=1,AB22=1),IF(COUNTIFS($J$17:J22,J22,$AA$17:AA22,1,$AB$17:AB22,1)=1,1,0),0) -> 0 | AD22: =IF(AND(AA22=1,AB22=1),IF(COUNTIFS($K$17:K22,K22,$AA$17:AA22,1,$AB$17:AB22,1)=1,1,0),0) -> 0 | AE22: =IF(AND(Z22=1,AB22=1),IF(COUNTIFS($J$17:J22,J22,$S$17:S22,S22,$Z$17:Z22,1,$AB$17:AB22,1)=1,1,0),0) -> 0 | AF22: =IF(AND(Z22=1,AB22=1),IF(COUNTIFS($K$17:K22,K22,$S$17:S22,S22,$Z$17:Z22,1,$AB$17:AB22,1)=1,1,0),0) -> 0 | AG22: =IF(AND(AA22=1,AB22=1),IF(COUNTIFS($J$17:J22,J22,$L$17:L22,L22,$AA$17:AA22,1,$AB$17:AB22,1)=1,1,0),0) -> 0 | AH22: =IF(AND(AA22=1,AB22=1),IF(COUNTIFS($J$17:J22,J22,$K$17:K22,K22,$AA$17:AA22,1,$AB$17:AB22,1)=1,1,0),0) -> 0 | AI22: =IF(V22=1,MAX(F22,0),0) -> 0 | AJ22: =IF(V22=1,MIN(F22,0),0) -> 0
B23: =IF(M23="","",IF(P23="",M23,HYPERLINK(P23,M23))) | C23: =IF(N23="","",IF(Q23="",N23,HYPERLINK(Q23,N23))) | E23: =IF(O23="","",IF(R23="",O23,HYPERLINK(R23,O23))) | S23: =IF(ISNUMBER(A23),YEAR(A23)+IF(MONTH(A23)>=10,1,0),"") | T23: =IF(ISNUMBER(A23),INT(MOD(MONTH(A23)-10,12)/3)+1,"") | U23: =IF(AND(I23<>"",D23<>"",OR(COUNTIFS(TransactionsData[Vendor ID],K23,TransactionsData[UEI],"<>"&D23,TransactionsData[UEI],"?*")>0,COUNTIFS(VendorGroups[Record ID],K23,VendorGroups[Source UEI],"<>"&D23,VendorGroups[Source UEI],"?*")>0)),"Conflicting vendor UEIs",IF(I23="",IF(COUNTA(A23,D23,F23:R23)>0,"Missing transaction ID",""),IF(COUNTIFS(TransactionsData[Transaction ID],I23)<>1,"Duplicate transaction ID",IF(OR(NOT(ISNUMBER(A23)),A23<1,A23>DATE(2099,1,1)),"Use a valid date",IF(OR(A23<$B$4,A23>$D$4),"Outside coverage",IF(NOT(ISNUMBER(F23)),"Missing or invalid amount",IF(OR(K23="",L23="",N23=""),"Add vendor and office identities",IF(G23="Exclude",IF(OR(F23<>0,H23=""),"Review nonzero or unexplained exclusion",""),IF(G23<>"Include","Choose Include or Exclude",IF(COUNTIFS(AwardsData[Award ID],J23)<>1,"Award link needs review",IF(INDEX(AwardsData[Input check],MATCH(J23,AwardsData[Award ID],0))<>"","Check award inputs",""))))))))))) | V23: =IF(AND(I23<>"",U23="",G23="Include"),1,0) -> 0 | W23: =IF(I23="","",IF(COUNTIFS(AwardsData[Award ID],J23)=1,INDEX(AwardsData[Current award type],MATCH(J23,AwardsData[Award ID],0)),"Unlinked")) | X23: =IF(I23="","",IF(COUNTIFS(AwardsData[Award ID],J23)=1,INDEX(AwardsData[Current set-aside],MATCH(J23,AwardsData[Award ID],0)),"Unlinked")) | Y23: =IF(I23="","",IF(COUNTIFS(AwardsData[Award ID],J23)=1,INDEX(AwardsData[Performance state],MATCH(J23,AwardsData[Award ID],0)),"Unlinked")) | Z23: =IF(AND(V23=1,OR(Dashboard!$AB$2="All",K23=Dashboard!$AB$2),OR(Dashboard!$AB$3="All",L23=Dashboard!$AB$3),OR(Dashboard!$N$10="All",W23=Dashboard!$N$10)),1,0) -> 0 | AA23: =IF(AND(Z23=1,OR(Dashboard!$B$7="All",S23=Dashboard!$B$7)),1,0) -> 0 | AB23: =IF(AND(V23=1,F23<>0),1,0) -> 0 | AC23: =IF(AND(AA23=1,AB23=1),IF(COUNTIFS($J$17:J23,J23,$AA$17:AA23,1,$AB$17:AB23,1)=1,1,0),0) -> 0 | AD23: =IF(AND(AA23=1,AB23=1),IF(COUNTIFS($K$17:K23,K23,$AA$17:AA23,1,$AB$17:AB23,1)=1,1,0),0) -> 0 | AE23: =IF(AND(Z23=1,AB23=1),IF(COUNTIFS($J$17:J23,J23,$S$17:S23,S23,$Z$17:Z23,1,$AB$17:AB23,1)=1,1,0),0) -> 0 | AF23: =IF(AND(Z23=1,AB23=1),IF(COUNTIFS($K$17:K23,K23,$S$17:S23,S23,$Z$17:Z23,1,$AB$17:AB23,1)=1,1,0),0) -> 0 | AG23: =IF(AND(AA23=1,AB23=1),IF(COUNTIFS($J$17:J23,J23,$L$17:L23,L23,$AA$17:AA23,1,$AB$17:AB23,1)=1,1,0),0) -> 0 | AH23: =IF(AND(AA23=1,AB23=1),IF(COUNTIFS($J$17:J23,J23,$K$17:K23,K23,$AA$17:AA23,1,$AB$17:AB23,1)=1,1,0),0) -> 0 | AI23: =IF(V23=1,MAX(F23,0),0) -> 0 | AJ23: =IF(V23=1,MIN(F23,0),0) -> 0
B24: =IF(M24="","",IF(P24="",M24,HYPERLINK(P24,M24))) | C24: =IF(N24="","",IF(Q24="",N24,HYPERLINK(Q24,N24))) | E24: =IF(O24="","",IF(R24="",O24,HYPERLINK(R24,O24))) | S24: =IF(ISNUMBER(A24),YEAR(A24)+IF(MONTH(A24)>=10,1,0),"") | T24: =IF(ISNUMBER(A24),INT(MOD(MONTH(A24)-10,12)/3)+1,"") | U24: =IF(AND(I24<>"",D24<>"",OR(COUNTIFS(TransactionsData[Vendor ID],K24,TransactionsData[UEI],"<>"&D24,TransactionsData[UEI],"?*")>0,COUNTIFS(VendorGroups[Record ID],K24,VendorGroups[Source UEI],"<>"&D24,VendorGroups[Source UEI],"?*")>0)),"Conflicting vendor UEIs",IF(I24="",IF(COUNTA(A24,D24,F24:R24)>0,"Missing transaction ID",""),IF(COUNTIFS(TransactionsData[Transaction ID],I24)<>1,"Duplicate transaction ID",IF(OR(NOT(ISNUMBER(A24)),A24<1,A24>DATE(2099,1,1)),"Use a valid date",IF(OR(A24<$B$4,A24>$D$4),"Outside coverage",IF(NOT(ISNUMBER(F24)),"Missing or invalid amount",IF(OR(K24="",L24="",N24=""),"Add vendor and office identities",IF(G24="Exclude",IF(OR(F24<>0,H24=""),"Review nonzero or unexplained exclusion",""),IF(G24<>"Include","Choose Include or Exclude",IF(COUNTIFS(AwardsData[Award ID],J24)<>1,"Award link needs review",IF(INDEX(AwardsData[Input check],MATCH(J24,AwardsData[Award ID],0))<>"","Check award inputs",""))))))))))) | V24: =IF(AND(I24<>"",U24="",G24="Include"),1,0) -> 0 | W24: =IF(I24="","",IF(COUNTIFS(AwardsData[Award ID],J24)=1,INDEX(AwardsData[Current award type],MATCH(J24,AwardsData[Award ID],0)),"Unlinked")) | X24: =IF(I24="","",IF(COUNTIFS(AwardsData[Award ID],J24)=1,INDEX(AwardsData[Current set-aside],MATCH(J24,AwardsData[Award ID],0)),"Unlinked")) | Y24: =IF(I24="","",IF(COUNTIFS(AwardsData[Award ID],J24)=1,INDEX(AwardsData[Performance state],MATCH(J24,AwardsData[Award ID],0)),"Unlinked")) | Z24: =IF(AND(V24=1,OR(Dashboard!$AB$2="All",K24=Dashboard!$AB$2),OR(Dashboard!$AB$3="All",L24=Dashboard!$AB$3),OR(Dashboard!$N$10="All",W24=Dashboard!$N$10)),1,0) -> 0 | AA24: =IF(AND(Z24=1,OR(Dashboard!$B$7="All",S24=Dashboard!$B$7)),1,0) -> 0 | AB24: =IF(AND(V24=1,F24<>0),1,0) -> 0 | AC24: =IF(AND(AA24=1,AB24=1),IF(COUNTIFS($J$17:J24,J24,$AA$17:AA24,1,$AB$17:AB24,1)=1,1,0),0) -> 0 | AD24: =IF(AND(AA24=1,AB24=1),IF(COUNTIFS($K$17:K24,K24,$AA$17:AA24,1,$AB$17:AB24,1)=1,1,0),0) -> 0 | AE24: =IF(AND(Z24=1,AB24=1),IF(COUNTIFS($J$17:J24,J24,$S$17:S24,S24,$Z$17:Z24,1,$AB$17:AB24,1)=1,1,0),0) -> 0 | AF24: =IF(AND(Z24=1,AB24=1),IF(COUNTIFS($K$17:K24,K24,$S$17:S24,S24,$Z$17:Z24,1,$AB$17:AB24,1)=1,1,0),0) -> 0 | AG24: =IF(AND(AA24=1,AB24=1),IF(COUNTIFS($J$17:J24,J24,$L$17:L24,L24,$AA$17:AA24,1,$AB$17:AB24,1)=1,1,0),0) -> 0 | AH24: =IF(AND(AA24=1,AB24=1),IF(COUNTIFS($J$17:J24,J24,$K$17:K24,K24,$AA$17:AA24,1,$AB$17:AB24,1)=1,1,0),0) -> 0 | AI24: =IF(V24=1,MAX(F24,0),0) -> 0 | AJ24: =IF(V24=1,MIN(F24,0),0) -> 0
B25: =IF(M25="","",IF(P25="",M25,HYPERLINK(P25,M25))) | C25: =IF(N25="","",IF(Q25="",N25,HYPERLINK(Q25,N25))) | E25: =IF(O25="","",IF(R25="",O25,HYPERLINK(R25,O25))) | S25: =IF(ISNUMBER(A25),YEAR(A25)+IF(MONTH(A25)>=10,1,0),"") | T25: =IF(ISNUMBER(A25),INT(MOD(MONTH(A25)-10,12)/3)+1,"") | U25: =IF(AND(I25<>"",D25<>"",OR(COUNTIFS(TransactionsData[Vendor ID],K25,TransactionsData[UEI],"<>"&D25,TransactionsData[UEI],"?*")>0,COUNTIFS(VendorGroups[Record ID],K25,VendorGroups[Source UEI],"<>"&D25,VendorGroups[Source UEI],"?*")>0)),"Conflicting vendor UEIs",IF(I25="",IF(COUNTA(A25,D25,F25:R25)>0,"Missing transaction ID",""),IF(COUNTIFS(TransactionsData[Transaction ID],I25)<>1,"Duplicate transaction ID",IF(OR(NOT(ISNUMBER(A25)),A25<1,A25>DATE(2099,1,1)),"Use a valid date",IF(OR(A25<$B$4,A25>$D$4),"Outside coverage",IF(NOT(ISNUMBER(F25)),"Missing or invalid amount",IF(OR(K25="",L25="",N25=""),"Add vendor and office identities",IF(G25="Exclude",IF(OR(F25<>0,H25=""),"Review nonzero or unexplained exclusion",""),IF(G25<>"Include","Choose Include or Exclude",IF(COUNTIFS(AwardsData[Award ID],J25)<>1,"Award link needs review",IF(INDEX(AwardsData[Input check],MATCH(J25,AwardsData[Award ID],0))<>"","Check award inputs",""))))))))))) | V25: =IF(AND(I25<>"",U25="",G25="Include"),1,0) -> 0 | W25: =IF(I25="","",IF(COUNTIFS(AwardsData[Award ID],J25)=1,INDEX(AwardsData[Current award type],MATCH(J25,AwardsData[Award ID],0)),"Unlinked")) | X25: =IF(I25="","",IF(COUNTIFS(AwardsData[Award ID],J25)=1,INDEX(AwardsData[Current set-aside],MATCH(J25,AwardsData[Award ID],0)),"Unlinked")) | Y25: =IF(I25="","",IF(COUNTIFS(AwardsData[Award ID],J25)=1,INDEX(AwardsData[Performance state],MATCH(J25,AwardsData[Award ID],0)),"Unlinked")) | Z25: =IF(AND(V25=1,OR(Dashboard!$AB$2="All",K25=Dashboard!$AB$2),OR(Dashboard!$AB$3="All",L25=Dashboard!$AB$3),OR(Dashboard!$N$10="All",W25=Dashboard!$N$10)),1,0) -> 0 | AA25: =IF(AND(Z25=1,OR(Dashboard!$B$7="All",S25=Dashboard!$B$7)),1,0) -> 0 | AB25: =IF(AND(V25=1,F25<>0),1,0) -> 0 | AC25: =IF(AND(AA25=1,AB25=1),IF(COUNTIFS($J$17:J25,J25,$AA$17:AA25,1,$AB$17:AB25,1)=1,1,0),0) -> 0 | AD25: =IF(AND(AA25=1,AB25=1),IF(COUNTIFS($K$17:K25,K25,$AA$17:AA25,1,$AB$17:AB25,1)=1,1,0),0) -> 0 | AE25: =IF(AND(Z25=1,AB25=1),IF(COUNTIFS($J$17:J25,J25,$S$17:S25,S25,$Z$17:Z25,1,$AB$17:AB25,1)=1,1,0),0) -> 0 | AF25: =IF(AND(Z25=1,AB25=1),IF(COUNTIFS($K$17:K25,K25,$S$17:S25,S25,$Z$17:Z25,1,$AB$17:AB25,1)=1,1,0),0) -> 0 | AG25: =IF(AND(AA25=1,AB25=1),IF(COUNTIFS($J$17:J25,J25,$L$17:L25,L25,$AA$17:AA25,1,$AB$17:AB25,1)=1,1,0),0) -> 0 | AH25: =IF(AND(AA25=1,AB25=1),IF(COUNTIFS($J$17:J25,J25,$K$17:K25,K25,$AA$17:AA25,1,$AB$17:AB25,1)=1,1,0),0) -> 0 | AI25: =IF(V25=1,MAX(F25,0),0) -> 0 | AJ25: =IF(V25=1,MIN(F25,0),0) -> 0
B26: =IF(M26="","",IF(P26="",M26,HYPERLINK(P26,M26))) | C26: =IF(N26="","",IF(Q26="",N26,HYPERLINK(Q26,N26))) | E26: =IF(O26="","",IF(R26="",O26,HYPERLINK(R26,O26))) | S26: =IF(ISNUMBER(A26),YEAR(A26)+IF(MONTH(A26)>=10,1,0),"") | T26: =IF(ISNUMBER(A26),INT(MOD(MONTH(A26)-10,12)/3)+1,"") | U26: =IF(AND(I26<>"",D26<>"",OR(COUNTIFS(TransactionsData[Vendor ID],K26,TransactionsData[UEI],"<>"&D26,TransactionsData[UEI],"?*")>0,COUNTIFS(VendorGroups[Record ID],K26,VendorGroups[Source UEI],"<>"&D26,VendorGroups[Source UEI],"?*")>0)),"Conflicting vendor UEIs",IF(I26="",IF(COUNTA(A26,D26,F26:R26)>0,"Missing transaction ID",""),IF(COUNTIFS(TransactionsData[Transaction ID],I26)<>1,"Duplicate transaction ID",IF(OR(NOT(ISNUMBER(A26)),A26<1,A26>DATE(2099,1,1)),"Use a valid date",IF(OR(A26<$B$4,A26>$D$4),"Outside coverage",IF(NOT(ISNUMBER(F26)),"Missing or invalid amount",IF(OR(K26="",L26="",N26=""),"Add vendor and office identities",IF(G26="Exclude",IF(OR(F26<>0,H26=""),"Review nonzero or unexplained exclusion",""),IF(G26<>"Include","Choose Include or Exclude",IF(COUNTIFS(AwardsData[Award ID],J26)<>1,"Award link needs review",IF(INDEX(AwardsData[Input check],MATCH(J26,AwardsData[Award ID],0))<>"","Check award inputs",""))))))))))) | V26: =IF(AND(I26<>"",U26="",G26="Include"),1,0) -> 0 | W26: =IF(I26="","",IF(COUNTIFS(AwardsData[Award ID],J26)=1,INDEX(AwardsData[Current award type],MATCH(J26,AwardsData[Award ID],0)),"Unlinked")) | X26: =IF(I26="","",IF(COUNTIFS(AwardsData[Award ID],J26)=1,INDEX(AwardsData[Current set-aside],MATCH(J26,AwardsData[Award ID],0)),"Unlinked")) | Y26: =IF(I26="","",IF(COUNTIFS(AwardsData[Award ID],J26)=1,INDEX(AwardsData[Performance state],MATCH(J26,AwardsData[Award ID],0)),"Unlinked")) | Z26: =IF(AND(V26=1,OR(Dashboard!$AB$2="All",K26=Dashboard!$AB$2),OR(Dashboard!$AB$3="All",L26=Dashboard!$AB$3),OR(Dashboard!$N$10="All",W26=Dashboard!$N$10)),1,0) -> 0 | AA26: =IF(AND(Z26=1,OR(Dashboard!$B$7="All",S26=Dashboard!$B$7)),1,0) -> 0 | AB26: =IF(AND(V26=1,F26<>0),1,0) -> 0 | AC26: =IF(AND(AA26=1,AB26=1),IF(COUNTIFS($J$17:J26,J26,$AA$17:AA26,1,$AB$17:AB26,1)=1,1,0),0) -> 0 | AD26: =IF(AND(AA26=1,AB26=1),IF(COUNTIFS($K$17:K26,K26,$AA$17:AA26,1,$AB$17:AB26,1)=1,1,0),0) -> 0 | AE26: =IF(AND(Z26=1,AB26=1),IF(COUNTIFS($J$17:J26,J26,$S$17:S26,S26,$Z$17:Z26,1,$AB$17:AB26,1)=1,1,0),0) -> 0 | AF26: =IF(AND(Z26=1,AB26=1),IF(COUNTIFS($K$17:K26,K26,$S$17:S26,S26,$Z$17:Z26,1,$AB$17:AB26,1)=1,1,0),0) -> 0 | AG26: =IF(AND(AA26=1,AB26=1),IF(COUNTIFS($J$17:J26,J26,$L$17:L26,L26,$AA$17:AA26,1,$AB$17:AB26,1)=1,1,0),0) -> 0 | AH26: =IF(AND(AA26=1,AB26=1),IF(COUNTIFS($J$17:J26,J26,$K$17:K26,K26,$AA$17:AA26,1,$AB$17:AB26,1)=1,1,0),0) -> 0 | AI26: =IF(V26=1,MAX(F26,0),0) -> 0 | AJ26: =IF(V26=1,MIN(F26,0),0) -> 0
B27: =IF(M27="","",IF(P27="",M27,HYPERLINK(P27,M27))) | C27: =IF(N27="","",IF(Q27="",N27,HYPERLINK(Q27,N27))) | E27: =IF(O27="","",IF(R27="",O27,HYPERLINK(R27,O27))) | S27: =IF(ISNUMBER(A27),YEAR(A27)+IF(MONTH(A27)>=10,1,0),"") | T27: =IF(ISNUMBER(A27),INT(MOD(MONTH(A27)-10,12)/3)+1,"") | U27: =IF(AND(I27<>"",D27<>"",OR(COUNTIFS(TransactionsData[Vendor ID],K27,TransactionsData[UEI],"<>"&D27,TransactionsData[UEI],"?*")>0,COUNTIFS(VendorGroups[Record ID],K27,VendorGroups[Source UEI],"<>"&D27,VendorGroups[Source UEI],"?*")>0)),"Conflicting vendor UEIs",IF(I27="",IF(COUNTA(A27,D27,F27:R27)>0,"Missing transaction ID",""),IF(COUNTIFS(TransactionsData[Transaction ID],I27)<>1,"Duplicate transaction ID",IF(OR(NOT(ISNUMBER(A27)),A27<1,A27>DATE(2099,1,1)),"Use a valid date",IF(OR(A27<$B$4,A27>$D$4),"Outside coverage",IF(NOT(ISNUMBER(F27)),"Missing or invalid amount",IF(OR(K27="",L27="",N27=""),"Add vendor and office identities",IF(G27="Exclude",IF(OR(F27<>0,H27=""),"Review nonzero or unexplained exclusion",""),IF(G27<>"Include","Choose Include or Exclude",IF(COUNTIFS(AwardsData[Award ID],J27)<>1,"Award link needs review",IF(INDEX(AwardsData[Input check],MATCH(J27,AwardsData[Award ID],0))<>"","Check award inputs",""))))))))))) | V27: =IF(AND(I27<>"",U27="",G27="Include"),1,0) -> 0 | W27: =IF(I27="","",IF(COUNTIFS(AwardsData[Award ID],J27)=1,INDEX(AwardsData[Current award type],MATCH(J27,AwardsData[Award ID],0)),"Unlinked")) | X27: =IF(I27="","",IF(COUNTIFS(AwardsData[Award ID],J27)=1,INDEX(AwardsData[Current set-aside],MATCH(J27,AwardsData[Award ID],0)),"Unlinked")) | Y27: =IF(I27="","",IF(COUNTIFS(AwardsData[Award ID],J27)=1,INDEX(AwardsData[Performance state],MATCH(J27,AwardsData[Award ID],0)),"Unlinked")) | Z27: =IF(AND(V27=1,OR(Dashboard!$AB$2="All",K27=Dashboard!$AB$2),OR(Dashboard!$AB$3="All",L27=Dashboard!$AB$3),OR(Dashboard!$N$10="All",W27=Dashboard!$N$10)),1,0) -> 0 | AA27: =IF(AND(Z27=1,OR(Dashboard!$B$7="All",S27=Dashboard!$B$7)),1,0) -> 0 | AB27: =IF(AND(V27=1,F27<>0),1,0) -> 0 | AC27: =IF(AND(AA27=1,AB27=1),IF(COUNTIFS($J$17:J27,J27,$AA$17:AA27,1,$AB$17:AB27,1)=1,1,0),0) -> 0 | AD27: =IF(AND(AA27=1,AB27=1),IF(COUNTIFS($K$17:K27,K27,$AA$17:AA27,1,$AB$17:AB27,1)=1,1,0),0) -> 0 | AE27: =IF(AND(Z27=1,AB27=1),IF(COUNTIFS($J$17:J27,J27,$S$17:S27,S27,$Z$17:Z27,1,$AB$17:AB27,1)=1,1,0),0) -> 0 | AF27: =IF(AND(Z27=1,AB27=1),IF(COUNTIFS($K$17:K27,K27,$S$17:S27,S27,$Z$17:Z27,1,$AB$17:AB27,1)=1,1,0),0) -> 0 | AG27: =IF(AND(AA27=1,AB27=1),IF(COUNTIFS($J$17:J27,J27,$L$17:L27,L27,$AA$17:AA27,1,$AB$17:AB27,1)=1,1,0),0) -> 0 | AH27: =IF(AND(AA27=1,AB27=1),IF(COUNTIFS($J$17:J27,J27,$K$17:K27,K27,$AA$17:AA27,1,$AB$17:AB27,1)=1,1,0),0) -> 0 | AI27: =IF(V27=1,MAX(F27,0),0) -> 0 | AJ27: =IF(V27=1,MIN(F27,0),0) -> 0
B28: =IF(M28="","",IF(P28="",M28,HYPERLINK(P28,M28))) | C28: =IF(N28="","",IF(Q28="",N28,HYPERLINK(Q28,N28))) | E28: =IF(O28="","",IF(R28="",O28,HYPERLINK(R28,O28))) | S28: =IF(ISNUMBER(A28),YEAR(A28)+IF(MONTH(A28)>=10,1,0),"") | T28: =IF(ISNUMBER(A28),INT(MOD(MONTH(A28)-10,12)/3)+1,"") | U28: =IF(AND(I28<>"",D28<>"",OR(COUNTIFS(TransactionsData[Vendor ID],K28,TransactionsData[UEI],"<>"&D28,TransactionsData[UEI],"?*")>0,COUNTIFS(VendorGroups[Record ID],K28,VendorGroups[Source UEI],"<>"&D28,VendorGroups[Source UEI],"?*")>0)),"Conflicting vendor UEIs",IF(I28="",IF(COUNTA(A28,D28,F28:R28)>0,"Missing transaction ID",""),IF(COUNTIFS(TransactionsData[Transaction ID],I28)<>1,"Duplicate transaction ID",IF(OR(NOT(ISNUMBER(A28)),A28<1,A28>DATE(2099,1,1)),"Use a valid date",IF(OR(A28<$B$4,A28>$D$4),"Outside coverage",IF(NOT(ISNUMBER(F28)),"Missing or invalid amount",IF(OR(K28="",L28="",N28=""),"Add vendor and office identities",IF(G28="Exclude",IF(OR(F28<>0,H28=""),"Review nonzero or unexplained exclusion",""),IF(G28<>"Include","Choose Include or Exclude",IF(COUNTIFS(AwardsData[Award ID],J28)<>1,"Award link needs review",IF(INDEX(AwardsData[Input check],MATCH(J28,AwardsData[Award ID],0))<>"","Check award inputs",""))))))))))) | V28: =IF(AND(I28<>"",U28="",G28="Include"),1,0) -> 0 | W28: =IF(I28="","",IF(COUNTIFS(AwardsData[Award ID],J28)=1,INDEX(AwardsData[Current award type],MATCH(J28,AwardsData[Award ID],0)),"Unlinked")) | X28: =IF(I28="","",IF(COUNTIFS(AwardsData[Award ID],J28)=1,INDEX(AwardsData[Current set-aside],MATCH(J28,AwardsData[Award ID],0)),"Unlinked")) | Y28: =IF(I28="","",IF(COUNTIFS(AwardsData[Award ID],J28)=1,INDEX(AwardsData[Performance state],MATCH(J28,AwardsData[Award ID],0)),"Unlinked")) | Z28: =IF(AND(V28=1,OR(Dashboard!$AB$2="All",K28=Dashboard!$AB$2),OR(Dashboard!$AB$3="All",L28=Dashboard!$AB$3),OR(Dashboard!$N$10="All",W28=Dashboard!$N$10)),1,0) -> 0 | AA28: =IF(AND(Z28=1,OR(Dashboard!$B$7="All",S28=Dashboard!$B$7)),1,0) -> 0 | AB28: =IF(AND(V28=1,F28<>0),1,0) -> 0 | AC28: =IF(AND(AA28=1,AB28=1),IF(COUNTIFS($J$17:J28,J28,$AA$17:AA28,1,$AB$17:AB28,1)=1,1,0),0) -> 0 | AD28: =IF(AND(AA28=1,AB28=1),IF(COUNTIFS($K$17:K28,K28,$AA$17:AA28,1,$AB$17:AB28,1)=1,1,0),0) -> 0 | AE28: =IF(AND(Z28=1,AB28=1),IF(COUNTIFS($J$17:J28,J28,$S$17:S28,S28,$Z$17:Z28,1,$AB$17:AB28,1)=1,1,0),0) -> 0 | AF28: =IF(AND(Z28=1,AB28=1),IF(COUNTIFS($K$17:K28,K28,$S$17:S28,S28,$Z$17:Z28,1,$AB$17:AB28,1)=1,1,0),0) -> 0 | AG28: =IF(AND(AA28=1,AB28=1),IF(COUNTIFS($J$17:J28,J28,$L$17:L28,L28,$AA$17:AA28,1,$AB$17:AB28,1)=1,1,0),0) -> 0 | AH28: =IF(AND(AA28=1,AB28=1),IF(COUNTIFS($J$17:J28,J28,$K$17:K28,K28,$AA$17:AA28,1,$AB$17:AB28,1)=1,1,0),0) -> 0 | AI28: =IF(V28=1,MAX(F28,0),0) -> 0 | AJ28: =IF(V28=1,MIN(F28,0),0) -> 0
... B46: =IF(M46="","",IF(P46="",M46,HYPERLINK(P46,M46))) | C46: =IF(N46="","",IF(Q46="",N46,HYPERLINK(Q46,N46))) | E46: =IF(O46="","",IF(R46="",O46,HYPERLINK(R46,O46))) | S46: =IF(ISNUMBER(A46),YEAR(A46)+IF(MONTH(A46)>=10,1,0),"") | T46: =IF(ISNUMBER(A46),INT(MOD(MONTH(A46)-10,12)/3)+1,"") | U46: =IF(AND(I46<>"",D46<>"",OR(COUNTIFS(TransactionsData[Vendor ID],K46,TransactionsData[UEI],"<>"&D46,TransactionsData[UEI],"?*")>0,COUNTIFS(VendorGroups[Record ID],K46,VendorGroups[Source UEI],"<>"&D46,VendorGroups[Source UEI],"?*")>0)),"Conflicting vendor UEIs",IF(I46="",IF(COUNTA(A46,D46,F46:R46)>0,"Missing transaction ID",""),IF(COUNTIFS(TransactionsData[Transaction ID],I46)<>1,"Duplicate transaction ID",IF(OR(NOT(ISNUMBER(A46)),A46<1,A46>DATE(2099,1,1)),"Use a valid date",IF(OR(A46<$B$4,A46>$D$4),"Outside coverage",IF(NOT(ISNUMBER(F46)),"Missing or invalid amount",IF(OR(K46="",L46="",N46=""),"Add vendor and office identities",IF(G46="Exclude",IF(OR(F46<>0,H46=""),"Review nonzero or unexplained exclusion",""),IF(G46<>"Include","Choose Include or Exclude",IF(COUNTIFS(AwardsData[Award ID],J46)<>1,"Award link needs review",IF(INDEX(AwardsData[Input check],MATCH(J46,AwardsData[Award ID],0))<>"","Check award inputs",""))))))))))) | V46: =IF(AND(I46<>"",U46="",G46="Include"),1,0) -> 0 | W46: =IF(I46="","",IF(COUNTIFS(AwardsData[Award ID],J46)=1,INDEX(AwardsData[Current award type],MATCH(J46,AwardsData[Award ID],0)),"Unlinked")) | X46: =IF(I46="","",IF(COUNTIFS(AwardsData[Award ID],J46)=1,INDEX(AwardsData[Current set-aside],MATCH(J46,AwardsData[Award ID],0)),"Unlinked")) | Y46: =IF(I46="","",IF(COUNTIFS(AwardsData[Award ID],J46)=1,INDEX(AwardsData[Performance state],MATCH(J46,AwardsData[Award ID],0)),"Unlinked")) | Z46: =IF(AND(V46=1,OR(Dashboard!$AB$2="All",K46=Dashboard!$AB$2),OR(Dashboard!$AB$3="All",L46=Dashboard!$AB$3),OR(Dashboard!$N$10="All",W46=Dashboard!$N$10)),1,0) -> 0 | AA46: =IF(AND(Z46=1,OR(Dashboard!$B$7="All",S46=Dashboard!$B$7)),1,0) -> 0 | AB46: =IF(AND(V46=1,F46<>0),1,0) -> 0 | AC46: =IF(AND(AA46=1,AB46=1),IF(COUNTIFS($J$17:J46,J46,$AA$17:AA46,1,$AB$17:AB46,1)=1,1,0),0) -> 0 | AD46: =IF(AND(AA46=1,AB46=1),IF(COUNTIFS($K$17:K46,K46,$AA$17:AA46,1,$AB$17:AB46,1)=1,1,0),0) -> 0 | AE46: =IF(AND(Z46=1,AB46=1),IF(COUNTIFS($J$17:J46,J46,$S$17:S46,S46,$Z$17:Z46,1,$AB$17:AB46,1)=1,1,0),0) -> 0 | AF46: =IF(AND(Z46=1,AB46=1),IF(COUNTIFS($K$17:K46,K46,$S$17:S46,S46,$Z$17:Z46,1,$AB$17:AB46,1)=1,1,0),0) -> 0 | AG46: =IF(AND(AA46=1,AB46=1),IF(COUNTIFS($J$17:J46,J46,$L$17:L46,L46,$AA$17:AA46,1,$AB$17:AB46,1)=1,1,0),0) -> 0 | AH46: =IF(AND(AA46=1,AB46=1),IF(COUNTIFS($J$17:J46,J46,$K$17:K46,K46,$AA$17:AA46,1,$AB$17:AB46,1)=1,1,0),0) -> 0 | AI46: =IF(V46=1,MAX(F46,0),0) -> 0 | AJ46: =IF(V46=1,MIN(F46,0),0) -> 0
