Workbook
Name AwardTypeCategories: 'Dashboard'!$AD$42:$AD$45
Name SetAsideCategories: 'Dashboard'!$AG$42:$AG$45
Name PerformanceStateCategories: 'Dashboard'!$AJ$42:$AJ$47
Name VendorChoices: 'Dashboard'!$AM$1:$AM$21
Name OfficeChoices: 'Dashboard'!$AN$1:$AN$13
Name TypeChoices: 'Dashboard'!$AO$1:$AO$5

Sheet Dashboard
AM1: All | AN1: All | AO1: All
B2: Contract awards & spend | AA2: Vendor ID | AB2: =IF(H7="All","All",IF(COUNTIFS(VendorGroups[Filter label],H7)=1,INDEX(VendorGroups[Record ID],MATCH(H7,VendorGroups[Filter label],0)),"Invalid")) -> All | AM2: Agility Technologies Inc. [Z9M6NN4AQLF7] | AN2: Directorate for Engineering [490700-A] | AO2: BPA Call
B3: =IF(Transactions!B3="","Buyer / market",Transactions!B3) -> National Science Foundation | Q3: =IF(Transactions!G4="","Retrieved: not supplied","Retrieved "&TEXT(Transactions!G4,"mmm d, yyyy")) -> Retrieved Sep 14, 2026 | AA3: Office ID | AB3: =IF(B10="All","All",IF(COUNTIFS(OfficeGroups[Filter label],B10)=1,INDEX(OfficeGroups[Record ID],MATCH(B10,OfficeGroups[Filter label],0)),"Invalid")) -> All | AM3: Anika Systems Incorporated [Y9V7J5VN9F68] | AN3: Directorate of Geosciences [490600-A] | AO3: Definitive Contract
B4: =IF(Transactions!G3="","Add reviewed records and reporting dates to populate this workbook.",Transactions!G3) -> Application support (PSC DA01) | AM4: Booz Allen Hamilton Inc. [JCBMLGPE6Z71] | AN4: Division of Acquisition and Cooperative Support [491004-A] | AO4: Delivery Order
B5: Prepared by GovTribe, Inc. · UEI EDJBUPNLCCL5 | AM5: Civicactions, Inc. [XSZFHRS5QFL5] | AN5: Division of Industrial Innovation [490707-A] | AO5: Purchase Order
B6: Fiscal year | H6: Vendor | AA6: Net obligations | AB6: =IF(Trends!$B$6<>"","",SUMIFS(TransactionsData[Obligations],TransactionsData[Selected],1)) -> 1.2031667e+08 | AM6: Criterion Systems, L.L.C. [MPGNDNHHWM33] | AN6: Division of Information Systems [490209-A]
B7: 2025 | H7: All | AA7: Awards with obligations | AB7: =IF(Trends!$B$6<>"","",SUM(TransactionsData[First selected award])) -> 34 | AM7: Directviz Solutions, LLC [YXH4AGD2LGF5] | AN7: Division of Social and Economic Science [490405-A]
AA8: Vendors with obligations | AB8: =IF(Trends!$B$6<>"","",SUM(TransactionsData[First selected vendor])) -> 18 | AM8: Expediteinfotech, Inc. [KX6EDEAPTKH5] | AN8: National Center for Science and Engineering Statistics [490403-A]
B9: Funding office | N9: Current award type | AA9: Transactions | AB9: =IF(Trends!$B$6<>"","",SUM(TransactionsData[Selected])) -> 106 | AM9: Gartner, Inc. [CFALLJBGZ697] | AN9: National Science Board [490001-A]
B10: All | N10: All | AM10: GBS Dakota IT, LLC [G9E9BR9MG9N7] | AN10: NSF — office not specified [4900-A]
AB11: =IF(OR(Dashboard!$B$7="All",NOT(ISNUMBER(Dashboard!$B$7))),0,IF(AND(COUNTIFS(Trends!$I$26:$I$28,Dashboard!$B$7)=1,COUNTIFS(Trends!$I$26:$I$28,Dashboard!$B$7-1)=1),IF(AND(INDEX(Trends!$J$26:$J$28,MATCH(Dashboard!$B$7,Trends!$I$26:$I$28,0))=1,INDEX(Trends!$J$26:$J$28,MATCH(Dashboard!$B$7-1,Trends!$I$26:$I$28,0))=1),1,0),0)) -> 1 | AM11: GBS Solutions Corp [NKNSTJBPABX9] | AN11: Office of Budget Finance and Award Management [491000-A]
B12: =Trends!$B$6 | AM12: Ibex It Business Experts LLC [XPA8X2BWTD49] | AN12: Office of Information Resource Management [490200-A]
AB13: =IF(AB11=1,INDEX(Trends!$D$26:$D$28,MATCH(Dashboard!$B$7-1,Trends!$I$26:$I$28,0)),"") -> 97611271 | AM13: Lynker Corporation [MCLPKDBCDKY7] | AN13: Office of the Inspector General [490002-A]
B14: Net obligations | H14: Awards with obligations | N14: Vendors with obligations | T14: Transactions | AB14: =IF(AB11=1,INDEX(Trends!$E$26:$E$28,MATCH(Dashboard!$B$7-1,Trends!$I$26:$I$28,0)),"") -> 34 | AM14: Montage + Magnum, LLC [XLJSS2NNHU27]
B15: =IF(Trends!$B$6<>"","—",TEXT(AB6/1000000,"$0.00")&"M") -> $120.32M | H15: =IF(Trends!$B$6<>"","—",AB7) -> 34 | N15: =IF(Trends!$B$6<>"","—",AB8) -> 18 | T15: =IF(Trends!$B$6<>"","—",AB9) -> 106 | AB15: =IF(AB11=1,INDEX(Trends!$F$26:$F$28,MATCH(Dashboard!$B$7-1,Trends!$I$26:$I$28,0)),"") -> 18 | AM15: Professional Management Consulting Services LLC [CD2QDS1EFHP3]
AB16: =IF(AB11=1,INDEX(Trends!$G$26:$G$28,MATCH(Dashboard!$B$7-1,Trends!$I$26:$I$28,0)),"") -> 74 | AM16: Rei Systems, Inc. [YRNMVN96JC17]
B17: =IF(OR(Trends!$B$6<>"",AB11<>1),"",IF(AB13>0,TEXT((AB6-AB13)/AB13,"+0.0%;-0.0%;+0.0%")&" vs FY"&(Dashboard!$B$7-1),"")) -> +23.3% vs FY2024 | H17: =IF(OR(Trends!$B$6<>"",AB11<>1),"",IF(AB7=AB14,"No change vs FY"&(Dashboard!$B$7-1),TEXT(AB7-AB14,"+#,##0;-#,##0;0")&" vs FY"&(Dashboard!$B$7-1))) -> No change vs FY2024 | N17: =IF(OR(Trends!$B$6<>"",AB11<>1),"",IF(AB8=AB15,"No change vs FY"&(Dashboard!$B$7-1),TEXT(AB8-AB15,"+#,##0;-#,##0;0")&" vs FY"&(Dashboard!$B$7-1))) -> No change vs FY2024 | T17: =IF(OR(Trends!$B$6<>"",AB11<>1),"",IF(AB9=AB16,"No change vs FY"&(Dashboard!$B$7-1),TEXT(AB9-AB16,"+#,##0;-#,##0;0")&" vs FY"&(Dashboard!$B$7-1))) -> +32 vs FY2024 | AM17: Scope It Consulting, LLC [KN99UT9W5N77]
AM18: Spatial Front Inc. [J1ADW6BL8MN5]
B19: =IF(Dashboard!$B$7="All","All covered years",IF(Dashboard!$B$7="","No reporting period","FY"&Dashboard!$B$7)) -> FY2025 | H19: =IF(Dashboard!$B$7="All","All covered years",IF(Dashboard!$B$7="","No reporting period","FY"&Dashboard!$B$7)) -> FY2025 | N19: =IF(Dashboard!$B$7="All","All covered years",IF(Dashboard!$B$7="","No reporting period","FY"&Dashboard!$B$7)) -> FY2025 | T19: =IF(Dashboard!$B$7="All","All covered years",IF(Dashboard!$B$7="","No reporting period","FY"&Dashboard!$B$7)) -> FY2025 | AM19: Strategic Communications LLC [LJZRP7SE5LN4]
B20: Charts in USD millions | AM20: Thundercat Technology, LLC [UER4AJLUB8D5]
B21: Annual net obligations | N21: Leading vendors | AA21: Category | AB21: Net obligations | AD21: Category | AE21: Net obligations | AM21: University Corporation For Advanced Internet Development [DZEBKFRD1ZN6]
AA22: =IF(Trends!A26="","",Trends!A26) -> FY2023 | AB22: =IF((IF(Trends!$B$6<>"","",Trends!D26))="","",(IF(Trends!$B$6<>"","",Trends!D26))/1000000) -> 24.025004 | AD22: =IF(Trends!$B$6<>"","",IF(COUNTIFS(VendorGroups[Source actions],">0")>5,"Other vendors","")) -> Other vendors | AE22: =IF((IF(Trends!$B$6<>"","",IF(AD22="","",SUMIFS(VendorGroups[Source net],VendorGroups[Source rank],">5"))))="","",(IF(Trends!$B$6<>"","",IF(AD22="","",SUMIFS(VendorGroups[Source net],VendorGroups[Source rank],">5"))))/1000000) -> 17.767082
AA23: =IF(Trends!A27="","",Trends!A27) -> FY2024 | AB23: =IF((IF(Trends!$B$6<>"","",Trends!D27))="","",(IF(Trends!$B$6<>"","",Trends!D27))/1000000) -> 97.611271 | AD23: =IF('Vendors & Buyers'!B12="","",'Vendors & Buyers'!B12) -> Strategic Communications LLC | AE23: =IF((IF(AD23="","",'Vendors & Buyers'!D12))="","",(IF(AD23="","",'Vendors & Buyers'!D12))/1000000) -> 7.2373027
AA24: =IF(Trends!A28="","",Trends!A28) -> FY2025 | AB24: =IF((IF(Trends!$B$6<>"","",Trends!D28))="","",(IF(Trends!$B$6<>"","",Trends!D28))/1000000) -> 120.31667 | AD24: =IF('Vendors & Buyers'!B11="","",'Vendors & Buyers'!B11) -> Spatial Front Inc. | AE24: =IF((IF(AD24="","",'Vendors & Buyers'!D11))="","",(IF(AD24="","",'Vendors & Buyers'!D11))/1000000) -> 8.845386
AD25: =IF('Vendors & Buyers'!B10="","",'Vendors & Buyers'!B10) -> Civicactions, Inc. | AE25: =IF((IF(AD25="","",'Vendors & Buyers'!D10))="","",(IF(AD25="","",'Vendors & Buyers'!D10))/1000000) -> 10.76911
AD26: =IF('Vendors & Buyers'!B9="","",'Vendors & Buyers'!B9) -> Directviz Solutions, LLC | AE26: =IF((IF(AD26="","",'Vendors & Buyers'!D9))="","",(IF(AD26="","",'Vendors & Buyers'!D9))/1000000) -> 22.532734
AD27: =IF('Vendors & Buyers'!B8="","",'Vendors & Buyers'!B8) -> Booz Allen Hamilton Inc. | AE27: =IF((IF(AD27="","",'Vendors & Buyers'!D8))="","",(IF(AD27="","",'Vendors & Buyers'!D8))/1000000) -> 53.165051
B36: Annual and quarterly history use all covered years. Rankings and breakdowns use the selected fiscal year.
B38: Contract awards & spend — breakdowns
B39: ="USD millions | Period: "&IF(B7="All","All covered years",IF(B7="","Not supplied","FY"&B7))&" | Award type: "&N10&CHAR(10)&"Vendor: "&H7&" | Funding office: "&B10 -> USD millions | Period: FY2025 | Award type: All Vendor: All | Funding office: All | AB39: =MAX(1,COUNTIFS(Trends!$K$34:$K$45,">0")) -> 4
B40: Quarterly history · all covered years | N40: Current award types
AA41: Category | AB41: Net obligations | AD41: Category | AE41: Net obligations | AG41: Category | AH41: Net obligations | AJ41: Category | AK41: Net obligations
AA42: =IF(Trends!A34="","",Trends!A34) -> FY2023 Q1 | AB42: =IF((IF(OR(Trends!$B$6<>"",AA42=""),"",Trends!D34))="","",(IF(OR(Trends!$B$6<>"",AA42=""),"",Trends!D34))/1000000) -> 6.1156203 | AD42: Purchase Order | AE42: =IF((IF(AD42="","",IF(Trends!$B$6<>"","",SUMIFS(TransactionsData[Obligations],TransactionsData[Current award type],AD42,TransactionsData[Selected],1))))="","",(IF(AD42="","",IF(Trends!$B$6<>"","",SUMIFS(TransactionsData[Obligations],TransactionsData[Current award type],AD42,TransactionsData[Selected],1))))/1000000) -> 0.039079 | AG42: Total Small Business | AH42: =IF((IF(AG42="","",IF(Trends!$B$6<>"","",SUMIFS(TransactionsData[Obligations],TransactionsData[Current set-aside],AG42,TransactionsData[Selected],1))))="","",(IF(AG42="","",IF(Trends!$B$6<>"","",SUMIFS(TransactionsData[Obligations],TransactionsData[Current set-aside],AG42,TransactionsData[Selected],1))))/1000000) -> 42.644429 | AJ42: Virginia | AK42: =IF((IF(AJ42="","",IF(Trends!$B$6<>"","",SUMIFS(TransactionsData[Obligations],TransactionsData[Performance state],AJ42,TransactionsData[Selected],1))))="","",(IF(AJ42="","",IF(Trends!$B$6<>"","",SUMIFS(TransactionsData[Obligations],TransactionsData[Performance state],AJ42,TransactionsData[Selected],1))))/1000000) -> 103.48523
AA43: =IF(Trends!A35="","",Trends!A35) -> FY2023 Q2 | AB43: =IF((IF(OR(Trends!$B$6<>"",AA43=""),"",Trends!D35))="","",(IF(OR(Trends!$B$6<>"",AA43=""),"",Trends!D35))/1000000) -> 9.2182711 | AD43: Delivery Order | AE43: =IF((IF(AD43="","",IF(Trends!$B$6<>"","",SUMIFS(TransactionsData[Obligations],TransactionsData[Current award type],AD43,TransactionsData[Selected],1))))="","",(IF(AD43="","",IF(Trends!$B$6<>"","",SUMIFS(TransactionsData[Obligations],TransactionsData[Current award type],AD43,TransactionsData[Selected],1))))/1000000) -> 80.714699 | AG43: No Set-Aside Used | AH43: =IF((IF(AG43="","",IF(Trends!$B$6<>"","",SUMIFS(TransactionsData[Obligations],TransactionsData[Current set-aside],AG43,TransactionsData[Selected],1))))="","",(IF(AG43="","",IF(Trends!$B$6<>"","",SUMIFS(TransactionsData[Obligations],TransactionsData[Current set-aside],AG43,TransactionsData[Selected],1))))/1000000) -> 70.815302 | AJ43: Utah | AK43: =IF((IF(AJ43="","",IF(Trends!$B$6<>"","",SUMIFS(TransactionsData[Obligations],TransactionsData[Performance state],AJ43,TransactionsData[Selected],1))))="","",(IF(AJ43="","",IF(Trends!$B$6<>"","",SUMIFS(TransactionsData[Obligations],TransactionsData[Performance state],AJ43,TransactionsData[Selected],1))))/1000000) -> 0.06175948
AA44: =IF(Trends!A36="","",Trends!A36) -> FY2023 Q3 | AB44: =IF((IF(OR(Trends!$B$6<>"",AA44=""),"",Trends!D36))="","",(IF(OR(Trends!$B$6<>"",AA44=""),"",Trends!D36))/1000000) -> 3.4499029 | AD44: Definitive Contract | AE44: =IF((IF(AD44="","",IF(Trends!$B$6<>"","",SUMIFS(TransactionsData[Obligations],TransactionsData[Current award type],AD44,TransactionsData[Selected],1))))="","",(IF(AD44="","",IF(Trends!$B$6<>"","",SUMIFS(TransactionsData[Obligations],TransactionsData[Current award type],AD44,TransactionsData[Selected],1))))/1000000) -> 3.2298286 | AG44: Competitive 8(a) | AH44: =IF((IF(AG44="","",IF(Trends!$B$6<>"","",SUMIFS(TransactionsData[Obligations],TransactionsData[Current set-aside],AG44,TransactionsData[Selected],1))))="","",(IF(AG44="","",IF(Trends!$B$6<>"","",SUMIFS(TransactionsData[Obligations],TransactionsData[Current set-aside],AG44,TransactionsData[Selected],1))))/1000000) -> 5.2792241 | AJ44: Maryland | AK44: =IF((IF(AJ44="","",IF(Trends!$B$6<>"","",SUMIFS(TransactionsData[Obligations],TransactionsData[Performance state],AJ44,TransactionsData[Selected],1))))="","",(IF(AJ44="","",IF(Trends!$B$6<>"","",SUMIFS(TransactionsData[Obligations],TransactionsData[Performance state],AJ44,TransactionsData[Selected],1))))/1000000) -> 5.0153911
AA45: =IF(Trends!A37="","",Trends!A37) -> FY2023 Q4 | AB45: =IF((IF(OR(Trends!$B$6<>"",AA45=""),"",Trends!D37))="","",(IF(OR(Trends!$B$6<>"",AA45=""),"",Trends!D37))/1000000) -> 5.2412096 | AD45: BPA Call | AE45: =IF((IF(AD45="","",IF(Trends!$B$6<>"","",SUMIFS(TransactionsData[Obligations],TransactionsData[Current award type],AD45,TransactionsData[Selected],1))))="","",(IF(AD45="","",IF(Trends!$B$6<>"","",SUMIFS(TransactionsData[Obligations],TransactionsData[Current award type],AD45,TransactionsData[Selected],1))))/1000000) -> 36.33306 | AG45: 8(a) Sole Source | AH45: =IF((IF(AG45="","",IF(Trends!$B$6<>"","",SUMIFS(TransactionsData[Obligations],TransactionsData[Current set-aside],AG45,TransactionsData[Selected],1))))="","",(IF(AG45="","",IF(Trends!$B$6<>"","",SUMIFS(TransactionsData[Obligations],TransactionsData[Current set-aside],AG45,TransactionsData[Selected],1))))/1000000) -> 1.5777104 | AJ45: Georgia | AK45: =IF((IF(AJ45="","",IF(Trends!$B$6<>"","",SUMIFS(TransactionsData[Obligations],TransactionsData[Performance state],AJ45,TransactionsData[Selected],1))))="","",(IF(AJ45="","",IF(Trends!$B$6<>"","",SUMIFS(TransactionsData[Obligations],TransactionsData[Performance state],AJ45,TransactionsData[Selected],1))))/1000000) -> 0.48979172
AA46: =IF(Trends!A38="","",Trends!A38) -> FY2024 Q1 | AB46: =IF((IF(OR(Trends!$B$6<>"",AA46=""),"",Trends!D38))="","",(IF(OR(Trends!$B$6<>"",AA46=""),"",Trends!D38))/1000000) -> 25.40001 | AJ46: District of Columbia | AK46: =IF((IF(AJ46="","",IF(Trends!$B$6<>"","",SUMIFS(TransactionsData[Obligations],TransactionsData[Performance state],AJ46,TransactionsData[Selected],1))))="","",(IF(AJ46="","",IF(Trends!$B$6<>"","",SUMIFS(TransactionsData[Obligations],TransactionsData[Performance state],AJ46,TransactionsData[Selected],1))))/1000000) -> 0.49538297
AA47: =IF(Trends!A39="","",Trends!A39) -> FY2024 Q2 | AB47: =IF((IF(OR(Trends!$B$6<>"",AA47=""),"",Trends!D39))="","",(IF(OR(Trends!$B$6<>"",AA47=""),"",Trends!D39))/1000000) -> 7.4993187 | AJ47: California | AK47: =IF((IF(AJ47="","",IF(Trends!$B$6<>"","",SUMIFS(TransactionsData[Obligations],TransactionsData[Performance state],AJ47,TransactionsData[Selected],1))))="","",(IF(AJ47="","",IF(Trends!$B$6<>"","",SUMIFS(TransactionsData[Obligations],TransactionsData[Performance state],AJ47,TransactionsData[Selected],1))))/1000000) -> 10.76911
AA48: =IF(Trends!A40="","",Trends!A40) -> FY2024 Q3 | AB48: =IF((IF(OR(Trends!$B$6<>"",AA48=""),"",Trends!D40))="","",(IF(OR(Trends!$B$6<>"",AA48=""),"",Trends!D40))/1000000) -> 23.742006
AA49: =IF(Trends!A41="","",Trends!A41) -> FY2024 Q4 | AB49: =IF((IF(OR(Trends!$B$6<>"",AA49=""),"",Trends!D41))="","",(IF(OR(Trends!$B$6<>"",AA49=""),"",Trends!D41))/1000000) -> 40.969937
AA50: =IF(Trends!A42="","",Trends!A42) -> FY2025 Q1 | AB50: =IF((IF(OR(Trends!$B$6<>"",AA50=""),"",Trends!D42))="","",(IF(OR(Trends!$B$6<>"",AA50=""),"",Trends!D42))/1000000) -> 15.412439
AA51: =IF(Trends!A43="","",Trends!A43) -> FY2025 Q2 | AB51: =IF((IF(OR(Trends!$B$6<>"",AA51=""),"",Trends!D43))="","",(IF(OR(Trends!$B$6<>"",AA51=""),"",Trends!D43))/1000000) -> 39.93078
AA52: =IF(Trends!A44="","",Trends!A44) -> FY2025 Q3 | AB52: =IF((IF(OR(Trends!$B$6<>"",AA52=""),"",Trends!D44))="","",(IF(OR(Trends!$B$6<>"",AA52=""),"",Trends!D44))/1000000) -> 14.093815
AA53: =IF(Trends!A45="","",Trends!A45) -> FY2025 Q4 | AB53: =IF((IF(OR(Trends!$B$6<>"",AA53=""),"",Trends!D45))="","",(IF(OR(Trends!$B$6<>"",AA53=""),"",Trends!D45))/1000000) -> 50.879631
B58: Current set-asides | N58: Place of performance by state
B76: Current award snapshots; set-asides do not measure small-business participation. Location is place of performance.

Sheet Trends
A2: Trends
A3: ="Buyer: "&IF(Transactions!B3="","Not supplied",Transactions!B3)&" | History: "&IF(Transactions!B4="","Not supplied",TEXT(Transactions!B4,"mmm d, yyyy"))&" through "&IF(Transactions!D4="","Not supplied",TEXT(Transactions!D4,"mmm d, yyyy"))&" | Award type: "&Dashboard!$N$10 -> Buyer: National Science Foundation | History: Oct 1, 2022 through Sep 30, 2025 | Award type: All
A4: ="Vendor: "&Dashboard!H7&CHAR(10)&"Funding office: "&Dashboard!B10 -> Vendor: All Funding office: All
A5: Chart in USD millions; supporting tables in USD.
A6: Report status | B6: =IF(COUNTIF(AwardsData[Input check],"New category: refresh report")>0,"Refresh report for new classifications",IF(COUNTA(TransactionsData[Transaction ID])=0,"Awaiting source data",IF(OR(NOT(ISNUMBER(Transactions!B4)),NOT(ISNUMBER(Transactions!D4)),Transactions!B4>Transactions!D4,NOT(ISNUMBER(Transactions!G4))),"Enter valid coverage and retrieval dates",IF(COUNTIFS(TransactionsData[Input check],"?*")+COUNTIFS(AwardsData[Input check],"?*")+COUNTIFS(VendorGroups[Input check],"?*")+COUNTIFS(OfficeGroups[Input check],"?*")>0,"Review source input checks",IF(OR(Dashboard!$AB$2="Invalid",Dashboard!$AB$3="Invalid",AND(Dashboard!$N$10<>"All",COUNTIFS(TypeChoices,Dashboard!$N$10)<>1)),"Choose valid Dashboard filters",IF(NOT(OR(Dashboard!$B$7="All",COUNTIFS($I$26:$I$28,Dashboard!$B$7)=1)),"Choose a reporting year",IF(SUMPRODUCT((TransactionsData[Eligible]=1)*(COUNTIFS(VendorGroups[Record ID],TransactionsData[Vendor ID])<>1))+SUMPRODUCT((TransactionsData[Eligible]=1)*(COUNTIFS(OfficeGroups[Record ID],TransactionsData[Funding office ID])<>1))>0,"Add missing vendor or office registry IDs","")))))))
A23: Four-quarter average begins after four complete consecutive quarters. Negative values retain their sign.
A25: Fiscal year | B25: Positive obligations | C25: Deobligations | D25: Net obligations | E25: Awards with obligations | F25: Vendors with obligations | G25: Transactions | H25: YoY change | I25: Year key | J25: Complete year
A26: =IF(I26="","","FY"&I26) -> FY2023 | B26: =IF(I26="","",IF(Trends!$B$6<>"","",SUMIFS(TransactionsData[Positive],TransactionsData[FY],I26,TransactionsData[Dimension match],1))) -> 24025004 | C26: =IF(I26="","",IF(Trends!$B$6<>"","",SUMIFS(TransactionsData[Deobligations],TransactionsData[FY],I26,TransactionsData[Dimension match],1))) -> 0 | D26: =IF(I26="","",IF(Trends!$B$6<>"","",SUMIFS(TransactionsData[Obligations],TransactionsData[FY],I26,TransactionsData[Dimension match],1))) -> 24025004 | E26: =IF(I26="","",IF(Trends!$B$6<>"","",SUMIFS(TransactionsData[First annual award],TransactionsData[FY],I26,TransactionsData[Dimension match],1))) -> 16 | F26: =IF(I26="","",IF(Trends!$B$6<>"","",SUMIFS(TransactionsData[First annual vendor],TransactionsData[FY],I26,TransactionsData[Dimension match],1))) -> 10 | G26: =IF(I26="","",IF(Trends!$B$6<>"","",COUNTIFS(TransactionsData[FY],I26,TransactionsData[Dimension match],1))) -> 34 | H26: ="" | I26: 2023 | J26: =IF(I26="","",IF(AND(Transactions!$B$4<=DATE(I26-1,10,1),Transactions!$D$4>=DATE(I26,9,30)),1,0)) -> 1
A27: =IF(I27="","","FY"&I27) -> FY2024 | B27: =IF(I27="","",IF(Trends!$B$6<>"","",SUMIFS(TransactionsData[Positive],TransactionsData[FY],I27,TransactionsData[Dimension match],1))) -> 97611271 | C27: =IF(I27="","",IF(Trends!$B$6<>"","",SUMIFS(TransactionsData[Deobligations],TransactionsData[FY],I27,TransactionsData[Dimension match],1))) -> 0 | D27: =IF(I27="","",IF(Trends!$B$6<>"","",SUMIFS(TransactionsData[Obligations],TransactionsData[FY],I27,TransactionsData[Dimension match],1))) -> 97611271 | E27: =IF(I27="","",IF(Trends!$B$6<>"","",SUMIFS(TransactionsData[First annual award],TransactionsData[FY],I27,TransactionsData[Dimension match],1))) -> 34 | F27: =IF(I27="","",IF(Trends!$B$6<>"","",SUMIFS(TransactionsData[First annual vendor],TransactionsData[FY],I27,TransactionsData[Dimension match],1))) -> 18 | G27: =IF(I27="","",IF(Trends!$B$6<>"","",COUNTIFS(TransactionsData[FY],I27,TransactionsData[Dimension match],1))) -> 74 | H27: =IF(AND(Trends!$B$6="",J27=1,J26=1,D26>0),(D27-D26)/D26,"") -> 3.0629035 | I27: 2024 | J27: =IF(I27="","",IF(AND(Transactions!$B$4<=DATE(I27-1,10,1),Transactions!$D$4>=DATE(I27,9,30)),1,0)) -> 1
A28: =IF(I28="","","FY"&I28) -> FY2025 | B28: =IF(I28="","",IF(Trends!$B$6<>"","",SUMIFS(TransactionsData[Positive],TransactionsData[FY],I28,TransactionsData[Dimension match],1))) -> 1.2161709e+08 | C28: =IF(I28="","",IF(Trends!$B$6<>"","",SUMIFS(TransactionsData[Deobligations],TransactionsData[FY],I28,TransactionsData[Dimension match],1))) -> -1300426.3 | D28: =IF(I28="","",IF(Trends!$B$6<>"","",SUMIFS(TransactionsData[Obligations],TransactionsData[FY],I28,TransactionsData[Dimension match],1))) -> 1.2031667e+08 | E28: =IF(I28="","",IF(Trends!$B$6<>"","",SUMIFS(TransactionsData[First annual award],TransactionsData[FY],I28,TransactionsData[Dimension match],1))) -> 34 | F28: =IF(I28="","",IF(Trends!$B$6<>"","",SUMIFS(TransactionsData[First annual vendor],TransactionsData[FY],I28,TransactionsData[Dimension match],1))) -> 18 | G28: =IF(I28="","",IF(Trends!$B$6<>"","",COUNTIFS(TransactionsData[FY],I28,TransactionsData[Dimension match],1))) -> 106 | H28: =IF(AND(Trends!$B$6="",J28=1,J27=1,D27>0),(D28-D27)/D27,"") -> 0.23261038 | I28: 2025 | J28: =IF(I28="","",IF(AND(Transactions!$B$4<=DATE(I28-1,10,1),Transactions!$D$4>=DATE(I28,9,30)),1,0)) -> 1
A33: Quarter | B33: From | C33: Through | D33: Net obligations | E33: Deobligations | F33: Transactions | G33: 4-quarter average | H33: Coverage | I33: Year key | J33: Quarter key | K33: Selected order | L33: Net obligations | M33: 4-quarter average
A34: =IF(I34="","","FY"&I34&" Q"&J34) -> FY2023 Q1 | B34: =IF(I34="","",DATE(I34-IF(J34=1,1,0),CHOOSE(J34,10,1,4,7),1)) -> 44835 | C34: =IF(B34="","",EDATE(B34,3)-1) -> 44926 | D34: =IF(I34="","",IF(Trends!$B$6<>"","",SUMIFS(TransactionsData[Obligations],TransactionsData[FY],I34,TransactionsData[Quarter],J34,TransactionsData[Dimension match],1))) -> 6115620.3 | E34: =IF(I34="","",IF(Trends!$B$6<>"","",SUMIFS(TransactionsData[Deobligations],TransactionsData[FY],I34,TransactionsData[Quarter],J34,TransactionsData[Dimension match],1))) -> 0 | F34: =IF(I34="","",IF(Trends!$B$6<>"","",COUNTIFS(TransactionsData[FY],I34,TransactionsData[Quarter],J34,TransactionsData[Dimension match],1))) -> 6 | H34: =IF(I34="","",IF(AND(B34>=Transactions!$B$4,C34<=Transactions!$D$4),"Complete","Partial")) -> Complete | I34: 2023 | J34: 1 | K34: =IF(OR(I34="",AND(Dashboard!$B$7<>"All",I34<>Dashboard!$B$7)),0,IF(Dashboard!$B$7="All",ROW()-33,J34)) -> 0 | L34: =IF(OR(Trends!$B$6<>"",I34=""),"",D34/1000000) -> 6.1156203
A35: =IF(I35="","","FY"&I35&" Q"&J35) -> FY2023 Q2 | B35: =IF(I35="","",DATE(I35-IF(J35=1,1,0),CHOOSE(J35,10,1,4,7),1)) -> 44927 | C35: =IF(B35="","",EDATE(B35,3)-1) -> 45016 | D35: =IF(I35="","",IF(Trends!$B$6<>"","",SUMIFS(TransactionsData[Obligations],TransactionsData[FY],I35,TransactionsData[Quarter],J35,TransactionsData[Dimension match],1))) -> 9218271.1 | E35: =IF(I35="","",IF(Trends!$B$6<>"","",SUMIFS(TransactionsData[Deobligations],TransactionsData[FY],I35,TransactionsData[Quarter],J35,TransactionsData[Dimension match],1))) -> 0 | F35: =IF(I35="","",IF(Trends!$B$6<>"","",COUNTIFS(TransactionsData[FY],I35,TransactionsData[Quarter],J35,TransactionsData[Dimension match],1))) -> 6 | H35: =IF(I35="","",IF(AND(B35>=Transactions!$B$4,C35<=Transactions!$D$4),"Complete","Partial")) -> Complete | I35: 2023 | J35: 2 | K35: =IF(OR(I35="",AND(Dashboard!$B$7<>"All",I35<>Dashboard!$B$7)),0,IF(Dashboard!$B$7="All",ROW()-33,J35)) -> 0 | L35: =IF(OR(Trends!$B$6<>"",I35=""),"",D35/1000000) -> 9.2182711
A36: =IF(I36="","","FY"&I36&" Q"&J36) -> FY2023 Q3 | B36: =IF(I36="","",DATE(I36-IF(J36=1,1,0),CHOOSE(J36,10,1,4,7),1)) -> 45017 | C36: =IF(B36="","",EDATE(B36,3)-1) -> 45107 | D36: =IF(I36="","",IF(Trends!$B$6<>"","",SUMIFS(TransactionsData[Obligations],TransactionsData[FY],I36,TransactionsData[Quarter],J36,TransactionsData[Dimension match],1))) -> 3449902.9 | E36: =IF(I36="","",IF(Trends!$B$6<>"","",SUMIFS(TransactionsData[Deobligations],TransactionsData[FY],I36,TransactionsData[Quarter],J36,TransactionsData[Dimension match],1))) -> 0 | F36: =IF(I36="","",IF(Trends!$B$6<>"","",COUNTIFS(TransactionsData[FY],I36,TransactionsData[Quarter],J36,TransactionsData[Dimension match],1))) -> 7 | H36: =IF(I36="","",IF(AND(B36>=Transactions!$B$4,C36<=Transactions!$D$4),"Complete","Partial")) -> Complete | I36: 2023 | J36: 3 | K36: =IF(OR(I36="",AND(Dashboard!$B$7<>"All",I36<>Dashboard!$B$7)),0,IF(Dashboard!$B$7="All",ROW()-33,J36)) -> 0 | L36: =IF(OR(Trends!$B$6<>"",I36=""),"",D36/1000000) -> 3.4499029
A37: =IF(I37="","","FY"&I37&" Q"&J37) -> FY2023 Q4 | B37: =IF(I37="","",DATE(I37-IF(J37=1,1,0),CHOOSE(J37,10,1,4,7),1)) -> 45108 | C37: =IF(B37="","",EDATE(B37,3)-1) -> 45199 | D37: =IF(I37="","",IF(Trends!$B$6<>"","",SUMIFS(TransactionsData[Obligations],TransactionsData[FY],I37,TransactionsData[Quarter],J37,TransactionsData[Dimension match],1))) -> 5241209.6 | E37: =IF(I37="","",IF(Trends!$B$6<>"","",SUMIFS(TransactionsData[Deobligations],TransactionsData[FY],I37,TransactionsData[Quarter],J37,TransactionsData[Dimension match],1))) -> 0 | F37: =IF(I37="","",IF(Trends!$B$6<>"","",COUNTIFS(TransactionsData[FY],I37,TransactionsData[Quarter],J37,TransactionsData[Dimension match],1))) -> 15 | G37: =IF(AND(Trends!$B$6="",COUNTIFS(H34:H37,"Complete")=4),SUM(D34:D37)/4,"") -> 6006251 | H37: =IF(I37="","",IF(AND(B37>=Transactions!$B$4,C37<=Transactions!$D$4),"Complete","Partial")) -> Complete | I37: 2023 | J37: 4 | K37: =IF(OR(I37="",AND(Dashboard!$B$7<>"All",I37<>Dashboard!$B$7)),0,IF(Dashboard!$B$7="All",ROW()-33,J37)) -> 0 | L37: =IF(OR(Trends!$B$6<>"",I37=""),"",D37/1000000) -> 5.2412096 | M37: =IF(G37="","",G37/1000000) -> 6.006251
A38: =IF(I38="","","FY"&I38&" Q"&J38) -> FY2024 Q1 | B38: =IF(I38="","",DATE(I38-IF(J38=1,1,0),CHOOSE(J38,10,1,4,7),1)) -> 45200 | C38: =IF(B38="","",EDATE(B38,3)-1) -> 45291 | D38: =IF(I38="","",IF(Trends!$B$6<>"","",SUMIFS(TransactionsData[Obligations],TransactionsData[FY],I38,TransactionsData[Quarter],J38,TransactionsData[Dimension match],1))) -> 25400010 | E38: =IF(I38="","",IF(Trends!$B$6<>"","",SUMIFS(TransactionsData[Deobligations],TransactionsData[FY],I38,TransactionsData[Quarter],J38,TransactionsData[Dimension match],1))) -> 0 | F38: =IF(I38="","",IF(Trends!$B$6<>"","",COUNTIFS(TransactionsData[FY],I38,TransactionsData[Quarter],J38,TransactionsData[Dimension match],1))) -> 13 | G38: =IF(AND(Trends!$B$6="",COUNTIFS(H35:H38,"Complete")=4),SUM(D35:D38)/4,"") -> 10827348 | H38: =IF(I38="","",IF(AND(B38>=Transactions!$B$4,C38<=Transactions!$D$4),"Complete","Partial")) -> Complete | I38: 2024 | J38: 1 | K38: =IF(OR(I38="",AND(Dashboard!$B$7<>"All",I38<>Dashboard!$B$7)),0,IF(Dashboard!$B$7="All",ROW()-33,J38)) -> 0 | L38: =IF(OR(Trends!$B$6<>"",I38=""),"",D38/1000000) -> 25.40001 | M38: =IF(G38="","",G38/1000000) -> 10.827348
A39: =IF(I39="","","FY"&I39&" Q"&J39) -> FY2024 Q2 | B39: =IF(I39="","",DATE(I39-IF(J39=1,1,0),CHOOSE(J39,10,1,4,7),1)) -> 45292 | C39: =IF(B39="","",EDATE(B39,3)-1) -> 45382 | D39: =IF(I39="","",IF(Trends!$B$6<>"","",SUMIFS(TransactionsData[Obligations],TransactionsData[FY],I39,TransactionsData[Quarter],J39,TransactionsData[Dimension match],1))) -> 7499318.7 | E39: =IF(I39="","",IF(Trends!$B$6<>"","",SUMIFS(TransactionsData[Deobligations],TransactionsData[FY],I39,TransactionsData[Quarter],J39,TransactionsData[Dimension match],1))) -> 0 | F39: =IF(I39="","",IF(Trends!$B$6<>"","",COUNTIFS(TransactionsData[FY],I39,TransactionsData[Quarter],J39,TransactionsData[Dimension match],1))) -> 16 | G39: =IF(AND(Trends!$B$6="",COUNTIFS(H36:H39,"Complete")=4),SUM(D36:D39)/4,"") -> 10397610 | H39: =IF(I39="","",IF(AND(B39>=Transactions!$B$4,C39<=Transactions!$D$4),"Complete","Partial")) -> Complete | I39: 2024 | J39: 2 | K39: =IF(OR(I39="",AND(Dashboard!$B$7<>"All",I39<>Dashboard!$B$7)),0,IF(Dashboard!$B$7="All",ROW()-33,J39)) -> 0 | L39: =IF(OR(Trends!$B$6<>"",I39=""),"",D39/1000000) -> 7.4993187 | M39: =IF(G39="","",G39/1000000) -> 10.39761
A40: =IF(I40="","","FY"&I40&" Q"&J40) -> FY2024 Q3 | B40: =IF(I40="","",DATE(I40-IF(J40=1,1,0),CHOOSE(J40,10,1,4,7),1)) -> 45383 | C40: =IF(B40="","",EDATE(B40,3)-1) -> 45473 | D40: =IF(I40="","",IF(Trends!$B$6<>"","",SUMIFS(TransactionsData[Obligations],TransactionsData[FY],I40,TransactionsData[Quarter],J40,TransactionsData[Dimension match],1))) -> 23742006 | E40: =IF(I40="","",IF(Trends!$B$6<>"","",SUMIFS(TransactionsData[Deobligations],TransactionsData[FY],I40,TransactionsData[Quarter],J40,TransactionsData[Dimension match],1))) -> 0 | F40: =IF(I40="","",IF(Trends!$B$6<>"","",COUNTIFS(TransactionsData[FY],I40,TransactionsData[Quarter],J40,TransactionsData[Dimension match],1))) -> 21 | G40: =IF(AND(Trends!$B$6="",COUNTIFS(H37:H40,"Complete")=4),SUM(D37:D40)/4,"") -> 15470636 | H40: =IF(I40="","",IF(AND(B40>=Transactions!$B$4,C40<=Transactions!$D$4),"Complete","Partial")) -> Complete | I40: 2024 | J40: 3 | K40: =IF(OR(I40="",AND(Dashboard!$B$7<>"All",I40<>Dashboard!$B$7)),0,IF(Dashboard!$B$7="All",ROW()-33,J40)) -> 0 | L40: =IF(OR(Trends!$B$6<>"",I40=""),"",D40/1000000) -> 23.742006 | M40: =IF(G40="","",G40/1000000) -> 15.470636
A41: =IF(I41="","","FY"&I41&" Q"&J41) -> FY2024 Q4 | B41: =IF(I41="","",DATE(I41-IF(J41=1,1,0),CHOOSE(J41,10,1,4,7),1)) -> 45474 | C41: =IF(B41="","",EDATE(B41,3)-1) -> 45565 | D41: =IF(I41="","",IF(Trends!$B$6<>"","",SUMIFS(TransactionsData[Obligations],TransactionsData[FY],I41,TransactionsData[Quarter],J41,TransactionsData[Dimension match],1))) -> 40969937 | E41: =IF(I41="","",IF(Trends!$B$6<>"","",SUMIFS(TransactionsData[Deobligations],TransactionsData[FY],I41,TransactionsData[Quarter],J41,TransactionsData[Dimension match],1))) -> 0 | F41: =IF(I41="","",IF(Trends!$B$6<>"","",COUNTIFS(TransactionsData[FY],I41,TransactionsData[Quarter],J41,TransactionsData[Dimension match],1))) -> 24 | G41: =IF(AND(Trends!$B$6="",COUNTIFS(H38:H41,"Complete")=4),SUM(D38:D41)/4,"") -> 24402818 | H41: =IF(I41="","",IF(AND(B41>=Transactions!$B$4,C41<=Transactions!$D$4),"Complete","Partial")) -> Complete | I41: 2024 | J41: 4 | K41: =IF(OR(I41="",AND(Dashboard!$B$7<>"All",I41<>Dashboard!$B$7)),0,IF(Dashboard!$B$7="All",ROW()-33,J41)) -> 0 | L41: =IF(OR(Trends!$B$6<>"",I41=""),"",D41/1000000) -> 40.969937 | M41: =IF(G41="","",G41/1000000) -> 24.402818
A42: =IF(I42="","","FY"&I42&" Q"&J42) -> FY2025 Q1 | B42: =IF(I42="","",DATE(I42-IF(J42=1,1,0),CHOOSE(J42,10,1,4,7),1)) -> 45566 | C42: =IF(B42="","",EDATE(B42,3)-1) -> 45657 | D42: =IF(I42="","",IF(Trends!$B$6<>"","",SUMIFS(TransactionsData[Obligations],TransactionsData[FY],I42,TransactionsData[Quarter],J42,TransactionsData[Dimension match],1))) -> 15412439 | E42: =IF(I42="","",IF(Trends!$B$6<>"","",SUMIFS(TransactionsData[Deobligations],TransactionsData[FY],I42,TransactionsData[Quarter],J42,TransactionsData[Dimension match],1))) -> 0 | F42: =IF(I42="","",IF(Trends!$B$6<>"","",COUNTIFS(TransactionsData[FY],I42,TransactionsData[Quarter],J42,TransactionsData[Dimension match],1))) -> 21 | G42: =IF(AND(Trends!$B$6="",COUNTIFS(H39:H42,"Complete")=4),SUM(D39:D42)/4,"") -> 21905925 | H42: =IF(I42="","",IF(AND(B42>=Transactions!$B$4,C42<=Transactions!$D$4),"Complete","Partial")) -> Complete | I42: 2025 | J42: 1 | K42: =IF(OR(I42="",AND(Dashboard!$B$7<>"All",I42<>Dashboard!$B$7)),0,IF(Dashboard!$B$7="All",ROW()-33,J42)) -> 1 | L42: =IF(OR(Trends!$B$6<>"",I42=""),"",D42/1000000) -> 15.412439 | M42: =IF(G42="","",G42/1000000) -> 21.905925
A43: =IF(I43="","","FY"&I43&" Q"&J43) -> FY2025 Q2 | B43: =IF(I43="","",DATE(I43-IF(J43=1,1,0),CHOOSE(J43,10,1,4,7),1)) -> 45658 | C43: =IF(B43="","",EDATE(B43,3)-1) -> 45747 | D43: =IF(I43="","",IF(Trends!$B$6<>"","",SUMIFS(TransactionsData[Obligations],TransactionsData[FY],I43,TransactionsData[Quarter],J43,TransactionsData[Dimension match],1))) -> 39930780 | E43: =IF(I43="","",IF(Trends!$B$6<>"","",SUMIFS(TransactionsData[Deobligations],TransactionsData[FY],I43,TransactionsData[Quarter],J43,TransactionsData[Dimension match],1))) -> -90.35 | F43: =IF(I43="","",IF(Trends!$B$6<>"","",COUNTIFS(TransactionsData[FY],I43,TransactionsData[Quarter],J43,TransactionsData[Dimension match],1))) -> 26 | G43: =IF(AND(Trends!$B$6="",COUNTIFS(H40:H43,"Complete")=4),SUM(D40:D43)/4,"") -> 30013791 | H43: =IF(I43="","",IF(AND(B43>=Transactions!$B$4,C43<=Transactions!$D$4),"Complete","Partial")) -> Complete | I43: 2025 | J43: 2 | K43: =IF(OR(I43="",AND(Dashboard!$B$7<>"All",I43<>Dashboard!$B$7)),0,IF(Dashboard!$B$7="All",ROW()-33,J43)) -> 2 | L43: =IF(OR(Trends!$B$6<>"",I43=""),"",D43/1000000) -> 39.93078 | M43: =IF(G43="","",G43/1000000) -> 30.013791
A44: =IF(I44="","","FY"&I44&" Q"&J44) -> FY2025 Q3 | B44: =IF(I44="","",DATE(I44-IF(J44=1,1,0),CHOOSE(J44,10,1,4,7),1)) -> 45748 | C44: =IF(B44="","",EDATE(B44,3)-1) -> 45838 | D44: =IF(I44="","",IF(Trends!$B$6<>"","",SUMIFS(TransactionsData[Obligations],TransactionsData[FY],I44,TransactionsData[Quarter],J44,TransactionsData[Dimension match],1))) -> 14093815 | E44: =IF(I44="","",IF(Trends!$B$6<>"","",SUMIFS(TransactionsData[Deobligations],TransactionsData[FY],I44,TransactionsData[Quarter],J44,TransactionsData[Dimension match],1))) -> -960102.33 | F44: =IF(I44="","",IF(Trends!$B$6<>"","",COUNTIFS(TransactionsData[FY],I44,TransactionsData[Quarter],J44,TransactionsData[Dimension match],1))) -> 15 | G44: =IF(AND(Trends!$B$6="",COUNTIFS(H41:H44,"Complete")=4),SUM(D41:D44)/4,"") -> 27601743 | H44: =IF(I44="","",IF(AND(B44>=Transactions!$B$4,C44<=Transactions!$D$4),"Complete","Partial")) -> Complete | I44: 2025 | J44: 3 | K44: =IF(OR(I44="",AND(Dashboard!$B$7<>"All",I44<>Dashboard!$B$7)),0,IF(Dashboard!$B$7="All",ROW()-33,J44)) -> 3 | L44: =IF(OR(Trends!$B$6<>"",I44=""),"",D44/1000000) -> 14.093815 | M44: =IF(G44="","",G44/1000000) -> 27.601743
A45: =IF(I45="","","FY"&I45&" Q"&J45) -> FY2025 Q4 | B45: =IF(I45="","",DATE(I45-IF(J45=1,1,0),CHOOSE(J45,10,1,4,7),1)) -> 45839 | C45: =IF(B45="","",EDATE(B45,3)-1) -> 45930 | D45: =IF(I45="","",IF(Trends!$B$6<>"","",SUMIFS(TransactionsData[Obligations],TransactionsData[FY],I45,TransactionsData[Quarter],J45,TransactionsData[Dimension match],1))) -> 50879631 | E45: =IF(I45="","",IF(Trends!$B$6<>"","",SUMIFS(TransactionsData[Deobligations],TransactionsData[FY],I45,TransactionsData[Quarter],J45,TransactionsData[Dimension match],1))) -> -340233.63 | F45: =IF(I45="","",IF(Trends!$B$6<>"","",COUNTIFS(TransactionsData[FY],I45,TransactionsData[Quarter],J45,TransactionsData[Dimension match],1))) -> 44 | G45: =IF(AND(Trends!$B$6="",COUNTIFS(H42:H45,"Complete")=4),SUM(D42:D45)/4,"") -> 30079166 | H45: =IF(I45="","",IF(AND(B45>=Transactions!$B$4,C45<=Transactions!$D$4),"Complete","Partial")) -> Complete | I45: 2025 | J45: 4 | K45: =IF(OR(I45="",AND(Dashboard!$B$7<>"All",I45<>Dashboard!$B$7)),0,IF(Dashboard!$B$7="All",ROW()-33,J45)) -> 4 | L45: =IF(OR(Trends!$B$6<>"",I45=""),"",D45/1000000) -> 50.879631 | M45: =IF(G45="","",G45/1000000) -> 30.079166

Sheet Vendors & Buyers
A2: Vendors & Buyers
A3: ="Buyer: "&IF(Transactions!B3="","Not supplied",Transactions!B3)&" | Period: "&IF(Dashboard!$B$7="All","All covered years",IF(Dashboard!$B$7="","Not supplied","FY"&Dashboard!$B$7))&" | Award type: "&Dashboard!$N$10 -> Buyer: National Science Foundation | Period: FY2025 | Award type: All
A4: ="Vendor: "&Dashboard!H7 -> Vendor: All
A5: ="Funding office: "&Dashboard!B10 -> Funding office: All
A6: Rankings follow the filters above. Award counts include nonzero obligation or deobligation actions.
A7: Rank | B7: Vendor | C7: UEI | D7: Net obligations | E7: Deobligations | F7: Awards with obligations | G7: Transactions | H7: Record ID | I7: Source name | J7: Source UEI | K7: Source URL | L7: Filter label | M7: Source net | N7: Source deobligations | O7: Source awards | P7: Source actions | Q7: Source rank | R7: Input check
A8: =IF(Trends!$B$6<>"","",IF(COUNTIFS(VendorGroups[Source rank],1)=1,1,"")) -> 1 | B8: =IF(Trends!$B$6<>"","",IF(COUNTIFS(VendorGroups[Source rank],1)=1,IF(INDEX(VendorGroups[Source URL],MATCH(1,VendorGroups[Source rank],0))="",INDEX(VendorGroups[Source name],MATCH(1,VendorGroups[Source rank],0)),HYPERLINK(INDEX(VendorGroups[Source URL],MATCH(1,VendorGroups[Source rank],0)),INDEX(VendorGroups[Source name],MATCH(1,VendorGroups[Source rank],0)))),"")) -> Booz Allen Hamilton Inc. | C8: =IF(Trends!$B$6<>"","",IF(COUNTIFS(VendorGroups[Source rank],1)=1,IF(INDEX(VendorGroups[Source UEI],MATCH(1,VendorGroups[Source rank],0))="","Not supplied",INDEX(VendorGroups[Source UEI],MATCH(1,VendorGroups[Source rank],0))),"")) -> JCBMLGPE6Z71 | D8: =IF(Trends!$B$6<>"","",IF(COUNTIFS(VendorGroups[Source rank],1)=1,INDEX(VendorGroups[Source net],MATCH(1,VendorGroups[Source rank],0)),"")) -> 53165051 | E8: =IF(Trends!$B$6<>"","",IF(COUNTIFS(VendorGroups[Source rank],1)=1,INDEX(VendorGroups[Source deobligations],MATCH(1,VendorGroups[Source rank],0)),"")) -> 0 | F8: =IF(Trends!$B$6<>"","",IF(COUNTIFS(VendorGroups[Source rank],1)=1,INDEX(VendorGroups[Source awards],MATCH(1,VendorGroups[Source rank],0)),"")) -> 1 | G8: =IF(Trends!$B$6<>"","",IF(COUNTIFS(VendorGroups[Source rank],1)=1,INDEX(VendorGroups[Source actions],MATCH(1,VendorGroups[Source rank],0)),"")) -> 15 | H8: OHd3bTBwbEZXcHJrNFVtbnphbjRJdz09 | I8: Agility Technologies Inc. | J8: Z9M6NN4AQLF7 | K8: https://govtribe.com/vendors/agility-technologies-inc-dot-5b8b7 | L8: =IF(H8="","",I8&IF(J8="",""," ["&J8&"]")) -> Agility Technologies Inc. [Z9M6NN4AQLF7] | M8: =IF(H8="","",SUMIFS(TransactionsData[Obligations],TransactionsData[Vendor ID],H8,TransactionsData[Selected],1)) -> 592445.36 | N8: =IF(H8="","",SUMIFS(TransactionsData[Deobligations],TransactionsData[Vendor ID],H8,TransactionsData[Selected],1)) -> -90.35 | O8: =IF(H8="","",SUMIFS(TransactionsData[First vendor award],TransactionsData[Vendor ID],H8)) -> 2 | P8: =IF(H8="","",COUNTIFS(TransactionsData[Vendor ID],H8,TransactionsData[Selected],1)) -> 2 | Q8: =IF(OR(H8="",P8=0),"",COUNTIFS(VendorGroups[Source net],">"&M8,VendorGroups[Source actions],">0")+COUNTIFS(VendorGroups[Source net],M8,VendorGroups[Record ID],"<"&H8,VendorGroups[Source actions],">0")+1) -> 11 | R8: =IF(H8="",IF(COUNTA(I8:K8)>0,"Missing record ID",""),IF(COUNTIFS(VendorGroups[Record ID],H8)<>1,"Duplicate record ID",IF(I8="","Add name","")))
A9: =IF(Trends!$B$6<>"","",IF(COUNTIFS(VendorGroups[Source rank],2)=1,2,"")) -> 2 | B9: =IF(Trends!$B$6<>"","",IF(COUNTIFS(VendorGroups[Source rank],2)=1,IF(INDEX(VendorGroups[Source URL],MATCH(2,VendorGroups[Source rank],0))="",INDEX(VendorGroups[Source name],MATCH(2,VendorGroups[Source rank],0)),HYPERLINK(INDEX(VendorGroups[Source URL],MATCH(2,VendorGroups[Source rank],0)),INDEX(VendorGroups[Source name],MATCH(2,VendorGroups[Source rank],0)))),"")) -> Directviz Solutions, LLC | C9: =IF(Trends!$B$6<>"","",IF(COUNTIFS(VendorGroups[Source rank],2)=1,IF(INDEX(VendorGroups[Source UEI],MATCH(2,VendorGroups[Source rank],0))="","Not supplied",INDEX(VendorGroups[Source UEI],MATCH(2,VendorGroups[Source rank],0))),"")) -> YXH4AGD2LGF5 | D9: =IF(Trends!$B$6<>"","",IF(COUNTIFS(VendorGroups[Source rank],2)=1,INDEX(VendorGroups[Source net],MATCH(2,VendorGroups[Source rank],0)),"")) -> 22532734 | E9: =IF(Trends!$B$6<>"","",IF(COUNTIFS(VendorGroups[Source rank],2)=1,INDEX(VendorGroups[Source deobligations],MATCH(2,VendorGroups[Source rank],0)),"")) -> 0 | F9: =IF(Trends!$B$6<>"","",IF(COUNTIFS(VendorGroups[Source rank],2)=1,INDEX(VendorGroups[Source awards],MATCH(2,VendorGroups[Source rank],0)),"")) -> 5 | G9: =IF(Trends!$B$6<>"","",IF(COUNTIFS(VendorGroups[Source rank],2)=1,INDEX(VendorGroups[Source actions],MATCH(2,VendorGroups[Source rank],0)),"")) -> 11 | H9: L0R0d3dCdlZtWHRzZklTY0R1ZStPdz09 | I9: Anika Systems Incorporated | J9: Y9V7J5VN9F68 | K9: https://govtribe.com/vendors/anika-systems-incorporated-61up0 | L9: =IF(H9="","",I9&IF(J9="",""," ["&J9&"]")) -> Anika Systems Incorporated [Y9V7J5VN9F68] | M9: =IF(H9="","",SUMIFS(TransactionsData[Obligations],TransactionsData[Vendor ID],H9,TransactionsData[Selected],1)) -> 4954939.8 | N9: =IF(H9="","",SUMIFS(TransactionsData[Deobligations],TransactionsData[Vendor ID],H9,TransactionsData[Selected],1)) -> 0 | O9: =IF(H9="","",SUMIFS(TransactionsData[First vendor award],TransactionsData[Vendor ID],H9)) -> 1 | P9: =IF(H9="","",COUNTIFS(TransactionsData[Vendor ID],H9,TransactionsData[Selected],1)) -> 4 | Q9: =IF(OR(H9="",P9=0),"",COUNTIFS(VendorGroups[Source net],">"&M9,VendorGroups[Source actions],">0")+COUNTIFS(VendorGroups[Source net],M9,VendorGroups[Record ID],"<"&H9,VendorGroups[Source actions],">0")+1) -> 7 | R9: =IF(H9="",IF(COUNTA(I9:K9)>0,"Missing record ID",""),IF(COUNTIFS(VendorGroups[Record ID],H9)<>1,"Duplicate record ID",IF(I9="","Add name","")))
A10: =IF(Trends!$B$6<>"","",IF(COUNTIFS(VendorGroups[Source rank],3)=1,3,"")) -> 3 | B10: =IF(Trends!$B$6<>"","",IF(COUNTIFS(VendorGroups[Source rank],3)=1,IF(INDEX(VendorGroups[Source URL],MATCH(3,VendorGroups[Source rank],0))="",INDEX(VendorGroups[Source name],MATCH(3,VendorGroups[Source rank],0)),HYPERLINK(INDEX(VendorGroups[Source URL],MATCH(3,VendorGroups[Source rank],0)),INDEX(VendorGroups[Source name],MATCH(3,VendorGroups[Source rank],0)))),"")) -> Civicactions, Inc. | C10: =IF(Trends!$B$6<>"","",IF(COUNTIFS(VendorGroups[Source rank],3)=1,IF(INDEX(VendorGroups[Source UEI],MATCH(3,VendorGroups[Source rank],0))="","Not supplied",INDEX(VendorGroups[Source UEI],MATCH(3,VendorGroups[Source rank],0))),"")) -> XSZFHRS5QFL5 | D10: =IF(Trends!$B$6<>"","",IF(COUNTIFS(VendorGroups[Source rank],3)=1,INDEX(VendorGroups[Source net],MATCH(3,VendorGroups[Source rank],0)),"")) -> 10769110 | E10: =IF(Trends!$B$6<>"","",IF(COUNTIFS(VendorGroups[Source rank],3)=1,INDEX(VendorGroups[Source deobligations],MATCH(3,VendorGroups[Source rank],0)),"")) -> -561.71 | F10: =IF(Trends!$B$6<>"","",IF(COUNTIFS(VendorGroups[Source rank],3)=1,INDEX(VendorGroups[Source awards],MATCH(3,VendorGroups[Source rank],0)),"")) -> 1 | G10: =IF(Trends!$B$6<>"","",IF(COUNTIFS(VendorGroups[Source rank],3)=1,INDEX(VendorGroups[Source actions],MATCH(3,VendorGroups[Source rank],0)),"")) -> 10 | H10: K1ZVMVVzSS81SWIveXlWTi93b2V0UT09 | I10: Booz Allen Hamilton Inc. | J10: JCBMLGPE6Z71 | K10: https://govtribe.com/vendors/booz-allen-hamilton-inc-dot-17038 | L10: =IF(H10="","",I10&IF(J10="",""," ["&J10&"]")) -> Booz Allen Hamilton Inc. [JCBMLGPE6Z71] | M10: =IF(H10="","",SUMIFS(TransactionsData[Obligations],TransactionsData[Vendor ID],H10,TransactionsData[Selected],1)) -> 53165051 | N10: =IF(H10="","",SUMIFS(TransactionsData[Deobligations],TransactionsData[Vendor ID],H10,TransactionsData[Selected],1)) -> 0 | O10: =IF(H10="","",SUMIFS(TransactionsData[First vendor award],TransactionsData[Vendor ID],H10)) -> 1 | P10: =IF(H10="","",COUNTIFS(TransactionsData[Vendor ID],H10,TransactionsData[Selected],1)) -> 15 | Q10: =IF(OR(H10="",P10=0),"",COUNTIFS(VendorGroups[Source net],">"&M10,VendorGroups[Source actions],">0")+COUNTIFS(VendorGroups[Source net],M10,VendorGroups[Record ID],"<"&H10,VendorGroups[Source actions],">0")+1) -> 1 | R10: =IF(H10="",IF(COUNTA(I10:K10)>0,"Missing record ID",""),IF(COUNTIFS(VendorGroups[Record ID],H10)<>1,"Duplicate record ID",IF(I10="","Add name","")))
A11: =IF(Trends!$B$6<>"","",IF(COUNTIFS(VendorGroups[Source rank],4)=1,4,"")) -> 4 | B11: =IF(Trends!$B$6<>"","",IF(COUNTIFS(VendorGroups[Source rank],4)=1,IF(INDEX(VendorGroups[Source URL],MATCH(4,VendorGroups[Source rank],0))="",INDEX(VendorGroups[Source name],MATCH(4,VendorGroups[Source rank],0)),HYPERLINK(INDEX(VendorGroups[Source URL],MATCH(4,VendorGroups[Source rank],0)),INDEX(VendorGroups[Source name],MATCH(4,VendorGroups[Source rank],0)))),"")) -> Spatial Front Inc. | C11: =IF(Trends!$B$6<>"","",IF(COUNTIFS(VendorGroups[Source rank],4)=1,IF(INDEX(VendorGroups[Source UEI],MATCH(4,VendorGroups[Source rank],0))="","Not supplied",INDEX(VendorGroups[Source UEI],MATCH(4,VendorGroups[Source rank],0))),"")) -> J1ADW6BL8MN5 | D11: =IF(Trends!$B$6<>"","",IF(COUNTIFS(VendorGroups[Source rank],4)=1,INDEX(VendorGroups[Source net],MATCH(4,VendorGroups[Source rank],0)),"")) -> 8845386 | E11: =IF(Trends!$B$6<>"","",IF(COUNTIFS(VendorGroups[Source rank],4)=1,INDEX(VendorGroups[Source deobligations],MATCH(4,VendorGroups[Source rank],0)),"")) -> -1096141.6 | F11: =IF(Trends!$B$6<>"","",IF(COUNTIFS(VendorGroups[Source rank],4)=1,INDEX(VendorGroups[Source awards],MATCH(4,VendorGroups[Source rank],0)),"")) -> 9 | G11: =IF(Trends!$B$6<>"","",IF(COUNTIFS(VendorGroups[Source rank],4)=1,INDEX(VendorGroups[Source actions],MATCH(4,VendorGroups[Source rank],0)),"")) -> 29 | H11: eU9TbVJvdFJnc1dJL2U5YUVPc2JCZz09 | I11: Civicactions, Inc. | J11: XSZFHRS5QFL5 | K11: https://govtribe.com/vendors/civicactions-inc-dot-65fk1 | L11: =IF(H11="","",I11&IF(J11="",""," ["&J11&"]")) -> Civicactions, Inc. [XSZFHRS5QFL5] | M11: =IF(H11="","",SUMIFS(TransactionsData[Obligations],TransactionsData[Vendor ID],H11,TransactionsData[Selected],1)) -> 10769110 | N11: =IF(H11="","",SUMIFS(TransactionsData[Deobligations],TransactionsData[Vendor ID],H11,TransactionsData[Selected],1)) -> -561.71 | O11: =IF(H11="","",SUMIFS(TransactionsData[First vendor award],TransactionsData[Vendor ID],H11)) -> 1 | P11: =IF(H11="","",COUNTIFS(TransactionsData[Vendor ID],H11,TransactionsData[Selected],1)) -> 10 | Q11: =IF(OR(H11="",P11=0),"",COUNTIFS(VendorGroups[Source net],">"&M11,VendorGroups[Source actions],">0")+COUNTIFS(VendorGroups[Source net],M11,VendorGroups[Record ID],"<"&H11,VendorGroups[Source actions],">0")+1) -> 3 | R11: =IF(H11="",IF(COUNTA(I11:K11)>0,"Missing record ID",""),IF(COUNTIFS(VendorGroups[Record ID],H11)<>1,"Duplicate record ID",IF(I11="","Add name","")))
A12: =IF(Trends!$B$6<>"","",IF(COUNTIFS(VendorGroups[Source rank],5)=1,5,"")) -> 5 | B12: =IF(Trends!$B$6<>"","",IF(COUNTIFS(VendorGroups[Source rank],5)=1,IF(INDEX(VendorGroups[Source URL],MATCH(5,VendorGroups[Source rank],0))="",INDEX(VendorGroups[Source name],MATCH(5,VendorGroups[Source rank],0)),HYPERLINK(INDEX(VendorGroups[Source URL],MATCH(5,VendorGroups[Source rank],0)),INDEX(VendorGroups[Source name],MATCH(5,VendorGroups[Source rank],0)))),"")) -> Strategic Communications LLC | C12: =IF(Trends!$B$6<>"","",IF(COUNTIFS(VendorGroups[Source rank],5)=1,IF(INDEX(VendorGroups[Source UEI],MATCH(5,VendorGroups[Source rank],0))="","Not supplied",INDEX(VendorGroups[Source UEI],MATCH(5,VendorGroups[Source rank],0))),"")) -> LJZRP7SE5LN4 | D12: =IF(Trends!$B$6<>"","",IF(COUNTIFS(VendorGroups[Source rank],5)=1,INDEX(VendorGroups[Source net],MATCH(5,VendorGroups[Source rank],0)),"")) -> 7237302.7 | E12: =IF(Trends!$B$6<>"","",IF(COUNTIFS(VendorGroups[Source rank],5)=1,INDEX(VendorGroups[Source deobligations],MATCH(5,VendorGroups[Source rank],0)),"")) -> 0 | F12: =IF(Trends!$B$6<>"","",IF(COUNTIFS(VendorGroups[Source rank],5)=1,INDEX(VendorGroups[Source awards],MATCH(5,VendorGroups[Source rank],0)),"")) -> 1 | G12: =IF(Trends!$B$6<>"","",IF(COUNTIFS(VendorGroups[Source rank],5)=1,INDEX(VendorGroups[Source actions],MATCH(5,VendorGroups[Source rank],0)),"")) -> 4 | H12: OWJtcjhIZU41SjlrOFJKOTI3MHE5QT09 | I12: Criterion Systems, L.L.C. | J12: MPGNDNHHWM33 | K12: https://govtribe.com/vendors/criterion-systems-inc-dot-8aep0 | L12: =IF(H12="","",I12&IF(J12="",""," ["&J12&"]")) -> Criterion Systems, L.L.C. [MPGNDNHHWM33] | M12: =IF(H12="","",SUMIFS(TransactionsData[Obligations],TransactionsData[Vendor ID],H12,TransactionsData[Selected],1)) -> 5033264 | N12: =IF(H12="","",SUMIFS(TransactionsData[Deobligations],TransactionsData[Vendor ID],H12,TransactionsData[Selected],1)) -> 0 | O12: =IF(H12="","",SUMIFS(TransactionsData[First vendor award],TransactionsData[Vendor ID],H12)) -> 2 | P12: =IF(H12="","",COUNTIFS(TransactionsData[Vendor ID],H12,TransactionsData[Selected],1)) -> 6 | Q12: =IF(OR(H12="",P12=0),"",COUNTIFS(VendorGroups[Source net],">"&M12,VendorGroups[Source actions],">0")+COUNTIFS(VendorGroups[Source net],M12,VendorGroups[Record ID],"<"&H12,VendorGroups[Source actions],">0")+1) -> 6 | R12: =IF(H12="",IF(COUNTA(I12:K12)>0,"Missing record ID",""),IF(COUNTIFS(VendorGroups[Record ID],H12)<>1,"Duplicate record ID",IF(I12="","Add name","")))
A13: =IF(Trends!$B$6<>"","",IF(COUNTIFS(VendorGroups[Source rank],6)=1,6,"")) -> 6 | B13: =IF(Trends!$B$6<>"","",IF(COUNTIFS(VendorGroups[Source rank],6)=1,IF(INDEX(VendorGroups[Source URL],MATCH(6,VendorGroups[Source rank],0))="",INDEX(VendorGroups[Source name],MATCH(6,VendorGroups[Source rank],0)),HYPERLINK(INDEX(VendorGroups[Source URL],MATCH(6,VendorGroups[Source rank],0)),INDEX(VendorGroups[Source name],MATCH(6,VendorGroups[Source rank],0)))),"")) -> Criterion Systems, L.L.C. | C13: =IF(Trends!$B$6<>"","",IF(COUNTIFS(VendorGroups[Source rank],6)=1,IF(INDEX(VendorGroups[Source UEI],MATCH(6,VendorGroups[Source rank],0))="","Not supplied",INDEX(VendorGroups[Source UEI],MATCH(6,VendorGroups[Source rank],0))),"")) -> MPGNDNHHWM33 | D13: =IF(Trends!$B$6<>"","",IF(COUNTIFS(VendorGroups[Source rank],6)=1,INDEX(VendorGroups[Source net],MATCH(6,VendorGroups[Source rank],0)),"")) -> 5033264 | E13: =IF(Trends!$B$6<>"","",IF(COUNTIFS(VendorGroups[Source rank],6)=1,INDEX(VendorGroups[Source deobligations],MATCH(6,VendorGroups[Source rank],0)),"")) -> 0 | F13: =IF(Trends!$B$6<>"","",IF(COUNTIFS(VendorGroups[Source rank],6)=1,INDEX(VendorGroups[Source awards],MATCH(6,VendorGroups[Source rank],0)),"")) -> 2 | G13: =IF(Trends!$B$6<>"","",IF(COUNTIFS(VendorGroups[Source rank],6)=1,INDEX(VendorGroups[Source actions],MATCH(6,VendorGroups[Source rank],0)),"")) -> 6 | H13: V0s3QTJhcWZOS0lyMkJLVzE4Y2tTdz09 | I13: Directviz Solutions, LLC | J13: YXH4AGD2LGF5 | K13: https://govtribe.com/vendors/directviz-solutions-llc-6evd4 | L13: =IF(H13="","",I13&IF(J13="",""," ["&J13&"]")) -> Directviz Solutions, LLC [YXH4AGD2LGF5] | M13: =IF(H13="","",SUMIFS(TransactionsData[Obligations],TransactionsData[Vendor ID],H13,TransactionsData[Selected],1)) -> 22532734 | N13: =IF(H13="","",SUMIFS(TransactionsData[Deobligations],TransactionsData[Vendor ID],H13,TransactionsData[Selected],1)) -> 0 | O13: =IF(H13="","",SUMIFS(TransactionsData[First vendor award],TransactionsData[Vendor ID],H13)) -> 5 | P13: =IF(H13="","",COUNTIFS(TransactionsData[Vendor ID],H13,TransactionsData[Selected],1)) -> 11 | Q13: =IF(OR(H13="",P13=0),"",COUNTIFS(VendorGroups[Source net],">"&M13,VendorGroups[Source actions],">0")+COUNTIFS(VendorGroups[Source net],M13,VendorGroups[Record ID],"<"&H13,VendorGroups[Source actions],">0")+1) -> 2 | R13: =IF(H13="",IF(COUNTA(I13:K13)>0,"Missing record ID",""),IF(COUNTIFS(VendorGroups[Record ID],H13)<>1,"Duplicate record ID",IF(I13="","Add name","")))
A14: =IF(Trends!$B$6<>"","",IF(COUNTIFS(VendorGroups[Source rank],7)=1,7,"")) -> 7 | B14: =IF(Trends!$B$6<>"","",IF(COUNTIFS(VendorGroups[Source rank],7)=1,IF(INDEX(VendorGroups[Source URL],MATCH(7,VendorGroups[Source rank],0))="",INDEX(VendorGroups[Source name],MATCH(7,VendorGroups[Source rank],0)),HYPERLINK(INDEX(VendorGroups[Source URL],MATCH(7,VendorGroups[Source rank],0)),INDEX(VendorGroups[Source name],MATCH(7,VendorGroups[Source rank],0)))),"")) -> Anika Systems Incorporated | C14: =IF(Trends!$B$6<>"","",IF(COUNTIFS(VendorGroups[Source rank],7)=1,IF(INDEX(VendorGroups[Source UEI],MATCH(7,VendorGroups[Source rank],0))="","Not supplied",INDEX(VendorGroups[Source UEI],MATCH(7,VendorGroups[Source rank],0))),"")) -> Y9V7J5VN9F68 | D14: =IF(Trends!$B$6<>"","",IF(COUNTIFS(VendorGroups[Source rank],7)=1,INDEX(VendorGroups[Source net],MATCH(7,VendorGroups[Source rank],0)),"")) -> 4954939.8 | E14: =IF(Trends!$B$6<>"","",IF(COUNTIFS(VendorGroups[Source rank],7)=1,INDEX(VendorGroups[Source deobligations],MATCH(7,VendorGroups[Source rank],0)),"")) -> 0 | F14: =IF(Trends!$B$6<>"","",IF(COUNTIFS(VendorGroups[Source rank],7)=1,INDEX(VendorGroups[Source awards],MATCH(7,VendorGroups[Source rank],0)),"")) -> 1 | G14: =IF(Trends!$B$6<>"","",IF(COUNTIFS(VendorGroups[Source rank],7)=1,INDEX(VendorGroups[Source actions],MATCH(7,VendorGroups[Source rank],0)),"")) -> 4 | H14: cFNFdDdxT05JcUJjUW92YlRySEh2dz09 | I14: Expediteinfotech, Inc. | J14: KX6EDEAPTKH5 | K14: https://govtribe.com/vendors/expediteinfotech-inc-dot-78dz9 | L14: =IF(H14="","",I14&IF(J14="",""," ["&J14&"]")) -> Expediteinfotech, Inc. [KX6EDEAPTKH5] | M14: =IF(H14="","",SUMIFS(TransactionsData[Obligations],TransactionsData[Vendor ID],H14,TransactionsData[Selected],1)) -> 150188.63 | N14: =IF(H14="","",SUMIFS(TransactionsData[Deobligations],TransactionsData[Vendor ID],H14,TransactionsData[Selected],1)) -> -77859 | O14: =IF(H14="","",SUMIFS(TransactionsData[First vendor award],TransactionsData[Vendor ID],H14)) -> 1 | P14: =IF(H14="","",COUNTIFS(TransactionsData[Vendor ID],H14,TransactionsData[Selected],1)) -> 3 | Q14: =IF(OR(H14="",P14=0),"",COUNTIFS(VendorGroups[Source net],">"&M14,VendorGroups[Source actions],">0")+COUNTIFS(VendorGroups[Source net],M14,VendorGroups[Record ID],"<"&H14,VendorGroups[Source actions],">0")+1) -> 15 | R14: =IF(H14="",IF(COUNTA(I14:K14)>0,"Missing record ID",""),IF(COUNTIFS(VendorGroups[Record ID],H14)<>1,"Duplicate record ID",IF(I14="","Add name","")))
A15: =IF(Trends!$B$6<>"","",IF(COUNTIFS(VendorGroups[Source rank],8)=1,8,"")) -> 8 | B15: =IF(Trends!$B$6<>"","",IF(COUNTIFS(VendorGroups[Source rank],8)=1,IF(INDEX(VendorGroups[Source URL],MATCH(8,VendorGroups[Source rank],0))="",INDEX(VendorGroups[Source name],MATCH(8,VendorGroups[Source rank],0)),HYPERLINK(INDEX(VendorGroups[Source URL],MATCH(8,VendorGroups[Source rank],0)),INDEX(VendorGroups[Source name],MATCH(8,VendorGroups[Source rank],0)))),"")) -> Lynker Corporation | C15: =IF(Trends!$B$6<>"","",IF(COUNTIFS(VendorGroups[Source rank],8)=1,IF(INDEX(VendorGroups[Source UEI],MATCH(8,VendorGroups[Source rank],0))="","Not supplied",INDEX(VendorGroups[Source UEI],MATCH(8,VendorGroups[Source rank],0))),"")) -> MCLPKDBCDKY7 | D15: =IF(Trends!$B$6<>"","",IF(COUNTIFS(VendorGroups[Source rank],8)=1,INDEX(VendorGroups[Source net],MATCH(8,VendorGroups[Source rank],0)),"")) -> 2603796 | E15: =IF(Trends!$B$6<>"","",IF(COUNTIFS(VendorGroups[Source rank],8)=1,INDEX(VendorGroups[Source deobligations],MATCH(8,VendorGroups[Source rank],0)),"")) -> 0 | F15: =IF(Trends!$B$6<>"","",IF(COUNTIFS(VendorGroups[Source rank],8)=1,INDEX(VendorGroups[Source awards],MATCH(8,VendorGroups[Source rank],0)),"")) -> 1 | G15: =IF(Trends!$B$6<>"","",IF(COUNTIFS(VendorGroups[Source rank],8)=1,INDEX(VendorGroups[Source actions],MATCH(8,VendorGroups[Source rank],0)),"")) -> 2 | H15: VlgvSWowSTJ2WlBTdlBXd2pxTFhBdz09 | I15: Gartner, Inc. | J15: CFALLJBGZ697 | K15: https://govtribe.com/vendors/gartner-inc-dot-0efu3 | L15: =IF(H15="","",I15&IF(J15="",""," ["&J15&"]")) -> Gartner, Inc. [CFALLJBGZ697] | M15: =IF(H15="","",SUMIFS(TransactionsData[Obligations],TransactionsData[Vendor ID],H15,TransactionsData[Selected],1)) -> 589968 | N15: =IF(H15="","",SUMIFS(TransactionsData[Deobligations],TransactionsData[Vendor ID],H15,TransactionsData[Selected],1)) -> 0 | O15: =IF(H15="","",SUMIFS(TransactionsData[First vendor award],TransactionsData[Vendor ID],H15)) -> 1 | P15: =IF(H15="","",COUNTIFS(TransactionsData[Vendor ID],H15,TransactionsData[Selected],1)) -> 3 | Q15: =IF(OR(H15="",P15=0),"",COUNTIFS(VendorGroups[Source net],">"&M15,VendorGroups[Source actions],">0")+COUNTIFS(VendorGroups[Source net],M15,VendorGroups[Record ID],"<"&H15,VendorGroups[Source actions],">0")+1) -> 12 | R15: =IF(H15="",IF(COUNTA(I15:K15)>0,"Missing record ID",""),IF(COUNTIFS(VendorGroups[Record ID],H15)<>1,"Duplicate record ID",IF(I15="","Add name","")))
A16: =IF(Trends!$B$6<>"","",IF(COUNTIFS(VendorGroups[Source rank],9)=1,9,"")) -> 9 | B16: =IF(Trends!$B$6<>"","",IF(COUNTIFS(VendorGroups[Source rank],9)=1,IF(INDEX(VendorGroups[Source URL],MATCH(9,VendorGroups[Source rank],0))="",INDEX(VendorGroups[Source name],MATCH(9,VendorGroups[Source rank],0)),HYPERLINK(INDEX(VendorGroups[Source URL],MATCH(9,VendorGroups[Source rank],0)),INDEX(VendorGroups[Source name],MATCH(9,VendorGroups[Source rank],0)))),"")) -> Rei Systems, Inc. | C16: =IF(Trends!$B$6<>"","",IF(COUNTIFS(VendorGroups[Source rank],9)=1,IF(INDEX(VendorGroups[Source UEI],MATCH(9,VendorGroups[Source rank],0))="","Not supplied",INDEX(VendorGroups[Source UEI],MATCH(9,VendorGroups[Source rank],0))),"")) -> YRNMVN96JC17 | D16: =IF(Trends!$B$6<>"","",IF(COUNTIFS(VendorGroups[Source rank],9)=1,INDEX(VendorGroups[Source net],MATCH(9,VendorGroups[Source rank],0)),"")) -> 1899378.1 | E16: =IF(Trends!$B$6<>"","",IF(COUNTIFS(VendorGroups[Source rank],9)=1,INDEX(VendorGroups[Source deobligations],MATCH(9,VendorGroups[Source rank],0)),"")) -> 0 | F16: =IF(Trends!$B$6<>"","",IF(COUNTIFS(VendorGroups[Source rank],9)=1,INDEX(VendorGroups[Source awards],MATCH(9,VendorGroups[Source rank],0)),"")) -> 2 | G16: =IF(Trends!$B$6<>"","",IF(COUNTIFS(VendorGroups[Source rank],9)=1,INDEX(VendorGroups[Source actions],MATCH(9,VendorGroups[Source rank],0)),"")) -> 5 | H16: c1krbWRVbVB4cEpvMEV4WEt5b05wdz09 | I16: GBS Dakota IT, LLC | J16: G9E9BR9MG9N7 | K16: https://govtribe.com/vendors/gbs-dakota-it-llc-8ph94 | L16: =IF(H16="","",I16&IF(J16="",""," ["&J16&"]")) -> GBS Dakota IT, LLC [G9E9BR9MG9N7] | M16: =IF(H16="","",SUMIFS(TransactionsData[Obligations],TransactionsData[Vendor ID],H16,TransactionsData[Selected],1)) -> 16430.4 | N16: =IF(H16="","",SUMIFS(TransactionsData[Deobligations],TransactionsData[Vendor ID],H16,TransactionsData[Selected],1)) -> 0 | O16: =IF(H16="","",SUMIFS(TransactionsData[First vendor award],TransactionsData[Vendor ID],H16)) -> 1 | P16: =IF(H16="","",COUNTIFS(TransactionsData[Vendor ID],H16,TransactionsData[Selected],1)) -> 1 | Q16: =IF(OR(H16="",P16=0),"",COUNTIFS(VendorGroups[Source net],">"&M16,VendorGroups[Source actions],">0")+COUNTIFS(VendorGroups[Source net],M16,VendorGroups[Record ID],"<"&H16,VendorGroups[Source actions],">0")+1) -> 18 | R16: =IF(H16="",IF(COUNTA(I16:K16)>0,"Missing record ID",""),IF(COUNTIFS(VendorGroups[Record ID],H16)<>1,"Duplicate record ID",IF(I16="","Add name","")))
A17: =IF(Trends!$B$6<>"","",IF(COUNTIFS(VendorGroups[Source rank],10)=1,10,"")) -> 10 | B17: =IF(Trends!$B$6<>"","",IF(COUNTIFS(VendorGroups[Source rank],10)=1,IF(INDEX(VendorGroups[Source URL],MATCH(10,VendorGroups[Source rank],0))="",INDEX(VendorGroups[Source name],MATCH(10,VendorGroups[Source rank],0)),HYPERLINK(INDEX(VendorGroups[Source URL],MATCH(10,VendorGroups[Source rank],0)),INDEX(VendorGroups[Source name],MATCH(10,VendorGroups[Source rank],0)))),"")) -> Montage + Magnum, LLC | C17: =IF(Trends!$B$6<>"","",IF(COUNTIFS(VendorGroups[Source rank],10)=1,IF(INDEX(VendorGroups[Source UEI],MATCH(10,VendorGroups[Source rank],0))="","Not supplied",INDEX(VendorGroups[Source UEI],MATCH(10,VendorGroups[Source rank],0))),"")) -> XLJSS2NNHU27 | D17: =IF(Trends!$B$6<>"","",IF(COUNTIFS(VendorGroups[Source rank],10)=1,INDEX(VendorGroups[Source net],MATCH(10,VendorGroups[Source rank],0)),"")) -> 840658.87 | E17: =IF(Trends!$B$6<>"","",IF(COUNTIFS(VendorGroups[Source rank],10)=1,INDEX(VendorGroups[Source deobligations],MATCH(10,VendorGroups[Source rank],0)),"")) -> 0 | F17: =IF(Trends!$B$6<>"","",IF(COUNTIFS(VendorGroups[Source rank],10)=1,INDEX(VendorGroups[Source awards],MATCH(10,VendorGroups[Source rank],0)),"")) -> 1 | G17: =IF(Trends!$B$6<>"","",IF(COUNTIFS(VendorGroups[Source rank],10)=1,INDEX(VendorGroups[Source actions],MATCH(10,VendorGroups[Source rank],0)),"")) -> 3 | H17: ejJEYUJ0cDdrQzV5VHVFMGc5bG9oQT09 | I17: GBS Solutions Corp | J17: NKNSTJBPABX9 | K17: https://govtribe.com/vendors/gbs-solutions-corporation-gbs-79pq1 | L17: =IF(H17="","",I17&IF(J17="",""," ["&J17&"]")) -> GBS Solutions Corp [NKNSTJBPABX9] | M17: =IF(H17="","",SUMIFS(TransactionsData[Obligations],TransactionsData[Vendor ID],H17,TransactionsData[Selected],1)) -> 61759.48 | N17: =IF(H17="","",SUMIFS(TransactionsData[Deobligations],TransactionsData[Vendor ID],H17,TransactionsData[Selected],1)) -> -112336.2 | O17: =IF(H17="","",SUMIFS(TransactionsData[First vendor award],TransactionsData[Vendor ID],H17)) -> 2 | P17: =IF(H17="","",COUNTIFS(TransactionsData[Vendor ID],H17,TransactionsData[Selected],1)) -> 4 | Q17: =IF(OR(H17="",P17=0),"",COUNTIFS(VendorGroups[Source net],">"&M17,VendorGroups[Source actions],">0")+COUNTIFS(VendorGroups[Source net],M17,VendorGroups[Record ID],"<"&H17,VendorGroups[Source actions],">0")+1) -> 16 | R17: =IF(H17="",IF(COUNTA(I17:K17)>0,"Missing record ID",""),IF(COUNTIFS(VendorGroups[Record ID],H17)<>1,"Duplicate record ID",IF(I17="","Add name","")))
A18: =IF(Trends!$B$6<>"","",IF(COUNTIFS(VendorGroups[Source rank],11)=1,11,"")) -> 11 | B18: =IF(Trends!$B$6<>"","",IF(COUNTIFS(VendorGroups[Source rank],11)=1,IF(INDEX(VendorGroups[Source URL],MATCH(11,VendorGroups[Source rank],0))="",INDEX(VendorGroups[Source name],MATCH(11,VendorGroups[Source rank],0)),HYPERLINK(INDEX(VendorGroups[Source URL],MATCH(11,VendorGroups[Source rank],0)),INDEX(VendorGroups[Source name],MATCH(11,VendorGroups[Source rank],0)))),"")) -> Agility Technologies Inc. | C18: =IF(Trends!$B$6<>"","",IF(COUNTIFS(VendorGroups[Source rank],11)=1,IF(INDEX(VendorGroups[Source UEI],MATCH(11,VendorGroups[Source rank],0))="","Not supplied",INDEX(VendorGroups[Source UEI],MATCH(11,VendorGroups[Source rank],0))),"")) -> Z9M6NN4AQLF7 | D18: =IF(Trends!$B$6<>"","",IF(COUNTIFS(VendorGroups[Source rank],11)=1,INDEX(VendorGroups[Source net],MATCH(11,VendorGroups[Source rank],0)),"")) -> 592445.36 | E18: =IF(Trends!$B$6<>"","",IF(COUNTIFS(VendorGroups[Source rank],11)=1,INDEX(VendorGroups[Source deobligations],MATCH(11,VendorGroups[Source rank],0)),"")) -> -90.35 | F18: =IF(Trends!$B$6<>"","",IF(COUNTIFS(VendorGroups[Source rank],11)=1,INDEX(VendorGroups[Source awards],MATCH(11,VendorGroups[Source rank],0)),"")) -> 2 | G18: =IF(Trends!$B$6<>"","",IF(COUNTIFS(VendorGroups[Source rank],11)=1,INDEX(VendorGroups[Source actions],MATCH(11,VendorGroups[Source rank],0)),"")) -> 2 | H18: R05KVnd4VlNxejdrdUxqNkVqYzlUQT09 | I18: Ibex It Business Experts LLC | J18: XPA8X2BWTD49 | K18: https://govtribe.com/vendors/ibex-it-business-experts-llc-ibex-it-business-experts-6dry3 | L18: =IF(H18="","",I18&IF(J18="",""," ["&J18&"]")) -> Ibex It Business Experts LLC [XPA8X2BWTD49] | M18: =IF(H18="","",SUMIFS(TransactionsData[Obligations],TransactionsData[Vendor ID],H18,TransactionsData[Selected],1)) -> 0 | N18: =IF(H18="","",SUMIFS(TransactionsData[Deobligations],TransactionsData[Vendor ID],H18,TransactionsData[Selected],1)) -> 0 | O18: =IF(H18="","",SUMIFS(TransactionsData[First vendor award],TransactionsData[Vendor ID],H18)) -> 0 | P18: =IF(H18="","",COUNTIFS(TransactionsData[Vendor ID],H18,TransactionsData[Selected],1)) -> 0 | Q18: =IF(OR(H18="",P18=0),"",COUNTIFS(VendorGroups[Source net],">"&M18,VendorGroups[Source actions],">0")+COUNTIFS(VendorGroups[Source net],M18,VendorGroups[Record ID],"<"&H18,VendorGroups[Source actions],">0")+1) | R18: =IF(H18="",IF(COUNTA(I18:K18)>0,"Missing record ID",""),IF(COUNTIFS(VendorGroups[Record ID],H18)<>1,"Duplicate record ID",IF(I18="","Add name","")))
A19: =IF(Trends!$B$6<>"","",IF(COUNTIFS(VendorGroups[Source rank],12)=1,12,"")) -> 12 | B19: =IF(Trends!$B$6<>"","",IF(COUNTIFS(VendorGroups[Source rank],12)=1,IF(INDEX(VendorGroups[Source URL],MATCH(12,VendorGroups[Source rank],0))="",INDEX(VendorGroups[Source name],MATCH(12,VendorGroups[Source rank],0)),HYPERLINK(INDEX(VendorGroups[Source URL],MATCH(12,VendorGroups[Source rank],0)),INDEX(VendorGroups[Source name],MATCH(12,VendorGroups[Source rank],0)))),"")) -> Gartner, Inc. | C19: =IF(Trends!$B$6<>"","",IF(COUNTIFS(VendorGroups[Source rank],12)=1,IF(INDEX(VendorGroups[Source UEI],MATCH(12,VendorGroups[Source rank],0))="","Not supplied",INDEX(VendorGroups[Source UEI],MATCH(12,VendorGroups[Source rank],0))),"")) -> CFALLJBGZ697 | D19: =IF(Trends!$B$6<>"","",IF(COUNTIFS(VendorGroups[Source rank],12)=1,INDEX(VendorGroups[Source net],MATCH(12,VendorGroups[Source rank],0)),"")) -> 589968 | E19: =IF(Trends!$B$6<>"","",IF(COUNTIFS(VendorGroups[Source rank],12)=1,INDEX(VendorGroups[Source deobligations],MATCH(12,VendorGroups[Source rank],0)),"")) -> 0 | F19: =IF(Trends!$B$6<>"","",IF(COUNTIFS(VendorGroups[Source rank],12)=1,INDEX(VendorGroups[Source awards],MATCH(12,VendorGroups[Source rank],0)),"")) -> 1 | G19: =IF(Trends!$B$6<>"","",IF(COUNTIFS(VendorGroups[Source rank],12)=1,INDEX(VendorGroups[Source actions],MATCH(12,VendorGroups[Source rank],0)),"")) -> 3 | H19: aDVFaWNOY0JZQnZMSWZpZE92MDM0Zz09 | I19: Lynker Corporation | J19: MCLPKDBCDKY7 | K19: https://govtribe.com/vendors/lynker-technologies-llc-56f28 | L19: =IF(H19="","",I19&IF(J19="",""," ["&J19&"]")) -> Lynker Corporation [MCLPKDBCDKY7] | M19: =IF(H19="","",SUMIFS(TransactionsData[Obligations],TransactionsData[Vendor ID],H19,TransactionsData[Selected],1)) -> 2603796 | N19: =IF(H19="","",SUMIFS(TransactionsData[Deobligations],TransactionsData[Vendor ID],H19,TransactionsData[Selected],1)) -> 0 | O19: =IF(H19="","",SUMIFS(TransactionsData[First vendor award],TransactionsData[Vendor ID],H19)) -> 1 | P19: =IF(H19="","",COUNTIFS(TransactionsData[Vendor ID],H19,TransactionsData[Selected],1)) -> 2 | Q19: =IF(OR(H19="",P19=0),"",COUNTIFS(VendorGroups[Source net],">"&M19,VendorGroups[Source actions],">0")+COUNTIFS(VendorGroups[Source net],M19,VendorGroups[Record ID],"<"&H19,VendorGroups[Source actions],">0")+1) -> 8 | R19: =IF(H19="",IF(COUNTA(I19:K19)>0,"Missing record ID",""),IF(COUNTIFS(VendorGroups[Record ID],H19)<>1,"Duplicate record ID",IF(I19="","Add name","")))
A20: =IF(Trends!$B$6<>"","",IF(COUNTIFS(VendorGroups[Source rank],13)=1,13,"")) -> 13 | B20: =IF(Trends!$B$6<>"","",IF(COUNTIFS(VendorGroups[Source rank],13)=1,IF(INDEX(VendorGroups[Source URL],MATCH(13,VendorGroups[Source rank],0))="",INDEX(VendorGroups[Source name],MATCH(13,VendorGroups[Source rank],0)),HYPERLINK(INDEX(VendorGroups[Source URL],MATCH(13,VendorGroups[Source rank],0)),INDEX(VendorGroups[Source name],MATCH(13,VendorGroups[Source rank],0)))),"")) -> Professional Management Consulting Services LLC | C20: =IF(Trends!$B$6<>"","",IF(COUNTIFS(VendorGroups[Source rank],13)=1,IF(INDEX(VendorGroups[Source UEI],MATCH(13,VendorGroups[Source rank],0))="","Not supplied",INDEX(VendorGroups[Source UEI],MATCH(13,VendorGroups[Source rank],0))),"")) -> CD2QDS1EFHP3 | D20: =IF(Trends!$B$6<>"","",IF(COUNTIFS(VendorGroups[Source rank],13)=1,INDEX(VendorGroups[Source net],MATCH(13,VendorGroups[Source rank],0)),"")) -> 495382.97 | E20: =IF(Trends!$B$6<>"","",IF(COUNTIFS(VendorGroups[Source rank],13)=1,INDEX(VendorGroups[Source deobligations],MATCH(13,VendorGroups[Source rank],0)),"")) -> -13437.43 | F20: =IF(Trends!$B$6<>"","",IF(COUNTIFS(VendorGroups[Source rank],13)=1,INDEX(VendorGroups[Source awards],MATCH(13,VendorGroups[Source rank],0)),"")) -> 1 | G20: =IF(Trends!$B$6<>"","",IF(COUNTIFS(VendorGroups[Source rank],13)=1,INDEX(VendorGroups[Source actions],MATCH(13,VendorGroups[Source rank],0)),"")) -> 2 | H20: XLJSS2NNHU27 | I20: Montage + Magnum, LLC | J20: XLJSS2NNHU27 | K20: https://govtribe.com/vendors/montage-magnum-llc-9rt59 | L20: =IF(H20="","",I20&IF(J20="",""," ["&J20&"]")) -> Montage + Magnum, LLC [XLJSS2NNHU27] | M20: =IF(H20="","",SUMIFS(TransactionsData[Obligations],TransactionsData[Vendor ID],H20,TransactionsData[Selected],1)) -> 840658.87 | N20: =IF(H20="","",SUMIFS(TransactionsData[Deobligations],TransactionsData[Vendor ID],H20,TransactionsData[Selected],1)) -> 0 | O20: =IF(H20="","",SUMIFS(TransactionsData[First vendor award],TransactionsData[Vendor ID],H20)) -> 1 | P20: =IF(H20="","",COUNTIFS(TransactionsData[Vendor ID],H20,TransactionsData[Selected],1)) -> 3 | Q20: =IF(OR(H20="",P20=0),"",COUNTIFS(VendorGroups[Source net],">"&M20,VendorGroups[Source actions],">0")+COUNTIFS(VendorGroups[Source net],M20,VendorGroups[Record ID],"<"&H20,VendorGroups[Source actions],">0")+1) -> 10 | R20: =IF(H20="",IF(COUNTA(I20:K20)>0,"Missing record ID",""),IF(COUNTIFS(VendorGroups[Record ID],H20)<>1,"Duplicate record ID",IF(I20="","Add name","")))
A21: =IF(Trends!$B$6<>"","",IF(COUNTIFS(VendorGroups[Source rank],14)=1,14,"")) -> 14 | B21: =IF(Trends!$B$6<>"","",IF(COUNTIFS(VendorGroups[Source rank],14)=1,IF(INDEX(VendorGroups[Source URL],MATCH(14,VendorGroups[Source rank],0))="",INDEX(VendorGroups[Source name],MATCH(14,VendorGroups[Source rank],0)),HYPERLINK(INDEX(VendorGroups[Source URL],MATCH(14,VendorGroups[Source rank],0)),INDEX(VendorGroups[Source name],MATCH(14,VendorGroups[Source rank],0)))),"")) -> Scope It Consulting, LLC | C21: =IF(Trends!$B$6<>"","",IF(COUNTIFS(VendorGroups[Source rank],14)=1,IF(INDEX(VendorGroups[Source UEI],MATCH(14,VendorGroups[Source rank],0))="","Not supplied",INDEX(VendorGroups[Source UEI],MATCH(14,VendorGroups[Source rank],0))),"")) -> KN99UT9W5N77 | D21: =IF(Trends!$B$6<>"","",IF(COUNTIFS(VendorGroups[Source rank],14)=1,INDEX(VendorGroups[Source net],MATCH(14,VendorGroups[Source rank],0)),"")) -> 489791.72 | E21: =IF(Trends!$B$6<>"","",IF(COUNTIFS(VendorGroups[Source rank],14)=1,INDEX(VendorGroups[Source deobligations],MATCH(14,VendorGroups[Source rank],0)),"")) -> 0 | F21: =IF(Trends!$B$6<>"","",IF(COUNTIFS(VendorGroups[Source rank],14)=1,INDEX(VendorGroups[Source awards],MATCH(14,VendorGroups[Source rank],0)),"")) -> 1 | G21: =IF(Trends!$B$6<>"","",IF(COUNTIFS(VendorGroups[Source rank],14)=1,INDEX(VendorGroups[Source actions],MATCH(14,VendorGroups[Source rank],0)),"")) -> 1 | H21: YkNyU0VDNWpHWnBRdGJ6bHErVmNjUT09 | I21: Professional Management Consulting Services LLC | J21: CD2QDS1EFHP3 | K21: https://govtribe.com/vendors/professional-management-consulting-services-llc-pmcs-5ahh1 | L21: =IF(H21="","",I21&IF(J21="",""," ["&J21&"]")) -> Professional Management Consulting Services LLC [CD2QDS1EFHP3] | M21: =IF(H21="","",SUMIFS(TransactionsData[Obligations],TransactionsData[Vendor ID],H21,TransactionsData[Selected],1)) -> 495382.97 | N21: =IF(H21="","",SUMIFS(TransactionsData[Deobligations],TransactionsData[Vendor ID],H21,TransactionsData[Selected],1)) -> -13437.43 | O21: =IF(H21="","",SUMIFS(TransactionsData[First vendor award],TransactionsData[Vendor ID],H21)) -> 1 | P21: =IF(H21="","",COUNTIFS(TransactionsData[Vendor ID],H21,TransactionsData[Selected],1)) -> 2 | Q21: =IF(OR(H21="",P21=0),"",COUNTIFS(VendorGroups[Source net],">"&M21,VendorGroups[Source actions],">0")+COUNTIFS(VendorGroups[Source net],M21,VendorGroups[Record ID],"<"&H21,VendorGroups[Source actions],">0")+1) -> 13 | R21: =IF(H21="",IF(COUNTA(I21:K21)>0,"Missing record ID",""),IF(COUNTIFS(VendorGroups[Record ID],H21)<>1,"Duplicate record ID",IF(I21="","Add name","")))
A22: =IF(Trends!$B$6<>"","",IF(COUNTIFS(VendorGroups[Source rank],15)=1,15,"")) -> 15 | B22: =IF(Trends!$B$6<>"","",IF(COUNTIFS(VendorGroups[Source rank],15)=1,IF(INDEX(VendorGroups[Source URL],MATCH(15,VendorGroups[Source rank],0))="",INDEX(VendorGroups[Source name],MATCH(15,VendorGroups[Source rank],0)),HYPERLINK(INDEX(VendorGroups[Source URL],MATCH(15,VendorGroups[Source rank],0)),INDEX(VendorGroups[Source name],MATCH(15,VendorGroups[Source rank],0)))),"")) -> Expediteinfotech, Inc. | C22: =IF(Trends!$B$6<>"","",IF(COUNTIFS(VendorGroups[Source rank],15)=1,IF(INDEX(VendorGroups[Source UEI],MATCH(15,VendorGroups[Source rank],0))="","Not supplied",INDEX(VendorGroups[Source UEI],MATCH(15,VendorGroups[Source rank],0))),"")) -> KX6EDEAPTKH5 | D22: =IF(Trends!$B$6<>"","",IF(COUNTIFS(VendorGroups[Source rank],15)=1,INDEX(VendorGroups[Source net],MATCH(15,VendorGroups[Source rank],0)),"")) -> 150188.63 | E22: =IF(Trends!$B$6<>"","",IF(COUNTIFS(VendorGroups[Source rank],15)=1,INDEX(VendorGroups[Source deobligations],MATCH(15,VendorGroups[Source rank],0)),"")) -> -77859 | F22: =IF(Trends!$B$6<>"","",IF(COUNTIFS(VendorGroups[Source rank],15)=1,INDEX(VendorGroups[Source awards],MATCH(15,VendorGroups[Source rank],0)),"")) -> 1 | G22: =IF(Trends!$B$6<>"","",IF(COUNTIFS(VendorGroups[Source rank],15)=1,INDEX(VendorGroups[Source actions],MATCH(15,VendorGroups[Source rank],0)),"")) -> 3 | H22: T1QzYW1RRG90aCtYMnErVERYWE9Xdz09 | I22: Rei Systems, Inc. | J22: YRNMVN96JC17 | K22: https://govtribe.com/vendors/rei-systems-inc-dot-1djp1 | L22: =IF(H22="","",I22&IF(J22="",""," ["&J22&"]")) -> Rei Systems, Inc. [YRNMVN96JC17] | M22: =IF(H22="","",SUMIFS(TransactionsData[Obligations],TransactionsData[Vendor ID],H22,TransactionsData[Selected],1)) -> 1899378.1 | N22: =IF(H22="","",SUMIFS(TransactionsData[Deobligations],TransactionsData[Vendor ID],H22,TransactionsData[Selected],1)) -> 0 | O22: =IF(H22="","",SUMIFS(TransactionsData[First vendor award],TransactionsData[Vendor ID],H22)) -> 2 | P22: =IF(H22="","",COUNTIFS(TransactionsData[Vendor ID],H22,TransactionsData[Selected],1)) -> 5 | Q22: =IF(OR(H22="",P22=0),"",COUNTIFS(VendorGroups[Source net],">"&M22,VendorGroups[Source actions],">0")+COUNTIFS(VendorGroups[Source net],M22,VendorGroups[Record ID],"<"&H22,VendorGroups[Source actions],">0")+1) -> 9 | R22: =IF(H22="",IF(COUNTA(I22:K22)>0,"Missing record ID",""),IF(COUNTIFS(VendorGroups[Record ID],H22)<>1,"Duplicate record ID",IF(I22="","Add name","")))
A23: =IF(Trends!$B$6<>"","",IF(COUNTIFS(VendorGroups[Source rank],16)=1,16,"")) -> 16 | B23: =IF(Trends!$B$6<>"","",IF(COUNTIFS(VendorGroups[Source rank],16)=1,IF(INDEX(VendorGroups[Source URL],MATCH(16,VendorGroups[Source rank],0))="",INDEX(VendorGroups[Source name],MATCH(16,VendorGroups[Source rank],0)),HYPERLINK(INDEX(VendorGroups[Source URL],MATCH(16,VendorGroups[Source rank],0)),INDEX(VendorGroups[Source name],MATCH(16,VendorGroups[Source rank],0)))),"")) -> GBS Solutions Corp | C23: =IF(Trends!$B$6<>"","",IF(COUNTIFS(VendorGroups[Source rank],16)=1,IF(INDEX(VendorGroups[Source UEI],MATCH(16,VendorGroups[Source rank],0))="","Not supplied",INDEX(VendorGroups[Source UEI],MATCH(16,VendorGroups[Source rank],0))),"")) -> NKNSTJBPABX9 | D23: =IF(Trends!$B$6<>"","",IF(COUNTIFS(VendorGroups[Source rank],16)=1,INDEX(VendorGroups[Source net],MATCH(16,VendorGroups[Source rank],0)),"")) -> 61759.48 | E23: =IF(Trends!$B$6<>"","",IF(COUNTIFS(VendorGroups[Source rank],16)=1,INDEX(VendorGroups[Source deobligations],MATCH(16,VendorGroups[Source rank],0)),"")) -> -112336.2 | F23: =IF(Trends!$B$6<>"","",IF(COUNTIFS(VendorGroups[Source rank],16)=1,INDEX(VendorGroups[Source awards],MATCH(16,VendorGroups[Source rank],0)),"")) -> 2 | G23: =IF(Trends!$B$6<>"","",IF(COUNTIFS(VendorGroups[Source rank],16)=1,INDEX(VendorGroups[Source actions],MATCH(16,VendorGroups[Source rank],0)),"")) -> 4 | H23: UjgxR3pRcTlIc1U0VkY3V1Q5NkNYZz09 | I23: Scope It Consulting, LLC | J23: KN99UT9W5N77 | K23: https://govtribe.com/vendors/scope-it-consulting-llc-7m3f4 | L23: =IF(H23="","",I23&IF(J23="",""," ["&J23&"]")) -> Scope It Consulting, LLC [KN99UT9W5N77] | M23: =IF(H23="","",SUMIFS(TransactionsData[Obligations],TransactionsData[Vendor ID],H23,TransactionsData[Selected],1)) -> 489791.72 | N23: =IF(H23="","",SUMIFS(TransactionsData[Deobligations],TransactionsData[Vendor ID],H23,TransactionsData[Selected],1)) -> 0 | O23: =IF(H23="","",SUMIFS(TransactionsData[First vendor award],TransactionsData[Vendor ID],H23)) -> 1 | P23: =IF(H23="","",COUNTIFS(TransactionsData[Vendor ID],H23,TransactionsData[Selected],1)) -> 1 | Q23: =IF(OR(H23="",P23=0),"",COUNTIFS(VendorGroups[Source net],">"&M23,VendorGroups[Source actions],">0")+COUNTIFS(VendorGroups[Source net],M23,VendorGroups[Record ID],"<"&H23,VendorGroups[Source actions],">0")+1) -> 14 | R23: =IF(H23="",IF(COUNTA(I23:K23)>0,"Missing record ID",""),IF(COUNTIFS(VendorGroups[Record ID],H23)<>1,"Duplicate record ID",IF(I23="","Add name","")))
A24: =IF(Trends!$B$6<>"","",IF(COUNTIFS(VendorGroups[Source rank],17)=1,17,"")) -> 17 | B24: =IF(Trends!$B$6<>"","",IF(COUNTIFS(VendorGroups[Source rank],17)=1,IF(INDEX(VendorGroups[Source URL],MATCH(17,VendorGroups[Source rank],0))="",INDEX(VendorGroups[Source name],MATCH(17,VendorGroups[Source rank],0)),HYPERLINK(INDEX(VendorGroups[Source URL],MATCH(17,VendorGroups[Source rank],0)),INDEX(VendorGroups[Source name],MATCH(17,VendorGroups[Source rank],0)))),"")) -> University Corporation For Advanced Internet Development | C24: =IF(Trends!$B$6<>"","",IF(COUNTIFS(VendorGroups[Source rank],17)=1,IF(INDEX(VendorGroups[Source UEI],MATCH(17,VendorGroups[Source rank],0))="","Not supplied",INDEX(VendorGroups[Source UEI],MATCH(17,VendorGroups[Source rank],0))),"")) -> DZEBKFRD1ZN6 | D24: =IF(Trends!$B$6<>"","",IF(COUNTIFS(VendorGroups[Source rank],17)=1,INDEX(VendorGroups[Source net],MATCH(17,VendorGroups[Source rank],0)),"")) -> 39079 | E24: =IF(Trends!$B$6<>"","",IF(COUNTIFS(VendorGroups[Source rank],17)=1,INDEX(VendorGroups[Source deobligations],MATCH(17,VendorGroups[Source rank],0)),"")) -> 0 | F24: =IF(Trends!$B$6<>"","",IF(COUNTIFS(VendorGroups[Source rank],17)=1,INDEX(VendorGroups[Source awards],MATCH(17,VendorGroups[Source rank],0)),"")) -> 1 | G24: =IF(Trends!$B$6<>"","",IF(COUNTIFS(VendorGroups[Source rank],17)=1,INDEX(VendorGroups[Source actions],MATCH(17,VendorGroups[Source rank],0)),"")) -> 1 | H24: c085KytxTnY1SHdzdW5HRDdzWjZHZz09 | I24: Spatial Front Inc. | J24: J1ADW6BL8MN5 | K24: https://govtribe.com/vendors/spatial-front-incorporated-5xgw3 | L24: =IF(H24="","",I24&IF(J24="",""," ["&J24&"]")) -> Spatial Front Inc. [J1ADW6BL8MN5] | M24: =IF(H24="","",SUMIFS(TransactionsData[Obligations],TransactionsData[Vendor ID],H24,TransactionsData[Selected],1)) -> 8845386 | N24: =IF(H24="","",SUMIFS(TransactionsData[Deobligations],TransactionsData[Vendor ID],H24,TransactionsData[Selected],1)) -> -1096141.6 | O24: =IF(H24="","",SUMIFS(TransactionsData[First vendor award],TransactionsData[Vendor ID],H24)) -> 9 | P24: =IF(H24="","",COUNTIFS(TransactionsData[Vendor ID],H24,TransactionsData[Selected],1)) -> 29 | Q24: =IF(OR(H24="",P24=0),"",COUNTIFS(VendorGroups[Source net],">"&M24,VendorGroups[Source actions],">0")+COUNTIFS(VendorGroups[Source net],M24,VendorGroups[Record ID],"<"&H24,VendorGroups[Source actions],">0")+1) -> 4 | R24: =IF(H24="",IF(COUNTA(I24:K24)>0,"Missing record ID",""),IF(COUNTIFS(VendorGroups[Record ID],H24)<>1,"Duplicate record ID",IF(I24="","Add name","")))
A25: =IF(Trends!$B$6<>"","",IF(COUNTIFS(VendorGroups[Source rank],18)=1,18,"")) -> 18 | B25: =IF(Trends!$B$6<>"","",IF(COUNTIFS(VendorGroups[Source rank],18)=1,IF(INDEX(VendorGroups[Source URL],MATCH(18,VendorGroups[Source rank],0))="",INDEX(VendorGroups[Source name],MATCH(18,VendorGroups[Source rank],0)),HYPERLINK(INDEX(VendorGroups[Source URL],MATCH(18,VendorGroups[Source rank],0)),INDEX(VendorGroups[Source name],MATCH(18,VendorGroups[Source rank],0)))),"")) -> GBS Dakota IT, LLC | C25: =IF(Trends!$B$6<>"","",IF(COUNTIFS(VendorGroups[Source rank],18)=1,IF(INDEX(VendorGroups[Source UEI],MATCH(18,VendorGroups[Source rank],0))="","Not supplied",INDEX(VendorGroups[Source UEI],MATCH(18,VendorGroups[Source rank],0))),"")) -> G9E9BR9MG9N7 | D25: =IF(Trends!$B$6<>"","",IF(COUNTIFS(VendorGroups[Source rank],18)=1,INDEX(VendorGroups[Source net],MATCH(18,VendorGroups[Source rank],0)),"")) -> 16430.4 | E25: =IF(Trends!$B$6<>"","",IF(COUNTIFS(VendorGroups[Source rank],18)=1,INDEX(VendorGroups[Source deobligations],MATCH(18,VendorGroups[Source rank],0)),"")) -> 0 | F25: =IF(Trends!$B$6<>"","",IF(COUNTIFS(VendorGroups[Source rank],18)=1,INDEX(VendorGroups[Source awards],MATCH(18,VendorGroups[Source rank],0)),"")) -> 1 | G25: =IF(Trends!$B$6<>"","",IF(COUNTIFS(VendorGroups[Source rank],18)=1,INDEX(VendorGroups[Source actions],MATCH(18,VendorGroups[Source rank],0)),"")) -> 1 | H25: Vk84djhvM2k0emtpdmJXQVNZYnNCdz09 | I25: Strategic Communications LLC | J25: LJZRP7SE5LN4 | K25: https://govtribe.com/vendors/strategic-communications-llc-3bgb4 | L25: =IF(H25="","",I25&IF(J25="",""," ["&J25&"]")) -> Strategic Communications LLC [LJZRP7SE5LN4] | M25: =IF(H25="","",SUMIFS(TransactionsData[Obligations],TransactionsData[Vendor ID],H25,TransactionsData[Selected],1)) -> 7237302.7 | N25: =IF(H25="","",SUMIFS(TransactionsData[Deobligations],TransactionsData[Vendor ID],H25,TransactionsData[Selected],1)) -> 0 | O25: =IF(H25="","",SUMIFS(TransactionsData[First vendor award],TransactionsData[Vendor ID],H25)) -> 1 | P25: =IF(H25="","",COUNTIFS(TransactionsData[Vendor ID],H25,TransactionsData[Selected],1)) -> 4 | Q25: =IF(OR(H25="",P25=0),"",COUNTIFS(VendorGroups[Source net],">"&M25,VendorGroups[Source actions],">0")+COUNTIFS(VendorGroups[Source net],M25,VendorGroups[Record ID],"<"&H25,VendorGroups[Source actions],">0")+1) -> 5 | R25: =IF(H25="",IF(COUNTA(I25:K25)>0,"Missing record ID",""),IF(COUNTIFS(VendorGroups[Record ID],H25)<>1,"Duplicate record ID",IF(I25="","Add name","")))
A26: =IF(Trends!$B$6<>"","",IF(COUNTIFS(VendorGroups[Source rank],19)=1,19,"")) | B26: =IF(Trends!$B$6<>"","",IF(COUNTIFS(VendorGroups[Source rank],19)=1,IF(INDEX(VendorGroups[Source URL],MATCH(19,VendorGroups[Source rank],0))="",INDEX(VendorGroups[Source name],MATCH(19,VendorGroups[Source rank],0)),HYPERLINK(INDEX(VendorGroups[Source URL],MATCH(19,VendorGroups[Source rank],0)),INDEX(VendorGroups[Source name],MATCH(19,VendorGroups[Source rank],0)))),"")) | C26: =IF(Trends!$B$6<>"","",IF(COUNTIFS(VendorGroups[Source rank],19)=1,IF(INDEX(VendorGroups[Source UEI],MATCH(19,VendorGroups[Source rank],0))="","Not supplied",INDEX(VendorGroups[Source UEI],MATCH(19,VendorGroups[Source rank],0))),"")) | D26: =IF(Trends!$B$6<>"","",IF(COUNTIFS(VendorGroups[Source rank],19)=1,INDEX(VendorGroups[Source net],MATCH(19,VendorGroups[Source rank],0)),"")) | E26: =IF(Trends!$B$6<>"","",IF(COUNTIFS(VendorGroups[Source rank],19)=1,INDEX(VendorGroups[Source deobligations],MATCH(19,VendorGroups[Source rank],0)),"")) | F26: =IF(Trends!$B$6<>"","",IF(COUNTIFS(VendorGroups[Source rank],19)=1,INDEX(VendorGroups[Source awards],MATCH(19,VendorGroups[Source rank],0)),"")) | G26: =IF(Trends!$B$6<>"","",IF(COUNTIFS(VendorGroups[Source rank],19)=1,INDEX(VendorGroups[Source actions],MATCH(19,VendorGroups[Source rank],0)),"")) | H26: NmFORnlOSEp3LytPU1VRVVRTWVJ0Zz09 | I26: Thundercat Technology, LLC | J26: UER4AJLUB8D5 | K26: https://govtribe.com/vendors/thundercat-technology-llc-50wm7 | L26: =IF(H26="","",I26&IF(J26="",""," ["&J26&"]")) -> Thundercat Technology, LLC [UER4AJLUB8D5] | M26: =IF(H26="","",SUMIFS(TransactionsData[Obligations],TransactionsData[Vendor ID],H26,TransactionsData[Selected],1)) -> 0 | N26: =IF(H26="","",SUMIFS(TransactionsData[Deobligations],TransactionsData[Vendor ID],H26,TransactionsData[Selected],1)) -> 0 | O26: =IF(H26="","",SUMIFS(TransactionsData[First vendor award],TransactionsData[Vendor ID],H26)) -> 0 | P26: =IF(H26="","",COUNTIFS(TransactionsData[Vendor ID],H26,TransactionsData[Selected],1)) -> 0 | Q26: =IF(OR(H26="",P26=0),"",COUNTIFS(VendorGroups[Source net],">"&M26,VendorGroups[Source actions],">0")+COUNTIFS(VendorGroups[Source net],M26,VendorGroups[Record ID],"<"&H26,VendorGroups[Source actions],">0")+1) | R26: =IF(H26="",IF(COUNTA(I26:K26)>0,"Missing record ID",""),IF(COUNTIFS(VendorGroups[Record ID],H26)<>1,"Duplicate record ID",IF(I26="","Add name","")))
A27: =IF(Trends!$B$6<>"","",IF(COUNTIFS(VendorGroups[Source rank],20)=1,20,"")) | B27: =IF(Trends!$B$6<>"","",IF(COUNTIFS(VendorGroups[Source rank],20)=1,IF(INDEX(VendorGroups[Source URL],MATCH(20,VendorGroups[Source rank],0))="",INDEX(VendorGroups[Source name],MATCH(20,VendorGroups[Source rank],0)),HYPERLINK(INDEX(VendorGroups[Source URL],MATCH(20,VendorGroups[Source rank],0)),INDEX(VendorGroups[Source name],MATCH(20,VendorGroups[Source rank],0)))),"")) | C27: =IF(Trends!$B$6<>"","",IF(COUNTIFS(VendorGroups[Source rank],20)=1,IF(INDEX(VendorGroups[Source UEI],MATCH(20,VendorGroups[Source rank],0))="","Not supplied",INDEX(VendorGroups[Source UEI],MATCH(20,VendorGroups[Source rank],0))),"")) | D27: =IF(Trends!$B$6<>"","",IF(COUNTIFS(VendorGroups[Source rank],20)=1,INDEX(VendorGroups[Source net],MATCH(20,VendorGroups[Source rank],0)),"")) | E27: =IF(Trends!$B$6<>"","",IF(COUNTIFS(VendorGroups[Source rank],20)=1,INDEX(VendorGroups[Source deobligations],MATCH(20,VendorGroups[Source rank],0)),"")) | F27: =IF(Trends!$B$6<>"","",IF(COUNTIFS(VendorGroups[Source rank],20)=1,INDEX(VendorGroups[Source awards],MATCH(20,VendorGroups[Source rank],0)),"")) | G27: =IF(Trends!$B$6<>"","",IF(COUNTIFS(VendorGroups[Source rank],20)=1,INDEX(VendorGroups[Source actions],MATCH(20,VendorGroups[Source rank],0)),"")) | H27: Sk1JT3ZIa0xIdGUrMjhSZWt0N2pvQT09 | I27: University Corporation For Advanced Internet Development | J27: DZEBKFRD1ZN6 | K27: https://govtribe.com/vendors/university-corporation-for-advanced-internet-development-internet2-1qu14 | L27: =IF(H27="","",I27&IF(J27="",""," ["&J27&"]")) -> University Corporation For Advanced Internet Development [DZEBKFRD1ZN6] | M27: =IF(H27="","",SUMIFS(TransactionsData[Obligations],TransactionsData[Vendor ID],H27,TransactionsData[Selected],1)) -> 39079 | N27: =IF(H27="","",SUMIFS(TransactionsData[Deobligations],TransactionsData[Vendor ID],H27,TransactionsData[Selected],1)) -> 0 | O27: =IF(H27="","",SUMIFS(TransactionsData[First vendor award],TransactionsData[Vendor ID],H27)) -> 1 | P27: =IF(H27="","",COUNTIFS(TransactionsData[Vendor ID],H27,TransactionsData[Selected],1)) -> 1 | Q27: =IF(OR(H27="",P27=0),"",COUNTIFS(VendorGroups[Source net],">"&M27,VendorGroups[Source actions],">0")+COUNTIFS(VendorGroups[Source net],M27,VendorGroups[Record ID],"<"&H27,VendorGroups[Source actions],">0")+1) -> 17 | R27: =IF(H27="",IF(COUNTA(I27:K27)>0,"Missing record ID",""),IF(COUNTIFS(VendorGroups[Record ID],H27)<>1,"Duplicate record ID",IF(I27="","Add name","")))
A28: =IF(Trends!$B$6<>"","",IF(COUNTIFS(VendorGroups[Source rank],21)=1,21,"")) | B28: =IF(Trends!$B$6<>"","",IF(COUNTIFS(VendorGroups[Source rank],21)=1,IF(INDEX(VendorGroups[Source URL],MATCH(21,VendorGroups[Source rank],0))="",INDEX(VendorGroups[Source name],MATCH(21,VendorGroups[Source rank],0)),HYPERLINK(INDEX(VendorGroups[Source URL],MATCH(21,VendorGroups[Source rank],0)),INDEX(VendorGroups[Source name],MATCH(21,VendorGroups[Source rank],0)))),"")) | C28: =IF(Trends!$B$6<>"","",IF(COUNTIFS(VendorGroups[Source rank],21)=1,IF(INDEX(VendorGroups[Source UEI],MATCH(21,VendorGroups[Source rank],0))="","Not supplied",INDEX(VendorGroups[Source UEI],MATCH(21,VendorGroups[Source rank],0))),"")) | D28: =IF(Trends!$B$6<>"","",IF(COUNTIFS(VendorGroups[Source rank],21)=1,INDEX(VendorGroups[Source net],MATCH(21,VendorGroups[Source rank],0)),"")) | E28: =IF(Trends!$B$6<>"","",IF(COUNTIFS(VendorGroups[Source rank],21)=1,INDEX(VendorGroups[Source deobligations],MATCH(21,VendorGroups[Source rank],0)),"")) | F28: =IF(Trends!$B$6<>"","",IF(COUNTIFS(VendorGroups[Source rank],21)=1,INDEX(VendorGroups[Source awards],MATCH(21,VendorGroups[Source rank],0)),"")) | G28: =IF(Trends!$B$6<>"","",IF(COUNTIFS(VendorGroups[Source rank],21)=1,INDEX(VendorGroups[Source actions],MATCH(21,VendorGroups[Source rank],0)),"")) | L28: =IF(H28="","",I28&IF(J28="",""," ["&J28&"]")) | M28: =IF(H28="","",SUMIFS(TransactionsData[Obligations],TransactionsData[Vendor ID],H28,TransactionsData[Selected],1)) | N28: =IF(H28="","",SUMIFS(TransactionsData[Deobligations],TransactionsData[Vendor ID],H28,TransactionsData[Selected],1)) | O28: =IF(H28="","",SUMIFS(TransactionsData[First vendor award],TransactionsData[Vendor ID],H28)) | P28: =IF(H28="","",COUNTIFS(TransactionsData[Vendor ID],H28,TransactionsData[Selected],1)) | Q28: =IF(OR(H28="",P28=0),"",COUNTIFS(VendorGroups[Source net],">"&M28,VendorGroups[Source actions],">0")+COUNTIFS(VendorGroups[Source net],M28,VendorGroups[Record ID],"<"&H28,VendorGroups[Source actions],">0")+1) | R28: =IF(H28="",IF(COUNTA(I28:K28)>0,"Missing record ID",""),IF(COUNTIFS(VendorGroups[Record ID],H28)<>1,"Duplicate record ID",IF(I28="","Add name","")))
A29: =IF(Trends!$B$6<>"","",IF(COUNTIFS(VendorGroups[Source rank],22)=1,22,"")) | B29: =IF(Trends!$B$6<>"","",IF(COUNTIFS(VendorGroups[Source rank],22)=1,IF(INDEX(VendorGroups[Source URL],MATCH(22,VendorGroups[Source rank],0))="",INDEX(VendorGroups[Source name],MATCH(22,VendorGroups[Source rank],0)),HYPERLINK(INDEX(VendorGroups[Source URL],MATCH(22,VendorGroups[Source rank],0)),INDEX(VendorGroups[Source name],MATCH(22,VendorGroups[Source rank],0)))),"")) | C29: =IF(Trends!$B$6<>"","",IF(COUNTIFS(VendorGroups[Source rank],22)=1,IF(INDEX(VendorGroups[Source UEI],MATCH(22,VendorGroups[Source rank],0))="","Not supplied",INDEX(VendorGroups[Source UEI],MATCH(22,VendorGroups[Source rank],0))),"")) | D29: =IF(Trends!$B$6<>"","",IF(COUNTIFS(VendorGroups[Source rank],22)=1,INDEX(VendorGroups[Source net],MATCH(22,VendorGroups[Source rank],0)),"")) | E29: =IF(Trends!$B$6<>"","",IF(COUNTIFS(VendorGroups[Source rank],22)=1,INDEX(VendorGroups[Source deobligations],MATCH(22,VendorGroups[Source rank],0)),"")) | F29: =IF(Trends!$B$6<>"","",IF(COUNTIFS(VendorGroups[Source rank],22)=1,INDEX(VendorGroups[Source awards],MATCH(22,VendorGroups[Source rank],0)),"")) | G29: =IF(Trends!$B$6<>"","",IF(COUNTIFS(VendorGroups[Source rank],22)=1,INDEX(VendorGroups[Source actions],MATCH(22,VendorGroups[Source rank],0)),"")) | L29: =IF(H29="","",I29&IF(J29="",""," ["&J29&"]")) | M29: =IF(H29="","",SUMIFS(TransactionsData[Obligations],TransactionsData[Vendor ID],H29,TransactionsData[Selected],1)) | N29: =IF(H29="","",SUMIFS(TransactionsData[Deobligations],TransactionsData[Vendor ID],H29,TransactionsData[Selected],1)) | O29: =IF(H29="","",SUMIFS(TransactionsData[First vendor award],TransactionsData[Vendor ID],H29)) | P29: =IF(H29="","",COUNTIFS(TransactionsData[Vendor ID],H29,TransactionsData[Selected],1)) | Q29: =IF(OR(H29="",P29=0),"",COUNTIFS(VendorGroups[Source net],">"&M29,VendorGroups[Source actions],">0")+COUNTIFS(VendorGroups[Source net],M29,VendorGroups[Record ID],"<"&H29,VendorGroups[Source actions],">0")+1) | R29: =IF(H29="",IF(COUNTA(I29:K29)>0,"Missing record ID",""),IF(COUNTIFS(VendorGroups[Record ID],H29)<>1,"Duplicate record ID",IF(I29="","Add name","")))
A30: =IF(Trends!$B$6<>"","",IF(COUNTIFS(VendorGroups[Source rank],23)=1,23,"")) | B30: =IF(Trends!$B$6<>"","",IF(COUNTIFS(VendorGroups[Source rank],23)=1,IF(INDEX(VendorGroups[Source URL],MATCH(23,VendorGroups[Source rank],0))="",INDEX(VendorGroups[Source name],MATCH(23,VendorGroups[Source rank],0)),HYPERLINK(INDEX(VendorGroups[Source URL],MATCH(23,VendorGroups[Source rank],0)),INDEX(VendorGroups[Source name],MATCH(23,VendorGroups[Source rank],0)))),"")) | C30: =IF(Trends!$B$6<>"","",IF(COUNTIFS(VendorGroups[Source rank],23)=1,IF(INDEX(VendorGroups[Source UEI],MATCH(23,VendorGroups[Source rank],0))="","Not supplied",INDEX(VendorGroups[Source UEI],MATCH(23,VendorGroups[Source rank],0))),"")) | D30: =IF(Trends!$B$6<>"","",IF(COUNTIFS(VendorGroups[Source rank],23)=1,INDEX(VendorGroups[Source net],MATCH(23,VendorGroups[Source rank],0)),"")) | E30: =IF(Trends!$B$6<>"","",IF(COUNTIFS(VendorGroups[Source rank],23)=1,INDEX(VendorGroups[Source deobligations],MATCH(23,VendorGroups[Source rank],0)),"")) | F30: =IF(Trends!$B$6<>"","",IF(COUNTIFS(VendorGroups[Source rank],23)=1,INDEX(VendorGroups[Source awards],MATCH(23,VendorGroups[Source rank],0)),"")) | G30: =IF(Trends!$B$6<>"","",IF(COUNTIFS(VendorGroups[Source rank],23)=1,INDEX(VendorGroups[Source actions],MATCH(23,VendorGroups[Source rank],0)),"")) | L30: =IF(H30="","",I30&IF(J30="",""," ["&J30&"]")) | M30: =IF(H30="","",SUMIFS(TransactionsData[Obligations],TransactionsData[Vendor ID],H30,TransactionsData[Selected],1)) | N30: =IF(H30="","",SUMIFS(TransactionsData[Deobligations],TransactionsData[Vendor ID],H30,TransactionsData[Selected],1)) | O30: =IF(H30="","",SUMIFS(TransactionsData[First vendor award],TransactionsData[Vendor ID],H30)) | P30: =IF(H30="","",COUNTIFS(TransactionsData[Vendor ID],H30,TransactionsData[Selected],1)) | Q30: =IF(OR(H30="",P30=0),"",COUNTIFS(VendorGroups[Source net],">"&M30,VendorGroups[Source actions],">0")+COUNTIFS(VendorGroups[Source net],M30,VendorGroups[Record ID],"<"&H30,VendorGroups[Source actions],">0")+1) | R30: =IF(H30="",IF(COUNTA(I30:K30)>0,"Missing record ID",""),IF(COUNTIFS(VendorGroups[Record ID],H30)<>1,"Duplicate record ID",IF(I30="","Add name","")))
A31: =IF(Trends!$B$6<>"","",IF(COUNTIFS(VendorGroups[Source rank],24)=1,24,"")) | B31: =IF(Trends!$B$6<>"","",IF(COUNTIFS(VendorGroups[Source rank],24)=1,IF(INDEX(VendorGroups[Source URL],MATCH(24,VendorGroups[Source rank],0))="",INDEX(VendorGroups[Source name],MATCH(24,VendorGroups[Source rank],0)),HYPERLINK(INDEX(VendorGroups[Source URL],MATCH(24,VendorGroups[Source rank],0)),INDEX(VendorGroups[Source name],MATCH(24,VendorGroups[Source rank],0)))),"")) | C31: =IF(Trends!$B$6<>"","",IF(COUNTIFS(VendorGroups[Source rank],24)=1,IF(INDEX(VendorGroups[Source UEI],MATCH(24,VendorGroups[Source rank],0))="","Not supplied",INDEX(VendorGroups[Source UEI],MATCH(24,VendorGroups[Source rank],0))),"")) | D31: =IF(Trends!$B$6<>"","",IF(COUNTIFS(VendorGroups[Source rank],24)=1,INDEX(VendorGroups[Source net],MATCH(24,VendorGroups[Source rank],0)),"")) | E31: =IF(Trends!$B$6<>"","",IF(COUNTIFS(VendorGroups[Source rank],24)=1,INDEX(VendorGroups[Source deobligations],MATCH(24,VendorGroups[Source rank],0)),"")) | F31: =IF(Trends!$B$6<>"","",IF(COUNTIFS(VendorGroups[Source rank],24)=1,INDEX(VendorGroups[Source awards],MATCH(24,VendorGroups[Source rank],0)),"")) | G31: =IF(Trends!$B$6<>"","",IF(COUNTIFS(VendorGroups[Source rank],24)=1,INDEX(VendorGroups[Source actions],MATCH(24,VendorGroups[Source rank],0)),"")) | L31: =IF(H31="","",I31&IF(J31="",""," ["&J31&"]")) | M31: =IF(H31="","",SUMIFS(TransactionsData[Obligations],TransactionsData[Vendor ID],H31,TransactionsData[Selected],1)) | N31: =IF(H31="","",SUMIFS(TransactionsData[Deobligations],TransactionsData[Vendor ID],H31,TransactionsData[Selected],1)) | O31: =IF(H31="","",SUMIFS(TransactionsData[First vendor award],TransactionsData[Vendor ID],H31)) | P31: =IF(H31="","",COUNTIFS(TransactionsData[Vendor ID],H31,TransactionsData[Selected],1)) | Q31: =IF(OR(H31="",P31=0),"",COUNTIFS(VendorGroups[Source net],">"&M31,VendorGroups[Source actions],">0")+COUNTIFS(VendorGroups[Source net],M31,VendorGroups[Record ID],"<"&H31,VendorGroups[Source actions],">0")+1) | R31: =IF(H31="",IF(COUNTA(I31:K31)>0,"Missing record ID",""),IF(COUNTIFS(VendorGroups[Record ID],H31)<>1,"Duplicate record ID",IF(I31="","Add name","")))
A32: =IF(Trends!$B$6<>"","",IF(COUNTIFS(VendorGroups[Source rank],25)=1,25,"")) | B32: =IF(Trends!$B$6<>"","",IF(COUNTIFS(VendorGroups[Source rank],25)=1,IF(INDEX(VendorGroups[Source URL],MATCH(25,VendorGroups[Source rank],0))="",INDEX(VendorGroups[Source name],MATCH(25,VendorGroups[Source rank],0)),HYPERLINK(INDEX(VendorGroups[Source URL],MATCH(25,VendorGroups[Source rank],0)),INDEX(VendorGroups[Source name],MATCH(25,VendorGroups[Source rank],0)))),"")) | C32: =IF(Trends!$B$6<>"","",IF(COUNTIFS(VendorGroups[Source rank],25)=1,IF(INDEX(VendorGroups[Source UEI],MATCH(25,VendorGroups[Source rank],0))="","Not supplied",INDEX(VendorGroups[Source UEI],MATCH(25,VendorGroups[Source rank],0))),"")) | D32: =IF(Trends!$B$6<>"","",IF(COUNTIFS(VendorGroups[Source rank],25)=1,INDEX(VendorGroups[Source net],MATCH(25,VendorGroups[Source rank],0)),"")) | E32: =IF(Trends!$B$6<>"","",IF(COUNTIFS(VendorGroups[Source rank],25)=1,INDEX(VendorGroups[Source deobligations],MATCH(25,VendorGroups[Source rank],0)),"")) | F32: =IF(Trends!$B$6<>"","",IF(COUNTIFS(VendorGroups[Source rank],25)=1,INDEX(VendorGroups[Source awards],MATCH(25,VendorGroups[Source rank],0)),"")) | G32: =IF(Trends!$B$6<>"","",IF(COUNTIFS(VendorGroups[Source rank],25)=1,INDEX(VendorGroups[Source actions],MATCH(25,VendorGroups[Source rank],0)),"")) | L32: =IF(H32="","",I32&IF(J32="",""," ["&J32&"]")) | M32: =IF(H32="","",SUMIFS(TransactionsData[Obligations],TransactionsData[Vendor ID],H32,TransactionsData[Selected],1)) | N32: =IF(H32="","",SUMIFS(TransactionsData[Deobligations],TransactionsData[Vendor ID],H32,TransactionsData[Selected],1)) | O32: =IF(H32="","",SUMIFS(TransactionsData[First vendor award],TransactionsData[Vendor ID],H32)) | P32: =IF(H32="","",COUNTIFS(TransactionsData[Vendor ID],H32,TransactionsData[Selected],1)) | Q32: =IF(OR(H32="",P32=0),"",COUNTIFS(VendorGroups[Source net],">"&M32,VendorGroups[Source actions],">0")+COUNTIFS(VendorGroups[Source net],M32,VendorGroups[Record ID],"<"&H32,VendorGroups[Source actions],">0")+1) | R32: =IF(H32="",IF(COUNTA(I32:K32)>0,"Missing record ID",""),IF(COUNTIFS(VendorGroups[Record ID],H32)<>1,"Duplicate record ID",IF(I32="","Add name","")))
A33: =IF(Trends!$B$6<>"","",IF(COUNTIFS(VendorGroups[Source rank],26)=1,26,"")) | B33: =IF(Trends!$B$6<>"","",IF(COUNTIFS(VendorGroups[Source rank],26)=1,IF(INDEX(VendorGroups[Source URL],MATCH(26,VendorGroups[Source rank],0))="",INDEX(VendorGroups[Source name],MATCH(26,VendorGroups[Source rank],0)),HYPERLINK(INDEX(VendorGroups[Source URL],MATCH(26,VendorGroups[Source rank],0)),INDEX(VendorGroups[Source name],MATCH(26,VendorGroups[Source rank],0)))),"")) | C33: =IF(Trends!$B$6<>"","",IF(COUNTIFS(VendorGroups[Source rank],26)=1,IF(INDEX(VendorGroups[Source UEI],MATCH(26,VendorGroups[Source rank],0))="","Not supplied",INDEX(VendorGroups[Source UEI],MATCH(26,VendorGroups[Source rank],0))),"")) | D33: =IF(Trends!$B$6<>"","",IF(COUNTIFS(VendorGroups[Source rank],26)=1,INDEX(VendorGroups[Source net],MATCH(26,VendorGroups[Source rank],0)),"")) | E33: =IF(Trends!$B$6<>"","",IF(COUNTIFS(VendorGroups[Source rank],26)=1,INDEX(VendorGroups[Source deobligations],MATCH(26,VendorGroups[Source rank],0)),"")) | F33: =IF(Trends!$B$6<>"","",IF(COUNTIFS(VendorGroups[Source rank],26)=1,INDEX(VendorGroups[Source awards],MATCH(26,VendorGroups[Source rank],0)),"")) | G33: =IF(Trends!$B$6<>"","",IF(COUNTIFS(VendorGroups[Source rank],26)=1,INDEX(VendorGroups[Source actions],MATCH(26,VendorGroups[Source rank],0)),"")) | L33: =IF(H33="","",I33&IF(J33="",""," ["&J33&"]")) | M33: =IF(H33="","",SUMIFS(TransactionsData[Obligations],TransactionsData[Vendor ID],H33,TransactionsData[Selected],1)) | N33: =IF(H33="","",SUMIFS(TransactionsData[Deobligations],TransactionsData[Vendor ID],H33,TransactionsData[Selected],1)) | O33: =IF(H33="","",SUMIFS(TransactionsData[First vendor award],TransactionsData[Vendor ID],H33)) | P33: =IF(H33="","",COUNTIFS(TransactionsData[Vendor ID],H33,TransactionsData[Selected],1)) | Q33: =IF(OR(H33="",P33=0),"",COUNTIFS(VendorGroups[Source net],">"&M33,VendorGroups[Source actions],">0")+COUNTIFS(VendorGroups[Source net],M33,VendorGroups[Record ID],"<"&H33,VendorGroups[Source actions],">0")+1) | R33: =IF(H33="",IF(COUNTA(I33:K33)>0,"Missing record ID",""),IF(COUNTIFS(VendorGroups[Record ID],H33)<>1,"Duplicate record ID",IF(I33="","Add name","")))
A34: =IF(Trends!$B$6<>"","",IF(COUNTIFS(VendorGroups[Source rank],27)=1,27,"")) | B34: =IF(Trends!$B$6<>"","",IF(COUNTIFS(VendorGroups[Source rank],27)=1,IF(INDEX(VendorGroups[Source URL],MATCH(27,VendorGroups[Source rank],0))="",INDEX(VendorGroups[Source name],MATCH(27,VendorGroups[Source rank],0)),HYPERLINK(INDEX(VendorGroups[Source URL],MATCH(27,VendorGroups[Source rank],0)),INDEX(VendorGroups[Source name],MATCH(27,VendorGroups[Source rank],0)))),"")) | C34: =IF(Trends!$B$6<>"","",IF(COUNTIFS(VendorGroups[Source rank],27)=1,IF(INDEX(VendorGroups[Source UEI],MATCH(27,VendorGroups[Source rank],0))="","Not supplied",INDEX(VendorGroups[Source UEI],MATCH(27,VendorGroups[Source rank],0))),"")) | D34: =IF(Trends!$B$6<>"","",IF(COUNTIFS(VendorGroups[Source rank],27)=1,INDEX(VendorGroups[Source net],MATCH(27,VendorGroups[Source rank],0)),"")) | E34: =IF(Trends!$B$6<>"","",IF(COUNTIFS(VendorGroups[Source rank],27)=1,INDEX(VendorGroups[Source deobligations],MATCH(27,VendorGroups[Source rank],0)),"")) | F34: =IF(Trends!$B$6<>"","",IF(COUNTIFS(VendorGroups[Source rank],27)=1,INDEX(VendorGroups[Source awards],MATCH(27,VendorGroups[Source rank],0)),"")) | G34: =IF(Trends!$B$6<>"","",IF(COUNTIFS(VendorGroups[Source rank],27)=1,INDEX(VendorGroups[Source actions],MATCH(27,VendorGroups[Source rank],0)),"")) | L34: =IF(H34="","",I34&IF(J34="",""," ["&J34&"]")) | M34: =IF(H34="","",SUMIFS(TransactionsData[Obligations],TransactionsData[Vendor ID],H34,TransactionsData[Selected],1)) | N34: =IF(H34="","",SUMIFS(TransactionsData[Deobligations],TransactionsData[Vendor ID],H34,TransactionsData[Selected],1)) | O34: =IF(H34="","",SUMIFS(TransactionsData[First vendor award],TransactionsData[Vendor ID],H34)) | P34: =IF(H34="","",COUNTIFS(TransactionsData[Vendor ID],H34,TransactionsData[Selected],1)) | Q34: =IF(OR(H34="",P34=0),"",COUNTIFS(VendorGroups[Source net],">"&M34,VendorGroups[Source actions],">0")+COUNTIFS(VendorGroups[Source net],M34,VendorGroups[Record ID],"<"&H34,VendorGroups[Source actions],">0")+1) | R34: =IF(H34="",IF(COUNTA(I34:K34)>0,"Missing record ID",""),IF(COUNTIFS(VendorGroups[Record ID],H34)<>1,"Duplicate record ID",IF(I34="","Add name","")))
A35: =IF(Trends!$B$6<>"","",IF(COUNTIFS(VendorGroups[Source rank],28)=1,28,"")) | B35: =IF(Trends!$B$6<>"","",IF(COUNTIFS(VendorGroups[Source rank],28)=1,IF(INDEX(VendorGroups[Source URL],MATCH(28,VendorGroups[Source rank],0))="",INDEX(VendorGroups[Source name],MATCH(28,VendorGroups[Source rank],0)),HYPERLINK(INDEX(VendorGroups[Source URL],MATCH(28,VendorGroups[Source rank],0)),INDEX(VendorGroups[Source name],MATCH(28,VendorGroups[Source rank],0)))),"")) | C35: =IF(Trends!$B$6<>"","",IF(COUNTIFS(VendorGroups[Source rank],28)=1,IF(INDEX(VendorGroups[Source UEI],MATCH(28,VendorGroups[Source rank],0))="","Not supplied",INDEX(VendorGroups[Source UEI],MATCH(28,VendorGroups[Source rank],0))),"")) | D35: =IF(Trends!$B$6<>"","",IF(COUNTIFS(VendorGroups[Source rank],28)=1,INDEX(VendorGroups[Source net],MATCH(28,VendorGroups[Source rank],0)),"")) | E35: =IF(Trends!$B$6<>"","",IF(COUNTIFS(VendorGroups[Source rank],28)=1,INDEX(VendorGroups[Source deobligations],MATCH(28,VendorGroups[Source rank],0)),"")) | F35: =IF(Trends!$B$6<>"","",IF(COUNTIFS(VendorGroups[Source rank],28)=1,INDEX(VendorGroups[Source awards],MATCH(28,VendorGroups[Source rank],0)),"")) | G35: =IF(Trends!$B$6<>"","",IF(COUNTIFS(VendorGroups[Source rank],28)=1,INDEX(VendorGroups[Source actions],MATCH(28,VendorGroups[Source rank],0)),"")) | L35: =IF(H35="","",I35&IF(J35="",""," ["&J35&"]")) | M35: =IF(H35="","",SUMIFS(TransactionsData[Obligations],TransactionsData[Vendor ID],H35,TransactionsData[Selected],1)) | N35: =IF(H35="","",SUMIFS(TransactionsData[Deobligations],TransactionsData[Vendor ID],H35,TransactionsData[Selected],1)) | O35: =IF(H35="","",SUMIFS(TransactionsData[First vendor award],TransactionsData[Vendor ID],H35)) | P35: =IF(H35="","",COUNTIFS(TransactionsData[Vendor ID],H35,TransactionsData[Selected],1)) | Q35: =IF(OR(H35="",P35=0),"",COUNTIFS(VendorGroups[Source net],">"&M35,VendorGroups[Source actions],">0")+COUNTIFS(VendorGroups[Source net],M35,VendorGroups[Record ID],"<"&H35,VendorGroups[Source actions],">0")+1) | R35: =IF(H35="",IF(COUNTA(I35:K35)>0,"Missing record ID",""),IF(COUNTIFS(VendorGroups[Record ID],H35)<>1,"Duplicate record ID",IF(I35="","Add name","")))
A40: Rank | B40: Funding office | C40: Office code | D40: Net obligations | E40: Deobligations | F40: Awards with obligations | G40: Transactions | H40: Record ID | I40: Source name | J40: Source UEI | K40: Source URL | L40: Filter label | M40: Source net | N40: Source deobligations | O40: Source awards | P40: Source actions | Q40: Source rank | R40: Input check
A41: =IF(Trends!$B$6<>"","",IF(COUNTIFS(OfficeGroups[Source rank],1)=1,1,"")) -> 1 | B41: =IF(Trends!$B$6<>"","",IF(COUNTIFS(OfficeGroups[Source rank],1)=1,IF(INDEX(OfficeGroups[Source URL],MATCH(1,OfficeGroups[Source rank],0))="",INDEX(OfficeGroups[Source name],MATCH(1,OfficeGroups[Source rank],0)),HYPERLINK(INDEX(OfficeGroups[Source URL],MATCH(1,OfficeGroups[Source rank],0)),INDEX(OfficeGroups[Source name],MATCH(1,OfficeGroups[Source rank],0)))),"")) -> NSF — office not specified | C41: =IF(Trends!$B$6<>"","",IF(COUNTIFS(OfficeGroups[Source rank],1)=1,IF(INDEX(OfficeGroups[Source UEI],MATCH(1,OfficeGroups[Source rank],0))="","Not supplied",INDEX(OfficeGroups[Source UEI],MATCH(1,OfficeGroups[Source rank],0))),"")) -> 4900-A | D41: =IF(Trends!$B$6<>"","",IF(COUNTIFS(OfficeGroups[Source rank],1)=1,INDEX(OfficeGroups[Source net],MATCH(1,OfficeGroups[Source rank],0)),"")) -> 89345634 | E41: =IF(Trends!$B$6<>"","",IF(COUNTIFS(OfficeGroups[Source rank],1)=1,INDEX(OfficeGroups[Source deobligations],MATCH(1,OfficeGroups[Source rank],0)),"")) -> -1128849.5 | F41: =IF(Trends!$B$6<>"","",IF(COUNTIFS(OfficeGroups[Source rank],1)=1,INDEX(OfficeGroups[Source awards],MATCH(1,OfficeGroups[Source rank],0)),"")) -> 19 | G41: =IF(Trends!$B$6<>"","",IF(COUNTIFS(OfficeGroups[Source rank],1)=1,INDEX(OfficeGroups[Source actions],MATCH(1,OfficeGroups[Source rank],0)),"")) -> 68 | H41: 4900|4900|490700-A | I41: Directorate for Engineering | J41: 490700-A | K41: https://govtribe.com/agency/federal-agency/national-science-foundation-directorate-for-engineering | L41: =IF(H41="","",I41&IF(J41="",""," ["&J41&"]")) -> Directorate for Engineering [490700-A] | M41: =IF(H41="","",SUMIFS(TransactionsData[Obligations],TransactionsData[Funding office ID],H41,TransactionsData[Selected],1)) -> 150188.63 | N41: =IF(H41="","",SUMIFS(TransactionsData[Deobligations],TransactionsData[Funding office ID],H41,TransactionsData[Selected],1)) -> -77859 | O41: =IF(H41="","",SUMIFS(TransactionsData[First office award],TransactionsData[Funding office ID],H41)) -> 1 | P41: =IF(H41="","",COUNTIFS(TransactionsData[Funding office ID],H41,TransactionsData[Selected],1)) -> 2 | Q41: =IF(OR(H41="",P41=0),"",COUNTIFS(OfficeGroups[Source net],">"&M41,OfficeGroups[Source actions],">0")+COUNTIFS(OfficeGroups[Source net],M41,OfficeGroups[Record ID],"<"&H41,OfficeGroups[Source actions],">0")+1) -> 7 | R41: =IF(H41="",IF(COUNTA(I41:K41)>0,"Missing record ID",""),IF(COUNTIFS(OfficeGroups[Record ID],H41)<>1,"Duplicate record ID",IF(I41="","Add name","")))
A42: =IF(Trends!$B$6<>"","",IF(COUNTIFS(OfficeGroups[Source rank],2)=1,2,"")) -> 2 | B42: =IF(Trends!$B$6<>"","",IF(COUNTIFS(OfficeGroups[Source rank],2)=1,IF(INDEX(OfficeGroups[Source URL],MATCH(2,OfficeGroups[Source rank],0))="",INDEX(OfficeGroups[Source name],MATCH(2,OfficeGroups[Source rank],0)),HYPERLINK(INDEX(OfficeGroups[Source URL],MATCH(2,OfficeGroups[Source rank],0)),INDEX(OfficeGroups[Source name],MATCH(2,OfficeGroups[Source rank],0)))),"")) -> Division of Information Systems | C42: =IF(Trends!$B$6<>"","",IF(COUNTIFS(OfficeGroups[Source rank],2)=1,IF(INDEX(OfficeGroups[Source UEI],MATCH(2,OfficeGroups[Source rank],0))="","Not supplied",INDEX(OfficeGroups[Source UEI],MATCH(2,OfficeGroups[Source rank],0))),"")) -> 490209-A | D42: =IF(Trends!$B$6<>"","",IF(COUNTIFS(OfficeGroups[Source rank],2)=1,INDEX(OfficeGroups[Source net],MATCH(2,OfficeGroups[Source rank],0)),"")) -> 26374874 | E42: =IF(Trends!$B$6<>"","",IF(COUNTIFS(OfficeGroups[Source rank],2)=1,INDEX(OfficeGroups[Source deobligations],MATCH(2,OfficeGroups[Source rank],0)),"")) -> -80190 | F42: =IF(Trends!$B$6<>"","",IF(COUNTIFS(OfficeGroups[Source rank],2)=1,INDEX(OfficeGroups[Source awards],MATCH(2,OfficeGroups[Source rank],0)),"")) -> 10 | G42: =IF(Trends!$B$6<>"","",IF(COUNTIFS(OfficeGroups[Source rank],2)=1,INDEX(OfficeGroups[Source actions],MATCH(2,OfficeGroups[Source rank],0)),"")) -> 24 | H42: 4900|4900|490600-A | I42: Directorate of Geosciences | J42: 490600-A | K42: https://govtribe.com/agency/federal-agency/national-science-foundation-directorate-of-geosciences | L42: =IF(H42="","",I42&IF(J42="",""," ["&J42&"]")) -> Directorate of Geosciences [490600-A] | M42: =IF(H42="","",SUMIFS(TransactionsData[Obligations],TransactionsData[Funding office ID],H42,TransactionsData[Selected],1)) -> 495382.97 | N42: =IF(H42="","",SUMIFS(TransactionsData[Deobligations],TransactionsData[Funding office ID],H42,TransactionsData[Selected],1)) -> -13437.43 | O42: =IF(H42="","",SUMIFS(TransactionsData[First office award],TransactionsData[Funding office ID],H42)) -> 1 | P42: =IF(H42="","",COUNTIFS(TransactionsData[Funding office ID],H42,TransactionsData[Selected],1)) -> 2 | Q42: =IF(OR(H42="",P42=0),"",COUNTIFS(OfficeGroups[Source net],">"&M42,OfficeGroups[Source actions],">0")+COUNTIFS(OfficeGroups[Source net],M42,OfficeGroups[Record ID],"<"&H42,OfficeGroups[Source actions],">0")+1) -> 5 | R42: =IF(H42="",IF(COUNTA(I42:K42)>0,"Missing record ID",""),IF(COUNTIFS(OfficeGroups[Record ID],H42)<>1,"Duplicate record ID",IF(I42="","Add name","")))
A43: =IF(Trends!$B$6<>"","",IF(COUNTIFS(OfficeGroups[Source rank],3)=1,3,"")) -> 3 | B43: =IF(Trends!$B$6<>"","",IF(COUNTIFS(OfficeGroups[Source rank],3)=1,IF(INDEX(OfficeGroups[Source URL],MATCH(3,OfficeGroups[Source rank],0))="",INDEX(OfficeGroups[Source name],MATCH(3,OfficeGroups[Source rank],0)),HYPERLINK(INDEX(OfficeGroups[Source URL],MATCH(3,OfficeGroups[Source rank],0)),INDEX(OfficeGroups[Source name],MATCH(3,OfficeGroups[Source rank],0)))),"")) -> Division of Social and Economic Science | C43: =IF(Trends!$B$6<>"","",IF(COUNTIFS(OfficeGroups[Source rank],3)=1,IF(INDEX(OfficeGroups[Source UEI],MATCH(3,OfficeGroups[Source rank],0))="","Not supplied",INDEX(OfficeGroups[Source UEI],MATCH(3,OfficeGroups[Source rank],0))),"")) -> 490405-A | D43: =IF(Trends!$B$6<>"","",IF(COUNTIFS(OfficeGroups[Source rank],3)=1,INDEX(OfficeGroups[Source net],MATCH(3,OfficeGroups[Source rank],0)),"")) -> 2603796 | E43: =IF(Trends!$B$6<>"","",IF(COUNTIFS(OfficeGroups[Source rank],3)=1,INDEX(OfficeGroups[Source deobligations],MATCH(3,OfficeGroups[Source rank],0)),"")) -> 0 | F43: =IF(Trends!$B$6<>"","",IF(COUNTIFS(OfficeGroups[Source rank],3)=1,INDEX(OfficeGroups[Source awards],MATCH(3,OfficeGroups[Source rank],0)),"")) -> 1 | G43: =IF(Trends!$B$6<>"","",IF(COUNTIFS(OfficeGroups[Source rank],3)=1,INDEX(OfficeGroups[Source actions],MATCH(3,OfficeGroups[Source rank],0)),"")) -> 2 | H43: 4900|4900|491004-A | I43: Division of Acquisition and Cooperative Support | J43: 491004-A | K43: https://govtribe.com/agency/federal-agency/national-science-foundation-division-of-acquisition-and-cooperative-support | L43: =IF(H43="","",I43&IF(J43="",""," ["&J43&"]")) -> Division of Acquisition and Cooperative Support [491004-A] | M43: =IF(H43="","",SUMIFS(TransactionsData[Obligations],TransactionsData[Funding office ID],H43,TransactionsData[Selected],1)) -> 0 | N43: =IF(H43="","",SUMIFS(TransactionsData[Deobligations],TransactionsData[Funding office ID],H43,TransactionsData[Selected],1)) -> 0 | O43: =IF(H43="","",SUMIFS(TransactionsData[First office award],TransactionsData[Funding office ID],H43)) -> 0 | P43: =IF(H43="","",COUNTIFS(TransactionsData[Funding office ID],H43,TransactionsData[Selected],1)) -> 0 | Q43: =IF(OR(H43="",P43=0),"",COUNTIFS(OfficeGroups[Source net],">"&M43,OfficeGroups[Source actions],">0")+COUNTIFS(OfficeGroups[Source net],M43,OfficeGroups[Record ID],"<"&H43,OfficeGroups[Source actions],">0")+1) | R43: =IF(H43="",IF(COUNTA(I43:K43)>0,"Missing record ID",""),IF(COUNTIFS(OfficeGroups[Record ID],H43)<>1,"Duplicate record ID",IF(I43="","Add name","")))
A44: =IF(Trends!$B$6<>"","",IF(COUNTIFS(OfficeGroups[Source rank],4)=1,4,"")) -> 4 | B44: =IF(Trends!$B$6<>"","",IF(COUNTIFS(OfficeGroups[Source rank],4)=1,IF(INDEX(OfficeGroups[Source URL],MATCH(4,OfficeGroups[Source rank],0))="",INDEX(OfficeGroups[Source name],MATCH(4,OfficeGroups[Source rank],0)),HYPERLINK(INDEX(OfficeGroups[Source URL],MATCH(4,OfficeGroups[Source rank],0)),INDEX(OfficeGroups[Source name],MATCH(4,OfficeGroups[Source rank],0)))),"")) -> National Center for Science and Engineering Statistics | C44: =IF(Trends!$B$6<>"","",IF(COUNTIFS(OfficeGroups[Source rank],4)=1,IF(INDEX(OfficeGroups[Source UEI],MATCH(4,OfficeGroups[Source rank],0))="","Not supplied",INDEX(OfficeGroups[Source UEI],MATCH(4,OfficeGroups[Source rank],0))),"")) -> 490403-A | D44: =IF(Trends!$B$6<>"","",IF(COUNTIFS(OfficeGroups[Source rank],4)=1,INDEX(OfficeGroups[Source net],MATCH(4,OfficeGroups[Source rank],0)),"")) -> 840658.87 | E44: =IF(Trends!$B$6<>"","",IF(COUNTIFS(OfficeGroups[Source rank],4)=1,INDEX(OfficeGroups[Source deobligations],MATCH(4,OfficeGroups[Source rank],0)),"")) -> 0 | F44: =IF(Trends!$B$6<>"","",IF(COUNTIFS(OfficeGroups[Source rank],4)=1,INDEX(OfficeGroups[Source awards],MATCH(4,OfficeGroups[Source rank],0)),"")) -> 1 | G44: =IF(Trends!$B$6<>"","",IF(COUNTIFS(OfficeGroups[Source rank],4)=1,INDEX(OfficeGroups[Source actions],MATCH(4,OfficeGroups[Source rank],0)),"")) -> 3 | H44: 4900|4900|490707-A | I44: Division of Industrial Innovation | J44: 490707-A | K44: https://govtribe.com/agency/federal-agency/national-science-foundation-division-of-industrial-innovation | L44: =IF(H44="","",I44&IF(J44="",""," ["&J44&"]")) -> Division of Industrial Innovation [490707-A] | M44: =IF(H44="","",SUMIFS(TransactionsData[Obligations],TransactionsData[Funding office ID],H44,TransactionsData[Selected],1)) -> -90.35 | N44: =IF(H44="","",SUMIFS(TransactionsData[Deobligations],TransactionsData[Funding office ID],H44,TransactionsData[Selected],1)) -> -90.35 | O44: =IF(H44="","",SUMIFS(TransactionsData[First office award],TransactionsData[Funding office ID],H44)) -> 1 | P44: =IF(H44="","",COUNTIFS(TransactionsData[Funding office ID],H44,TransactionsData[Selected],1)) -> 1 | Q44: =IF(OR(H44="",P44=0),"",COUNTIFS(OfficeGroups[Source net],">"&M44,OfficeGroups[Source actions],">0")+COUNTIFS(OfficeGroups[Source net],M44,OfficeGroups[Record ID],"<"&H44,OfficeGroups[Source actions],">0")+1) -> 10 | R44: =IF(H44="",IF(COUNTA(I44:K44)>0,"Missing record ID",""),IF(COUNTIFS(OfficeGroups[Record ID],H44)<>1,"Duplicate record ID",IF(I44="","Add name","")))
A45: =IF(Trends!$B$6<>"","",IF(COUNTIFS(OfficeGroups[Source rank],5)=1,5,"")) -> 5 | B45: =IF(Trends!$B$6<>"","",IF(COUNTIFS(OfficeGroups[Source rank],5)=1,IF(INDEX(OfficeGroups[Source URL],MATCH(5,OfficeGroups[Source rank],0))="",INDEX(OfficeGroups[Source name],MATCH(5,OfficeGroups[Source rank],0)),HYPERLINK(INDEX(OfficeGroups[Source URL],MATCH(5,OfficeGroups[Source rank],0)),INDEX(OfficeGroups[Source name],MATCH(5,OfficeGroups[Source rank],0)))),"")) -> Directorate of Geosciences | C45: =IF(Trends!$B$6<>"","",IF(COUNTIFS(OfficeGroups[Source rank],5)=1,IF(INDEX(OfficeGroups[Source UEI],MATCH(5,OfficeGroups[Source rank],0))="","Not supplied",INDEX(OfficeGroups[Source UEI],MATCH(5,OfficeGroups[Source rank],0))),"")) -> 490600-A | D45: =IF(Trends!$B$6<>"","",IF(COUNTIFS(OfficeGroups[Source rank],5)=1,INDEX(OfficeGroups[Source net],MATCH(5,OfficeGroups[Source rank],0)),"")) -> 495382.97 | E45: =IF(Trends!$B$6<>"","",IF(COUNTIFS(OfficeGroups[Source rank],5)=1,INDEX(OfficeGroups[Source deobligations],MATCH(5,OfficeGroups[Source rank],0)),"")) -> -13437.43 | F45: =IF(Trends!$B$6<>"","",IF(COUNTIFS(OfficeGroups[Source rank],5)=1,INDEX(OfficeGroups[Source awards],MATCH(5,OfficeGroups[Source rank],0)),"")) -> 1 | G45: =IF(Trends!$B$6<>"","",IF(COUNTIFS(OfficeGroups[Source rank],5)=1,INDEX(OfficeGroups[Source actions],MATCH(5,OfficeGroups[Source rank],0)),"")) -> 2 | H45: 4900|4900|490209-A | I45: Division of Information Systems | J45: 490209-A | K45: https://govtribe.com/agency/federal-agency/national-science-foundation-division-of-information-systems | L45: =IF(H45="","",I45&IF(J45="",""," ["&J45&"]")) -> Division of Information Systems [490209-A] | M45: =IF(H45="","",SUMIFS(TransactionsData[Obligations],TransactionsData[Funding office ID],H45,TransactionsData[Selected],1)) -> 26374874 | N45: =IF(H45="","",SUMIFS(TransactionsData[Deobligations],TransactionsData[Funding office ID],H45,TransactionsData[Selected],1)) -> -80190 | O45: =IF(H45="","",SUMIFS(TransactionsData[First office award],TransactionsData[Funding office ID],H45)) -> 10 | P45: =IF(H45="","",COUNTIFS(TransactionsData[Funding office ID],H45,TransactionsData[Selected],1)) -> 24 | Q45: =IF(OR(H45="",P45=0),"",COUNTIFS(OfficeGroups[Source net],">"&M45,OfficeGroups[Source actions],">0")+COUNTIFS(OfficeGroups[Source net],M45,OfficeGroups[Record ID],"<"&H45,OfficeGroups[Source actions],">0")+1) -> 2 | R45: =IF(H45="",IF(COUNTA(I45:K45)>0,"Missing record ID",""),IF(COUNTIFS(OfficeGroups[Record ID],H45)<>1,"Duplicate record ID",IF(I45="","Add name","")))
A46: =IF(Trends!$B$6<>"","",IF(COUNTIFS(OfficeGroups[Source rank],6)=1,6,"")) -> 6 | B46: =IF(Trends!$B$6<>"","",IF(COUNTIFS(OfficeGroups[Source rank],6)=1,IF(INDEX(OfficeGroups[Source URL],MATCH(6,OfficeGroups[Source rank],0))="",INDEX(OfficeGroups[Source name],MATCH(6,OfficeGroups[Source rank],0)),HYPERLINK(INDEX(OfficeGroups[Source URL],MATCH(6,OfficeGroups[Source rank],0)),INDEX(OfficeGroups[Source name],MATCH(6,OfficeGroups[Source rank],0)))),"")) -> Office of the Inspector General | C46: =IF(Trends!$B$6<>"","",IF(COUNTIFS(OfficeGroups[Source rank],6)=1,IF(INDEX(OfficeGroups[Source UEI],MATCH(6,OfficeGroups[Source rank],0))="","Not supplied",INDEX(OfficeGroups[Source UEI],MATCH(6,OfficeGroups[Source rank],0))),"")) -> 490002-A | D46: =IF(Trends!$B$6<>"","",IF(COUNTIFS(OfficeGroups[Source rank],6)=1,INDEX(OfficeGroups[Source net],MATCH(6,OfficeGroups[Source rank],0)),"")) -> 489791.72 | E46: =IF(Trends!$B$6<>"","",IF(COUNTIFS(OfficeGroups[Source rank],6)=1,INDEX(OfficeGroups[Source deobligations],MATCH(6,OfficeGroups[Source rank],0)),"")) -> 0 | F46: =IF(Trends!$B$6<>"","",IF(COUNTIFS(OfficeGroups[Source rank],6)=1,INDEX(OfficeGroups[Source awards],MATCH(6,OfficeGroups[Source rank],0)),"")) -> 1 | G46: =IF(Trends!$B$6<>"","",IF(COUNTIFS(OfficeGroups[Source rank],6)=1,INDEX(OfficeGroups[Source actions],MATCH(6,OfficeGroups[Source rank],0)),"")) -> 1 | H46: 4900|4900|490405-A | I46: Division of Social and Economic Science | J46: 490405-A | K46: https://govtribe.com/agency/federal-agency/national-science-foundation-division-of-social-and-economic-science | L46: =IF(H46="","",I46&IF(J46="",""," ["&J46&"]")) -> Division of Social and Economic Science [490405-A] | M46: =IF(H46="","",SUMIFS(TransactionsData[Obligations],TransactionsData[Funding office ID],H46,TransactionsData[Selected],1)) -> 2603796 | N46: =IF(H46="","",SUMIFS(TransactionsData[Deobligations],TransactionsData[Funding office ID],H46,TransactionsData[Selected],1)) -> 0 | O46: =IF(H46="","",SUMIFS(TransactionsData[First office award],TransactionsData[Funding office ID],H46)) -> 1 | P46: =IF(H46="","",COUNTIFS(TransactionsData[Funding office ID],H46,TransactionsData[Selected],1)) -> 2 | Q46: =IF(OR(H46="",P46=0),"",COUNTIFS(OfficeGroups[Source net],">"&M46,OfficeGroups[Source actions],">0")+COUNTIFS(OfficeGroups[Source net],M46,OfficeGroups[Record ID],"<"&H46,OfficeGroups[Source actions],">0")+1) -> 3 | R46: =IF(H46="",IF(COUNTA(I46:K46)>0,"Missing record ID",""),IF(COUNTIFS(OfficeGroups[Record ID],H46)<>1,"Duplicate record ID",IF(I46="","Add name","")))
A47: =IF(Trends!$B$6<>"","",IF(COUNTIFS(OfficeGroups[Source rank],7)=1,7,"")) -> 7 | B47: =IF(Trends!$B$6<>"","",IF(COUNTIFS(OfficeGroups[Source rank],7)=1,IF(INDEX(OfficeGroups[Source URL],MATCH(7,OfficeGroups[Source rank],0))="",INDEX(OfficeGroups[Source name],MATCH(7,OfficeGroups[Source rank],0)),HYPERLINK(INDEX(OfficeGroups[Source URL],MATCH(7,OfficeGroups[Source rank],0)),INDEX(OfficeGroups[Source name],MATCH(7,OfficeGroups[Source rank],0)))),"")) -> Directorate for Engineering | C47: =IF(Trends!$B$6<>"","",IF(COUNTIFS(OfficeGroups[Source rank],7)=1,IF(INDEX(OfficeGroups[Source UEI],MATCH(7,OfficeGroups[Source rank],0))="","Not supplied",INDEX(OfficeGroups[Source UEI],MATCH(7,OfficeGroups[Source rank],0))),"")) -> 490700-A | D47: =IF(Trends!$B$6<>"","",IF(COUNTIFS(OfficeGroups[Source rank],7)=1,INDEX(OfficeGroups[Source net],MATCH(7,OfficeGroups[Source rank],0)),"")) -> 150188.63 | E47: =IF(Trends!$B$6<>"","",IF(COUNTIFS(OfficeGroups[Source rank],7)=1,INDEX(OfficeGroups[Source deobligations],MATCH(7,OfficeGroups[Source rank],0)),"")) -> -77859 | F47: =IF(Trends!$B$6<>"","",IF(COUNTIFS(OfficeGroups[Source rank],7)=1,INDEX(OfficeGroups[Source awards],MATCH(7,OfficeGroups[Source rank],0)),"")) -> 1 | G47: =IF(Trends!$B$6<>"","",IF(COUNTIFS(OfficeGroups[Source rank],7)=1,INDEX(OfficeGroups[Source actions],MATCH(7,OfficeGroups[Source rank],0)),"")) -> 2 | H47: 4900|4900|490403-A | I47: National Center for Science and Engineering Statistics | J47: 490403-A | K47: https://govtribe.com/agency/federal-agency/national-science-foundation-national-center-for-science-and-engineering-statistics | L47: =IF(H47="","",I47&IF(J47="",""," ["&J47&"]")) -> National Center for Science and Engineering Statistics [490403-A] | M47: =IF(H47="","",SUMIFS(TransactionsData[Obligations],TransactionsData[Funding office ID],H47,TransactionsData[Selected],1)) -> 840658.87 | N47: =IF(H47="","",SUMIFS(TransactionsData[Deobligations],TransactionsData[Funding office ID],H47,TransactionsData[Selected],1)) -> 0 | O47: =IF(H47="","",SUMIFS(TransactionsData[First office award],TransactionsData[Funding office ID],H47)) -> 1 | P47: =IF(H47="","",COUNTIFS(TransactionsData[Funding office ID],H47,TransactionsData[Selected],1)) -> 3 | Q47: =IF(OR(H47="",P47=0),"",COUNTIFS(OfficeGroups[Source net],">"&M47,OfficeGroups[Source actions],">0")+COUNTIFS(OfficeGroups[Source net],M47,OfficeGroups[Record ID],"<"&H47,OfficeGroups[Source actions],">0")+1) -> 4 | R47: =IF(H47="",IF(COUNTA(I47:K47)>0,"Missing record ID",""),IF(COUNTIFS(OfficeGroups[Record ID],H47)<>1,"Duplicate record ID",IF(I47="","Add name","")))
A48: =IF(Trends!$B$6<>"","",IF(COUNTIFS(OfficeGroups[Source rank],8)=1,8,"")) -> 8 | B48: =IF(Trends!$B$6<>"","",IF(COUNTIFS(OfficeGroups[Source rank],8)=1,IF(INDEX(OfficeGroups[Source URL],MATCH(8,OfficeGroups[Source rank],0))="",INDEX(OfficeGroups[Source name],MATCH(8,OfficeGroups[Source rank],0)),HYPERLINK(INDEX(OfficeGroups[Source URL],MATCH(8,OfficeGroups[Source rank],0)),INDEX(OfficeGroups[Source name],MATCH(8,OfficeGroups[Source rank],0)))),"")) -> National Science Board | C48: =IF(Trends!$B$6<>"","",IF(COUNTIFS(OfficeGroups[Source rank],8)=1,IF(INDEX(OfficeGroups[Source UEI],MATCH(8,OfficeGroups[Source rank],0))="","Not supplied",INDEX(OfficeGroups[Source UEI],MATCH(8,OfficeGroups[Source rank],0))),"")) -> 490001-A | D48: =IF(Trends!$B$6<>"","",IF(COUNTIFS(OfficeGroups[Source rank],8)=1,INDEX(OfficeGroups[Source net],MATCH(8,OfficeGroups[Source rank],0)),"")) -> 16430.4 | E48: =IF(Trends!$B$6<>"","",IF(COUNTIFS(OfficeGroups[Source rank],8)=1,INDEX(OfficeGroups[Source deobligations],MATCH(8,OfficeGroups[Source rank],0)),"")) -> 0 | F48: =IF(Trends!$B$6<>"","",IF(COUNTIFS(OfficeGroups[Source rank],8)=1,INDEX(OfficeGroups[Source awards],MATCH(8,OfficeGroups[Source rank],0)),"")) -> 1 | G48: =IF(Trends!$B$6<>"","",IF(COUNTIFS(OfficeGroups[Source rank],8)=1,INDEX(OfficeGroups[Source actions],MATCH(8,OfficeGroups[Source rank],0)),"")) -> 2 | H48: 4900|4900|490001-A | I48: National Science Board | J48: 490001-A | K48: https://govtribe.com/agency/federal-agency/national-science-foundation-national-science-board | L48: =IF(H48="","",I48&IF(J48="",""," ["&J48&"]")) -> National Science Board [490001-A] | M48: =IF(H48="","",SUMIFS(TransactionsData[Obligations],TransactionsData[Funding office ID],H48,TransactionsData[Selected],1)) -> 16430.4 | N48: =IF(H48="","",SUMIFS(TransactionsData[Deobligations],TransactionsData[Funding office ID],H48,TransactionsData[Selected],1)) -> 0 | O48: =IF(H48="","",SUMIFS(TransactionsData[First office award],TransactionsData[Funding office ID],H48)) -> 1 | P48: =IF(H48="","",COUNTIFS(TransactionsData[Funding office ID],H48,TransactionsData[Selected],1)) -> 2 | Q48: =IF(OR(H48="",P48=0),"",COUNTIFS(OfficeGroups[Source net],">"&M48,OfficeGroups[Source actions],">0")+COUNTIFS(OfficeGroups[Source net],M48,OfficeGroups[Record ID],"<"&H48,OfficeGroups[Source actions],">0")+1) -> 8 | R48: =IF(H48="",IF(COUNTA(I48:K48)>0,"Missing record ID",""),IF(COUNTIFS(OfficeGroups[Record ID],H48)<>1,"Duplicate record ID",IF(I48="","Add name","")))
A49: =IF(Trends!$B$6<>"","",IF(COUNTIFS(OfficeGroups[Source rank],9)=1,9,"")) -> 9 | B49: =IF(Trends!$B$6<>"","",IF(COUNTIFS(OfficeGroups[Source rank],9)=1,IF(INDEX(OfficeGroups[Source URL],MATCH(9,OfficeGroups[Source rank],0))="",INDEX(OfficeGroups[Source name],MATCH(9,OfficeGroups[Source rank],0)),HYPERLINK(INDEX(OfficeGroups[Source URL],MATCH(9,OfficeGroups[Source rank],0)),INDEX(OfficeGroups[Source name],MATCH(9,OfficeGroups[Source rank],0)))),"")) -> Office of Budget Finance and Award Management | C49: =IF(Trends!$B$6<>"","",IF(COUNTIFS(OfficeGroups[Source rank],9)=1,IF(INDEX(OfficeGroups[Source UEI],MATCH(9,OfficeGroups[Source rank],0))="","Not supplied",INDEX(OfficeGroups[Source UEI],MATCH(9,OfficeGroups[Source rank],0))),"")) -> 491000-A | D49: =IF(Trends!$B$6<>"","",IF(COUNTIFS(OfficeGroups[Source rank],9)=1,INDEX(OfficeGroups[Source net],MATCH(9,OfficeGroups[Source rank],0)),"")) -> 0 | E49: =IF(Trends!$B$6<>"","",IF(COUNTIFS(OfficeGroups[Source rank],9)=1,INDEX(OfficeGroups[Source deobligations],MATCH(9,OfficeGroups[Source rank],0)),"")) -> 0 | F49: =IF(Trends!$B$6<>"","",IF(COUNTIFS(OfficeGroups[Source rank],9)=1,INDEX(OfficeGroups[Source awards],MATCH(9,OfficeGroups[Source rank],0)),"")) -> 0 | G49: =IF(Trends!$B$6<>"","",IF(COUNTIFS(OfficeGroups[Source rank],9)=1,INDEX(OfficeGroups[Source actions],MATCH(9,OfficeGroups[Source rank],0)),"")) -> 1 | H49: 4900-A | I49: NSF — office not specified | J49: 4900-A | K49: https://govtribe.com/agency/federal-agency/national-science-foundation | L49: =IF(H49="","",I49&IF(J49="",""," ["&J49&"]")) -> NSF — office not specified [4900-A] | M49: =IF(H49="","",SUMIFS(TransactionsData[Obligations],TransactionsData[Funding office ID],H49,TransactionsData[Selected],1)) -> 89345634 | N49: =IF(H49="","",SUMIFS(TransactionsData[Deobligations],TransactionsData[Funding office ID],H49,TransactionsData[Selected],1)) -> -1128849.5 | O49: =IF(H49="","",SUMIFS(TransactionsData[First office award],TransactionsData[Funding office ID],H49)) -> 19 | P49: =IF(H49="","",COUNTIFS(TransactionsData[Funding office ID],H49,TransactionsData[Selected],1)) -> 68 | Q49: =IF(OR(H49="",P49=0),"",COUNTIFS(OfficeGroups[Source net],">"&M49,OfficeGroups[Source actions],">0")+COUNTIFS(OfficeGroups[Source net],M49,OfficeGroups[Record ID],"<"&H49,OfficeGroups[Source actions],">0")+1) -> 1 | R49: =IF(H49="",IF(COUNTA(I49:K49)>0,"Missing record ID",""),IF(COUNTIFS(OfficeGroups[Record ID],H49)<>1,"Duplicate record ID",IF(I49="","Add name","")))
A50: =IF(Trends!$B$6<>"","",IF(COUNTIFS(OfficeGroups[Source rank],10)=1,10,"")) -> 10 | B50: =IF(Trends!$B$6<>"","",IF(COUNTIFS(OfficeGroups[Source rank],10)=1,IF(INDEX(OfficeGroups[Source URL],MATCH(10,OfficeGroups[Source rank],0))="",INDEX(OfficeGroups[Source name],MATCH(10,OfficeGroups[Source rank],0)),HYPERLINK(INDEX(OfficeGroups[Source URL],MATCH(10,OfficeGroups[Source rank],0)),INDEX(OfficeGroups[Source name],MATCH(10,OfficeGroups[Source rank],0)))),"")) -> Division of Industrial Innovation | C50: =IF(Trends!$B$6<>"","",IF(COUNTIFS(OfficeGroups[Source rank],10)=1,IF(INDEX(OfficeGroups[Source UEI],MATCH(10,OfficeGroups[Source rank],0))="","Not supplied",INDEX(OfficeGroups[Source UEI],MATCH(10,OfficeGroups[Source rank],0))),"")) -> 490707-A | D50: =IF(Trends!$B$6<>"","",IF(COUNTIFS(OfficeGroups[Source rank],10)=1,INDEX(OfficeGroups[Source net],MATCH(10,OfficeGroups[Source rank],0)),"")) -> -90.35 | E50: =IF(Trends!$B$6<>"","",IF(COUNTIFS(OfficeGroups[Source rank],10)=1,INDEX(OfficeGroups[Source deobligations],MATCH(10,OfficeGroups[Source rank],0)),"")) -> -90.35 | F50: =IF(Trends!$B$6<>"","",IF(COUNTIFS(OfficeGroups[Source rank],10)=1,INDEX(OfficeGroups[Source awards],MATCH(10,OfficeGroups[Source rank],0)),"")) -> 1 | G50: =IF(Trends!$B$6<>"","",IF(COUNTIFS(OfficeGroups[Source rank],10)=1,INDEX(OfficeGroups[Source actions],MATCH(10,OfficeGroups[Source rank],0)),"")) -> 1 | H50: 4900|4900|491000-A | I50: Office of Budget Finance and Award Management | J50: 491000-A | K50: https://govtribe.com/agency/federal-agency/national-science-foundation-office-of-budget-finance-and-award-management | L50: =IF(H50="","",I50&IF(J50="",""," ["&J50&"]")) -> Office of Budget Finance and Award Management [491000-A] | M50: =IF(H50="","",SUMIFS(TransactionsData[Obligations],TransactionsData[Funding office ID],H50,TransactionsData[Selected],1)) -> 0 | N50: =IF(H50="","",SUMIFS(TransactionsData[Deobligations],TransactionsData[Funding office ID],H50,TransactionsData[Selected],1)) -> 0 | O50: =IF(H50="","",SUMIFS(TransactionsData[First office award],TransactionsData[Funding office ID],H50)) -> 0 | P50: =IF(H50="","",COUNTIFS(TransactionsData[Funding office ID],H50,TransactionsData[Selected],1)) -> 1 | Q50: =IF(OR(H50="",P50=0),"",COUNTIFS(OfficeGroups[Source net],">"&M50,OfficeGroups[Source actions],">0")+COUNTIFS(OfficeGroups[Source net],M50,OfficeGroups[Record ID],"<"&H50,OfficeGroups[Source actions],">0")+1) -> 9 | R50: =IF(H50="",IF(COUNTA(I50:K50)>0,"Missing record ID",""),IF(COUNTIFS(OfficeGroups[Record ID],H50)<>1,"Duplicate record ID",IF(I50="","Add name","")))
A51: =IF(Trends!$B$6<>"","",IF(COUNTIFS(OfficeGroups[Source rank],11)=1,11,"")) | B51: =IF(Trends!$B$6<>"","",IF(COUNTIFS(OfficeGroups[Source rank],11)=1,IF(INDEX(OfficeGroups[Source URL],MATCH(11,OfficeGroups[Source rank],0))="",INDEX(OfficeGroups[Source name],MATCH(11,OfficeGroups[Source rank],0)),HYPERLINK(INDEX(OfficeGroups[Source URL],MATCH(11,OfficeGroups[Source rank],0)),INDEX(OfficeGroups[Source name],MATCH(11,OfficeGroups[Source rank],0)))),"")) | C51: =IF(Trends!$B$6<>"","",IF(COUNTIFS(OfficeGroups[Source rank],11)=1,IF(INDEX(OfficeGroups[Source UEI],MATCH(11,OfficeGroups[Source rank],0))="","Not supplied",INDEX(OfficeGroups[Source UEI],MATCH(11,OfficeGroups[Source rank],0))),"")) | D51: =IF(Trends!$B$6<>"","",IF(COUNTIFS(OfficeGroups[Source rank],11)=1,INDEX(OfficeGroups[Source net],MATCH(11,OfficeGroups[Source rank],0)),"")) | E51: =IF(Trends!$B$6<>"","",IF(COUNTIFS(OfficeGroups[Source rank],11)=1,INDEX(OfficeGroups[Source deobligations],MATCH(11,OfficeGroups[Source rank],0)),"")) | F51: =IF(Trends!$B$6<>"","",IF(COUNTIFS(OfficeGroups[Source rank],11)=1,INDEX(OfficeGroups[Source awards],MATCH(11,OfficeGroups[Source rank],0)),"")) | G51: =IF(Trends!$B$6<>"","",IF(COUNTIFS(OfficeGroups[Source rank],11)=1,INDEX(OfficeGroups[Source actions],MATCH(11,OfficeGroups[Source rank],0)),"")) | H51: 4900|4900|490200-A | I51: Office of Information Resource Management | J51: 490200-A | K51: https://govtribe.com/agency/federal-agency/national-science-foundation-office-of-information-resource-management | L51: =IF(H51="","",I51&IF(J51="",""," ["&J51&"]")) -> Office of Information Resource Management [490200-A] | M51: =IF(H51="","",SUMIFS(TransactionsData[Obligations],TransactionsData[Funding office ID],H51,TransactionsData[Selected],1)) -> 0 | N51: =IF(H51="","",SUMIFS(TransactionsData[Deobligations],TransactionsData[Funding office ID],H51,TransactionsData[Selected],1)) -> 0 | O51: =IF(H51="","",SUMIFS(TransactionsData[First office award],TransactionsData[Funding office ID],H51)) -> 0 | P51: =IF(H51="","",COUNTIFS(TransactionsData[Funding office ID],H51,TransactionsData[Selected],1)) -> 0 | Q51: =IF(OR(H51="",P51=0),"",COUNTIFS(OfficeGroups[Source net],">"&M51,OfficeGroups[Source actions],">0")+COUNTIFS(OfficeGroups[Source net],M51,OfficeGroups[Record ID],"<"&H51,OfficeGroups[Source actions],">0")+1) | R51: =IF(H51="",IF(COUNTA(I51:K51)>0,"Missing record ID",""),IF(COUNTIFS(OfficeGroups[Record ID],H51)<>1,"Duplicate record ID",IF(I51="","Add name","")))
A52: =IF(Trends!$B$6<>"","",IF(COUNTIFS(OfficeGroups[Source rank],12)=1,12,"")) | B52: =IF(Trends!$B$6<>"","",IF(COUNTIFS(OfficeGroups[Source rank],12)=1,IF(INDEX(OfficeGroups[Source URL],MATCH(12,OfficeGroups[Source rank],0))="",INDEX(OfficeGroups[Source name],MATCH(12,OfficeGroups[Source rank],0)),HYPERLINK(INDEX(OfficeGroups[Source URL],MATCH(12,OfficeGroups[Source rank],0)),INDEX(OfficeGroups[Source name],MATCH(12,OfficeGroups[Source rank],0)))),"")) | C52: =IF(Trends!$B$6<>"","",IF(COUNTIFS(OfficeGroups[Source rank],12)=1,IF(INDEX(OfficeGroups[Source UEI],MATCH(12,OfficeGroups[Source rank],0))="","Not supplied",INDEX(OfficeGroups[Source UEI],MATCH(12,OfficeGroups[Source rank],0))),"")) | D52: =IF(Trends!$B$6<>"","",IF(COUNTIFS(OfficeGroups[Source rank],12)=1,INDEX(OfficeGroups[Source net],MATCH(12,OfficeGroups[Source rank],0)),"")) | E52: =IF(Trends!$B$6<>"","",IF(COUNTIFS(OfficeGroups[Source rank],12)=1,INDEX(OfficeGroups[Source deobligations],MATCH(12,OfficeGroups[Source rank],0)),"")) | F52: =IF(Trends!$B$6<>"","",IF(COUNTIFS(OfficeGroups[Source rank],12)=1,INDEX(OfficeGroups[Source awards],MATCH(12,OfficeGroups[Source rank],0)),"")) | G52: =IF(Trends!$B$6<>"","",IF(COUNTIFS(OfficeGroups[Source rank],12)=1,INDEX(OfficeGroups[Source actions],MATCH(12,OfficeGroups[Source rank],0)),"")) | H52: 4900|4900|490002-A | I52: Office of the Inspector General | J52: 490002-A | K52: https://govtribe.com/agency/federal-agency/national-science-foundation-office-of-the-inspector-general | L52: =IF(H52="","",I52&IF(J52="",""," ["&J52&"]")) -> Office of the Inspector General [490002-A] | M52: =IF(H52="","",SUMIFS(TransactionsData[Obligations],TransactionsData[Funding office ID],H52,TransactionsData[Selected],1)) -> 489791.72 | N52: =IF(H52="","",SUMIFS(TransactionsData[Deobligations],TransactionsData[Funding office ID],H52,TransactionsData[Selected],1)) -> 0 | O52: =IF(H52="","",SUMIFS(TransactionsData[First office award],TransactionsData[Funding office ID],H52)) -> 1 | P52: =IF(H52="","",COUNTIFS(TransactionsData[Funding office ID],H52,TransactionsData[Selected],1)) -> 1 | Q52: =IF(OR(H52="",P52=0),"",COUNTIFS(OfficeGroups[Source net],">"&M52,OfficeGroups[Source actions],">0")+COUNTIFS(OfficeGroups[Source net],M52,OfficeGroups[Record ID],"<"&H52,OfficeGroups[Source actions],">0")+1) -> 6 | R52: =IF(H52="",IF(COUNTA(I52:K52)>0,"Missing record ID",""),IF(COUNTIFS(OfficeGroups[Record ID],H52)<>1,"Duplicate record ID",IF(I52="","Add name","")))
A53: =IF(Trends!$B$6<>"","",IF(COUNTIFS(OfficeGroups[Source rank],13)=1,13,"")) | B53: =IF(Trends!$B$6<>"","",IF(COUNTIFS(OfficeGroups[Source rank],13)=1,IF(INDEX(OfficeGroups[Source URL],MATCH(13,OfficeGroups[Source rank],0))="",INDEX(OfficeGroups[Source name],MATCH(13,OfficeGroups[Source rank],0)),HYPERLINK(INDEX(OfficeGroups[Source URL],MATCH(13,OfficeGroups[Source rank],0)),INDEX(OfficeGroups[Source name],MATCH(13,OfficeGroups[Source rank],0)))),"")) | C53: =IF(Trends!$B$6<>"","",IF(COUNTIFS(OfficeGroups[Source rank],13)=1,IF(INDEX(OfficeGroups[Source UEI],MATCH(13,OfficeGroups[Source rank],0))="","Not supplied",INDEX(OfficeGroups[Source UEI],MATCH(13,OfficeGroups[Source rank],0))),"")) | D53: =IF(Trends!$B$6<>"","",IF(COUNTIFS(OfficeGroups[Source rank],13)=1,INDEX(OfficeGroups[Source net],MATCH(13,OfficeGroups[Source rank],0)),"")) | E53: =IF(Trends!$B$6<>"","",IF(COUNTIFS(OfficeGroups[Source rank],13)=1,INDEX(OfficeGroups[Source deobligations],MATCH(13,OfficeGroups[Source rank],0)),"")) | F53: =IF(Trends!$B$6<>"","",IF(COUNTIFS(OfficeGroups[Source rank],13)=1,INDEX(OfficeGroups[Source awards],MATCH(13,OfficeGroups[Source rank],0)),"")) | G53: =IF(Trends!$B$6<>"","",IF(COUNTIFS(OfficeGroups[Source rank],13)=1,INDEX(OfficeGroups[Source actions],MATCH(13,OfficeGroups[Source rank],0)),"")) | L53: =IF(H53="","",I53&IF(J53="",""," ["&J53&"]")) | M53: =IF(H53="","",SUMIFS(TransactionsData[Obligations],TransactionsData[Funding office ID],H53,TransactionsData[Selected],1)) | N53: =IF(H53="","",SUMIFS(TransactionsData[Deobligations],TransactionsData[Funding office ID],H53,TransactionsData[Selected],1)) | O53: =IF(H53="","",SUMIFS(TransactionsData[First office award],TransactionsData[Funding office ID],H53)) | P53: =IF(H53="","",COUNTIFS(TransactionsData[Funding office ID],H53,TransactionsData[Selected],1)) | Q53: =IF(OR(H53="",P53=0),"",COUNTIFS(OfficeGroups[Source net],">"&M53,OfficeGroups[Source actions],">0")+COUNTIFS(OfficeGroups[Source net],M53,OfficeGroups[Record ID],"<"&H53,OfficeGroups[Source actions],">0")+1) | R53: =IF(H53="",IF(COUNTA(I53:K53)>0,"Missing record ID",""),IF(COUNTIFS(OfficeGroups[Record ID],H53)<>1,"Duplicate record ID",IF(I53="","Add name","")))
A54: =IF(Trends!$B$6<>"","",IF(COUNTIFS(OfficeGroups[Source rank],14)=1,14,"")) | B54: =IF(Trends!$B$6<>"","",IF(COUNTIFS(OfficeGroups[Source rank],14)=1,IF(INDEX(OfficeGroups[Source URL],MATCH(14,OfficeGroups[Source rank],0))="",INDEX(OfficeGroups[Source name],MATCH(14,OfficeGroups[Source rank],0)),HYPERLINK(INDEX(OfficeGroups[Source URL],MATCH(14,OfficeGroups[Source rank],0)),INDEX(OfficeGroups[Source name],MATCH(14,OfficeGroups[Source rank],0)))),"")) | C54: =IF(Trends!$B$6<>"","",IF(COUNTIFS(OfficeGroups[Source rank],14)=1,IF(INDEX(OfficeGroups[Source UEI],MATCH(14,OfficeGroups[Source rank],0))="","Not supplied",INDEX(OfficeGroups[Source UEI],MATCH(14,OfficeGroups[Source rank],0))),"")) | D54: =IF(Trends!$B$6<>"","",IF(COUNTIFS(OfficeGroups[Source rank],14)=1,INDEX(OfficeGroups[Source net],MATCH(14,OfficeGroups[Source rank],0)),"")) | E54: =IF(Trends!$B$6<>"","",IF(COUNTIFS(OfficeGroups[Source rank],14)=1,INDEX(OfficeGroups[Source deobligations],MATCH(14,OfficeGroups[Source rank],0)),"")) | F54: =IF(Trends!$B$6<>"","",IF(COUNTIFS(OfficeGroups[Source rank],14)=1,INDEX(OfficeGroups[Source awards],MATCH(14,OfficeGroups[Source rank],0)),"")) | G54: =IF(Trends!$B$6<>"","",IF(COUNTIFS(OfficeGroups[Source rank],14)=1,INDEX(OfficeGroups[Source actions],MATCH(14,OfficeGroups[Source rank],0)),"")) | L54: =IF(H54="","",I54&IF(J54="",""," ["&J54&"]")) | M54: =IF(H54="","",SUMIFS(TransactionsData[Obligations],TransactionsData[Funding office ID],H54,TransactionsData[Selected],1)) | N54: =IF(H54="","",SUMIFS(TransactionsData[Deobligations],TransactionsData[Funding office ID],H54,TransactionsData[Selected],1)) | O54: =IF(H54="","",SUMIFS(TransactionsData[First office award],TransactionsData[Funding office ID],H54)) | P54: =IF(H54="","",COUNTIFS(TransactionsData[Funding office ID],H54,TransactionsData[Selected],1)) | Q54: =IF(OR(H54="",P54=0),"",COUNTIFS(OfficeGroups[Source net],">"&M54,OfficeGroups[Source actions],">0")+COUNTIFS(OfficeGroups[Source net],M54,OfficeGroups[Record ID],"<"&H54,OfficeGroups[Source actions],">0")+1) | R54: =IF(H54="",IF(COUNTA(I54:K54)>0,"Missing record ID",""),IF(COUNTIFS(OfficeGroups[Record ID],H54)<>1,"Duplicate record ID",IF(I54="","Add name","")))
A55: =IF(Trends!$B$6<>"","",IF(COUNTIFS(OfficeGroups[Source rank],15)=1,15,"")) | B55: =IF(Trends!$B$6<>"","",IF(COUNTIFS(OfficeGroups[Source rank],15)=1,IF(INDEX(OfficeGroups[Source URL],MATCH(15,OfficeGroups[Source rank],0))="",INDEX(OfficeGroups[Source name],MATCH(15,OfficeGroups[Source rank],0)),HYPERLINK(INDEX(OfficeGroups[Source URL],MATCH(15,OfficeGroups[Source rank],0)),INDEX(OfficeGroups[Source name],MATCH(15,OfficeGroups[Source rank],0)))),"")) | C55: =IF(Trends!$B$6<>"","",IF(COUNTIFS(OfficeGroups[Source rank],15)=1,IF(INDEX(OfficeGroups[Source UEI],MATCH(15,OfficeGroups[Source rank],0))="","Not supplied",INDEX(OfficeGroups[Source UEI],MATCH(15,OfficeGroups[Source rank],0))),"")) | D55: =IF(Trends!$B$6<>"","",IF(COUNTIFS(OfficeGroups[Source rank],15)=1,INDEX(OfficeGroups[Source net],MATCH(15,OfficeGroups[Source rank],0)),"")) | E55: =IF(Trends!$B$6<>"","",IF(COUNTIFS(OfficeGroups[Source rank],15)=1,INDEX(OfficeGroups[Source deobligations],MATCH(15,OfficeGroups[Source rank],0)),"")) | F55: =IF(Trends!$B$6<>"","",IF(COUNTIFS(OfficeGroups[Source rank],15)=1,INDEX(OfficeGroups[Source awards],MATCH(15,OfficeGroups[Source rank],0)),"")) | G55: =IF(Trends!$B$6<>"","",IF(COUNTIFS(OfficeGroups[Source rank],15)=1,INDEX(OfficeGroups[Source actions],MATCH(15,OfficeGroups[Source rank],0)),"")) | L55: =IF(H55="","",I55&IF(J55="",""," ["&J55&"]")) | M55: =IF(H55="","",SUMIFS(TransactionsData[Obligations],TransactionsData[Funding office ID],H55,TransactionsData[Selected],1)) | N55: =IF(H55="","",SUMIFS(TransactionsData[Deobligations],TransactionsData[Funding office ID],H55,TransactionsData[Selected],1)) | O55: =IF(H55="","",SUMIFS(TransactionsData[First office award],TransactionsData[Funding office ID],H55)) | P55: =IF(H55="","",COUNTIFS(TransactionsData[Funding office ID],H55,TransactionsData[Selected],1)) | Q55: =IF(OR(H55="",P55=0),"",COUNTIFS(OfficeGroups[Source net],">"&M55,OfficeGroups[Source actions],">0")+COUNTIFS(OfficeGroups[Source net],M55,OfficeGroups[Record ID],"<"&H55,OfficeGroups[Source actions],">0")+1) | R55: =IF(H55="",IF(COUNTA(I55:K55)>0,"Missing record ID",""),IF(COUNTIFS(OfficeGroups[Record ID],H55)<>1,"Duplicate record ID",IF(I55="","Add name","")))
A56: =IF(Trends!$B$6<>"","",IF(COUNTIFS(OfficeGroups[Source rank],16)=1,16,"")) | B56: =IF(Trends!$B$6<>"","",IF(COUNTIFS(OfficeGroups[Source rank],16)=1,IF(INDEX(OfficeGroups[Source URL],MATCH(16,OfficeGroups[Source rank],0))="",INDEX(OfficeGroups[Source name],MATCH(16,OfficeGroups[Source rank],0)),HYPERLINK(INDEX(OfficeGroups[Source URL],MATCH(16,OfficeGroups[Source rank],0)),INDEX(OfficeGroups[Source name],MATCH(16,OfficeGroups[Source rank],0)))),"")) | C56: =IF(Trends!$B$6<>"","",IF(COUNTIFS(OfficeGroups[Source rank],16)=1,IF(INDEX(OfficeGroups[Source UEI],MATCH(16,OfficeGroups[Source rank],0))="","Not supplied",INDEX(OfficeGroups[Source UEI],MATCH(16,OfficeGroups[Source rank],0))),"")) | D56: =IF(Trends!$B$6<>"","",IF(COUNTIFS(OfficeGroups[Source rank],16)=1,INDEX(OfficeGroups[Source net],MATCH(16,OfficeGroups[Source rank],0)),"")) | E56: =IF(Trends!$B$6<>"","",IF(COUNTIFS(OfficeGroups[Source rank],16)=1,INDEX(OfficeGroups[Source deobligations],MATCH(16,OfficeGroups[Source rank],0)),"")) | F56: =IF(Trends!$B$6<>"","",IF(COUNTIFS(OfficeGroups[Source rank],16)=1,INDEX(OfficeGroups[Source awards],MATCH(16,OfficeGroups[Source rank],0)),"")) | G56: =IF(Trends!$B$6<>"","",IF(COUNTIFS(OfficeGroups[Source rank],16)=1,INDEX(OfficeGroups[Source actions],MATCH(16,OfficeGroups[Source rank],0)),"")) | L56: =IF(H56="","",I56&IF(J56="",""," ["&J56&"]")) | M56: =IF(H56="","",SUMIFS(TransactionsData[Obligations],TransactionsData[Funding office ID],H56,TransactionsData[Selected],1)) | N56: =IF(H56="","",SUMIFS(TransactionsData[Deobligations],TransactionsData[Funding office ID],H56,TransactionsData[Selected],1)) | O56: =IF(H56="","",SUMIFS(TransactionsData[First office award],TransactionsData[Funding office ID],H56)) | P56: =IF(H56="","",COUNTIFS(TransactionsData[Funding office ID],H56,TransactionsData[Selected],1)) | Q56: =IF(OR(H56="",P56=0),"",COUNTIFS(OfficeGroups[Source net],">"&M56,OfficeGroups[Source actions],">0")+COUNTIFS(OfficeGroups[Source net],M56,OfficeGroups[Record ID],"<"&H56,OfficeGroups[Source actions],">0")+1) | R56: =IF(H56="",IF(COUNTA(I56:K56)>0,"Missing record ID",""),IF(COUNTIFS(OfficeGroups[Record ID],H56)<>1,"Duplicate record ID",IF(I56="","Add name","")))
A57: =IF(Trends!$B$6<>"","",IF(COUNTIFS(OfficeGroups[Source rank],17)=1,17,"")) | B57: =IF(Trends!$B$6<>"","",IF(COUNTIFS(OfficeGroups[Source rank],17)=1,IF(INDEX(OfficeGroups[Source URL],MATCH(17,OfficeGroups[Source rank],0))="",INDEX(OfficeGroups[Source name],MATCH(17,OfficeGroups[Source rank],0)),HYPERLINK(INDEX(OfficeGroups[Source URL],MATCH(17,OfficeGroups[Source rank],0)),INDEX(OfficeGroups[Source name],MATCH(17,OfficeGroups[Source rank],0)))),"")) | C57: =IF(Trends!$B$6<>"","",IF(COUNTIFS(OfficeGroups[Source rank],17)=1,IF(INDEX(OfficeGroups[Source UEI],MATCH(17,OfficeGroups[Source rank],0))="","Not supplied",INDEX(OfficeGroups[Source UEI],MATCH(17,OfficeGroups[Source rank],0))),"")) | D57: =IF(Trends!$B$6<>"","",IF(COUNTIFS(OfficeGroups[Source rank],17)=1,INDEX(OfficeGroups[Source net],MATCH(17,OfficeGroups[Source rank],0)),"")) | E57: =IF(Trends!$B$6<>"","",IF(COUNTIFS(OfficeGroups[Source rank],17)=1,INDEX(OfficeGroups[Source deobligations],MATCH(17,OfficeGroups[Source rank],0)),"")) | F57: =IF(Trends!$B$6<>"","",IF(COUNTIFS(OfficeGroups[Source rank],17)=1,INDEX(OfficeGroups[Source awards],MATCH(17,OfficeGroups[Source rank],0)),"")) | G57: =IF(Trends!$B$6<>"","",IF(COUNTIFS(OfficeGroups[Source rank],17)=1,INDEX(OfficeGroups[Source actions],MATCH(17,OfficeGroups[Source rank],0)),"")) | L57: =IF(H57="","",I57&IF(J57="",""," ["&J57&"]")) | M57: =IF(H57="","",SUMIFS(TransactionsData[Obligations],TransactionsData[Funding office ID],H57,TransactionsData[Selected],1)) | N57: =IF(H57="","",SUMIFS(TransactionsData[Deobligations],TransactionsData[Funding office ID],H57,TransactionsData[Selected],1)) | O57: =IF(H57="","",SUMIFS(TransactionsData[First office award],TransactionsData[Funding office ID],H57)) | P57: =IF(H57="","",COUNTIFS(TransactionsData[Funding office ID],H57,TransactionsData[Selected],1)) | Q57: =IF(OR(H57="",P57=0),"",COUNTIFS(OfficeGroups[Source net],">"&M57,OfficeGroups[Source actions],">0")+COUNTIFS(OfficeGroups[Source net],M57,OfficeGroups[Record ID],"<"&H57,OfficeGroups[Source actions],">0")+1) | R57: =IF(H57="",IF(COUNTA(I57:K57)>0,"Missing record ID",""),IF(COUNTIFS(OfficeGroups[Record ID],H57)<>1,"Duplicate record ID",IF(I57="","Add name","")))
A58: =IF(Trends!$B$6<>"","",IF(COUNTIFS(OfficeGroups[Source rank],18)=1,18,"")) | B58: =IF(Trends!$B$6<>"","",IF(COUNTIFS(OfficeGroups[Source rank],18)=1,IF(INDEX(OfficeGroups[Source URL],MATCH(18,OfficeGroups[Source rank],0))="",INDEX(OfficeGroups[Source name],MATCH(18,OfficeGroups[Source rank],0)),HYPERLINK(INDEX(OfficeGroups[Source URL],MATCH(18,OfficeGroups[Source rank],0)),INDEX(OfficeGroups[Source name],MATCH(18,OfficeGroups[Source rank],0)))),"")) | C58: =IF(Trends!$B$6<>"","",IF(COUNTIFS(OfficeGroups[Source rank],18)=1,IF(INDEX(OfficeGroups[Source UEI],MATCH(18,OfficeGroups[Source rank],0))="","Not supplied",INDEX(OfficeGroups[Source UEI],MATCH(18,OfficeGroups[Source rank],0))),"")) | D58: =IF(Trends!$B$6<>"","",IF(COUNTIFS(OfficeGroups[Source rank],18)=1,INDEX(OfficeGroups[Source net],MATCH(18,OfficeGroups[Source rank],0)),"")) | E58: =IF(Trends!$B$6<>"","",IF(COUNTIFS(OfficeGroups[Source rank],18)=1,INDEX(OfficeGroups[Source deobligations],MATCH(18,OfficeGroups[Source rank],0)),"")) | F58: =IF(Trends!$B$6<>"","",IF(COUNTIFS(OfficeGroups[Source rank],18)=1,INDEX(OfficeGroups[Source awards],MATCH(18,OfficeGroups[Source rank],0)),"")) | G58: =IF(Trends!$B$6<>"","",IF(COUNTIFS(OfficeGroups[Source rank],18)=1,INDEX(OfficeGroups[Source actions],MATCH(18,OfficeGroups[Source rank],0)),"")) | L58: =IF(H58="","",I58&IF(J58="",""," ["&J58&"]")) | M58: =IF(H58="","",SUMIFS(TransactionsData[Obligations],TransactionsData[Funding office ID],H58,TransactionsData[Selected],1)) | N58: =IF(H58="","",SUMIFS(TransactionsData[Deobligations],TransactionsData[Funding office ID],H58,TransactionsData[Selected],1)) | O58: =IF(H58="","",SUMIFS(TransactionsData[First office award],TransactionsData[Funding office ID],H58)) | P58: =IF(H58="","",COUNTIFS(TransactionsData[Funding office ID],H58,TransactionsData[Selected],1)) | Q58: =IF(OR(H58="",P58=0),"",COUNTIFS(OfficeGroups[Source net],">"&M58,OfficeGroups[Source actions],">0")+COUNTIFS(OfficeGroups[Source net],M58,OfficeGroups[Record ID],"<"&H58,OfficeGroups[Source actions],">0")+1) | R58: =IF(H58="",IF(COUNTA(I58:K58)>0,"Missing record ID",""),IF(COUNTIFS(OfficeGroups[Record ID],H58)<>1,"Duplicate record ID",IF(I58="","Add name","")))
A59: =IF(Trends!$B$6<>"","",IF(COUNTIFS(OfficeGroups[Source rank],19)=1,19,"")) | B59: =IF(Trends!$B$6<>"","",IF(COUNTIFS(OfficeGroups[Source rank],19)=1,IF(INDEX(OfficeGroups[Source URL],MATCH(19,OfficeGroups[Source rank],0))="",INDEX(OfficeGroups[Source name],MATCH(19,OfficeGroups[Source rank],0)),HYPERLINK(INDEX(OfficeGroups[Source URL],MATCH(19,OfficeGroups[Source rank],0)),INDEX(OfficeGroups[Source name],MATCH(19,OfficeGroups[Source rank],0)))),"")) | C59: =IF(Trends!$B$6<>"","",IF(COUNTIFS(OfficeGroups[Source rank],19)=1,IF(INDEX(OfficeGroups[Source UEI],MATCH(19,OfficeGroups[Source rank],0))="","Not supplied",INDEX(OfficeGroups[Source UEI],MATCH(19,OfficeGroups[Source rank],0))),"")) | D59: =IF(Trends!$B$6<>"","",IF(COUNTIFS(OfficeGroups[Source rank],19)=1,INDEX(OfficeGroups[Source net],MATCH(19,OfficeGroups[Source rank],0)),"")) | E59: =IF(Trends!$B$6<>"","",IF(COUNTIFS(OfficeGroups[Source rank],19)=1,INDEX(OfficeGroups[Source deobligations],MATCH(19,OfficeGroups[Source rank],0)),"")) | F59: =IF(Trends!$B$6<>"","",IF(COUNTIFS(OfficeGroups[Source rank],19)=1,INDEX(OfficeGroups[Source awards],MATCH(19,OfficeGroups[Source rank],0)),"")) | G59: =IF(Trends!$B$6<>"","",IF(COUNTIFS(OfficeGroups[Source rank],19)=1,INDEX(OfficeGroups[Source actions],MATCH(19,OfficeGroups[Source rank],0)),"")) | L59: =IF(H59="","",I59&IF(J59="",""," ["&J59&"]")) | M59: =IF(H59="","",SUMIFS(TransactionsData[Obligations],TransactionsData[Funding office ID],H59,TransactionsData[Selected],1)) | N59: =IF(H59="","",SUMIFS(TransactionsData[Deobligations],TransactionsData[Funding office ID],H59,TransactionsData[Selected],1)) | O59: =IF(H59="","",SUMIFS(TransactionsData[First office award],TransactionsData[Funding office ID],H59)) | P59: =IF(H59="","",COUNTIFS(TransactionsData[Funding office ID],H59,TransactionsData[Selected],1)) | Q59: =IF(OR(H59="",P59=0),"",COUNTIFS(OfficeGroups[Source net],">"&M59,OfficeGroups[Source actions],">0")+COUNTIFS(OfficeGroups[Source net],M59,OfficeGroups[Record ID],"<"&H59,OfficeGroups[Source actions],">0")+1) | R59: =IF(H59="",IF(COUNTA(I59:K59)>0,"Missing record ID",""),IF(COUNTIFS(OfficeGroups[Record ID],H59)<>1,"Duplicate record ID",IF(I59="","Add name","")))
A60: =IF(Trends!$B$6<>"","",IF(COUNTIFS(OfficeGroups[Source rank],20)=1,20,"")) | B60: =IF(Trends!$B$6<>"","",IF(COUNTIFS(OfficeGroups[Source rank],20)=1,IF(INDEX(OfficeGroups[Source URL],MATCH(20,OfficeGroups[Source rank],0))="",INDEX(OfficeGroups[Source name],MATCH(20,OfficeGroups[Source rank],0)),HYPERLINK(INDEX(OfficeGroups[Source URL],MATCH(20,OfficeGroups[Source rank],0)),INDEX(OfficeGroups[Source name],MATCH(20,OfficeGroups[Source rank],0)))),"")) | C60: =IF(Trends!$B$6<>"","",IF(COUNTIFS(OfficeGroups[Source rank],20)=1,IF(INDEX(OfficeGroups[Source UEI],MATCH(20,OfficeGroups[Source rank],0))="","Not supplied",INDEX(OfficeGroups[Source UEI],MATCH(20,OfficeGroups[Source rank],0))),"")) | D60: =IF(Trends!$B$6<>"","",IF(COUNTIFS(OfficeGroups[Source rank],20)=1,INDEX(OfficeGroups[Source net],MATCH(20,OfficeGroups[Source rank],0)),"")) | E60: =IF(Trends!$B$6<>"","",IF(COUNTIFS(OfficeGroups[Source rank],20)=1,INDEX(OfficeGroups[Source deobligations],MATCH(20,OfficeGroups[Source rank],0)),"")) | F60: =IF(Trends!$B$6<>"","",IF(COUNTIFS(OfficeGroups[Source rank],20)=1,INDEX(OfficeGroups[Source awards],MATCH(20,OfficeGroups[Source rank],0)),"")) | G60: =IF(Trends!$B$6<>"","",IF(COUNTIFS(OfficeGroups[Source rank],20)=1,INDEX(OfficeGroups[Source actions],MATCH(20,OfficeGroups[Source rank],0)),"")) | L60: =IF(H60="","",I60&IF(J60="",""," ["&J60&"]")) | M60: =IF(H60="","",SUMIFS(TransactionsData[Obligations],TransactionsData[Funding office ID],H60,TransactionsData[Selected],1)) | N60: =IF(H60="","",SUMIFS(TransactionsData[Deobligations],TransactionsData[Funding office ID],H60,TransactionsData[Selected],1)) | O60: =IF(H60="","",SUMIFS(TransactionsData[First office award],TransactionsData[Funding office ID],H60)) | P60: =IF(H60="","",COUNTIFS(TransactionsData[Funding office ID],H60,TransactionsData[Selected],1)) | Q60: =IF(OR(H60="",P60=0),"",COUNTIFS(OfficeGroups[Source net],">"&M60,OfficeGroups[Source actions],">0")+COUNTIFS(OfficeGroups[Source net],M60,OfficeGroups[Record ID],"<"&H60,OfficeGroups[Source actions],">0")+1) | R60: =IF(H60="",IF(COUNTA(I60:K60)>0,"Missing record ID",""),IF(COUNTIFS(OfficeGroups[Record ID],H60)<>1,"Duplicate record ID",IF(I60="","Add name","")))

Sheet Awards
A2: Awards
B3: ="Buyer: "&IF(Transactions!B3="","Not supplied",Transactions!B3)&" | Amount period: "&IF(Dashboard!$B$7="All","All covered years",IF(Dashboard!$B$7="","Not supplied","FY"&Dashboard!$B$7))&" | Award-type filter: "&Dashboard!$N$10 -> Buyer: National Science Foundation | Amount period: FY2025 | Award-type filter: All | H3: ="Buyer: "&IF(Transactions!B3="","Not supplied",Transactions!B3)&" | Amount period: "&IF(Dashboard!$B$7="All","All covered years",IF(Dashboard!$B$7="","Not supplied","FY"&Dashboard!$B$7))&" | Award-type filter: "&Dashboard!$N$10 -> Buyer: National Science Foundation | Amount period: FY2025 | Award-type filter: All
B4: ="Amount filter — vendor: "&Dashboard!H7 -> Amount filter — vendor: All | H4: ="Amount filter — vendor: "&Dashboard!H7 -> Amount filter — vendor: All
B5: ="Amount filter — funding office: "&Dashboard!B10 -> Amount filter — funding office: All | H5: ="Amount filter — funding office: "&Dashboard!B10 -> Amount filter — funding office: All
B6: All source awards are listed. Only amounts follow the filters; covered amounts span all covered dates. | H6: ="All source awards are listed. Current snapshots are unfiltered; retrieved "&IF(Transactions!G4="","Not supplied",TEXT(Transactions!G4,"mmm d, yyyy")) -> All source awards are listed. Current snapshots are unfiltered; retrieved Sep 14, 2026
A7: Award reference | B7: Vendor | C7: UEI | D7: Period obligations | E7: Covered obligations | F7: Current award type | G7: Current set-aside | H7: Performance state | I7: Current obligations | J7: Potential ceiling | K7: Award date | L7: Completion date | M7: Place of performance | N7: Parent vehicle | O7: PSC | P7: NAICS | Q7: Retrieved | R7: Award ID | S7: Original award reference | T7: Original vendor name | U7: Source URL | V7: Vendor URL | W7: Input check | X7: Period actions | Y7: Covered actions
A8: =IF(S8="","",IF(U8="",S8,HYPERLINK(U8,S8))) -> 47QTCA18D008L-49100425F0010 | B8: =IF(T8="","",IF(V8="",T8,HYPERLINK(V8,T8))) -> Gartner, Inc. | C8: CFALLJBGZ697 | D8: =IF(R8="","",IF(Trends!$B$6<>"","",SUMIFS(TransactionsData[Obligations],TransactionsData[Award ID],R8,TransactionsData[Selected],1))) -> 589968 | E8: =IF(R8="","",IF(Trends!$B$6<>"","",SUMIFS(TransactionsData[Obligations],TransactionsData[Award ID],R8,TransactionsData[Dimension match],1))) -> 589968 | F8: Delivery Order | G8: No Set-Aside Used | H8: Virginia | I8: 589968 | J8: 589968 | K8: 45663 | L8: 45929 | M8: Alexandria, VA 22314, USA | N8: Federal Supply Schedule 47QTCA18D008L | O8: DA01 | P8: 541519 | Q8: 46279 | R8: 47QTCA18D008L|49100425F0010 | S8: 47QTCA18D008L-49100425F0010 | T8: Gartner, Inc. | U8: https://govtribe.com/award/federal-contract-award/delivery-order-47qtca18d008l-49100425f0010 | V8: https://govtribe.com/vendors/gartner-inc-dot-0efu3 | W8: =IF(R8="",IF(COUNTA(C8,F8:V8)>0,"Missing award ID",""),IF(COUNTIFS(AwardsData[Award ID],R8)<>1,"Duplicate award ID",IF(OR(S8="",T8="",F8=""),"Add reference, vendor and award type",IF(OR(AND(I8<>"",NOT(ISNUMBER(I8))),AND(J8<>"",NOT(ISNUMBER(J8)))),"Use numeric snapshot amounts",IF(OR(COUNTIF(AwardTypeCategories,F8)<>1,COUNTIF(SetAsideCategories,G8)<>1,COUNTIF(PerformanceStateCategories,H8)<>1),"New category: refresh report",""))))) | X8: =IF(R8="","",COUNTIFS(TransactionsData[Award ID],R8,TransactionsData[Selected],1)) -> 3 | Y8: =IF(R8="","",COUNTIFS(TransactionsData[Award ID],R8,TransactionsData[Dimension match],1)) -> 3
A9: =IF(S9="","",IF(U9="",S9,HYPERLINK(U9,S9))) -> 47QTCA19D00GN-49100421F0206 | B9: =IF(T9="","",IF(V9="",T9,HYPERLINK(V9,T9))) -> Lynker Corporation | C9: MCLPKDBCDKY7 | D9: =IF(R9="","",IF(Trends!$B$6<>"","",SUMIFS(TransactionsData[Obligations],TransactionsData[Award ID],R9,TransactionsData[Selected],1))) -> 2603796 | E9: =IF(R9="","",IF(Trends!$B$6<>"","",SUMIFS(TransactionsData[Obligations],TransactionsData[Award ID],R9,TransactionsData[Dimension match],1))) -> 11767038 | F9: Delivery Order | G9: No Set-Aside Used | H9: Virginia | I9: 21463884 | J9: 24021678 | K9: 44510 | L9: 46350 | M9: Arlington, VA 22230, USA | N9: Federal Supply Schedule 47QTCA19D00GN | O9: DA01 | P9: 541511 | Q9: 46279 | R9: 47QTCA19D00GN|49100421F0206 | S9: 47QTCA19D00GN-49100421F0206 | T9: Lynker Corporation | U9: https://govtribe.com/award/federal-contract-award/delivery-order-47qtca19d00gn-49100421f0206 | V9: https://govtribe.com/vendors/lynker-technologies-llc-56f28 | W9: =IF(R9="",IF(COUNTA(C9,F9:V9)>0,"Missing award ID",""),IF(COUNTIFS(AwardsData[Award ID],R9)<>1,"Duplicate award ID",IF(OR(S9="",T9="",F9=""),"Add reference, vendor and award type",IF(OR(AND(I9<>"",NOT(ISNUMBER(I9))),AND(J9<>"",NOT(ISNUMBER(J9)))),"Use numeric snapshot amounts",IF(OR(COUNTIF(AwardTypeCategories,F9)<>1,COUNTIF(SetAsideCategories,G9)<>1,COUNTIF(PerformanceStateCategories,H9)<>1),"New category: refresh report",""))))) | X9: =IF(R9="","",COUNTIFS(TransactionsData[Award ID],R9,TransactionsData[Selected],1)) -> 2 | Y9: =IF(R9="","",COUNTIFS(TransactionsData[Award ID],R9,TransactionsData[Dimension match],1)) -> 9
A10: =IF(S10="","",IF(U10="",S10,HYPERLINK(U10,S10))) -> 47QTCA23D0037-49100424F0196 | B10: =IF(T10="","",IF(V10="",T10,HYPERLINK(V10,T10))) -> Criterion Systems, L.L.C. | C10: MPGNDNHHWM33 | D10: =IF(R10="","",IF(Trends!$B$6<>"","",SUMIFS(TransactionsData[Obligations],TransactionsData[Award ID],R10,TransactionsData[Selected],1))) -> 4033264 | E10: =IF(R10="","",IF(Trends!$B$6<>"","",SUMIFS(TransactionsData[Obligations],TransactionsData[Award ID],R10,TransactionsData[Dimension match],1))) -> 5442892.9 | F10: Delivery Order | G10: No Set-Aside Used | H10: Virginia | I10: 5322165.2 | J10: 5442892.9 | K10: 45536 | L10: 45900 | M10: Alexandria, VA 22314, USA | N10: Federal Supply Schedule 47QTCA23D0037 | O10: DA01 | P10: 541519 | Q10: 46279 | R10: 47QTCA23D0037|49100424F0196 | S10: 47QTCA23D0037-49100424F0196 | T10: Criterion Systems, L.L.C. | U10: https://govtribe.com/award/federal-contract-award/delivery-order-47qtca23d0037-49100424f0196 | V10: https://govtribe.com/vendors/criterion-systems-inc-dot-8aep0 | W10: =IF(R10="",IF(COUNTA(C10,F10:V10)>0,"Missing award ID",""),IF(COUNTIFS(AwardsData[Award ID],R10)<>1,"Duplicate award ID",IF(OR(S10="",T10="",F10=""),"Add reference, vendor and award type",IF(OR(AND(I10<>"",NOT(ISNUMBER(I10))),AND(J10<>"",NOT(ISNUMBER(J10)))),"Use numeric snapshot amounts",IF(OR(COUNTIF(AwardTypeCategories,F10)<>1,COUNTIF(SetAsideCategories,G10)<>1,COUNTIF(PerformanceStateCategories,H10)<>1),"New category: refresh report",""))))) | X10: =IF(R10="","",COUNTIFS(TransactionsData[Award ID],R10,TransactionsData[Selected],1)) -> 5 | Y10: =IF(R10="","",COUNTIFS(TransactionsData[Award ID],R10,TransactionsData[Dimension match],1)) -> 6
A11: =IF(S11="","",IF(U11="",S11,HYPERLINK(U11,S11))) -> 47QTCA23D0037-49100425F0092 | B11: =IF(T11="","",IF(V11="",T11,HYPERLINK(V11,T11))) -> Criterion Systems, L.L.C. | C11: MPGNDNHHWM33 | D11: =IF(R11="","",IF(Trends!$B$6<>"","",SUMIFS(TransactionsData[Obligations],TransactionsData[Award ID],R11,TransactionsData[Selected],1))) -> 1000000 | E11: =IF(R11="","",IF(Trends!$B$6<>"","",SUMIFS(TransactionsData[Obligations],TransactionsData[Award ID],R11,TransactionsData[Dimension match],1))) -> 1000000 | F11: Delivery Order | G11: No Set-Aside Used | H11: Virginia | I11: 2828000 | J11: 2958705 | K11: 45901 | L11: 46081 | M11: Alexandria, VA 22314, USA | N11: Federal Supply Schedule 47QTCA23D0037 | O11: DA01 | P11: 541519 | Q11: 46279 | R11: 47QTCA23D0037|49100425F0092 | S11: 47QTCA23D0037-49100425F0092 | T11: Criterion Systems, L.L.C. | U11: https://govtribe.com/award/federal-contract-award/delivery-order-47qtca23d0037-49100425f0092 | V11: https://govtribe.com/vendors/criterion-systems-inc-dot-8aep0 | W11: =IF(R11="",IF(COUNTA(C11,F11:V11)>0,"Missing award ID",""),IF(COUNTIFS(AwardsData[Award ID],R11)<>1,"Duplicate award ID",IF(OR(S11="",T11="",F11=""),"Add reference, vendor and award type",IF(OR(AND(I11<>"",NOT(ISNUMBER(I11))),AND(J11<>"",NOT(ISNUMBER(J11)))),"Use numeric snapshot amounts",IF(OR(COUNTIF(AwardTypeCategories,F11)<>1,COUNTIF(SetAsideCategories,G11)<>1,COUNTIF(PerformanceStateCategories,H11)<>1),"New category: refresh report",""))))) | X11: =IF(R11="","",COUNTIFS(TransactionsData[Award ID],R11,TransactionsData[Selected],1)) -> 1 | Y11: =IF(R11="","",COUNTIFS(TransactionsData[Award ID],R11,TransactionsData[Dimension match],1)) -> 1
A12: =IF(S12="","",IF(U12="",S12,HYPERLINK(U12,S12))) -> 47QTCB21D0005-49100422F0014 | B12: =IF(T12="","",IF(V12="",T12,HYPERLINK(V12,T12))) -> GBS Solutions Corp | C12: NKNSTJBPABX9 | D12: =IF(R12="","",IF(Trends!$B$6<>"","",SUMIFS(TransactionsData[Obligations],TransactionsData[Award ID],R12,TransactionsData[Selected],1))) -> 16430.4 | E12: =IF(R12="","",IF(Trends!$B$6<>"","",SUMIFS(TransactionsData[Obligations],TransactionsData[Award ID],R12,TransactionsData[Dimension match],1))) -> 189283.8 | F12: Delivery Order | G12: No Set-Aside Used | H12: Virginia | I12: 340482.41 | J12: 372893.57 | K12: 44593 | L12: 46053 | M12: Alexandria, VA 22314, USA | N12: Government Wide Acquisition Contract (GWAC) 47QTCB21D0005 | O12: DA01 | P12: 541512 | Q12: 46279 | R12: 47QTCB21D0005|49100422F0014 | S12: 47QTCB21D0005-49100422F0014 | T12: GBS Solutions Corp | U12: https://govtribe.com/award/federal-contract-award/delivery-order-47qtcb21d0005-49100422f0014 | V12: https://govtribe.com/vendors/gbs-solutions-corporation-gbs-79pq1 | W12: =IF(R12="",IF(COUNTA(C12,F12:V12)>0,"Missing award ID",""),IF(COUNTIFS(AwardsData[Award ID],R12)<>1,"Duplicate award ID",IF(OR(S12="",T12="",F12=""),"Add reference, vendor and award type",IF(OR(AND(I12<>"",NOT(ISNUMBER(I12))),AND(J12<>"",NOT(ISNUMBER(J12)))),"Use numeric snapshot amounts",IF(OR(COUNTIF(AwardTypeCategories,F12)<>1,COUNTIF(SetAsideCategories,G12)<>1,COUNTIF(PerformanceStateCategories,H12)<>1),"New category: refresh report",""))))) | X12: =IF(R12="","",COUNTIFS(TransactionsData[Award ID],R12,TransactionsData[Selected],1)) -> 2 | Y12: =IF(R12="","",COUNTIFS(TransactionsData[Award ID],R12,TransactionsData[Dimension match],1)) -> 4
A13: =IF(S13="","",IF(U13="",S13,HYPERLINK(U13,S13))) -> 47QTCB21D0005-49100422F0104 | B13: =IF(T13="","",IF(V13="",T13,HYPERLINK(V13,T13))) -> GBS Solutions Corp | C13: NKNSTJBPABX9 | D13: =IF(R13="","",IF(Trends!$B$6<>"","",SUMIFS(TransactionsData[Obligations],TransactionsData[Award ID],R13,TransactionsData[Selected],1))) -> 174095.68 | E13: =IF(R13="","",IF(Trends!$B$6<>"","",SUMIFS(TransactionsData[Obligations],TransactionsData[Award ID],R13,TransactionsData[Dimension match],1))) -> 3343911.5 | F13: Delivery Order | G13: Competitive 8(a) | H13: Utah | I13: 1490088.4 | J13: 4674057.4 | K13: 44743 | L13: 45838 | M13: Syracuse, UT, USA | N13: Government Wide Acquisition Contract (GWAC) 47QTCB21D0005 | O13: DA01 | P13: 541512 | Q13: 46279 | R13: 47QTCB21D0005|49100422F0104 | S13: 47QTCB21D0005-49100422F0104 | T13: GBS Solutions Corp | U13: https://govtribe.com/award/federal-contract-award/delivery-order-47qtcb21d0005-49100422f0104 | V13: https://govtribe.com/vendors/gbs-solutions-corporation-gbs-79pq1 | W13: =IF(R13="",IF(COUNTA(C13,F13:V13)>0,"Missing award ID",""),IF(COUNTIFS(AwardsData[Award ID],R13)<>1,"Duplicate award ID",IF(OR(S13="",T13="",F13=""),"Add reference, vendor and award type",IF(OR(AND(I13<>"",NOT(ISNUMBER(I13))),AND(J13<>"",NOT(ISNUMBER(J13)))),"Use numeric snapshot amounts",IF(OR(COUNTIF(AwardTypeCategories,F13)<>1,COUNTIF(SetAsideCategories,G13)<>1,COUNTIF(PerformanceStateCategories,H13)<>1),"New category: refresh report",""))))) | X13: =IF(R13="","",COUNTIFS(TransactionsData[Award ID],R13,TransactionsData[Selected],1)) -> 2 | Y13: =IF(R13="","",COUNTIFS(TransactionsData[Award ID],R13,TransactionsData[Dimension match],1)) -> 6
A14: =IF(S14="","",IF(U14="",S14,HYPERLINK(U14,S14))) -> 47QTCB21D0005-49100423F0061 | B14: =IF(T14="","",IF(V14="",T14,HYPERLINK(V14,T14))) -> GBS Solutions Corp | C14: NKNSTJBPABX9 | D14: =IF(R14="","",IF(Trends!$B$6<>"","",SUMIFS(TransactionsData[Obligations],TransactionsData[Award ID],R14,TransactionsData[Selected],1))) -> -112336.2 | E14: =IF(R14="","",IF(Trends!$B$6<>"","",SUMIFS(TransactionsData[Obligations],TransactionsData[Award ID],R14,TransactionsData[Dimension match],1))) -> 386256.6 | F14: Delivery Order | G14: No Set-Aside Used | H14: Utah | I14: 386256.6 | J14: 498592.8 | K14: 45026 | L14: 45291 | M14: Syracuse, UT, USA | N14: Government Wide Acquisition Contract (GWAC) 47QTCB21D0005 | O14: DA01 | P14: 541512 | Q14: 46279 | R14: 47QTCB21D0005|49100423F0061 | S14: 47QTCB21D0005-49100423F0061 | T14: GBS Solutions Corp | U14: https://govtribe.com/award/federal-contract-award/delivery-order-47qtcb21d0005-49100423f0061 | V14: https://govtribe.com/vendors/gbs-solutions-corporation-gbs-79pq1 | W14: =IF(R14="",IF(COUNTA(C14,F14:V14)>0,"Missing award ID",""),IF(COUNTIFS(AwardsData[Award ID],R14)<>1,"Duplicate award ID",IF(OR(S14="",T14="",F14=""),"Add reference, vendor and award type",IF(OR(AND(I14<>"",NOT(ISNUMBER(I14))),AND(J14<>"",NOT(ISNUMBER(J14)))),"Use numeric snapshot amounts",IF(OR(COUNTIF(AwardTypeCategories,F14)<>1,COUNTIF(SetAsideCategories,G14)<>1,COUNTIF(PerformanceStateCategories,H14)<>1),"New category: refresh report",""))))) | X14: =IF(R14="","",COUNTIFS(TransactionsData[Award ID],R14,TransactionsData[Selected],1)) -> 1 | Y14: =IF(R14="","",COUNTIFS(TransactionsData[Award ID],R14,TransactionsData[Dimension match],1)) -> 2
A15: =IF(S15="","",IF(U15="",S15,HYPERLINK(U15,S15))) -> 47QTCB21D0016-49100424F0029 | B15: =IF(T15="","",IF(V15="",T15,HYPERLINK(V15,T15))) -> Professional Management Consulting Services LLC | C15: CD2QDS1EFHP3 | D15: =IF(R15="","",IF(Trends!$B$6<>"","",SUMIFS(TransactionsData[Obligations],TransactionsData[Award ID],R15,TransactionsData[Selected],1))) -> 495382.97 | E15: =IF(R15="","",IF(Trends!$B$6<>"","",SUMIFS(TransactionsData[Obligations],TransactionsData[Award ID],R15,TransactionsData[Dimension match],1))) -> 1024335.1 | F15: Delivery Order | G15: 8(a) Sole Source | H15: District of Columbia | I15: 1024335.1 | J15: 2611752.1 | K15: 45362 | L15: 46022 | M15: Washington, DC 20005, USA | N15: Government Wide Acquisition Contract (GWAC) 47QTCB21D0016 | O15: DA01 | P15: 541512 | Q15: 46279 | R15: 47QTCB21D0016|49100424F0029 | S15: 47QTCB21D0016-49100424F0029 | T15: Professional Management Consulting Services LLC | U15: https://govtribe.com/award/federal-contract-award/delivery-order-47qtcb21d0016-49100424f0029 | V15: https://govtribe.com/vendors/professional-management-consulting-services-llc-pmcs-5ahh1 | W15: =IF(R15="",IF(COUNTA(C15,F15:V15)>0,"Missing award ID",""),IF(COUNTIFS(AwardsData[Award ID],R15)<>1,"Duplicate award ID",IF(OR(S15="",T15="",F15=""),"Add reference, vendor and award type",IF(OR(AND(I15<>"",NOT(ISNUMBER(I15))),AND(J15<>"",NOT(ISNUMBER(J15)))),"Use numeric snapshot amounts",IF(OR(COUNTIF(AwardTypeCategories,F15)<>1,COUNTIF(SetAsideCategories,G15)<>1,COUNTIF(PerformanceStateCategories,H15)<>1),"New category: refresh report",""))))) | X15: =IF(R15="","",COUNTIFS(TransactionsData[Award ID],R15,TransactionsData[Selected],1)) -> 2 | Y15: =IF(R15="","",COUNTIFS(TransactionsData[Award ID],R15,TransactionsData[Dimension match],1)) -> 3
A16: =IF(S16="","",IF(U16="",S16,HYPERLINK(U16,S16))) -> 47QTCB21D0271-49100424F0075 | B16: =IF(T16="","",IF(V16="",T16,HYPERLINK(V16,T16))) -> Expediteinfotech, Inc. | C16: KX6EDEAPTKH5 | D16: =IF(R16="","",IF(Trends!$B$6<>"","",SUMIFS(TransactionsData[Obligations],TransactionsData[Award ID],R16,TransactionsData[Selected],1))) -> 150188.63 | E16: =IF(R16="","",IF(Trends!$B$6<>"","",SUMIFS(TransactionsData[Obligations],TransactionsData[Award ID],R16,TransactionsData[Dimension match],1))) -> 401509.51 | F16: Delivery Order | G16: Competitive 8(a) | H16: Maryland | I16: 401509.51 | J16: 401509.51 | K16: 45393 | L16: 46122 | M16: Rockville, MD 20850, USA | N16: Government Wide Acquisition Contract (GWAC) 47QTCB21D0271 | O16: DA01 | P16: 541512 | Q16: 46279 | R16: 47QTCB21D0271|49100424F0075 | S16: 47QTCB21D0271-49100424F0075 | T16: Expediteinfotech, Inc. | U16: https://govtribe.com/award/federal-contract-award/delivery-order-47qtcb21d0271-49100424f0075 | V16: https://govtribe.com/vendors/expediteinfotech-inc-dot-78dz9 | W16: =IF(R16="",IF(COUNTA(C16,F16:V16)>0,"Missing award ID",""),IF(COUNTIFS(AwardsData[Award ID],R16)<>1,"Duplicate award ID",IF(OR(S16="",T16="",F16=""),"Add reference, vendor and award type",IF(OR(AND(I16<>"",NOT(ISNUMBER(I16))),AND(J16<>"",NOT(ISNUMBER(J16)))),"Use numeric snapshot amounts",IF(OR(COUNTIF(AwardTypeCategories,F16)<>1,COUNTIF(SetAsideCategories,G16)<>1,COUNTIF(PerformanceStateCategories,H16)<>1),"New category: refresh report",""))))) | X16: =IF(R16="","",COUNTIFS(TransactionsData[Award ID],R16,TransactionsData[Selected],1)) -> 2 | Y16: =IF(R16="","",COUNTIFS(TransactionsData[Award ID],R16,TransactionsData[Dimension match],1)) -> 3
A17: =IF(S17="","",IF(U17="",S17,HYPERLINK(U17,S17))) -> 47QTCB22D0076-49100423F0221 | B17: =IF(T17="","",IF(V17="",T17,HYPERLINK(V17,T17))) -> Ibex It Business Experts LLC | C17: XPA8X2BWTD49 | D17: =IF(R17="","",IF(Trends!$B$6<>"","",SUMIFS(TransactionsData[Obligations],TransactionsData[Award ID],R17,TransactionsData[Selected],1))) -> 0 | E17: =IF(R17="","",IF(Trends!$B$6<>"","",SUMIFS(TransactionsData[Obligations],TransactionsData[Award ID],R17,TransactionsData[Dimension match],1))) -> 232001.07 | F17: Delivery Order | G17: No Set-Aside Used | H17: Virginia | I17: 232001.07 | J17: 292897.87 | K17: 45180 | L17: 45910 | M17: Alexandria, VA 22314, USA | N17: Government Wide Acquisition Contract (GWAC) 47QTCB22D0076 | O17: DA01 | P17: 541512 | Q17: 46279 | R17: 47QTCB22D0076|49100423F0221 | S17: 47QTCB22D0076-49100423F0221 | T17: Ibex It Business Experts LLC | U17: https://govtribe.com/award/federal-contract-award/delivery-order-47qtcb22d0076-49100423f0221 | V17: https://govtribe.com/vendors/ibex-it-business-experts-llc-ibex-it-business-experts-6dry3 | W17: =IF(R17="",IF(COUNTA(C17,F17:V17)>0,"Missing award ID",""),IF(COUNTIFS(AwardsData[Award ID],R17)<>1,"Duplicate award ID",IF(OR(S17="",T17="",F17=""),"Add reference, vendor and award type",IF(OR(AND(I17<>"",NOT(ISNUMBER(I17))),AND(J17<>"",NOT(ISNUMBER(J17)))),"Use numeric snapshot amounts",IF(OR(COUNTIF(AwardTypeCategories,F17)<>1,COUNTIF(SetAsideCategories,G17)<>1,COUNTIF(PerformanceStateCategories,H17)<>1),"New category: refresh report",""))))) | X17: =IF(R17="","",COUNTIFS(TransactionsData[Award ID],R17,TransactionsData[Selected],1)) -> 0 | Y17: =IF(R17="","",COUNTIFS(TransactionsData[Award ID],R17,TransactionsData[Dimension match],1)) -> 2
A18: =IF(S18="","",IF(U18="",S18,HYPERLINK(U18,S18))) -> 47QTCK18D0004-49100424F0001 | B18: =IF(T18="","",IF(V18="",T18,HYPERLINK(V18,T18))) -> Booz Allen Hamilton Inc. | C18: JCBMLGPE6Z71 | D18: =IF(R18="","",IF(Trends!$B$6<>"","",SUMIFS(TransactionsData[Obligations],TransactionsData[Award ID],R18,TransactionsData[Selected],1))) -> 53165051 | E18: =IF(R18="","",IF(Trends!$B$6<>"","",SUMIFS(TransactionsData[Obligations],TransactionsData[Award ID],R18,TransactionsData[Dimension match],1))) -> 1.0100333e+08 | F18: Delivery Order | G18: No Set-Aside Used | H18: Virginia | I18: 1.4917653e+08 | J18: 4.1934181e+08 | K18: 45292 | L18: 46387 | M18: Alexandria, VA 22314, USA | N18: Government Wide Acquisition Contract (GWAC) 47QTCK18D0004 | O18: DA01 | P18: 541512 | Q18: 46279 | R18: 47QTCK18D0004|49100424F0001 | S18: 47QTCK18D0004-49100424F0001 | T18: Booz Allen Hamilton Inc. | U18: https://govtribe.com/award/federal-contract-award/delivery-order-47qtck18d0004-49100424f0001 | V18: https://govtribe.com/vendors/booz-allen-hamilton-inc-dot-17038 | W18: =IF(R18="",IF(COUNTA(C18,F18:V18)>0,"Missing award ID",""),IF(COUNTIFS(AwardsData[Award ID],R18)<>1,"Duplicate award ID",IF(OR(S18="",T18="",F18=""),"Add reference, vendor and award type",IF(OR(AND(I18<>"",NOT(ISNUMBER(I18))),AND(J18<>"",NOT(ISNUMBER(J18)))),"Use numeric snapshot amounts",IF(OR(COUNTIF(AwardTypeCategories,F18)<>1,COUNTIF(SetAsideCategories,G18)<>1,COUNTIF(PerformanceStateCategories,H18)<>1),"New category: refresh report",""))))) | X18: =IF(R18="","",COUNTIFS(TransactionsData[Award ID],R18,TransactionsData[Selected],1)) -> 15 | Y18: =IF(R18="","",COUNTIFS(TransactionsData[Award ID],R18,TransactionsData[Dimension match],1)) -> 21
A19: =IF(S19="","",IF(U19="",S19,HYPERLINK(U19,S19))) -> 49100422A0002-49100423F0008 | B19: =IF(T19="","",IF(V19="",T19,HYPERLINK(V19,T19))) -> Directviz Solutions, LLC | C19: YXH4AGD2LGF5 | D19: =IF(R19="","",IF(Trends!$B$6<>"","",SUMIFS(TransactionsData[Obligations],TransactionsData[Award ID],R19,TransactionsData[Selected],1))) -> 0 | E19: =IF(R19="","",IF(Trends!$B$6<>"","",SUMIFS(TransactionsData[Obligations],TransactionsData[Award ID],R19,TransactionsData[Dimension match],1))) -> 6769904.4 | F19: BPA Call | G19: No Set-Aside Used | H19: Virginia | I19: 6769904.4 | J19: 6769904.4 | K19: 44915 | L19: 45279 | M19: Alexandria, VA 22314, USA | N19: Blanket Purchase Agreement 47QTCA18D002W-49100422A0002 | O19: DA01 | P19: 541511 | Q19: 46279 | R19: 49100422A0002|49100423F0008 | S19: 49100422A0002-49100423F0008 | T19: Directviz Solutions, LLC | U19: https://govtribe.com/award/federal-contract-award/bpa-call-49100422a0002-49100423f0008 | V19: https://govtribe.com/vendors/directviz-solutions-llc-6evd4 | W19: =IF(R19="",IF(COUNTA(C19,F19:V19)>0,"Missing award ID",""),IF(COUNTIFS(AwardsData[Award ID],R19)<>1,"Duplicate award ID",IF(OR(S19="",T19="",F19=""),"Add reference, vendor and award type",IF(OR(AND(I19<>"",NOT(ISNUMBER(I19))),AND(J19<>"",NOT(ISNUMBER(J19)))),"Use numeric snapshot amounts",IF(OR(COUNTIF(AwardTypeCategories,F19)<>1,COUNTIF(SetAsideCategories,G19)<>1,COUNTIF(PerformanceStateCategories,H19)<>1),"New category: refresh report",""))))) | X19: =IF(R19="","",COUNTIFS(TransactionsData[Award ID],R19,TransactionsData[Selected],1)) -> 0 | Y19: =IF(R19="","",COUNTIFS(TransactionsData[Award ID],R19,TransactionsData[Dimension match],1)) -> 3
... A26: =IF(S26="","",IF(U26="",S26,HYPERLINK(U26,S26))) -> 49100422A0002-49100425F0017 | B26: =IF(T26="","",IF(V26="",T26,HYPERLINK(V26,T26))) -> Directviz Solutions, LLC | C26: YXH4AGD2LGF5 | D26: =IF(R26="","",IF(Trends!$B$6<>"","",SUMIFS(TransactionsData[Obligations],TransactionsData[Award ID],R26,TransactionsData[Selected],1))) -> 13426489 | E26: =IF(R26="","",IF(Trends!$B$6<>"","",SUMIFS(TransactionsData[Obligations],TransactionsData[Award ID],R26,TransactionsData[Dimension match],1))) -> 13426489 | F26: BPA Call | G26: Total Small Business | H26: Virginia | I26: 18900956 | J26: 40980621 | K26: 45646 | L26: 46477 | M26: Alexandria, VA 22314, USA | N26: Blanket Purchase Agreement 47QTCA18D002W-49100422A0002 | O26: DA01 | P26: 541511 | Q26: 46279 | R26: 49100422A0002|49100425F0017 | S26: 49100422A0002-49100425F0017 | T26: Directviz Solutions, LLC | U26: https://govtribe.com/award/federal-contract-award/bpa-call-49100422a0002-49100425f0017 | V26: https://govtribe.com/vendors/directviz-solutions-llc-6evd4 | W26: =IF(R26="",IF(COUNTA(C26,F26:V26)>0,"Missing award ID",""),IF(COUNTIFS(AwardsData[Award ID],R26)<>1,"Duplicate award ID",IF(OR(S26="",T26="",F26=""),"Add reference, vendor and award type",IF(OR(AND(I26<>"",NOT(ISNUMBER(I26))),AND(J26<>"",NOT(ISNUMBER(J26)))),"Use numeric snapshot amounts",IF(OR(COUNTIF(AwardTypeCategories,F26)<>1,COUNTIF(SetAsideCategories,G26)<>1,COUNTIF(PerformanceStateCategories,H26)<>1),"New category: refresh report",""))))) | X26: =IF(R26="","",COUNTIFS(TransactionsData[Award ID],R26,TransactionsData[Selected],1)) -> 3 | Y26: =IF(R26="","",COUNTIFS(TransactionsData[Award ID],R26,TransactionsData[Dimension match],1)) -> 3
A27: =IF(S27="","",IF(U27="",S27,HYPERLINK(U27,S27))) -> 49100422C0029 | B27: =IF(T27="","",IF(V27="",T27,HYPERLINK(V27,T27))) -> Rei Systems, Inc. | C27: YRNMVN96JC17 | D27: =IF(R27="","",IF(Trends!$B$6<>"","",SUMIFS(TransactionsData[Obligations],TransactionsData[Award ID],R27,TransactionsData[Selected],1))) -> 0 | E27: =IF(R27="","",IF(Trends!$B$6<>"","",SUMIFS(TransactionsData[Obligations],TransactionsData[Award ID],R27,TransactionsData[Dimension match],1))) -> 4016723 | F27: Definitive Contract | G27: No Set-Aside Used | H27: Virginia | I27: 5584648.1 | J27: 5654362.7 | K27: 44820 | L27: 45565 | M27: Alexandria, VA 22314, USA | O27: DA01 | P27: 541715 | Q27: 46279 | R27: 49100422C0029 | S27: 49100422C0029 | T27: Rei Systems, Inc. | U27: https://govtribe.com/award/federal-contract-award/definitive-contract-49100422c0029 | V27: https://govtribe.com/vendors/rei-systems-inc-dot-1djp1 | W27: =IF(R27="",IF(COUNTA(C27,F27:V27)>0,"Missing award ID",""),IF(COUNTIFS(AwardsData[Award ID],R27)<>1,"Duplicate award ID",IF(OR(S27="",T27="",F27=""),"Add reference, vendor and award type",IF(OR(AND(I27<>"",NOT(ISNUMBER(I27))),AND(J27<>"",NOT(ISNUMBER(J27)))),"Use numeric snapshot amounts",IF(OR(COUNTIF(AwardTypeCategories,F27)<>1,COUNTIF(SetAsideCategories,G27)<>1,COUNTIF(PerformanceStateCategories,H27)<>1),"New category: refresh report",""))))) | X27: =IF(R27="","",COUNTIFS(TransactionsData[Award ID],R27,TransactionsData[Selected],1)) -> 0 | Y27: =IF(R27="","",COUNTIFS(TransactionsData[Award ID],R27,TransactionsData[Dimension match],1)) -> 9
A28: =IF(S28="","",IF(U28="",S28,HYPERLINK(U28,S28))) -> 49100422D0010-49100423F0015 | B28: =IF(T28="","",IF(V28="",T28,HYPERLINK(V28,T28))) -> Agility Technologies Inc. | C28: Z9M6NN4AQLF7 | D28: =IF(R28="","",IF(Trends!$B$6<>"","",SUMIFS(TransactionsData[Obligations],TransactionsData[Award ID],R28,TransactionsData[Selected],1))) -> 0 | E28: =IF(R28="","",IF(Trends!$B$6<>"","",SUMIFS(TransactionsData[Obligations],TransactionsData[Award ID],R28,TransactionsData[Dimension match],1))) -> 8448.67 | F28: Delivery Order | G28: No Set-Aside Used | H28: Virginia | I28: 8448.67 | J28: 8448.67 | K28: 44916 | L28: 45060 | M28: Ashburn, VA 20148, USA | N28: Indefinite Delivery Contract 49100422D0010 | O28: DA01 | P28: 541512 | Q28: 46279 | R28: 49100422D0010|49100423F0015 | S28: 49100422D0010-49100423F0015 | T28: Agility Technologies Inc. | U28: https://govtribe.com/award/federal-contract-award/delivery-order-49100422d0010-49100423f0015 | V28: https://govtribe.com/vendors/agility-technologies-inc-dot-5b8b7 | W28: =IF(R28="",IF(COUNTA(C28,F28:V28)>0,"Missing award ID",""),IF(COUNTIFS(AwardsData[Award ID],R28)<>1,"Duplicate award ID",IF(OR(S28="",T28="",F28=""),"Add reference, vendor and award type",IF(OR(AND(I28<>"",NOT(ISNUMBER(I28))),AND(J28<>"",NOT(ISNUMBER(J28)))),"Use numeric snapshot amounts",IF(OR(COUNTIF(AwardTypeCategories,F28)<>1,COUNTIF(SetAsideCategories,G28)<>1,COUNTIF(PerformanceStateCategories,H28)<>1),"New category: refresh report",""))))) | X28: =IF(R28="","",COUNTIFS(TransactionsData[Award ID],R28,TransactionsData[Selected],1)) -> 0 | Y28: =IF(R28="","",COUNTIFS(TransactionsData[Award ID],R28,TransactionsData[Dimension match],1)) -> 1
A29: =IF(S29="","",IF(U29="",S29,HYPERLINK(U29,S29))) -> 49100422D0010-49100423F0016 | B29: =IF(T29="","",IF(V29="",T29,HYPERLINK(V29,T29))) -> Agility Technologies Inc. | C29: Z9M6NN4AQLF7 | D29: =IF(R29="","",IF(Trends!$B$6<>"","",SUMIFS(TransactionsData[Obligations],TransactionsData[Award ID],R29,TransactionsData[Selected],1))) -> 0 | E29: =IF(R29="","",IF(Trends!$B$6<>"","",SUMIFS(TransactionsData[Obligations],TransactionsData[Award ID],R29,TransactionsData[Dimension match],1))) -> 215727.6 | F29: Delivery Order | G29: No Set-Aside Used | H29: Virginia | I29: 215727.6 | J29: 215727.6 | K29: 44935 | L29: 44974 | M29: Ashburn, VA 20148, USA | N29: Indefinite Delivery Contract 49100422D0010 | O29: DA01 | P29: 541512 | Q29: 46279 | R29: 49100422D0010|49100423F0016 | S29: 49100422D0010-49100423F0016 | T29: Agility Technologies Inc. | U29: https://govtribe.com/award/federal-contract-award/delivery-order-49100422d0010-49100423f0016 | V29: https://govtribe.com/vendors/agility-technologies-inc-dot-5b8b7 | W29: =IF(R29="",IF(COUNTA(C29,F29:V29)>0,"Missing award ID",""),IF(COUNTIFS(AwardsData[Award ID],R29)<>1,"Duplicate award ID",IF(OR(S29="",T29="",F29=""),"Add reference, vendor and award type",IF(OR(AND(I29<>"",NOT(ISNUMBER(I29))),AND(J29<>"",NOT(ISNUMBER(J29)))),"Use numeric snapshot amounts",IF(OR(COUNTIF(AwardTypeCategories,F29)<>1,COUNTIF(SetAsideCategories,G29)<>1,COUNTIF(PerformanceStateCategories,H29)<>1),"New category: refresh report",""))))) | X29: =IF(R29="","",COUNTIFS(TransactionsData[Award ID],R29,TransactionsData[Selected],1)) -> 0 | Y29: =IF(R29="","",COUNTIFS(TransactionsData[Award ID],R29,TransactionsData[Dimension match],1)) -> 1
A30: =IF(S30="","",IF(U30="",S30,HYPERLINK(U30,S30))) -> 49100422D0010-49100423F0076 | B30: =IF(T30="","",IF(V30="",T30,HYPERLINK(V30,T30))) -> Agility Technologies Inc. | C30: Z9M6NN4AQLF7 | D30: =IF(R30="","",IF(Trends!$B$6<>"","",SUMIFS(TransactionsData[Obligations],TransactionsData[Award ID],R30,TransactionsData[Selected],1))) -> 0 | E30: =IF(R30="","",IF(Trends!$B$6<>"","",SUMIFS(TransactionsData[Obligations],TransactionsData[Award ID],R30,TransactionsData[Dimension match],1))) -> 33848.24 | F30: Delivery Order | G30: No Set-Aside Used | H30: Virginia | I30: 33848.24 | J30: 33848.24 | K30: 45061 | L30: 45426 | M30: Ashburn, VA 20148, USA | N30: Indefinite Delivery Contract 49100422D0010 | O30: DA01 | P30: 541512 | Q30: 46279 | R30: 49100422D0010|49100423F0076 | S30: 49100422D0010-49100423F0076 | T30: Agility Technologies Inc. | U30: https://govtribe.com/award/federal-contract-award/delivery-order-49100422d0010-49100423f0076 | V30: https://govtribe.com/vendors/agility-technologies-inc-dot-5b8b7 | W30: =IF(R30="",IF(COUNTA(C30,F30:V30)>0,"Missing award ID",""),IF(COUNTIFS(AwardsData[Award ID],R30)<>1,"Duplicate award ID",IF(OR(S30="",T30="",F30=""),"Add reference, vendor and award type",IF(OR(AND(I30<>"",NOT(ISNUMBER(I30))),AND(J30<>"",NOT(ISNUMBER(J30)))),"Use numeric snapshot amounts",IF(OR(COUNTIF(AwardTypeCategories,F30)<>1,COUNTIF(SetAsideCategories,G30)<>1,COUNTIF(PerformanceStateCategories,H30)<>1),"New category: refresh report",""))))) | X30: =IF(R30="","",COUNTIFS(TransactionsData[Award ID],R30,TransactionsData[Selected],1)) -> 0 | Y30: =IF(R30="","",COUNTIFS(TransactionsData[Award ID],R30,TransactionsData[Dimension match],1)) -> 1
A31: =IF(S31="","",IF(U31="",S31,HYPERLINK(U31,S31))) -> 49100422D0010-49100423F0226 | B31: =IF(T31="","",IF(V31="",T31,HYPERLINK(V31,T31))) -> Agility Technologies Inc. | C31: Z9M6NN4AQLF7 | D31: =IF(R31="","",IF(Trends!$B$6<>"","",SUMIFS(TransactionsData[Obligations],TransactionsData[Award ID],R31,TransactionsData[Selected],1))) -> 0 | E31: =IF(R31="","",IF(Trends!$B$6<>"","",SUMIFS(TransactionsData[Obligations],TransactionsData[Award ID],R31,TransactionsData[Dimension match],1))) -> 1068350.3 | F31: Delivery Order | G31: No Set-Aside Used | H31: Virginia | I31: 1068350.3 | J31: 1068350.3 | K31: 45193 | L31: 45503 | M31: Alexandria, VA 22314, USA | N31: Indefinite Delivery Contract 49100422D0010 | O31: DA01 | P31: 541512 | Q31: 46279 | R31: 49100422D0010|49100423F0226 | S31: 49100422D0010-49100423F0226 | T31: Agility Technologies Inc. | U31: https://govtribe.com/award/federal-contract-award/delivery-order-49100422d0010-49100423f0226 | V31: https://govtribe.com/vendors/agility-technologies-inc-dot-5b8b7 | W31: =IF(R31="",IF(COUNTA(C31,F31:V31)>0,"Missing award ID",""),IF(COUNTIFS(AwardsData[Award ID],R31)<>1,"Duplicate award ID",IF(OR(S31="",T31="",F31=""),"Add reference, vendor and award type",IF(OR(AND(I31<>"",NOT(ISNUMBER(I31))),AND(J31<>"",NOT(ISNUMBER(J31)))),"Use numeric snapshot amounts",IF(OR(COUNTIF(AwardTypeCategories,F31)<>1,COUNTIF(SetAsideCategories,G31)<>1,COUNTIF(PerformanceStateCategories,H31)<>1),"New category: refresh report",""))))) | X31: =IF(R31="","",COUNTIFS(TransactionsData[Award ID],R31,TransactionsData[Selected],1)) -> 0 | Y31: =IF(R31="","",COUNTIFS(TransactionsData[Award ID],R31,TransactionsData[Dimension match],1)) -> 2
A32: =IF(S32="","",IF(U32="",S32,HYPERLINK(U32,S32))) -> 49100422D0010-49100424F0097 | B32: =IF(T32="","",IF(V32="",T32,HYPERLINK(V32,T32))) -> Agility Technologies Inc. | C32: Z9M6NN4AQLF7 | D32: =IF(R32="","",IF(Trends!$B$6<>"","",SUMIFS(TransactionsData[Obligations],TransactionsData[Award ID],R32,TransactionsData[Selected],1))) -> 0 | E32: =IF(R32="","",IF(Trends!$B$6<>"","",SUMIFS(TransactionsData[Obligations],TransactionsData[Award ID],R32,TransactionsData[Dimension match],1))) -> 45287.91 | F32: Delivery Order | G32: No Set-Aside Used | H32: Virginia | I32: 45287.91 | J32: 45287.91 | K32: 45427 | L32: 45791 | M32: Ashburn, VA 20148, USA | N32: Indefinite Delivery Contract 49100422D0010 | O32: DA01 | P32: 541512 | Q32: 46279 | R32: 49100422D0010|49100424F0097 | S32: 49100422D0010-49100424F0097 | T32: Agility Technologies Inc. | U32: https://govtribe.com/award/federal-contract-award/delivery-order-49100422d0010-49100424f0097 | V32: https://govtribe.com/vendors/agility-technologies-inc-dot-5b8b7 | W32: =IF(R32="",IF(COUNTA(C32,F32:V32)>0,"Missing award ID",""),IF(COUNTIFS(AwardsData[Award ID],R32)<>1,"Duplicate award ID",IF(OR(S32="",T32="",F32=""),"Add reference, vendor and award type",IF(OR(AND(I32<>"",NOT(ISNUMBER(I32))),AND(J32<>"",NOT(ISNUMBER(J32)))),"Use numeric snapshot amounts",IF(OR(COUNTIF(AwardTypeCategories,F32)<>1,COUNTIF(SetAsideCategories,G32)<>1,COUNTIF(PerformanceStateCategories,H32)<>1),"New category: refresh report",""))))) | X32: =IF(R32="","",COUNTIFS(TransactionsData[Award ID],R32,TransactionsData[Selected],1)) -> 0 | Y32: =IF(R32="","",COUNTIFS(TransactionsData[Award ID],R32,TransactionsData[Dimension match],1)) -> 1
A33: =IF(S33="","",IF(U33="",S33,HYPERLINK(U33,S33))) -> 49100422D0010-49100424F0099 | B33: =IF(T33="","",IF(V33="",T33,HYPERLINK(V33,T33))) -> Agility Technologies Inc. | C33: Z9M6NN4AQLF7 | D33: =IF(R33="","",IF(Trends!$B$6<>"","",SUMIFS(TransactionsData[Obligations],TransactionsData[Award ID],R33,TransactionsData[Selected],1))) -> 0 | E33: =IF(R33="","",IF(Trends!$B$6<>"","",SUMIFS(TransactionsData[Obligations],TransactionsData[Award ID],R33,TransactionsData[Dimension match],1))) -> 294827.54 | F33: Delivery Order | G33: No Set-Aside Used | H33: Virginia | I33: 294827.54 | J33: 294827.54 | K33: 45443 | L33: 45559 | M33: Ashburn, VA 20148, USA | N33: Indefinite Delivery Contract 49100422D0010 | O33: DA01 | P33: 541512 | Q33: 46279 | R33: 49100422D0010|49100424F0099 | S33: 49100422D0010-49100424F0099 | T33: Agility Technologies Inc. | U33: https://govtribe.com/award/federal-contract-award/delivery-order-49100422d0010-49100424f0099 | V33: https://govtribe.com/vendors/agility-technologies-inc-dot-5b8b7 | W33: =IF(R33="",IF(COUNTA(C33,F33:V33)>0,"Missing award ID",""),IF(COUNTIFS(AwardsData[Award ID],R33)<>1,"Duplicate award ID",IF(OR(S33="",T33="",F33=""),"Add reference, vendor and award type",IF(OR(AND(I33<>"",NOT(ISNUMBER(I33))),AND(J33<>"",NOT(ISNUMBER(J33)))),"Use numeric snapshot amounts",IF(OR(COUNTIF(AwardTypeCategories,F33)<>1,COUNTIF(SetAsideCategories,G33)<>1,COUNTIF(PerformanceStateCategories,H33)<>1),"New category: refresh report",""))))) | X33: =IF(R33="","",COUNTIFS(TransactionsData[Award ID],R33,TransactionsData[Selected],1)) -> 0 | Y33: =IF(R33="","",COUNTIFS(TransactionsData[Award ID],R33,TransactionsData[Dimension match],1)) -> 1
A34: =IF(S34="","",IF(U34="",S34,HYPERLINK(U34,S34))) -> 49100422D0010-49100424F0165 | B34: =IF(T34="","",IF(V34="",T34,HYPERLINK(V34,T34))) -> Agility Technologies Inc. | C34: Z9M6NN4AQLF7 | D34: =IF(R34="","",IF(Trends!$B$6<>"","",SUMIFS(TransactionsData[Obligations],TransactionsData[Award ID],R34,TransactionsData[Selected],1))) -> 0 | E34: =IF(R34="","",IF(Trends!$B$6<>"","",SUMIFS(TransactionsData[Obligations],TransactionsData[Award ID],R34,TransactionsData[Dimension match],1))) -> 377748 | F34: Delivery Order | G34: No Set-Aside Used | H34: Virginia | I34: 377748 | J34: 377748 | K34: 45560 | L34: 45924 | M34: Ashburn, VA 20148, USA | N34: Indefinite Delivery Contract 49100422D0010 | O34: DA01 | P34: 541512 | Q34: 46279 | R34: 49100422D0010|49100424F0165 | S34: 49100422D0010-49100424F0165 | T34: Agility Technologies Inc. | U34: https://govtribe.com/award/federal-contract-award/delivery-order-49100422d0010-49100424f0165 | V34: https://govtribe.com/vendors/agility-technologies-inc-dot-5b8b7 | W34: =IF(R34="",IF(COUNTA(C34,F34:V34)>0,"Missing award ID",""),IF(COUNTIFS(AwardsData[Award ID],R34)<>1,"Duplicate award ID",IF(OR(S34="",T34="",F34=""),"Add reference, vendor and award type",IF(OR(AND(I34<>"",NOT(ISNUMBER(I34))),AND(J34<>"",NOT(ISNUMBER(J34)))),"Use numeric snapshot amounts",IF(OR(COUNTIF(AwardTypeCategories,F34)<>1,COUNTIF(SetAsideCategories,G34)<>1,COUNTIF(PerformanceStateCategories,H34)<>1),"New category: refresh report",""))))) | X34: =IF(R34="","",COUNTIFS(TransactionsData[Award ID],R34,TransactionsData[Selected],1)) -> 0 | Y34: =IF(R34="","",COUNTIFS(TransactionsData[Award ID],R34,TransactionsData[Dimension match],1)) -> 1
A35: =IF(S35="","",IF(U35="",S35,HYPERLINK(U35,S35))) -> 49100422D0010-49100424F0187 | B35: =IF(T35="","",IF(V35="",T35,HYPERLINK(V35,T35))) -> Agility Technologies Inc. | C35: Z9M6NN4AQLF7 | D35: =IF(R35="","",IF(Trends!$B$6<>"","",SUMIFS(TransactionsData[Obligations],TransactionsData[Award ID],R35,TransactionsData[Selected],1))) -> 0 | E35: =IF(R35="","",IF(Trends!$B$6<>"","",SUMIFS(TransactionsData[Obligations],TransactionsData[Award ID],R35,TransactionsData[Dimension match],1))) -> 521160.4 | F35: Delivery Order | G35: No Set-Aside Used | H35: Virginia | I35: 521160.4 | J35: 521160.4 | K35: 45560 | L35: 45924 | M35: Ashburn, VA 20148, USA | N35: Indefinite Delivery Contract 49100422D0010 | O35: DA01 | P35: 541512 | Q35: 46279 | R35: 49100422D0010|49100424F0187 | S35: 49100422D0010-49100424F0187 | T35: Agility Technologies Inc. | U35: https://govtribe.com/award/federal-contract-award/delivery-order-49100422d0010-49100424f0187 | V35: https://govtribe.com/vendors/agility-technologies-inc-dot-5b8b7 | W35: =IF(R35="",IF(COUNTA(C35,F35:V35)>0,"Missing award ID",""),IF(COUNTIFS(AwardsData[Award ID],R35)<>1,"Duplicate award ID",IF(OR(S35="",T35="",F35=""),"Add reference, vendor and award type",IF(OR(AND(I35<>"",NOT(ISNUMBER(I35))),AND(J35<>"",NOT(ISNUMBER(J35)))),"Use numeric snapshot amounts",IF(OR(COUNTIF(AwardTypeCategories,F35)<>1,COUNTIF(SetAsideCategories,G35)<>1,COUNTIF(PerformanceStateCategories,H35)<>1),"New category: refresh report",""))))) | X35: =IF(R35="","",COUNTIFS(TransactionsData[Award ID],R35,TransactionsData[Selected],1)) -> 0 | Y35: =IF(R35="","",COUNTIFS(TransactionsData[Award ID],R35,TransactionsData[Dimension match],1)) -> 1
A36: =IF(S36="","",IF(U36="",S36,HYPERLINK(U36,S36))) -> 49100423C0050 | B36: =IF(T36="","",IF(V36="",T36,HYPERLINK(V36,T36))) -> Scope It Consulting, LLC | C36: KN99UT9W5N77 | D36: =IF(R36="","",IF(Trends!$B$6<>"","",SUMIFS(TransactionsData[Obligations],TransactionsData[Award ID],R36,TransactionsData[Selected],1))) -> 489791.72 | E36: =IF(R36="","",IF(Trends!$B$6<>"","",SUMIFS(TransactionsData[Obligations],TransactionsData[Award ID],R36,TransactionsData[Dimension match],1))) -> 1760927.3 | F36: Definitive Contract | G36: 8(a) Sole Source | H36: Georgia | I36: 1930662.8 | J36: 2322012.3 | K36: 45194 | L36: 46654 | M36: Berkeley Lake, GA 30096, USA | O36: DA01 | P36: 541512 | Q36: 46279 | R36: 49100423C0050 | S36: 49100423C0050 | T36: Scope It Consulting, LLC | U36: https://govtribe.com/award/federal-contract-award/definitive-contract-49100423c0050 | V36: https://govtribe.com/vendors/scope-it-consulting-llc-7m3f4 | W36: =IF(R36="",IF(COUNTA(C36,F36:V36)>0,"Missing award ID",""),IF(COUNTIFS(AwardsData[Award ID],R36)<>1,"Duplicate award ID",IF(OR(S36="",T36="",F36=""),"Add reference, vendor and award type",IF(OR(AND(I36<>"",NOT(ISNUMBER(I36))),AND(J36<>"",NOT(ISNUMBER(J36)))),"Use numeric snapshot amounts",IF(OR(COUNTIF(AwardTypeCategories,F36)<>1,COUNTIF(SetAsideCategories,G36)<>1,COUNTIF(PerformanceStateCategories,H36)<>1),"New category: refresh report",""))))) | X36: =IF(R36="","",COUNTIFS(TransactionsData[Award ID],R36,TransactionsData[Selected],1)) -> 1 | Y36: =IF(R36="","",COUNTIFS(TransactionsData[Award ID],R36,TransactionsData[Dimension match],1)) -> 3
A37: =IF(S37="","",IF(U37="",S37,HYPERLINK(U37,S37))) -> 49100423C0052 | B37: =IF(T37="","",IF(V37="",T37,HYPERLINK(V37,T37))) -> Expediteinfotech, Inc. | C37: KX6EDEAPTKH5 | D37: =IF(R37="","",IF(Trends!$B$6<>"","",SUMIFS(TransactionsData[Obligations],TransactionsData[Award ID],R37,TransactionsData[Selected],1))) -> 0 | E37: =IF(R37="","",IF(Trends!$B$6<>"","",SUMIFS(TransactionsData[Obligations],TransactionsData[Award ID],R37,TransactionsData[Dimension match],1))) -> 300000 | F37: Definitive Contract | G37: 8(a) Sole Source | H37: Maryland | I37: 300000 | J37: 300000 | K37: 45200 | L37: 45695 | M37: Rockville, MD 20850, USA | O37: DA01 | P37: 541511 | Q37: 46279 | R37: 49100423C0052 | S37: 49100423C0052 | T37: Expediteinfotech, Inc. | U37: https://govtribe.com/award/federal-contract-award/definitive-contract-49100423c0052 | V37: https://govtribe.com/vendors/expediteinfotech-inc-dot-78dz9 | W37: =IF(R37="",IF(COUNTA(C37,F37:V37)>0,"Missing award ID",""),IF(COUNTIFS(AwardsData[Award ID],R37)<>1,"Duplicate award ID",IF(OR(S37="",T37="",F37=""),"Add reference, vendor and award type",IF(OR(AND(I37<>"",NOT(ISNUMBER(I37))),AND(J37<>"",NOT(ISNUMBER(J37)))),"Use numeric snapshot amounts",IF(OR(COUNTIF(AwardTypeCategories,F37)<>1,COUNTIF(SetAsideCategories,G37)<>1,COUNTIF(PerformanceStateCategories,H37)<>1),"New category: refresh report",""))))) | X37: =IF(R37="","",COUNTIFS(TransactionsData[Award ID],R37,TransactionsData[Selected],1)) -> 1 | Y37: =IF(R37="","",COUNTIFS(TransactionsData[Award ID],R37,TransactionsData[Dimension match],1)) -> 4
A38: =IF(S38="","",IF(U38="",S38,HYPERLINK(U38,S38))) -> 49100423P0060 | B38: =IF(T38="","",IF(V38="",T38,HYPERLINK(V38,T38))) -> University Corporation For Advanced Internet Development | C38: DZEBKFRD1ZN6 | D38: =IF(R38="","",IF(Trends!$B$6<>"","",SUMIFS(TransactionsData[Obligations],TransactionsData[Award ID],R38,TransactionsData[Selected],1))) -> 0 | E38: =IF(R38="","",IF(Trends!$B$6<>"","",SUMIFS(TransactionsData[Obligations],TransactionsData[Award ID],R38,TransactionsData[Dimension match],1))) -> 37941 | F38: Purchase Order | G38: No Set-Aside Used | H38: Virginia | I38: 37941 | J38: 37941 | K38: 44927 | L38: 45291 | M38: Alexandria, VA 22314, USA | O38: DA01 | P38: 813910 | Q38: 46279 | R38: 49100423P0060 | S38: 49100423P0060 | T38: University Corporation For Advanced Internet Development | U38: https://govtribe.com/award/federal-contract-award/purchase-order-49100423p0060 | V38: https://govtribe.com/vendors/university-corporation-for-advanced-internet-development-internet2-1qu14 | W38: =IF(R38="",IF(COUNTA(C38,F38:V38)>0,"Missing award ID",""),IF(COUNTIFS(AwardsData[Award ID],R38)<>1,"Duplicate award ID",IF(OR(S38="",T38="",F38=""),"Add reference, vendor and award type",IF(OR(AND(I38<>"",NOT(ISNUMBER(I38))),AND(J38<>"",NOT(ISNUMBER(J38)))),"Use numeric snapshot amounts",IF(OR(COUNTIF(AwardTypeCategories,F38)<>1,COUNTIF(SetAsideCategories,G38)<>1,COUNTIF(PerformanceStateCategories,H38)<>1),"New category: refresh report",""))))) | X38: =IF(R38="","",COUNTIFS(TransactionsData[Award ID],R38,TransactionsData[Selected],1)) -> 0 | Y38: =IF(R38="","",COUNTIFS(TransactionsData[Award ID],R38,TransactionsData[Dimension match],1)) -> 1
A39: =IF(S39="","",IF(U39="",S39,HYPERLINK(U39,S39))) -> 49100424A0001-49100424F0030 | B39: =IF(T39="","",IF(V39="",T39,HYPERLINK(V39,T39))) -> Spatial Front Inc. | C39: J1ADW6BL8MN5 | D39: =IF(R39="","",IF(Trends!$B$6<>"","",SUMIFS(TransactionsData[Obligations],TransactionsData[Award ID],R39,TransactionsData[Selected],1))) -> -3349.7 | E39: =IF(R39="","",IF(Trends!$B$6<>"","",SUMIFS(TransactionsData[Obligations],TransactionsData[Award ID],R39,TransactionsData[Dimension match],1))) -> 1472100.2 | F39: BPA Call | G39: No Set-Aside Used | H39: Virginia | I39: 1472100.2 | J39: 1606370.2 | K39: 45331 | L39: 45730 | M39: Alexandria, VA 22314, USA | N39: Blanket Purchase Agreement GS35F0648Y-49100424A0001 | O39: DA01 | P39: 541511 | Q39: 46279 | R39: 49100424A0001|49100424F0030 | S39: 49100424A0001-49100424F0030 | T39: Spatial Front Inc. | U39: https://govtribe.com/award/federal-contract-award/bpa-call-49100424a0001-49100424f0030 | V39: https://govtribe.com/vendors/spatial-front-incorporated-5xgw3 | W39: =IF(R39="",IF(COUNTA(C39,F39:V39)>0,"Missing award ID",""),IF(COUNTIFS(AwardsData[Award ID],R39)<>1,"Duplicate award ID",IF(OR(S39="",T39="",F39=""),"Add reference, vendor and award type",IF(OR(AND(I39<>"",NOT(ISNUMBER(I39))),AND(J39<>"",NOT(ISNUMBER(J39)))),"Use numeric snapshot amounts",IF(OR(COUNTIF(AwardTypeCategories,F39)<>1,COUNTIF(SetAsideCategories,G39)<>1,COUNTIF(PerformanceStateCategories,H39)<>1),"New category: refresh report",""))))) | X39: =IF(R39="","",COUNTIFS(TransactionsData[Award ID],R39,TransactionsData[Selected],1)) -> 4 | Y39: =IF(R39="","",COUNTIFS(TransactionsData[Award ID],R39,TransactionsData[Dimension match],1)) -> 8
A40: =IF(S40="","",IF(U40="",S40,HYPERLINK(U40,S40))) -> 49100424A0001-49100424F0051 | B40: =IF(T40="","",IF(V40="",T40,HYPERLINK(V40,T40))) -> Spatial Front Inc. | C40: J1ADW6BL8MN5 | D40: =IF(R40="","",IF(Trends!$B$6<>"","",SUMIFS(TransactionsData[Obligations],TransactionsData[Award ID],R40,TransactionsData[Selected],1))) -> 722435.9 | E40: =IF(R40="","",IF(Trends!$B$6<>"","",SUMIFS(TransactionsData[Obligations],TransactionsData[Award ID],R40,TransactionsData[Dimension match],1))) -> 1352279.3 | F40: BPA Call | G40: Total Small Business | H40: Virginia | I40: 2527654 | J40: 4404604.1 | K40: 45364 | L40: 46477 | M40: Alexandria, VA 22314, USA | N40: Blanket Purchase Agreement GS35F0648Y-49100424A0001 | O40: DA01 | P40: 541511 | Q40: 46279 | R40: 49100424A0001|49100424F0051 | S40: 49100424A0001-49100424F0051 | T40: Spatial Front Inc. | U40: https://govtribe.com/award/federal-contract-award/bpa-call-49100424a0001-49100424f0051 | V40: https://govtribe.com/vendors/spatial-front-incorporated-5xgw3 | W40: =IF(R40="",IF(COUNTA(C40,F40:V40)>0,"Missing award ID",""),IF(COUNTIFS(AwardsData[Award ID],R40)<>1,"Duplicate award ID",IF(OR(S40="",T40="",F40=""),"Add reference, vendor and award type",IF(OR(AND(I40<>"",NOT(ISNUMBER(I40))),AND(J40<>"",NOT(ISNUMBER(J40)))),"Use numeric snapshot amounts",IF(OR(COUNTIF(AwardTypeCategories,F40)<>1,COUNTIF(SetAsideCategories,G40)<>1,COUNTIF(PerformanceStateCategories,H40)<>1),"New category: refresh report",""))))) | X40: =IF(R40="","",COUNTIFS(TransactionsData[Award ID],R40,TransactionsData[Selected],1)) -> 4 | Y40: =IF(R40="","",COUNTIFS(TransactionsData[Award ID],R40,TransactionsData[Dimension match],1)) -> 6
A41: =IF(S41="","",IF(U41="",S41,HYPERLINK(U41,S41))) -> 49100424A0001-49100424F0052 | B41: =IF(T41="","",IF(V41="",T41,HYPERLINK(V41,T41))) -> Spatial Front Inc. | C41: J1ADW6BL8MN5 | D41: =IF(R41="","",IF(Trends!$B$6<>"","",SUMIFS(TransactionsData[Obligations],TransactionsData[Award ID],R41,TransactionsData[Selected],1))) -> 534742.27 | E41: =IF(R41="","",IF(Trends!$B$6<>"","",SUMIFS(TransactionsData[Obligations],TransactionsData[Award ID],R41,TransactionsData[Dimension match],1))) -> 873966.27 | F41: BPA Call | G41: No Set-Aside Used | H41: Virginia | I41: 873966.27 | J41: 3945495 | K41: 45364 | L41: 45870 | M41: Alexandria, VA 22314, USA | N41: Blanket Purchase Agreement GS35F0648Y-49100424A0001 | O41: DA01 | P41: 541511 | Q41: 46279 | R41: 49100424A0001|49100424F0052 | S41: 49100424A0001-49100424F0052 | T41: Spatial Front Inc. | U41: https://govtribe.com/award/federal-contract-award/bpa-call-49100424a0001-49100424f0052 | V41: https://govtribe.com/vendors/spatial-front-incorporated-5xgw3 | W41: =IF(R41="",IF(COUNTA(C41,F41:V41)>0,"Missing award ID",""),IF(COUNTIFS(AwardsData[Award ID],R41)<>1,"Duplicate award ID",IF(OR(S41="",T41="",F41=""),"Add reference, vendor and award type",IF(OR(AND(I41<>"",NOT(ISNUMBER(I41))),AND(J41<>"",NOT(ISNUMBER(J41)))),"Use numeric snapshot amounts",IF(OR(COUNTIF(AwardTypeCategories,F41)<>1,COUNTIF(SetAsideCategories,G41)<>1,COUNTIF(PerformanceStateCategories,H41)<>1),"New category: refresh report",""))))) | X41: =IF(R41="","",COUNTIFS(TransactionsData[Award ID],R41,TransactionsData[Selected],1)) -> 5 | Y41: =IF(R41="","",COUNTIFS(TransactionsData[Award ID],R41,TransactionsData[Dimension match],1)) -> 8
