Workbook

Sheet Summary
C2: Labor pricing & staffing
C4: Scenario | D4: =Assumptions!$D$4 -> Base | E4: GovTribe, Inc. · UEI EDJBUPNLCCL5
C7: Buyer | D7: =IF('Source Data'!D6="","",'Source Data'!D6) -> Federal Enterprise Finance Office
C8: Project | D8: =IF('Source Data'!D7="","",'Source Data'!D7) -> Financial Oversight and Program Support
C9: Solicitation | D9: =IF('Source Data'!D8="","",'Source Data'!D8) -> DEMO-LABOR-001
C10: Location | D10: =IF('Source Data'!D9="","",'Source Data'!D9) -> Washington, DC
C11: As of | D11: =IF('Source Data'!D10="","",'Source Data'!D10) -> 46276
C13: GovTribe’s identity is real; scenario assumptions and past performance are illustrative. Fictional buyer.
C16: Period | D16: Pricing hours | E16: Est. positions | F16: Paid FTE | G16: Price | H16: Modeled cost | I16: Profit
C17: Base | D17: =IF(Pricing!E16="","",Pricing!E16) -> 16640 | E17: =IF(COUNT('Source Data'!E21:E26)<6,"",SUM('Source Data'!E21:E26)) -> 8 | F17: =IF(COUNT(Staffing!D13,Staffing!D25,Staffing!D37,Staffing!D49,Staffing!D61,Staffing!D73)<6,"",SUM(Staffing!D13,Staffing!D25,Staffing!D37,Staffing!D49,Staffing!D61,Staffing!D73)) -> 9.0434783 | G17: =IF(Pricing!G16="","",Pricing!G16) -> 1771701.8 | H17: =IF(Pricing!H16="","",Pricing!H16) -> 1610637.9 | I17: =IF(Pricing!I16="","",Pricing!I16) -> 161063.85
C18: Option 1 | D18: =IF(Pricing!E27="","",Pricing!E27) -> 16640 | E18: =IF(COUNT('Source Data'!E21:E26)<6,"",SUM('Source Data'!E21:E26)) -> 8 | F18: =IF(COUNT(Staffing!E13,Staffing!E25,Staffing!E37,Staffing!E49,Staffing!E61,Staffing!E73)<6,"",SUM(Staffing!E13,Staffing!E25,Staffing!E37,Staffing!E49,Staffing!E61,Staffing!E73)) -> 9.0434783 | G18: =IF(Pricing!G27="","",Pricing!G27) -> 1824852.6 | H18: =IF(Pricing!H27="","",Pricing!H27) -> 1658957.1 | I18: =IF(Pricing!I27="","",Pricing!I27) -> 165895.58
C19: Option 2 | D19: =IF(Pricing!E38="","",Pricing!E38) -> 16640 | E19: =IF(COUNT('Source Data'!E21:E26)<6,"",SUM('Source Data'!E21:E26)) -> 8 | F19: =IF(COUNT(Staffing!F13,Staffing!F25,Staffing!F37,Staffing!F49,Staffing!F61,Staffing!F73)<6,"",SUM(Staffing!F13,Staffing!F25,Staffing!F37,Staffing!F49,Staffing!F61,Staffing!F73)) -> 9.0434783 | G19: =IF(Pricing!G38="","",Pricing!G38) -> 1879598.4 | H19: =IF(Pricing!H38="","",Pricing!H38) -> 1708725.8 | I19: =IF(Pricing!I38="","",Pricing!I38) -> 170872.67
C20: Option 3 | D20: =IF(Pricing!E49="","",Pricing!E49) -> 16640 | E20: =IF(COUNT('Source Data'!E21:E26)<6,"",SUM('Source Data'!E21:E26)) -> 8 | F20: =IF(COUNT(Staffing!G13,Staffing!G25,Staffing!G37,Staffing!G49,Staffing!G61,Staffing!G73)<6,"",SUM(Staffing!G13,Staffing!G25,Staffing!G37,Staffing!G49,Staffing!G61,Staffing!G73)) -> 9.0434783 | G20: =IF(Pricing!G49="","",Pricing!G49) -> 1935986.4 | H20: =IF(Pricing!H49="","",Pricing!H49) -> 1759987.5 | I20: =IF(Pricing!I49="","",Pricing!I49) -> 175998.88
C21: Option 4 | D21: =IF(Pricing!E60="","",Pricing!E60) -> 16640 | E21: =IF(COUNT('Source Data'!E21:E26)<6,"",SUM('Source Data'!E21:E26)) -> 8 | F21: =IF(COUNT(Staffing!H13,Staffing!H25,Staffing!H37,Staffing!H49,Staffing!H61,Staffing!H73)<6,"",SUM(Staffing!H13,Staffing!H25,Staffing!H37,Staffing!H49,Staffing!H61,Staffing!H73)) -> 9.0434783 | G21: =IF(Pricing!G60="","",Pricing!G60) -> 1994065.8 | H21: =IF(Pricing!H60="","",Pricing!H60) -> 1812787.2 | I21: =IF(Pricing!I60="","",Pricing!I60) -> 181278.67
C22: Extension | D22: =IF(Pricing!E71="","",Pricing!E71) -> 8320 | E22: =IF(COUNT('Source Data'!E21:E26)<6,"",SUM('Source Data'!E21:E26)) -> 8 | F22: =IF(COUNT(Staffing!I13,Staffing!I25,Staffing!I37,Staffing!I49,Staffing!I61,Staffing!I73)<6,"",SUM(Staffing!I13,Staffing!I25,Staffing!I37,Staffing!I49,Staffing!I61,Staffing!I73)) -> 9.0434783 | G22: =IF(Pricing!G71="","",Pricing!G71) -> 997032.92 | H22: =IF(Pricing!H71="","",Pricing!H71) -> 906393.59 | I22: =IF(Pricing!I71="","",Pricing!I71) -> 90639.33
C24: Five-year total | D24: =IF(COUNT(D17:D21)<5,"",SUM(D17:D21)) -> 83200 | G24: =IF(COUNT(G17:G21)<5,"",SUM(G17:G21)) -> 9406205.1 | H24: =IF(COUNT(H17:H21)<5,"n.a.",SUM(H17:H21)) -> 8551095.5 | I24: =IF(COUNT(I17:I21)<5,"n.a.",SUM(I17:I21)) -> 855109.65
C25: Extension — separate | D25: =IF(D22="","",D22) -> 8320 | G25: =IF(G22="","",G22) -> 997032.92 | H25: =IF(H22="","",H22) -> 906393.59 | I25: =IF(I22="","",I22) -> 90639.33
C28: Model status | D28: =IF(OR('Source Data'!D6="",'Source Data'!D7="",'Source Data'!D8="",'Source Data'!D9="",NOT(ISNUMBER('Source Data'!D10))),"Complete the project inputs",IF(COUNT(Assumptions!D19:I19)<6,"Check period dates in Source Data",IF(SUM(IF('Labor Rates'!D27="Staffing shortfall",1,0),IF('Labor Rates'!E27="Staffing shortfall",1,0),IF('Labor Rates'!F27="Staffing shortfall",1,0),IF('Labor Rates'!G27="Staffing shortfall",1,0),IF('Labor Rates'!H27="Staffing shortfall",1,0),IF('Labor Rates'!I27="Staffing shortfall",1,0),IF('Labor Rates'!D50="Staffing shortfall",1,0),IF('Labor Rates'!E50="Staffing shortfall",1,0),IF('Labor Rates'!F50="Staffing shortfall",1,0),IF('Labor Rates'!G50="Staffing shortfall",1,0),IF('Labor Rates'!H50="Staffing shortfall",1,0),IF('Labor Rates'!I50="Staffing shortfall",1,0),IF('Labor Rates'!D73="Staffing shortfall",1,0),IF('Labor Rates'!E73="Staffing shortfall",1,0),IF('Labor Rates'!F73="Staffing shortfall",1,0),IF('Labor Rates'!G73="Staffing shortfall",1,0),IF('Labor Rates'!H73="Staffing shortfall",1,0),IF('Labor Rates'!I73="Staffing shortfall",1,0),IF('Labor Rates'!D96="Staffing shortfall",1,0),IF('Labor Rates'!E96="Staffing shortfall",1,0),IF('Labor Rates'!F96="Staffing shortfall",1,0),IF('Labor Rates'!G96="Staffing shortfall",1,0),IF('Labor Rates'!H96="Staffing shortfall",1,0),IF('Labor Rates'!I96="Staffing shortfall",1,0),IF('Labor Rates'!D119="Staffing shortfall",1,0),IF('Labor Rates'!E119="Staffing shortfall",1,0),IF('Labor Rates'!F119="Staffing shortfall",1,0),IF('Labor Rates'!G119="Staffing shortfall",1,0),IF('Labor Rates'!H119="Staffing shortfall",1,0),IF('Labor Rates'!I119="Staffing shortfall",1,0),IF('Labor Rates'!D142="Staffing shortfall",1,0),IF('Labor Rates'!E142="Staffing shortfall",1,0),IF('Labor Rates'!F142="Staffing shortfall",1,0),IF('Labor Rates'!G142="Staffing shortfall",1,0),IF('Labor Rates'!H142="Staffing shortfall",1,0),IF('Labor Rates'!I142="Staffing shortfall",1,0))>0,"Staffing shortfall — review Staffing",IF(SUM(IF(OR('Labor Rates'!D27="Complete",'Labor Rates'!D27="Zero hours"),0,1),IF(OR('Labor Rates'!E27="Complete",'Labor Rates'!E27="Zero hours"),0,1),IF(OR('Labor Rates'!F27="Complete",'Labor Rates'!F27="Zero hours"),0,1),IF(OR('Labor Rates'!G27="Complete",'Labor Rates'!G27="Zero hours"),0,1),IF(OR('Labor Rates'!H27="Complete",'Labor Rates'!H27="Zero hours"),0,1),IF(OR('Labor Rates'!I27="Complete",'Labor Rates'!I27="Zero hours"),0,1),IF(OR('Labor Rates'!D50="Complete",'Labor Rates'!D50="Zero hours"),0,1),IF(OR('Labor Rates'!E50="Complete",'Labor Rates'!E50="Zero hours"),0,1),IF(OR('Labor Rates'!F50="Complete",'Labor Rates'!F50="Zero hours"),0,1),IF(OR('Labor Rates'!G50="Complete",'Labor Rates'!G50="Zero hours"),0,1),IF(OR('Labor Rates'!H50="Complete",'Labor Rates'!H50="Zero hours"),0,1),IF(OR('Labor Rates'!I50="Complete",'Labor Rates'!I50="Zero hours"),0,1),IF(OR('Labor Rates'!D73="Complete",'Labor Rates'!D73="Zero hours"),0,1),IF(OR('Labor Rates'!E73="Complete",'Labor Rates'!E73="Zero hours"),0,1),IF(OR('Labor Rates'!F73="Complete",'Labor Rates'!F73="Zero hours"),0,1),IF(OR('Labor Rates'!G73="Complete",'Labor Rates'!G73="Zero hours"),0,1),IF(OR('Labor Rates'!H73="Complete",'Labor Rates'!H73="Zero hours"),0,1),IF(OR('Labor Rates'!I73="Complete",'Labor Rates'!I73="Zero hours"),0,1),IF(OR('Labor Rates'!D96="Complete",'Labor Rates'!D96="Zero hours"),0,1),IF(OR('Labor Rates'!E96="Complete",'Labor Rates'!E96="Zero hours"),0,1),IF(OR('Labor Rates'!F96="Complete",'Labor Rates'!F96="Zero hours"),0,1),IF(OR('Labor Rates'!G96="Complete",'Labor Rates'!G96="Zero hours"),0,1),IF(OR('Labor Rates'!H96="Complete",'Labor Rates'!H96="Zero hours"),0,1),IF(OR('Labor Rates'!I96="Complete",'Labor Rates'!I96="Zero hours"),0,1),IF(OR('Labor Rates'!D119="Complete",'Labor Rates'!D119="Zero hours"),0,1),IF(OR('Labor Rates'!E119="Complete",'Labor Rates'!E119="Zero hours"),0,1),IF(OR('Labor Rates'!F119="Complete",'Labor Rates'!F119="Zero hours"),0,1),IF(OR('Labor Rates'!G119="Complete",'Labor Rates'!G119="Zero hours"),0,1),IF(OR('Labor Rates'!H119="Complete",'Labor Rates'!H119="Zero hours"),0,1),IF(OR('Labor Rates'!I119="Complete",'Labor Rates'!I119="Zero hours"),0,1),IF(OR('Labor Rates'!D142="Complete",'Labor Rates'!D142="Zero hours"),0,1),IF(OR('Labor Rates'!E142="Complete",'Labor Rates'!E142="Zero hours"),0,1),IF(OR('Labor Rates'!F142="Complete",'Labor Rates'!F142="Zero hours"),0,1),IF(OR('Labor Rates'!G142="Complete",'Labor Rates'!G142="Zero hours"),0,1),IF(OR('Labor Rates'!H142="Complete",'Labor Rates'!H142="Zero hours"),0,1),IF(OR('Labor Rates'!I142="Complete",'Labor Rates'!I142="Zero hours"),0,1))>0,"Missing or invalid inputs — review detail","Calculated")))) -> Calculated
C30: Paid FTE includes capacity for nonbillable time; it is not a count of named people. Prices use requested hours and do not represent guaranteed orders.
C32: Edit amber inputs in Source Data and Assumptions. Use Staffing for FTE overrides and Labor Rates for period-rate overrides.
C34: Input key: blue = editable input; black = calculation; green = linked input. Missing values remain incomplete; n.a. means cost or profit is unavailable.

Sheet Assumptions
C2: Assumptions
C4: Scenario | D4: Base
C7: Annual paid hours | D7: 2080
C8: Annual nonbillable hours | D8: 240
C9: Additional benefit / paid hour | D9: 0
C10: Profit or margin | D10: 0.1
C11: Profit calculation | D11: Profit on cost
C12: Nonbillable time includes paid leave; fringe excludes it. Management is included in indirect costs. Duration uses complete months plus actual-day fractions of the final month, with inclusive end dates.
D16: Base | E16: Option 1 | F16: Option 2 | G16: Option 3 | H16: Option 4 | I16: Extension
C17: Period starts | D17: =IF('Source Data'!D15="","",'Source Data'!D15) -> 46296 | E17: =IF('Source Data'!E15="","",'Source Data'!E15) -> 46661 | F17: =IF('Source Data'!F15="","",'Source Data'!F15) -> 47027 | G17: =IF('Source Data'!G15="","",'Source Data'!G15) -> 47392 | H17: =IF('Source Data'!H15="","",'Source Data'!H15) -> 47757 | I17: =IF('Source Data'!I15="","",'Source Data'!I15) -> 48122
C18: Period ends | D18: =IF('Source Data'!D16="","",'Source Data'!D16) -> 46660 | E18: =IF('Source Data'!E16="","",'Source Data'!E16) -> 47026 | F18: =IF('Source Data'!F16="","",'Source Data'!F16) -> 47391 | G18: =IF('Source Data'!G16="","",'Source Data'!G16) -> 47756 | H18: =IF('Source Data'!H16="","",'Source Data'!H16) -> 48121 | I18: =IF('Source Data'!I16="","",'Source Data'!I16) -> 48304
C19: Years of staffing | D19: =IF(COUNT(D20:D21)<2,"",SUM(D20:D21)/12) -> 1 | E19: =IF(COUNT(E20:E21)<2,"",SUM(E20:E21)/12) -> 1 | F19: =IF(COUNT(F20:F21)<2,"",SUM(F20:F21)/12) -> 1 | G19: =IF(COUNT(G20:G21)<2,"",SUM(G20:G21)/12) -> 1 | H19: =IF(COUNT(H20:H21)<2,"",SUM(H20:H21)/12) -> 1 | I19: =IF(COUNT(I20:I21)<2,"",SUM(I20:I21)/12) -> 0.5
C20: Complete months | D20: =IF(COUNT(D17:D18)<2,"",IF(NOT(AND(D17>0,D18>=D17,D17=INT(D17),D18=INT(D18),D18<2958465)),"",(12*(YEAR(D18+1)-YEAR(D17))+MONTH(D18+1)-MONTH(D17))-IF(EDATE(D17,(12*(YEAR(D18+1)-YEAR(D17))+MONTH(D18+1)-MONTH(D17)))>D18+1,1,0))) -> 12 | E20: =IF(COUNT(E17:E18,D18)<3,"",IF(NOT(AND(E17>0,E18>=E17,E17=INT(E17),E18=INT(E18),E18<2958465,ISNUMBER(D18),E17=D18+1)),"",(12*(YEAR(E18+1)-YEAR(E17))+MONTH(E18+1)-MONTH(E17))-IF(EDATE(E17,(12*(YEAR(E18+1)-YEAR(E17))+MONTH(E18+1)-MONTH(E17)))>E18+1,1,0))) -> 12 | F20: =IF(COUNT(F17:F18,E18)<3,"",IF(NOT(AND(F17>0,F18>=F17,F17=INT(F17),F18=INT(F18),F18<2958465,ISNUMBER(E18),F17=E18+1)),"",(12*(YEAR(F18+1)-YEAR(F17))+MONTH(F18+1)-MONTH(F17))-IF(EDATE(F17,(12*(YEAR(F18+1)-YEAR(F17))+MONTH(F18+1)-MONTH(F17)))>F18+1,1,0))) -> 12 | G20: =IF(COUNT(G17:G18,F18)<3,"",IF(NOT(AND(G17>0,G18>=G17,G17=INT(G17),G18=INT(G18),G18<2958465,ISNUMBER(F18),G17=F18+1)),"",(12*(YEAR(G18+1)-YEAR(G17))+MONTH(G18+1)-MONTH(G17))-IF(EDATE(G17,(12*(YEAR(G18+1)-YEAR(G17))+MONTH(G18+1)-MONTH(G17)))>G18+1,1,0))) -> 12 | H20: =IF(COUNT(H17:H18,G18)<3,"",IF(NOT(AND(H17>0,H18>=H17,H17=INT(H17),H18=INT(H18),H18<2958465,ISNUMBER(G18),H17=G18+1)),"",(12*(YEAR(H18+1)-YEAR(H17))+MONTH(H18+1)-MONTH(H17))-IF(EDATE(H17,(12*(YEAR(H18+1)-YEAR(H17))+MONTH(H18+1)-MONTH(H17)))>H18+1,1,0))) -> 12 | I20: =IF(COUNT(I17:I18,H18)<3,"",IF(NOT(AND(I17>0,I18>=I17,I17=INT(I17),I18=INT(I18),I18<2958465,ISNUMBER(H18),I17=H18+1)),"",(12*(YEAR(I18+1)-YEAR(I17))+MONTH(I18+1)-MONTH(I17))-IF(EDATE(I17,(12*(YEAR(I18+1)-YEAR(I17))+MONTH(I18+1)-MONTH(I17)))>I18+1,1,0))) -> 6
C21: Partial month | D21: =IF(NOT(ISNUMBER(D20)),"",(D18+1-EDATE(D17,D20))/(EDATE(D17,D20+1)-EDATE(D17,D20))) -> 0 | E21: =IF(NOT(ISNUMBER(E20)),"",(E18+1-EDATE(E17,E20))/(EDATE(E17,E20+1)-EDATE(E17,E20))) -> 0 | F21: =IF(NOT(ISNUMBER(F20)),"",(F18+1-EDATE(F17,F20))/(EDATE(F17,F20+1)-EDATE(F17,F20))) -> 0 | G21: =IF(NOT(ISNUMBER(G20)),"",(G18+1-EDATE(G17,G20))/(EDATE(G17,G20+1)-EDATE(G17,G20))) -> 0 | H21: =IF(NOT(ISNUMBER(H20)),"",(H18+1-EDATE(H17,H20))/(EDATE(H17,H20+1)-EDATE(H17,H20))) -> 0 | I21: =IF(NOT(ISNUMBER(I20)),"",(I18+1-EDATE(I17,I20))/(EDATE(I17,I20+1)-EDATE(I17,I20))) -> 0
C22: Annual wage escalation — active | D22: =IF(ISNA(MATCH($D$4,$C$23:$C$25,0)),"",IF(INDEX(D23:D25,MATCH($D$4,$C$23:$C$25,0))="","",INDEX(D23:D25,MATCH($D$4,$C$23:$C$25,0)))) -> 0.03 | E22: =IF(ISNA(MATCH($D$4,$C$23:$C$25,0)),"",IF(INDEX(E23:E25,MATCH($D$4,$C$23:$C$25,0))="","",INDEX(E23:E25,MATCH($D$4,$C$23:$C$25,0)))) -> 0.03 | F22: =IF(ISNA(MATCH($D$4,$C$23:$C$25,0)),"",IF(INDEX(F23:F25,MATCH($D$4,$C$23:$C$25,0))="","",INDEX(F23:F25,MATCH($D$4,$C$23:$C$25,0)))) -> 0.03 | G22: =IF(ISNA(MATCH($D$4,$C$23:$C$25,0)),"",IF(INDEX(G23:G25,MATCH($D$4,$C$23:$C$25,0))="","",INDEX(G23:G25,MATCH($D$4,$C$23:$C$25,0)))) -> 0.03 | H22: =IF(ISNA(MATCH($D$4,$C$23:$C$25,0)),"",IF(INDEX(H23:H25,MATCH($D$4,$C$23:$C$25,0))="","",INDEX(H23:H25,MATCH($D$4,$C$23:$C$25,0)))) -> 0.03 | I22: =IF(H22="","",H22) -> 0.03
C23: Low | D23: 0.02 | E23: 0.02 | F23: 0.02 | G23: 0.02 | H23: 0.02 | I23: =IF(H23="","",H23) -> 0.02
C24: Base | D24: 0.03 | E24: 0.03 | F24: 0.03 | G24: 0.03 | H24: 0.03 | I24: =IF(H24="","",H24) -> 0.03
C25: High | D25: 0.04 | E25: 0.04 | F25: 0.04 | G25: 0.04 | H25: 0.04 | I25: =IF(H25="","",H25) -> 0.04
C28: Fringe, excluding paid leave — active | D28: =IF(ISNA(MATCH($D$4,$C$29:$C$31,0)),"",IF(INDEX(D29:D31,MATCH($D$4,$C$29:$C$31,0))="","",INDEX(D29:D31,MATCH($D$4,$C$29:$C$31,0)))) -> 0.25 | E28: =IF(ISNA(MATCH($D$4,$C$29:$C$31,0)),"",IF(INDEX(E29:E31,MATCH($D$4,$C$29:$C$31,0))="","",INDEX(E29:E31,MATCH($D$4,$C$29:$C$31,0)))) -> 0.25 | F28: =IF(ISNA(MATCH($D$4,$C$29:$C$31,0)),"",IF(INDEX(F29:F31,MATCH($D$4,$C$29:$C$31,0))="","",INDEX(F29:F31,MATCH($D$4,$C$29:$C$31,0)))) -> 0.25 | G28: =IF(ISNA(MATCH($D$4,$C$29:$C$31,0)),"",IF(INDEX(G29:G31,MATCH($D$4,$C$29:$C$31,0))="","",INDEX(G29:G31,MATCH($D$4,$C$29:$C$31,0)))) -> 0.25 | H28: =IF(ISNA(MATCH($D$4,$C$29:$C$31,0)),"",IF(INDEX(H29:H31,MATCH($D$4,$C$29:$C$31,0))="","",INDEX(H29:H31,MATCH($D$4,$C$29:$C$31,0)))) -> 0.25 | I28: =IF(H28="","",H28) -> 0.25
C29: Low | D29: 0.2 | E29: 0.2 | F29: 0.2 | G29: 0.2 | H29: 0.2 | I29: =IF(H29="","",H29) -> 0.2
C30: Base | D30: 0.25 | E30: 0.25 | F30: 0.25 | G30: 0.25 | H30: 0.25 | I30: =IF(H30="","",H30) -> 0.25
C31: High | D31: 0.3 | E31: 0.3 | F31: 0.3 | G31: 0.3 | H31: 0.3 | I31: =IF(H31="","",H31) -> 0.3
D33: Base | E33: Option 1 | F33: Option 2 | G33: Option 3 | H33: Option 4 | I33: Extension
C34: Overhead — active | D34: =IF(ISNA(MATCH($D$4,$C$35:$C$37,0)),"",IF(INDEX(D35:D37,MATCH($D$4,$C$35:$C$37,0))="","",INDEX(D35:D37,MATCH($D$4,$C$35:$C$37,0)))) -> 0.1 | E34: =IF(ISNA(MATCH($D$4,$C$35:$C$37,0)),"",IF(INDEX(E35:E37,MATCH($D$4,$C$35:$C$37,0))="","",INDEX(E35:E37,MATCH($D$4,$C$35:$C$37,0)))) -> 0.1 | F34: =IF(ISNA(MATCH($D$4,$C$35:$C$37,0)),"",IF(INDEX(F35:F37,MATCH($D$4,$C$35:$C$37,0))="","",INDEX(F35:F37,MATCH($D$4,$C$35:$C$37,0)))) -> 0.1 | G34: =IF(ISNA(MATCH($D$4,$C$35:$C$37,0)),"",IF(INDEX(G35:G37,MATCH($D$4,$C$35:$C$37,0))="","",INDEX(G35:G37,MATCH($D$4,$C$35:$C$37,0)))) -> 0.1 | H34: =IF(ISNA(MATCH($D$4,$C$35:$C$37,0)),"",IF(INDEX(H35:H37,MATCH($D$4,$C$35:$C$37,0))="","",INDEX(H35:H37,MATCH($D$4,$C$35:$C$37,0)))) -> 0.1 | I34: =IF(H34="","",H34) -> 0.1
C35: Low | D35: 0.08 | E35: 0.08 | F35: 0.08 | G35: 0.08 | H35: 0.08 | I35: =IF(H35="","",H35) -> 0.08
C36: Base | D36: 0.1 | E36: 0.1 | F36: 0.1 | G36: 0.1 | H36: 0.1 | I36: =IF(H36="","",H36) -> 0.1
C37: High | D37: 0.12 | E37: 0.12 | F37: 0.12 | G37: 0.12 | H37: 0.12 | I37: =IF(H37="","",H37) -> 0.12
C40: G&A — active | D40: =IF(ISNA(MATCH($D$4,$C$41:$C$43,0)),"",IF(INDEX(D41:D43,MATCH($D$4,$C$41:$C$43,0))="","",INDEX(D41:D43,MATCH($D$4,$C$41:$C$43,0)))) -> 0.1 | E40: =IF(ISNA(MATCH($D$4,$C$41:$C$43,0)),"",IF(INDEX(E41:E43,MATCH($D$4,$C$41:$C$43,0))="","",INDEX(E41:E43,MATCH($D$4,$C$41:$C$43,0)))) -> 0.1 | F40: =IF(ISNA(MATCH($D$4,$C$41:$C$43,0)),"",IF(INDEX(F41:F43,MATCH($D$4,$C$41:$C$43,0))="","",INDEX(F41:F43,MATCH($D$4,$C$41:$C$43,0)))) -> 0.1 | G40: =IF(ISNA(MATCH($D$4,$C$41:$C$43,0)),"",IF(INDEX(G41:G43,MATCH($D$4,$C$41:$C$43,0))="","",INDEX(G41:G43,MATCH($D$4,$C$41:$C$43,0)))) -> 0.1 | H40: =IF(ISNA(MATCH($D$4,$C$41:$C$43,0)),"",IF(INDEX(H41:H43,MATCH($D$4,$C$41:$C$43,0))="","",INDEX(H41:H43,MATCH($D$4,$C$41:$C$43,0)))) -> 0.1 | I40: =IF(H40="","",H40) -> 0.1
C41: Low | D41: 0.08 | E41: 0.08 | F41: 0.08 | G41: 0.08 | H41: 0.08 | I41: =IF(H41="","",H41) -> 0.08
C42: Base | D42: 0.1 | E42: 0.1 | F42: 0.1 | G42: 0.1 | H42: 0.1 | I42: =IF(H42="","",H42) -> 0.1
C43: High | D43: 0.12 | E43: 0.12 | F43: 0.12 | G43: 0.12 | H43: 0.12 | I43: =IF(H43="","",H43) -> 0.12
C46: Supplied-rate escalation — active | D46: =IF(ISNA(MATCH($D$4,$C$47:$C$49,0)),"",IF(INDEX(D47:D49,MATCH($D$4,$C$47:$C$49,0))="","",INDEX(D47:D49,MATCH($D$4,$C$47:$C$49,0)))) -> 0 | E46: =IF(ISNA(MATCH($D$4,$C$47:$C$49,0)),"",IF(INDEX(E47:E49,MATCH($D$4,$C$47:$C$49,0))="","",INDEX(E47:E49,MATCH($D$4,$C$47:$C$49,0)))) -> 0 | F46: =IF(ISNA(MATCH($D$4,$C$47:$C$49,0)),"",IF(INDEX(F47:F49,MATCH($D$4,$C$47:$C$49,0))="","",INDEX(F47:F49,MATCH($D$4,$C$47:$C$49,0)))) -> 0 | G46: =IF(ISNA(MATCH($D$4,$C$47:$C$49,0)),"",IF(INDEX(G47:G49,MATCH($D$4,$C$47:$C$49,0))="","",INDEX(G47:G49,MATCH($D$4,$C$47:$C$49,0)))) -> 0 | H46: =IF(ISNA(MATCH($D$4,$C$47:$C$49,0)),"",IF(INDEX(H47:H49,MATCH($D$4,$C$47:$C$49,0))="","",INDEX(H47:H49,MATCH($D$4,$C$47:$C$49,0)))) -> 0 | I46: =IF(H46="","",H46) -> 0
C47: Low | D47: 0 | E47: 0 | F47: 0 | G47: 0 | H47: 0 | I47: =IF(H47="","",H47) -> 0
C48: Base | D48: 0 | E48: 0 | F48: 0 | G48: 0 | H48: 0 | I48: =IF(H48="","",H48) -> 0
C49: High | D49: 0 | E49: 0 | F49: 0 | G49: 0 | H49: 0 | I49: =IF(H49="","",H49) -> 0
C52: Wage escalation: fixed annual assumption. The base wage is adjusted from its benchmark year to the first pricing year; each later option uses that period’s active rate.
C54: Supplied-rate escalation: applies only to a supplied loaded base rate. Zero holds it flat. A period override replaces only that period; the extension defaults to Option 4’s final rate.
C56: Low/Base/High company-cost assumptions are illustrative. Dates must be consecutive. The extension inherits Option 4 cost assumptions; its quantities and duration remain separate.

Sheet Staffing
C2: Staffing
C4: Scenario | D4: =Assumptions!$D$4 -> Base
D5: Base | E5: Option 1 | F5: Option 2 | G5: Option 3 | H5: Option 4 | I5: Extension
C8: R01 | D8: =IF(COUNTIFS('Source Data'!$C$21:$C$26,$C8)<>1,"",IF(INDEX('Source Data'!$D$21:$D$26,MATCH($C8,'Source Data'!$C$21:$C$26,0))="","",INDEX('Source Data'!$D$21:$D$26,MATCH($C8,'Source Data'!$C$21:$C$26,0)))) -> On-Site Supervisor
C9: Requested hours | D9: =IF(COUNTIFS('Source Data'!$C$30:$C$35,$C8)<>1,"",IF(INDEX('Source Data'!$D$30:$D$35,MATCH($C8,'Source Data'!$C$30:$C$35,0))="","",INDEX('Source Data'!$D$30:$D$35,MATCH($C8,'Source Data'!$C$30:$C$35,0)))) -> 2080 | E9: =IF(COUNTIFS('Source Data'!$C$30:$C$35,$C8)<>1,"",IF(INDEX('Source Data'!$E$30:$E$35,MATCH($C8,'Source Data'!$C$30:$C$35,0))="","",INDEX('Source Data'!$E$30:$E$35,MATCH($C8,'Source Data'!$C$30:$C$35,0)))) -> 2080 | F9: =IF(COUNTIFS('Source Data'!$C$30:$C$35,$C8)<>1,"",IF(INDEX('Source Data'!$F$30:$F$35,MATCH($C8,'Source Data'!$C$30:$C$35,0))="","",INDEX('Source Data'!$F$30:$F$35,MATCH($C8,'Source Data'!$C$30:$C$35,0)))) -> 2080 | G9: =IF(COUNTIFS('Source Data'!$C$30:$C$35,$C8)<>1,"",IF(INDEX('Source Data'!$G$30:$G$35,MATCH($C8,'Source Data'!$C$30:$C$35,0))="","",INDEX('Source Data'!$G$30:$G$35,MATCH($C8,'Source Data'!$C$30:$C$35,0)))) -> 2080 | H9: =IF(COUNTIFS('Source Data'!$C$30:$C$35,$C8)<>1,"",IF(INDEX('Source Data'!$H$30:$H$35,MATCH($C8,'Source Data'!$C$30:$C$35,0))="","",INDEX('Source Data'!$H$30:$H$35,MATCH($C8,'Source Data'!$C$30:$C$35,0)))) -> 2080 | I9: =IF(COUNTIFS('Source Data'!$C$30:$C$35,$C8)<>1,"",IF(INDEX('Source Data'!$I$30:$I$35,MATCH($C8,'Source Data'!$C$30:$C$35,0))="","",INDEX('Source Data'!$I$30:$I$35,MATCH($C8,'Source Data'!$C$30:$C$35,0)))) -> 1040
C10: Estimated positions | D10: =IF(COUNTIFS('Source Data'!$C$21:$C$26,$C8)<>1,"",IF(INDEX('Source Data'!$E$21:$E$26,MATCH($C8,'Source Data'!$C$21:$C$26,0))="","",INDEX('Source Data'!$E$21:$E$26,MATCH($C8,'Source Data'!$C$21:$C$26,0)))) -> 1 | E10: =IF(COUNTIFS('Source Data'!$C$21:$C$26,$C8)<>1,"",IF(INDEX('Source Data'!$E$21:$E$26,MATCH($C8,'Source Data'!$C$21:$C$26,0))="","",INDEX('Source Data'!$E$21:$E$26,MATCH($C8,'Source Data'!$C$21:$C$26,0)))) -> 1 | F10: =IF(COUNTIFS('Source Data'!$C$21:$C$26,$C8)<>1,"",IF(INDEX('Source Data'!$E$21:$E$26,MATCH($C8,'Source Data'!$C$21:$C$26,0))="","",INDEX('Source Data'!$E$21:$E$26,MATCH($C8,'Source Data'!$C$21:$C$26,0)))) -> 1 | G10: =IF(COUNTIFS('Source Data'!$C$21:$C$26,$C8)<>1,"",IF(INDEX('Source Data'!$E$21:$E$26,MATCH($C8,'Source Data'!$C$21:$C$26,0))="","",INDEX('Source Data'!$E$21:$E$26,MATCH($C8,'Source Data'!$C$21:$C$26,0)))) -> 1 | H10: =IF(COUNTIFS('Source Data'!$C$21:$C$26,$C8)<>1,"",IF(INDEX('Source Data'!$E$21:$E$26,MATCH($C8,'Source Data'!$C$21:$C$26,0))="","",INDEX('Source Data'!$E$21:$E$26,MATCH($C8,'Source Data'!$C$21:$C$26,0)))) -> 1 | I10: =IF(COUNTIFS('Source Data'!$C$21:$C$26,$C8)<>1,"",IF(INDEX('Source Data'!$E$21:$E$26,MATCH($C8,'Source Data'!$C$21:$C$26,0))="","",INDEX('Source Data'!$E$21:$E$26,MATCH($C8,'Source Data'!$C$21:$C$26,0)))) -> 1
C11: Required paid FTE | D11: =IF(COUNT(D9,Assumptions!$D$7,Assumptions!$D$8,Assumptions!D$19)<4,"",IF(OR(D9<0,Assumptions!$D$7<=Assumptions!$D$8,Assumptions!$D$8<0,Assumptions!D$19<=0),"",D9/((Assumptions!$D$7-Assumptions!$D$8)*Assumptions!D$19))) -> 1.1304348 | E11: =IF(COUNT(E9,Assumptions!$D$7,Assumptions!$D$8,Assumptions!E$19)<4,"",IF(OR(E9<0,Assumptions!$D$7<=Assumptions!$D$8,Assumptions!$D$8<0,Assumptions!E$19<=0),"",E9/((Assumptions!$D$7-Assumptions!$D$8)*Assumptions!E$19))) -> 1.1304348 | F11: =IF(COUNT(F9,Assumptions!$D$7,Assumptions!$D$8,Assumptions!F$19)<4,"",IF(OR(F9<0,Assumptions!$D$7<=Assumptions!$D$8,Assumptions!$D$8<0,Assumptions!F$19<=0),"",F9/((Assumptions!$D$7-Assumptions!$D$8)*Assumptions!F$19))) -> 1.1304348 | G11: =IF(COUNT(G9,Assumptions!$D$7,Assumptions!$D$8,Assumptions!G$19)<4,"",IF(OR(G9<0,Assumptions!$D$7<=Assumptions!$D$8,Assumptions!$D$8<0,Assumptions!G$19<=0),"",G9/((Assumptions!$D$7-Assumptions!$D$8)*Assumptions!G$19))) -> 1.1304348 | H11: =IF(COUNT(H9,Assumptions!$D$7,Assumptions!$D$8,Assumptions!H$19)<4,"",IF(OR(H9<0,Assumptions!$D$7<=Assumptions!$D$8,Assumptions!$D$8<0,Assumptions!H$19<=0),"",H9/((Assumptions!$D$7-Assumptions!$D$8)*Assumptions!H$19))) -> 1.1304348 | I11: =IF(COUNT(I9,Assumptions!$D$7,Assumptions!$D$8,Assumptions!I$19)<4,"",IF(OR(I9<0,Assumptions!$D$7<=Assumptions!$D$8,Assumptions!$D$8<0,Assumptions!I$19<=0),"",I9/((Assumptions!$D$7-Assumptions!$D$8)*Assumptions!I$19))) -> 1.1304348
C12: Proposed FTE override
C13: Paid FTE used | D13: =IF(D12="",IF(D11="","",D11),IF(AND(ISNUMBER(D12),D12>=0),D12,"")) -> 1.1304348 | E13: =IF(E12="",IF(E11="","",E11),IF(AND(ISNUMBER(E12),E12>=0),E12,"")) -> 1.1304348 | F13: =IF(F12="",IF(F11="","",F11),IF(AND(ISNUMBER(F12),F12>=0),F12,"")) -> 1.1304348 | G13: =IF(G12="",IF(G11="","",G11),IF(AND(ISNUMBER(G12),G12>=0),G12,"")) -> 1.1304348 | H13: =IF(H12="",IF(H11="","",H11),IF(AND(ISNUMBER(H12),H12>=0),H12,"")) -> 1.1304348 | I13: =IF(I12="",IF(I11="","",I11),IF(AND(ISNUMBER(I12),I12>=0),I12,"")) -> 1.1304348
C14: Available billable hours | D14: =IF(OR(COUNT(D13,Assumptions!$D$7,Assumptions!$D$8,Assumptions!D$19)<4,Assumptions!$D$7<=Assumptions!$D$8,Assumptions!$D$8<0,Assumptions!D$19<=0),"",D13*(Assumptions!$D$7-Assumptions!$D$8)*Assumptions!D$19) -> 2080 | E14: =IF(OR(COUNT(E13,Assumptions!$D$7,Assumptions!$D$8,Assumptions!E$19)<4,Assumptions!$D$7<=Assumptions!$D$8,Assumptions!$D$8<0,Assumptions!E$19<=0),"",E13*(Assumptions!$D$7-Assumptions!$D$8)*Assumptions!E$19) -> 2080 | F14: =IF(OR(COUNT(F13,Assumptions!$D$7,Assumptions!$D$8,Assumptions!F$19)<4,Assumptions!$D$7<=Assumptions!$D$8,Assumptions!$D$8<0,Assumptions!F$19<=0),"",F13*(Assumptions!$D$7-Assumptions!$D$8)*Assumptions!F$19) -> 2080 | G14: =IF(OR(COUNT(G13,Assumptions!$D$7,Assumptions!$D$8,Assumptions!G$19)<4,Assumptions!$D$7<=Assumptions!$D$8,Assumptions!$D$8<0,Assumptions!G$19<=0),"",G13*(Assumptions!$D$7-Assumptions!$D$8)*Assumptions!G$19) -> 2080 | H14: =IF(OR(COUNT(H13,Assumptions!$D$7,Assumptions!$D$8,Assumptions!H$19)<4,Assumptions!$D$7<=Assumptions!$D$8,Assumptions!$D$8<0,Assumptions!H$19<=0),"",H13*(Assumptions!$D$7-Assumptions!$D$8)*Assumptions!H$19) -> 2080 | I14: =IF(OR(COUNT(I13,Assumptions!$D$7,Assumptions!$D$8,Assumptions!I$19)<4,Assumptions!$D$7<=Assumptions!$D$8,Assumptions!$D$8<0,Assumptions!I$19<=0),"",I13*(Assumptions!$D$7-Assumptions!$D$8)*Assumptions!I$19) -> 1040
C15: Hours above / (below) need | D15: =IF(COUNT(D14,D9)<2,"",D14-D9) -> 0 | E15: =IF(COUNT(E14,E9)<2,"",E14-E9) -> 0 | F15: =IF(COUNT(F14,F9)<2,"",F14-F9) -> 0 | G15: =IF(COUNT(G14,G9)<2,"",G14-G9) -> 0 | H15: =IF(COUNT(H14,H9)<2,"",H14-H9) -> 0 | I15: =IF(COUNT(I14,I9)<2,"",I14-I9) -> 0
C16: Paid hours for cost | D16: =IF(OR(COUNT(D13,Assumptions!$D$7,Assumptions!D$19)<3,Assumptions!$D$7<=0,Assumptions!D$19<=0),"",D13*Assumptions!$D$7*Assumptions!D$19) -> 2351.3043 | E16: =IF(OR(COUNT(E13,Assumptions!$D$7,Assumptions!E$19)<3,Assumptions!$D$7<=0,Assumptions!E$19<=0),"",E13*Assumptions!$D$7*Assumptions!E$19) -> 2351.3043 | F16: =IF(OR(COUNT(F13,Assumptions!$D$7,Assumptions!F$19)<3,Assumptions!$D$7<=0,Assumptions!F$19<=0),"",F13*Assumptions!$D$7*Assumptions!F$19) -> 2351.3043 | G16: =IF(OR(COUNT(G13,Assumptions!$D$7,Assumptions!G$19)<3,Assumptions!$D$7<=0,Assumptions!G$19<=0),"",G13*Assumptions!$D$7*Assumptions!G$19) -> 2351.3043 | H16: =IF(OR(COUNT(H13,Assumptions!$D$7,Assumptions!H$19)<3,Assumptions!$D$7<=0,Assumptions!H$19<=0),"",H13*Assumptions!$D$7*Assumptions!H$19) -> 2351.3043 | I16: =IF(OR(COUNT(I13,Assumptions!$D$7,Assumptions!I$19)<3,Assumptions!$D$7<=0,Assumptions!I$19<=0),"",I13*Assumptions!$D$7*Assumptions!I$19) -> 1175.6522
C17: Input status | D17: =IF(COUNTIFS('Source Data'!$C$21:$C$26,$C8)<>1,"Duplicate / missing role",IF(OR($D8="",COUNT(D9:D10)<2,COUNT(D11,D13,D15)<3),"Missing / invalid",IF(OR(D9<0,D10<0),"Invalid input",IF(D15<-0.01,"Staffing shortfall","Complete")))) -> Complete | E17: =IF(COUNTIFS('Source Data'!$C$21:$C$26,$C8)<>1,"Duplicate / missing role",IF(OR($D8="",COUNT(E9:E10)<2,COUNT(E11,E13,E15)<3),"Missing / invalid",IF(OR(E9<0,E10<0),"Invalid input",IF(E15<-0.01,"Staffing shortfall","Complete")))) -> Complete | F17: =IF(COUNTIFS('Source Data'!$C$21:$C$26,$C8)<>1,"Duplicate / missing role",IF(OR($D8="",COUNT(F9:F10)<2,COUNT(F11,F13,F15)<3),"Missing / invalid",IF(OR(F9<0,F10<0),"Invalid input",IF(F15<-0.01,"Staffing shortfall","Complete")))) -> Complete | G17: =IF(COUNTIFS('Source Data'!$C$21:$C$26,$C8)<>1,"Duplicate / missing role",IF(OR($D8="",COUNT(G9:G10)<2,COUNT(G11,G13,G15)<3),"Missing / invalid",IF(OR(G9<0,G10<0),"Invalid input",IF(G15<-0.01,"Staffing shortfall","Complete")))) -> Complete | H17: =IF(COUNTIFS('Source Data'!$C$21:$C$26,$C8)<>1,"Duplicate / missing role",IF(OR($D8="",COUNT(H9:H10)<2,COUNT(H11,H13,H15)<3),"Missing / invalid",IF(OR(H9<0,H10<0),"Invalid input",IF(H15<-0.01,"Staffing shortfall","Complete")))) -> Complete | I17: =IF(COUNTIFS('Source Data'!$C$21:$C$26,$C8)<>1,"Duplicate / missing role",IF(OR($D8="",COUNT(I9:I10)<2,COUNT(I11,I13,I15)<3),"Missing / invalid",IF(OR(I9<0,I10<0),"Invalid input",IF(I15<-0.01,"Staffing shortfall","Complete")))) -> Complete
C20: R02 | D20: =IF(COUNTIFS('Source Data'!$C$21:$C$26,$C20)<>1,"",IF(INDEX('Source Data'!$D$21:$D$26,MATCH($C20,'Source Data'!$C$21:$C$26,0))="","",INDEX('Source Data'!$D$21:$D$26,MATCH($C20,'Source Data'!$C$21:$C$26,0)))) -> Financial Analyst
C21: Requested hours | D21: =IF(COUNTIFS('Source Data'!$C$30:$C$35,$C20)<>1,"",IF(INDEX('Source Data'!$D$30:$D$35,MATCH($C20,'Source Data'!$C$30:$C$35,0))="","",INDEX('Source Data'!$D$30:$D$35,MATCH($C20,'Source Data'!$C$30:$C$35,0)))) -> 4160 | E21: =IF(COUNTIFS('Source Data'!$C$30:$C$35,$C20)<>1,"",IF(INDEX('Source Data'!$E$30:$E$35,MATCH($C20,'Source Data'!$C$30:$C$35,0))="","",INDEX('Source Data'!$E$30:$E$35,MATCH($C20,'Source Data'!$C$30:$C$35,0)))) -> 4160 | F21: =IF(COUNTIFS('Source Data'!$C$30:$C$35,$C20)<>1,"",IF(INDEX('Source Data'!$F$30:$F$35,MATCH($C20,'Source Data'!$C$30:$C$35,0))="","",INDEX('Source Data'!$F$30:$F$35,MATCH($C20,'Source Data'!$C$30:$C$35,0)))) -> 4160 | G21: =IF(COUNTIFS('Source Data'!$C$30:$C$35,$C20)<>1,"",IF(INDEX('Source Data'!$G$30:$G$35,MATCH($C20,'Source Data'!$C$30:$C$35,0))="","",INDEX('Source Data'!$G$30:$G$35,MATCH($C20,'Source Data'!$C$30:$C$35,0)))) -> 4160 | H21: =IF(COUNTIFS('Source Data'!$C$30:$C$35,$C20)<>1,"",IF(INDEX('Source Data'!$H$30:$H$35,MATCH($C20,'Source Data'!$C$30:$C$35,0))="","",INDEX('Source Data'!$H$30:$H$35,MATCH($C20,'Source Data'!$C$30:$C$35,0)))) -> 4160 | I21: =IF(COUNTIFS('Source Data'!$C$30:$C$35,$C20)<>1,"",IF(INDEX('Source Data'!$I$30:$I$35,MATCH($C20,'Source Data'!$C$30:$C$35,0))="","",INDEX('Source Data'!$I$30:$I$35,MATCH($C20,'Source Data'!$C$30:$C$35,0)))) -> 2080
C22: Estimated positions | D22: =IF(COUNTIFS('Source Data'!$C$21:$C$26,$C20)<>1,"",IF(INDEX('Source Data'!$E$21:$E$26,MATCH($C20,'Source Data'!$C$21:$C$26,0))="","",INDEX('Source Data'!$E$21:$E$26,MATCH($C20,'Source Data'!$C$21:$C$26,0)))) -> 2 | E22: =IF(COUNTIFS('Source Data'!$C$21:$C$26,$C20)<>1,"",IF(INDEX('Source Data'!$E$21:$E$26,MATCH($C20,'Source Data'!$C$21:$C$26,0))="","",INDEX('Source Data'!$E$21:$E$26,MATCH($C20,'Source Data'!$C$21:$C$26,0)))) -> 2 | F22: =IF(COUNTIFS('Source Data'!$C$21:$C$26,$C20)<>1,"",IF(INDEX('Source Data'!$E$21:$E$26,MATCH($C20,'Source Data'!$C$21:$C$26,0))="","",INDEX('Source Data'!$E$21:$E$26,MATCH($C20,'Source Data'!$C$21:$C$26,0)))) -> 2 | G22: =IF(COUNTIFS('Source Data'!$C$21:$C$26,$C20)<>1,"",IF(INDEX('Source Data'!$E$21:$E$26,MATCH($C20,'Source Data'!$C$21:$C$26,0))="","",INDEX('Source Data'!$E$21:$E$26,MATCH($C20,'Source Data'!$C$21:$C$26,0)))) -> 2 | H22: =IF(COUNTIFS('Source Data'!$C$21:$C$26,$C20)<>1,"",IF(INDEX('Source Data'!$E$21:$E$26,MATCH($C20,'Source Data'!$C$21:$C$26,0))="","",INDEX('Source Data'!$E$21:$E$26,MATCH($C20,'Source Data'!$C$21:$C$26,0)))) -> 2 | I22: =IF(COUNTIFS('Source Data'!$C$21:$C$26,$C20)<>1,"",IF(INDEX('Source Data'!$E$21:$E$26,MATCH($C20,'Source Data'!$C$21:$C$26,0))="","",INDEX('Source Data'!$E$21:$E$26,MATCH($C20,'Source Data'!$C$21:$C$26,0)))) -> 2
C23: Required paid FTE | D23: =IF(COUNT(D21,Assumptions!$D$7,Assumptions!$D$8,Assumptions!D$19)<4,"",IF(OR(D21<0,Assumptions!$D$7<=Assumptions!$D$8,Assumptions!$D$8<0,Assumptions!D$19<=0),"",D21/((Assumptions!$D$7-Assumptions!$D$8)*Assumptions!D$19))) -> 2.2608696 | E23: =IF(COUNT(E21,Assumptions!$D$7,Assumptions!$D$8,Assumptions!E$19)<4,"",IF(OR(E21<0,Assumptions!$D$7<=Assumptions!$D$8,Assumptions!$D$8<0,Assumptions!E$19<=0),"",E21/((Assumptions!$D$7-Assumptions!$D$8)*Assumptions!E$19))) -> 2.2608696 | F23: =IF(COUNT(F21,Assumptions!$D$7,Assumptions!$D$8,Assumptions!F$19)<4,"",IF(OR(F21<0,Assumptions!$D$7<=Assumptions!$D$8,Assumptions!$D$8<0,Assumptions!F$19<=0),"",F21/((Assumptions!$D$7-Assumptions!$D$8)*Assumptions!F$19))) -> 2.2608696 | G23: =IF(COUNT(G21,Assumptions!$D$7,Assumptions!$D$8,Assumptions!G$19)<4,"",IF(OR(G21<0,Assumptions!$D$7<=Assumptions!$D$8,Assumptions!$D$8<0,Assumptions!G$19<=0),"",G21/((Assumptions!$D$7-Assumptions!$D$8)*Assumptions!G$19))) -> 2.2608696 | H23: =IF(COUNT(H21,Assumptions!$D$7,Assumptions!$D$8,Assumptions!H$19)<4,"",IF(OR(H21<0,Assumptions!$D$7<=Assumptions!$D$8,Assumptions!$D$8<0,Assumptions!H$19<=0),"",H21/((Assumptions!$D$7-Assumptions!$D$8)*Assumptions!H$19))) -> 2.2608696 | I23: =IF(COUNT(I21,Assumptions!$D$7,Assumptions!$D$8,Assumptions!I$19)<4,"",IF(OR(I21<0,Assumptions!$D$7<=Assumptions!$D$8,Assumptions!$D$8<0,Assumptions!I$19<=0),"",I21/((Assumptions!$D$7-Assumptions!$D$8)*Assumptions!I$19))) -> 2.2608696
C24: Proposed FTE override
C25: Paid FTE used | D25: =IF(D24="",IF(D23="","",D23),IF(AND(ISNUMBER(D24),D24>=0),D24,"")) -> 2.2608696 | E25: =IF(E24="",IF(E23="","",E23),IF(AND(ISNUMBER(E24),E24>=0),E24,"")) -> 2.2608696 | F25: =IF(F24="",IF(F23="","",F23),IF(AND(ISNUMBER(F24),F24>=0),F24,"")) -> 2.2608696 | G25: =IF(G24="",IF(G23="","",G23),IF(AND(ISNUMBER(G24),G24>=0),G24,"")) -> 2.2608696 | H25: =IF(H24="",IF(H23="","",H23),IF(AND(ISNUMBER(H24),H24>=0),H24,"")) -> 2.2608696 | I25: =IF(I24="",IF(I23="","",I23),IF(AND(ISNUMBER(I24),I24>=0),I24,"")) -> 2.2608696
C26: Available billable hours | D26: =IF(OR(COUNT(D25,Assumptions!$D$7,Assumptions!$D$8,Assumptions!D$19)<4,Assumptions!$D$7<=Assumptions!$D$8,Assumptions!$D$8<0,Assumptions!D$19<=0),"",D25*(Assumptions!$D$7-Assumptions!$D$8)*Assumptions!D$19) -> 4160 | E26: =IF(OR(COUNT(E25,Assumptions!$D$7,Assumptions!$D$8,Assumptions!E$19)<4,Assumptions!$D$7<=Assumptions!$D$8,Assumptions!$D$8<0,Assumptions!E$19<=0),"",E25*(Assumptions!$D$7-Assumptions!$D$8)*Assumptions!E$19) -> 4160 | F26: =IF(OR(COUNT(F25,Assumptions!$D$7,Assumptions!$D$8,Assumptions!F$19)<4,Assumptions!$D$7<=Assumptions!$D$8,Assumptions!$D$8<0,Assumptions!F$19<=0),"",F25*(Assumptions!$D$7-Assumptions!$D$8)*Assumptions!F$19) -> 4160 | G26: =IF(OR(COUNT(G25,Assumptions!$D$7,Assumptions!$D$8,Assumptions!G$19)<4,Assumptions!$D$7<=Assumptions!$D$8,Assumptions!$D$8<0,Assumptions!G$19<=0),"",G25*(Assumptions!$D$7-Assumptions!$D$8)*Assumptions!G$19) -> 4160 | H26: =IF(OR(COUNT(H25,Assumptions!$D$7,Assumptions!$D$8,Assumptions!H$19)<4,Assumptions!$D$7<=Assumptions!$D$8,Assumptions!$D$8<0,Assumptions!H$19<=0),"",H25*(Assumptions!$D$7-Assumptions!$D$8)*Assumptions!H$19) -> 4160 | I26: =IF(OR(COUNT(I25,Assumptions!$D$7,Assumptions!$D$8,Assumptions!I$19)<4,Assumptions!$D$7<=Assumptions!$D$8,Assumptions!$D$8<0,Assumptions!I$19<=0),"",I25*(Assumptions!$D$7-Assumptions!$D$8)*Assumptions!I$19) -> 2080
C27: Hours above / (below) need | D27: =IF(COUNT(D26,D21)<2,"",D26-D21) -> 0 | E27: =IF(COUNT(E26,E21)<2,"",E26-E21) -> 0 | F27: =IF(COUNT(F26,F21)<2,"",F26-F21) -> 0 | G27: =IF(COUNT(G26,G21)<2,"",G26-G21) -> 0 | H27: =IF(COUNT(H26,H21)<2,"",H26-H21) -> 0 | I27: =IF(COUNT(I26,I21)<2,"",I26-I21) -> 0
C28: Paid hours for cost | D28: =IF(OR(COUNT(D25,Assumptions!$D$7,Assumptions!D$19)<3,Assumptions!$D$7<=0,Assumptions!D$19<=0),"",D25*Assumptions!$D$7*Assumptions!D$19) -> 4702.6087 | E28: =IF(OR(COUNT(E25,Assumptions!$D$7,Assumptions!E$19)<3,Assumptions!$D$7<=0,Assumptions!E$19<=0),"",E25*Assumptions!$D$7*Assumptions!E$19) -> 4702.6087 | F28: =IF(OR(COUNT(F25,Assumptions!$D$7,Assumptions!F$19)<3,Assumptions!$D$7<=0,Assumptions!F$19<=0),"",F25*Assumptions!$D$7*Assumptions!F$19) -> 4702.6087 | G28: =IF(OR(COUNT(G25,Assumptions!$D$7,Assumptions!G$19)<3,Assumptions!$D$7<=0,Assumptions!G$19<=0),"",G25*Assumptions!$D$7*Assumptions!G$19) -> 4702.6087 | H28: =IF(OR(COUNT(H25,Assumptions!$D$7,Assumptions!H$19)<3,Assumptions!$D$7<=0,Assumptions!H$19<=0),"",H25*Assumptions!$D$7*Assumptions!H$19) -> 4702.6087 | I28: =IF(OR(COUNT(I25,Assumptions!$D$7,Assumptions!I$19)<3,Assumptions!$D$7<=0,Assumptions!I$19<=0),"",I25*Assumptions!$D$7*Assumptions!I$19) -> 2351.3043
C29: Input status | D29: =IF(COUNTIFS('Source Data'!$C$21:$C$26,$C20)<>1,"Duplicate / missing role",IF(OR($D20="",COUNT(D21:D22)<2,COUNT(D23,D25,D27)<3),"Missing / invalid",IF(OR(D21<0,D22<0),"Invalid input",IF(D27<-0.01,"Staffing shortfall","Complete")))) -> Complete | E29: =IF(COUNTIFS('Source Data'!$C$21:$C$26,$C20)<>1,"Duplicate / missing role",IF(OR($D20="",COUNT(E21:E22)<2,COUNT(E23,E25,E27)<3),"Missing / invalid",IF(OR(E21<0,E22<0),"Invalid input",IF(E27<-0.01,"Staffing shortfall","Complete")))) -> Complete | F29: =IF(COUNTIFS('Source Data'!$C$21:$C$26,$C20)<>1,"Duplicate / missing role",IF(OR($D20="",COUNT(F21:F22)<2,COUNT(F23,F25,F27)<3),"Missing / invalid",IF(OR(F21<0,F22<0),"Invalid input",IF(F27<-0.01,"Staffing shortfall","Complete")))) -> Complete | G29: =IF(COUNTIFS('Source Data'!$C$21:$C$26,$C20)<>1,"Duplicate / missing role",IF(OR($D20="",COUNT(G21:G22)<2,COUNT(G23,G25,G27)<3),"Missing / invalid",IF(OR(G21<0,G22<0),"Invalid input",IF(G27<-0.01,"Staffing shortfall","Complete")))) -> Complete | H29: =IF(COUNTIFS('Source Data'!$C$21:$C$26,$C20)<>1,"Duplicate / missing role",IF(OR($D20="",COUNT(H21:H22)<2,COUNT(H23,H25,H27)<3),"Missing / invalid",IF(OR(H21<0,H22<0),"Invalid input",IF(H27<-0.01,"Staffing shortfall","Complete")))) -> Complete | I29: =IF(COUNTIFS('Source Data'!$C$21:$C$26,$C20)<>1,"Duplicate / missing role",IF(OR($D20="",COUNT(I21:I22)<2,COUNT(I23,I25,I27)<3),"Missing / invalid",IF(OR(I21<0,I22<0),"Invalid input",IF(I27<-0.01,"Staffing shortfall","Complete")))) -> Complete
C32: R03 | D32: =IF(COUNTIFS('Source Data'!$C$21:$C$26,$C32)<>1,"",IF(INDEX('Source Data'!$D$21:$D$26,MATCH($C32,'Source Data'!$C$21:$C$26,0))="","",INDEX('Source Data'!$D$21:$D$26,MATCH($C32,'Source Data'!$C$21:$C$26,0)))) -> Administrative Assistant
C33: Requested hours | D33: =IF(COUNTIFS('Source Data'!$C$30:$C$35,$C32)<>1,"",IF(INDEX('Source Data'!$D$30:$D$35,MATCH($C32,'Source Data'!$C$30:$C$35,0))="","",INDEX('Source Data'!$D$30:$D$35,MATCH($C32,'Source Data'!$C$30:$C$35,0)))) -> 2080 | E33: =IF(COUNTIFS('Source Data'!$C$30:$C$35,$C32)<>1,"",IF(INDEX('Source Data'!$E$30:$E$35,MATCH($C32,'Source Data'!$C$30:$C$35,0))="","",INDEX('Source Data'!$E$30:$E$35,MATCH($C32,'Source Data'!$C$30:$C$35,0)))) -> 2080 | F33: =IF(COUNTIFS('Source Data'!$C$30:$C$35,$C32)<>1,"",IF(INDEX('Source Data'!$F$30:$F$35,MATCH($C32,'Source Data'!$C$30:$C$35,0))="","",INDEX('Source Data'!$F$30:$F$35,MATCH($C32,'Source Data'!$C$30:$C$35,0)))) -> 2080 | G33: =IF(COUNTIFS('Source Data'!$C$30:$C$35,$C32)<>1,"",IF(INDEX('Source Data'!$G$30:$G$35,MATCH($C32,'Source Data'!$C$30:$C$35,0))="","",INDEX('Source Data'!$G$30:$G$35,MATCH($C32,'Source Data'!$C$30:$C$35,0)))) -> 2080 | H33: =IF(COUNTIFS('Source Data'!$C$30:$C$35,$C32)<>1,"",IF(INDEX('Source Data'!$H$30:$H$35,MATCH($C32,'Source Data'!$C$30:$C$35,0))="","",INDEX('Source Data'!$H$30:$H$35,MATCH($C32,'Source Data'!$C$30:$C$35,0)))) -> 2080 | I33: =IF(COUNTIFS('Source Data'!$C$30:$C$35,$C32)<>1,"",IF(INDEX('Source Data'!$I$30:$I$35,MATCH($C32,'Source Data'!$C$30:$C$35,0))="","",INDEX('Source Data'!$I$30:$I$35,MATCH($C32,'Source Data'!$C$30:$C$35,0)))) -> 1040
C34: Estimated positions | D34: =IF(COUNTIFS('Source Data'!$C$21:$C$26,$C32)<>1,"",IF(INDEX('Source Data'!$E$21:$E$26,MATCH($C32,'Source Data'!$C$21:$C$26,0))="","",INDEX('Source Data'!$E$21:$E$26,MATCH($C32,'Source Data'!$C$21:$C$26,0)))) -> 1 | E34: =IF(COUNTIFS('Source Data'!$C$21:$C$26,$C32)<>1,"",IF(INDEX('Source Data'!$E$21:$E$26,MATCH($C32,'Source Data'!$C$21:$C$26,0))="","",INDEX('Source Data'!$E$21:$E$26,MATCH($C32,'Source Data'!$C$21:$C$26,0)))) -> 1 | F34: =IF(COUNTIFS('Source Data'!$C$21:$C$26,$C32)<>1,"",IF(INDEX('Source Data'!$E$21:$E$26,MATCH($C32,'Source Data'!$C$21:$C$26,0))="","",INDEX('Source Data'!$E$21:$E$26,MATCH($C32,'Source Data'!$C$21:$C$26,0)))) -> 1 | G34: =IF(COUNTIFS('Source Data'!$C$21:$C$26,$C32)<>1,"",IF(INDEX('Source Data'!$E$21:$E$26,MATCH($C32,'Source Data'!$C$21:$C$26,0))="","",INDEX('Source Data'!$E$21:$E$26,MATCH($C32,'Source Data'!$C$21:$C$26,0)))) -> 1 | H34: =IF(COUNTIFS('Source Data'!$C$21:$C$26,$C32)<>1,"",IF(INDEX('Source Data'!$E$21:$E$26,MATCH($C32,'Source Data'!$C$21:$C$26,0))="","",INDEX('Source Data'!$E$21:$E$26,MATCH($C32,'Source Data'!$C$21:$C$26,0)))) -> 1 | I34: =IF(COUNTIFS('Source Data'!$C$21:$C$26,$C32)<>1,"",IF(INDEX('Source Data'!$E$21:$E$26,MATCH($C32,'Source Data'!$C$21:$C$26,0))="","",INDEX('Source Data'!$E$21:$E$26,MATCH($C32,'Source Data'!$C$21:$C$26,0)))) -> 1
C35: Required paid FTE | D35: =IF(COUNT(D33,Assumptions!$D$7,Assumptions!$D$8,Assumptions!D$19)<4,"",IF(OR(D33<0,Assumptions!$D$7<=Assumptions!$D$8,Assumptions!$D$8<0,Assumptions!D$19<=0),"",D33/((Assumptions!$D$7-Assumptions!$D$8)*Assumptions!D$19))) -> 1.1304348 | E35: =IF(COUNT(E33,Assumptions!$D$7,Assumptions!$D$8,Assumptions!E$19)<4,"",IF(OR(E33<0,Assumptions!$D$7<=Assumptions!$D$8,Assumptions!$D$8<0,Assumptions!E$19<=0),"",E33/((Assumptions!$D$7-Assumptions!$D$8)*Assumptions!E$19))) -> 1.1304348 | F35: =IF(COUNT(F33,Assumptions!$D$7,Assumptions!$D$8,Assumptions!F$19)<4,"",IF(OR(F33<0,Assumptions!$D$7<=Assumptions!$D$8,Assumptions!$D$8<0,Assumptions!F$19<=0),"",F33/((Assumptions!$D$7-Assumptions!$D$8)*Assumptions!F$19))) -> 1.1304348 | G35: =IF(COUNT(G33,Assumptions!$D$7,Assumptions!$D$8,Assumptions!G$19)<4,"",IF(OR(G33<0,Assumptions!$D$7<=Assumptions!$D$8,Assumptions!$D$8<0,Assumptions!G$19<=0),"",G33/((Assumptions!$D$7-Assumptions!$D$8)*Assumptions!G$19))) -> 1.1304348 | H35: =IF(COUNT(H33,Assumptions!$D$7,Assumptions!$D$8,Assumptions!H$19)<4,"",IF(OR(H33<0,Assumptions!$D$7<=Assumptions!$D$8,Assumptions!$D$8<0,Assumptions!H$19<=0),"",H33/((Assumptions!$D$7-Assumptions!$D$8)*Assumptions!H$19))) -> 1.1304348 | I35: =IF(COUNT(I33,Assumptions!$D$7,Assumptions!$D$8,Assumptions!I$19)<4,"",IF(OR(I33<0,Assumptions!$D$7<=Assumptions!$D$8,Assumptions!$D$8<0,Assumptions!I$19<=0),"",I33/((Assumptions!$D$7-Assumptions!$D$8)*Assumptions!I$19))) -> 1.1304348
C36: Proposed FTE override
C37: Paid FTE used | D37: =IF(D36="",IF(D35="","",D35),IF(AND(ISNUMBER(D36),D36>=0),D36,"")) -> 1.1304348 | E37: =IF(E36="",IF(E35="","",E35),IF(AND(ISNUMBER(E36),E36>=0),E36,"")) -> 1.1304348 | F37: =IF(F36="",IF(F35="","",F35),IF(AND(ISNUMBER(F36),F36>=0),F36,"")) -> 1.1304348 | G37: =IF(G36="",IF(G35="","",G35),IF(AND(ISNUMBER(G36),G36>=0),G36,"")) -> 1.1304348 | H37: =IF(H36="",IF(H35="","",H35),IF(AND(ISNUMBER(H36),H36>=0),H36,"")) -> 1.1304348 | I37: =IF(I36="",IF(I35="","",I35),IF(AND(ISNUMBER(I36),I36>=0),I36,"")) -> 1.1304348
C38: Available billable hours | D38: =IF(OR(COUNT(D37,Assumptions!$D$7,Assumptions!$D$8,Assumptions!D$19)<4,Assumptions!$D$7<=Assumptions!$D$8,Assumptions!$D$8<0,Assumptions!D$19<=0),"",D37*(Assumptions!$D$7-Assumptions!$D$8)*Assumptions!D$19) -> 2080 | E38: =IF(OR(COUNT(E37,Assumptions!$D$7,Assumptions!$D$8,Assumptions!E$19)<4,Assumptions!$D$7<=Assumptions!$D$8,Assumptions!$D$8<0,Assumptions!E$19<=0),"",E37*(Assumptions!$D$7-Assumptions!$D$8)*Assumptions!E$19) -> 2080 | F38: =IF(OR(COUNT(F37,Assumptions!$D$7,Assumptions!$D$8,Assumptions!F$19)<4,Assumptions!$D$7<=Assumptions!$D$8,Assumptions!$D$8<0,Assumptions!F$19<=0),"",F37*(Assumptions!$D$7-Assumptions!$D$8)*Assumptions!F$19) -> 2080 | G38: =IF(OR(COUNT(G37,Assumptions!$D$7,Assumptions!$D$8,Assumptions!G$19)<4,Assumptions!$D$7<=Assumptions!$D$8,Assumptions!$D$8<0,Assumptions!G$19<=0),"",G37*(Assumptions!$D$7-Assumptions!$D$8)*Assumptions!G$19) -> 2080 | H38: =IF(OR(COUNT(H37,Assumptions!$D$7,Assumptions!$D$8,Assumptions!H$19)<4,Assumptions!$D$7<=Assumptions!$D$8,Assumptions!$D$8<0,Assumptions!H$19<=0),"",H37*(Assumptions!$D$7-Assumptions!$D$8)*Assumptions!H$19) -> 2080 | I38: =IF(OR(COUNT(I37,Assumptions!$D$7,Assumptions!$D$8,Assumptions!I$19)<4,Assumptions!$D$7<=Assumptions!$D$8,Assumptions!$D$8<0,Assumptions!I$19<=0),"",I37*(Assumptions!$D$7-Assumptions!$D$8)*Assumptions!I$19) -> 1040
C39: Hours above / (below) need | D39: =IF(COUNT(D38,D33)<2,"",D38-D33) -> 0 | E39: =IF(COUNT(E38,E33)<2,"",E38-E33) -> 0 | F39: =IF(COUNT(F38,F33)<2,"",F38-F33) -> 0 | G39: =IF(COUNT(G38,G33)<2,"",G38-G33) -> 0 | H39: =IF(COUNT(H38,H33)<2,"",H38-H33) -> 0 | I39: =IF(COUNT(I38,I33)<2,"",I38-I33) -> 0
C40: Paid hours for cost | D40: =IF(OR(COUNT(D37,Assumptions!$D$7,Assumptions!D$19)<3,Assumptions!$D$7<=0,Assumptions!D$19<=0),"",D37*Assumptions!$D$7*Assumptions!D$19) -> 2351.3043 | E40: =IF(OR(COUNT(E37,Assumptions!$D$7,Assumptions!E$19)<3,Assumptions!$D$7<=0,Assumptions!E$19<=0),"",E37*Assumptions!$D$7*Assumptions!E$19) -> 2351.3043 | F40: =IF(OR(COUNT(F37,Assumptions!$D$7,Assumptions!F$19)<3,Assumptions!$D$7<=0,Assumptions!F$19<=0),"",F37*Assumptions!$D$7*Assumptions!F$19) -> 2351.3043 | G40: =IF(OR(COUNT(G37,Assumptions!$D$7,Assumptions!G$19)<3,Assumptions!$D$7<=0,Assumptions!G$19<=0),"",G37*Assumptions!$D$7*Assumptions!G$19) -> 2351.3043 | H40: =IF(OR(COUNT(H37,Assumptions!$D$7,Assumptions!H$19)<3,Assumptions!$D$7<=0,Assumptions!H$19<=0),"",H37*Assumptions!$D$7*Assumptions!H$19) -> 2351.3043 | I40: =IF(OR(COUNT(I37,Assumptions!$D$7,Assumptions!I$19)<3,Assumptions!$D$7<=0,Assumptions!I$19<=0),"",I37*Assumptions!$D$7*Assumptions!I$19) -> 1175.6522
C41: Input status | D41: =IF(COUNTIFS('Source Data'!$C$21:$C$26,$C32)<>1,"Duplicate / missing role",IF(OR($D32="",COUNT(D33:D34)<2,COUNT(D35,D37,D39)<3),"Missing / invalid",IF(OR(D33<0,D34<0),"Invalid input",IF(D39<-0.01,"Staffing shortfall","Complete")))) -> Complete | E41: =IF(COUNTIFS('Source Data'!$C$21:$C$26,$C32)<>1,"Duplicate / missing role",IF(OR($D32="",COUNT(E33:E34)<2,COUNT(E35,E37,E39)<3),"Missing / invalid",IF(OR(E33<0,E34<0),"Invalid input",IF(E39<-0.01,"Staffing shortfall","Complete")))) -> Complete | F41: =IF(COUNTIFS('Source Data'!$C$21:$C$26,$C32)<>1,"Duplicate / missing role",IF(OR($D32="",COUNT(F33:F34)<2,COUNT(F35,F37,F39)<3),"Missing / invalid",IF(OR(F33<0,F34<0),"Invalid input",IF(F39<-0.01,"Staffing shortfall","Complete")))) -> Complete | G41: =IF(COUNTIFS('Source Data'!$C$21:$C$26,$C32)<>1,"Duplicate / missing role",IF(OR($D32="",COUNT(G33:G34)<2,COUNT(G35,G37,G39)<3),"Missing / invalid",IF(OR(G33<0,G34<0),"Invalid input",IF(G39<-0.01,"Staffing shortfall","Complete")))) -> Complete | H41: =IF(COUNTIFS('Source Data'!$C$21:$C$26,$C32)<>1,"Duplicate / missing role",IF(OR($D32="",COUNT(H33:H34)<2,COUNT(H35,H37,H39)<3),"Missing / invalid",IF(OR(H33<0,H34<0),"Invalid input",IF(H39<-0.01,"Staffing shortfall","Complete")))) -> Complete | I41: =IF(COUNTIFS('Source Data'!$C$21:$C$26,$C32)<>1,"Duplicate / missing role",IF(OR($D32="",COUNT(I33:I34)<2,COUNT(I35,I37,I39)<3),"Missing / invalid",IF(OR(I33<0,I34<0),"Invalid input",IF(I39<-0.01,"Staffing shortfall","Complete")))) -> Complete
C44: R04 | D44: =IF(COUNTIFS('Source Data'!$C$21:$C$26,$C44)<>1,"",IF(INDEX('Source Data'!$D$21:$D$26,MATCH($C44,'Source Data'!$C$21:$C$26,0))="","",INDEX('Source Data'!$D$21:$D$26,MATCH($C44,'Source Data'!$C$21:$C$26,0)))) -> Program Analyst I
C45: Requested hours | D45: =IF(COUNTIFS('Source Data'!$C$30:$C$35,$C44)<>1,"",IF(INDEX('Source Data'!$D$30:$D$35,MATCH($C44,'Source Data'!$C$30:$C$35,0))="","",INDEX('Source Data'!$D$30:$D$35,MATCH($C44,'Source Data'!$C$30:$C$35,0)))) -> 2080 | E45: =IF(COUNTIFS('Source Data'!$C$30:$C$35,$C44)<>1,"",IF(INDEX('Source Data'!$E$30:$E$35,MATCH($C44,'Source Data'!$C$30:$C$35,0))="","",INDEX('Source Data'!$E$30:$E$35,MATCH($C44,'Source Data'!$C$30:$C$35,0)))) -> 2080 | F45: =IF(COUNTIFS('Source Data'!$C$30:$C$35,$C44)<>1,"",IF(INDEX('Source Data'!$F$30:$F$35,MATCH($C44,'Source Data'!$C$30:$C$35,0))="","",INDEX('Source Data'!$F$30:$F$35,MATCH($C44,'Source Data'!$C$30:$C$35,0)))) -> 2080 | G45: =IF(COUNTIFS('Source Data'!$C$30:$C$35,$C44)<>1,"",IF(INDEX('Source Data'!$G$30:$G$35,MATCH($C44,'Source Data'!$C$30:$C$35,0))="","",INDEX('Source Data'!$G$30:$G$35,MATCH($C44,'Source Data'!$C$30:$C$35,0)))) -> 2080 | H45: =IF(COUNTIFS('Source Data'!$C$30:$C$35,$C44)<>1,"",IF(INDEX('Source Data'!$H$30:$H$35,MATCH($C44,'Source Data'!$C$30:$C$35,0))="","",INDEX('Source Data'!$H$30:$H$35,MATCH($C44,'Source Data'!$C$30:$C$35,0)))) -> 2080 | I45: =IF(COUNTIFS('Source Data'!$C$30:$C$35,$C44)<>1,"",IF(INDEX('Source Data'!$I$30:$I$35,MATCH($C44,'Source Data'!$C$30:$C$35,0))="","",INDEX('Source Data'!$I$30:$I$35,MATCH($C44,'Source Data'!$C$30:$C$35,0)))) -> 1040
C46: Estimated positions | D46: =IF(COUNTIFS('Source Data'!$C$21:$C$26,$C44)<>1,"",IF(INDEX('Source Data'!$E$21:$E$26,MATCH($C44,'Source Data'!$C$21:$C$26,0))="","",INDEX('Source Data'!$E$21:$E$26,MATCH($C44,'Source Data'!$C$21:$C$26,0)))) -> 1 | E46: =IF(COUNTIFS('Source Data'!$C$21:$C$26,$C44)<>1,"",IF(INDEX('Source Data'!$E$21:$E$26,MATCH($C44,'Source Data'!$C$21:$C$26,0))="","",INDEX('Source Data'!$E$21:$E$26,MATCH($C44,'Source Data'!$C$21:$C$26,0)))) -> 1 | F46: =IF(COUNTIFS('Source Data'!$C$21:$C$26,$C44)<>1,"",IF(INDEX('Source Data'!$E$21:$E$26,MATCH($C44,'Source Data'!$C$21:$C$26,0))="","",INDEX('Source Data'!$E$21:$E$26,MATCH($C44,'Source Data'!$C$21:$C$26,0)))) -> 1 | G46: =IF(COUNTIFS('Source Data'!$C$21:$C$26,$C44)<>1,"",IF(INDEX('Source Data'!$E$21:$E$26,MATCH($C44,'Source Data'!$C$21:$C$26,0))="","",INDEX('Source Data'!$E$21:$E$26,MATCH($C44,'Source Data'!$C$21:$C$26,0)))) -> 1 | H46: =IF(COUNTIFS('Source Data'!$C$21:$C$26,$C44)<>1,"",IF(INDEX('Source Data'!$E$21:$E$26,MATCH($C44,'Source Data'!$C$21:$C$26,0))="","",INDEX('Source Data'!$E$21:$E$26,MATCH($C44,'Source Data'!$C$21:$C$26,0)))) -> 1 | I46: =IF(COUNTIFS('Source Data'!$C$21:$C$26,$C44)<>1,"",IF(INDEX('Source Data'!$E$21:$E$26,MATCH($C44,'Source Data'!$C$21:$C$26,0))="","",INDEX('Source Data'!$E$21:$E$26,MATCH($C44,'Source Data'!$C$21:$C$26,0)))) -> 1
C47: Required paid FTE | D47: =IF(COUNT(D45,Assumptions!$D$7,Assumptions!$D$8,Assumptions!D$19)<4,"",IF(OR(D45<0,Assumptions!$D$7<=Assumptions!$D$8,Assumptions!$D$8<0,Assumptions!D$19<=0),"",D45/((Assumptions!$D$7-Assumptions!$D$8)*Assumptions!D$19))) -> 1.1304348 | E47: =IF(COUNT(E45,Assumptions!$D$7,Assumptions!$D$8,Assumptions!E$19)<4,"",IF(OR(E45<0,Assumptions!$D$7<=Assumptions!$D$8,Assumptions!$D$8<0,Assumptions!E$19<=0),"",E45/((Assumptions!$D$7-Assumptions!$D$8)*Assumptions!E$19))) -> 1.1304348 | F47: =IF(COUNT(F45,Assumptions!$D$7,Assumptions!$D$8,Assumptions!F$19)<4,"",IF(OR(F45<0,Assumptions!$D$7<=Assumptions!$D$8,Assumptions!$D$8<0,Assumptions!F$19<=0),"",F45/((Assumptions!$D$7-Assumptions!$D$8)*Assumptions!F$19))) -> 1.1304348 | G47: =IF(COUNT(G45,Assumptions!$D$7,Assumptions!$D$8,Assumptions!G$19)<4,"",IF(OR(G45<0,Assumptions!$D$7<=Assumptions!$D$8,Assumptions!$D$8<0,Assumptions!G$19<=0),"",G45/((Assumptions!$D$7-Assumptions!$D$8)*Assumptions!G$19))) -> 1.1304348 | H47: =IF(COUNT(H45,Assumptions!$D$7,Assumptions!$D$8,Assumptions!H$19)<4,"",IF(OR(H45<0,Assumptions!$D$7<=Assumptions!$D$8,Assumptions!$D$8<0,Assumptions!H$19<=0),"",H45/((Assumptions!$D$7-Assumptions!$D$8)*Assumptions!H$19))) -> 1.1304348 | I47: =IF(COUNT(I45,Assumptions!$D$7,Assumptions!$D$8,Assumptions!I$19)<4,"",IF(OR(I45<0,Assumptions!$D$7<=Assumptions!$D$8,Assumptions!$D$8<0,Assumptions!I$19<=0),"",I45/((Assumptions!$D$7-Assumptions!$D$8)*Assumptions!I$19))) -> 1.1304348
C48: Proposed FTE override
C49: Paid FTE used | D49: =IF(D48="",IF(D47="","",D47),IF(AND(ISNUMBER(D48),D48>=0),D48,"")) -> 1.1304348 | E49: =IF(E48="",IF(E47="","",E47),IF(AND(ISNUMBER(E48),E48>=0),E48,"")) -> 1.1304348 | F49: =IF(F48="",IF(F47="","",F47),IF(AND(ISNUMBER(F48),F48>=0),F48,"")) -> 1.1304348 | G49: =IF(G48="",IF(G47="","",G47),IF(AND(ISNUMBER(G48),G48>=0),G48,"")) -> 1.1304348 | H49: =IF(H48="",IF(H47="","",H47),IF(AND(ISNUMBER(H48),H48>=0),H48,"")) -> 1.1304348 | I49: =IF(I48="",IF(I47="","",I47),IF(AND(ISNUMBER(I48),I48>=0),I48,"")) -> 1.1304348
C50: Available billable hours | D50: =IF(OR(COUNT(D49,Assumptions!$D$7,Assumptions!$D$8,Assumptions!D$19)<4,Assumptions!$D$7<=Assumptions!$D$8,Assumptions!$D$8<0,Assumptions!D$19<=0),"",D49*(Assumptions!$D$7-Assumptions!$D$8)*Assumptions!D$19) -> 2080 | E50: =IF(OR(COUNT(E49,Assumptions!$D$7,Assumptions!$D$8,Assumptions!E$19)<4,Assumptions!$D$7<=Assumptions!$D$8,Assumptions!$D$8<0,Assumptions!E$19<=0),"",E49*(Assumptions!$D$7-Assumptions!$D$8)*Assumptions!E$19) -> 2080 | F50: =IF(OR(COUNT(F49,Assumptions!$D$7,Assumptions!$D$8,Assumptions!F$19)<4,Assumptions!$D$7<=Assumptions!$D$8,Assumptions!$D$8<0,Assumptions!F$19<=0),"",F49*(Assumptions!$D$7-Assumptions!$D$8)*Assumptions!F$19) -> 2080 | G50: =IF(OR(COUNT(G49,Assumptions!$D$7,Assumptions!$D$8,Assumptions!G$19)<4,Assumptions!$D$7<=Assumptions!$D$8,Assumptions!$D$8<0,Assumptions!G$19<=0),"",G49*(Assumptions!$D$7-Assumptions!$D$8)*Assumptions!G$19) -> 2080 | H50: =IF(OR(COUNT(H49,Assumptions!$D$7,Assumptions!$D$8,Assumptions!H$19)<4,Assumptions!$D$7<=Assumptions!$D$8,Assumptions!$D$8<0,Assumptions!H$19<=0),"",H49*(Assumptions!$D$7-Assumptions!$D$8)*Assumptions!H$19) -> 2080 | I50: =IF(OR(COUNT(I49,Assumptions!$D$7,Assumptions!$D$8,Assumptions!I$19)<4,Assumptions!$D$7<=Assumptions!$D$8,Assumptions!$D$8<0,Assumptions!I$19<=0),"",I49*(Assumptions!$D$7-Assumptions!$D$8)*Assumptions!I$19) -> 1040
C51: Hours above / (below) need | D51: =IF(COUNT(D50,D45)<2,"",D50-D45) -> 0 | E51: =IF(COUNT(E50,E45)<2,"",E50-E45) -> 0 | F51: =IF(COUNT(F50,F45)<2,"",F50-F45) -> 0 | G51: =IF(COUNT(G50,G45)<2,"",G50-G45) -> 0 | H51: =IF(COUNT(H50,H45)<2,"",H50-H45) -> 0 | I51: =IF(COUNT(I50,I45)<2,"",I50-I45) -> 0
C52: Paid hours for cost | D52: =IF(OR(COUNT(D49,Assumptions!$D$7,Assumptions!D$19)<3,Assumptions!$D$7<=0,Assumptions!D$19<=0),"",D49*Assumptions!$D$7*Assumptions!D$19) -> 2351.3043 | E52: =IF(OR(COUNT(E49,Assumptions!$D$7,Assumptions!E$19)<3,Assumptions!$D$7<=0,Assumptions!E$19<=0),"",E49*Assumptions!$D$7*Assumptions!E$19) -> 2351.3043 | F52: =IF(OR(COUNT(F49,Assumptions!$D$7,Assumptions!F$19)<3,Assumptions!$D$7<=0,Assumptions!F$19<=0),"",F49*Assumptions!$D$7*Assumptions!F$19) -> 2351.3043 | G52: =IF(OR(COUNT(G49,Assumptions!$D$7,Assumptions!G$19)<3,Assumptions!$D$7<=0,Assumptions!G$19<=0),"",G49*Assumptions!$D$7*Assumptions!G$19) -> 2351.3043 | H52: =IF(OR(COUNT(H49,Assumptions!$D$7,Assumptions!H$19)<3,Assumptions!$D$7<=0,Assumptions!H$19<=0),"",H49*Assumptions!$D$7*Assumptions!H$19) -> 2351.3043 | I52: =IF(OR(COUNT(I49,Assumptions!$D$7,Assumptions!I$19)<3,Assumptions!$D$7<=0,Assumptions!I$19<=0),"",I49*Assumptions!$D$7*Assumptions!I$19) -> 1175.6522
C53: Input status | D53: =IF(COUNTIFS('Source Data'!$C$21:$C$26,$C44)<>1,"Duplicate / missing role",IF(OR($D44="",COUNT(D45:D46)<2,COUNT(D47,D49,D51)<3),"Missing / invalid",IF(OR(D45<0,D46<0),"Invalid input",IF(D51<-0.01,"Staffing shortfall","Complete")))) -> Complete | E53: =IF(COUNTIFS('Source Data'!$C$21:$C$26,$C44)<>1,"Duplicate / missing role",IF(OR($D44="",COUNT(E45:E46)<2,COUNT(E47,E49,E51)<3),"Missing / invalid",IF(OR(E45<0,E46<0),"Invalid input",IF(E51<-0.01,"Staffing shortfall","Complete")))) -> Complete | F53: =IF(COUNTIFS('Source Data'!$C$21:$C$26,$C44)<>1,"Duplicate / missing role",IF(OR($D44="",COUNT(F45:F46)<2,COUNT(F47,F49,F51)<3),"Missing / invalid",IF(OR(F45<0,F46<0),"Invalid input",IF(F51<-0.01,"Staffing shortfall","Complete")))) -> Complete | G53: =IF(COUNTIFS('Source Data'!$C$21:$C$26,$C44)<>1,"Duplicate / missing role",IF(OR($D44="",COUNT(G45:G46)<2,COUNT(G47,G49,G51)<3),"Missing / invalid",IF(OR(G45<0,G46<0),"Invalid input",IF(G51<-0.01,"Staffing shortfall","Complete")))) -> Complete | H53: =IF(COUNTIFS('Source Data'!$C$21:$C$26,$C44)<>1,"Duplicate / missing role",IF(OR($D44="",COUNT(H45:H46)<2,COUNT(H47,H49,H51)<3),"Missing / invalid",IF(OR(H45<0,H46<0),"Invalid input",IF(H51<-0.01,"Staffing shortfall","Complete")))) -> Complete | I53: =IF(COUNTIFS('Source Data'!$C$21:$C$26,$C44)<>1,"Duplicate / missing role",IF(OR($D44="",COUNT(I45:I46)<2,COUNT(I47,I49,I51)<3),"Missing / invalid",IF(OR(I45<0,I46<0),"Invalid input",IF(I51<-0.01,"Staffing shortfall","Complete")))) -> Complete
C56: R05 | D56: =IF(COUNTIFS('Source Data'!$C$21:$C$26,$C56)<>1,"",IF(INDEX('Source Data'!$D$21:$D$26,MATCH($C56,'Source Data'!$C$21:$C$26,0))="","",INDEX('Source Data'!$D$21:$D$26,MATCH($C56,'Source Data'!$C$21:$C$26,0)))) -> Program Analyst II
C57: Requested hours | D57: =IF(COUNTIFS('Source Data'!$C$30:$C$35,$C56)<>1,"",IF(INDEX('Source Data'!$D$30:$D$35,MATCH($C56,'Source Data'!$C$30:$C$35,0))="","",INDEX('Source Data'!$D$30:$D$35,MATCH($C56,'Source Data'!$C$30:$C$35,0)))) -> 4160 | E57: =IF(COUNTIFS('Source Data'!$C$30:$C$35,$C56)<>1,"",IF(INDEX('Source Data'!$E$30:$E$35,MATCH($C56,'Source Data'!$C$30:$C$35,0))="","",INDEX('Source Data'!$E$30:$E$35,MATCH($C56,'Source Data'!$C$30:$C$35,0)))) -> 4160 | F57: =IF(COUNTIFS('Source Data'!$C$30:$C$35,$C56)<>1,"",IF(INDEX('Source Data'!$F$30:$F$35,MATCH($C56,'Source Data'!$C$30:$C$35,0))="","",INDEX('Source Data'!$F$30:$F$35,MATCH($C56,'Source Data'!$C$30:$C$35,0)))) -> 4160 | G57: =IF(COUNTIFS('Source Data'!$C$30:$C$35,$C56)<>1,"",IF(INDEX('Source Data'!$G$30:$G$35,MATCH($C56,'Source Data'!$C$30:$C$35,0))="","",INDEX('Source Data'!$G$30:$G$35,MATCH($C56,'Source Data'!$C$30:$C$35,0)))) -> 4160 | H57: =IF(COUNTIFS('Source Data'!$C$30:$C$35,$C56)<>1,"",IF(INDEX('Source Data'!$H$30:$H$35,MATCH($C56,'Source Data'!$C$30:$C$35,0))="","",INDEX('Source Data'!$H$30:$H$35,MATCH($C56,'Source Data'!$C$30:$C$35,0)))) -> 4160 | I57: =IF(COUNTIFS('Source Data'!$C$30:$C$35,$C56)<>1,"",IF(INDEX('Source Data'!$I$30:$I$35,MATCH($C56,'Source Data'!$C$30:$C$35,0))="","",INDEX('Source Data'!$I$30:$I$35,MATCH($C56,'Source Data'!$C$30:$C$35,0)))) -> 2080
C58: Estimated positions | D58: =IF(COUNTIFS('Source Data'!$C$21:$C$26,$C56)<>1,"",IF(INDEX('Source Data'!$E$21:$E$26,MATCH($C56,'Source Data'!$C$21:$C$26,0))="","",INDEX('Source Data'!$E$21:$E$26,MATCH($C56,'Source Data'!$C$21:$C$26,0)))) -> 2 | E58: =IF(COUNTIFS('Source Data'!$C$21:$C$26,$C56)<>1,"",IF(INDEX('Source Data'!$E$21:$E$26,MATCH($C56,'Source Data'!$C$21:$C$26,0))="","",INDEX('Source Data'!$E$21:$E$26,MATCH($C56,'Source Data'!$C$21:$C$26,0)))) -> 2 | F58: =IF(COUNTIFS('Source Data'!$C$21:$C$26,$C56)<>1,"",IF(INDEX('Source Data'!$E$21:$E$26,MATCH($C56,'Source Data'!$C$21:$C$26,0))="","",INDEX('Source Data'!$E$21:$E$26,MATCH($C56,'Source Data'!$C$21:$C$26,0)))) -> 2 | G58: =IF(COUNTIFS('Source Data'!$C$21:$C$26,$C56)<>1,"",IF(INDEX('Source Data'!$E$21:$E$26,MATCH($C56,'Source Data'!$C$21:$C$26,0))="","",INDEX('Source Data'!$E$21:$E$26,MATCH($C56,'Source Data'!$C$21:$C$26,0)))) -> 2 | H58: =IF(COUNTIFS('Source Data'!$C$21:$C$26,$C56)<>1,"",IF(INDEX('Source Data'!$E$21:$E$26,MATCH($C56,'Source Data'!$C$21:$C$26,0))="","",INDEX('Source Data'!$E$21:$E$26,MATCH($C56,'Source Data'!$C$21:$C$26,0)))) -> 2 | I58: =IF(COUNTIFS('Source Data'!$C$21:$C$26,$C56)<>1,"",IF(INDEX('Source Data'!$E$21:$E$26,MATCH($C56,'Source Data'!$C$21:$C$26,0))="","",INDEX('Source Data'!$E$21:$E$26,MATCH($C56,'Source Data'!$C$21:$C$26,0)))) -> 2
C59: Required paid FTE | D59: =IF(COUNT(D57,Assumptions!$D$7,Assumptions!$D$8,Assumptions!D$19)<4,"",IF(OR(D57<0,Assumptions!$D$7<=Assumptions!$D$8,Assumptions!$D$8<0,Assumptions!D$19<=0),"",D57/((Assumptions!$D$7-Assumptions!$D$8)*Assumptions!D$19))) -> 2.2608696 | E59: =IF(COUNT(E57,Assumptions!$D$7,Assumptions!$D$8,Assumptions!E$19)<4,"",IF(OR(E57<0,Assumptions!$D$7<=Assumptions!$D$8,Assumptions!$D$8<0,Assumptions!E$19<=0),"",E57/((Assumptions!$D$7-Assumptions!$D$8)*Assumptions!E$19))) -> 2.2608696 | F59: =IF(COUNT(F57,Assumptions!$D$7,Assumptions!$D$8,Assumptions!F$19)<4,"",IF(OR(F57<0,Assumptions!$D$7<=Assumptions!$D$8,Assumptions!$D$8<0,Assumptions!F$19<=0),"",F57/((Assumptions!$D$7-Assumptions!$D$8)*Assumptions!F$19))) -> 2.2608696 | G59: =IF(COUNT(G57,Assumptions!$D$7,Assumptions!$D$8,Assumptions!G$19)<4,"",IF(OR(G57<0,Assumptions!$D$7<=Assumptions!$D$8,Assumptions!$D$8<0,Assumptions!G$19<=0),"",G57/((Assumptions!$D$7-Assumptions!$D$8)*Assumptions!G$19))) -> 2.2608696 | H59: =IF(COUNT(H57,Assumptions!$D$7,Assumptions!$D$8,Assumptions!H$19)<4,"",IF(OR(H57<0,Assumptions!$D$7<=Assumptions!$D$8,Assumptions!$D$8<0,Assumptions!H$19<=0),"",H57/((Assumptions!$D$7-Assumptions!$D$8)*Assumptions!H$19))) -> 2.2608696 | I59: =IF(COUNT(I57,Assumptions!$D$7,Assumptions!$D$8,Assumptions!I$19)<4,"",IF(OR(I57<0,Assumptions!$D$7<=Assumptions!$D$8,Assumptions!$D$8<0,Assumptions!I$19<=0),"",I57/((Assumptions!$D$7-Assumptions!$D$8)*Assumptions!I$19))) -> 2.2608696
C60: Proposed FTE override
C61: Paid FTE used | D61: =IF(D60="",IF(D59="","",D59),IF(AND(ISNUMBER(D60),D60>=0),D60,"")) -> 2.2608696 | E61: =IF(E60="",IF(E59="","",E59),IF(AND(ISNUMBER(E60),E60>=0),E60,"")) -> 2.2608696 | F61: =IF(F60="",IF(F59="","",F59),IF(AND(ISNUMBER(F60),F60>=0),F60,"")) -> 2.2608696 | G61: =IF(G60="",IF(G59="","",G59),IF(AND(ISNUMBER(G60),G60>=0),G60,"")) -> 2.2608696 | H61: =IF(H60="",IF(H59="","",H59),IF(AND(ISNUMBER(H60),H60>=0),H60,"")) -> 2.2608696 | I61: =IF(I60="",IF(I59="","",I59),IF(AND(ISNUMBER(I60),I60>=0),I60,"")) -> 2.2608696
C62: Available billable hours | D62: =IF(OR(COUNT(D61,Assumptions!$D$7,Assumptions!$D$8,Assumptions!D$19)<4,Assumptions!$D$7<=Assumptions!$D$8,Assumptions!$D$8<0,Assumptions!D$19<=0),"",D61*(Assumptions!$D$7-Assumptions!$D$8)*Assumptions!D$19) -> 4160 | E62: =IF(OR(COUNT(E61,Assumptions!$D$7,Assumptions!$D$8,Assumptions!E$19)<4,Assumptions!$D$7<=Assumptions!$D$8,Assumptions!$D$8<0,Assumptions!E$19<=0),"",E61*(Assumptions!$D$7-Assumptions!$D$8)*Assumptions!E$19) -> 4160 | F62: =IF(OR(COUNT(F61,Assumptions!$D$7,Assumptions!$D$8,Assumptions!F$19)<4,Assumptions!$D$7<=Assumptions!$D$8,Assumptions!$D$8<0,Assumptions!F$19<=0),"",F61*(Assumptions!$D$7-Assumptions!$D$8)*Assumptions!F$19) -> 4160 | G62: =IF(OR(COUNT(G61,Assumptions!$D$7,Assumptions!$D$8,Assumptions!G$19)<4,Assumptions!$D$7<=Assumptions!$D$8,Assumptions!$D$8<0,Assumptions!G$19<=0),"",G61*(Assumptions!$D$7-Assumptions!$D$8)*Assumptions!G$19) -> 4160 | H62: =IF(OR(COUNT(H61,Assumptions!$D$7,Assumptions!$D$8,Assumptions!H$19)<4,Assumptions!$D$7<=Assumptions!$D$8,Assumptions!$D$8<0,Assumptions!H$19<=0),"",H61*(Assumptions!$D$7-Assumptions!$D$8)*Assumptions!H$19) -> 4160 | I62: =IF(OR(COUNT(I61,Assumptions!$D$7,Assumptions!$D$8,Assumptions!I$19)<4,Assumptions!$D$7<=Assumptions!$D$8,Assumptions!$D$8<0,Assumptions!I$19<=0),"",I61*(Assumptions!$D$7-Assumptions!$D$8)*Assumptions!I$19) -> 2080
C63: Hours above / (below) need | D63: =IF(COUNT(D62,D57)<2,"",D62-D57) -> 0 | E63: =IF(COUNT(E62,E57)<2,"",E62-E57) -> 0 | F63: =IF(COUNT(F62,F57)<2,"",F62-F57) -> 0 | G63: =IF(COUNT(G62,G57)<2,"",G62-G57) -> 0 | H63: =IF(COUNT(H62,H57)<2,"",H62-H57) -> 0 | I63: =IF(COUNT(I62,I57)<2,"",I62-I57) -> 0
C64: Paid hours for cost | D64: =IF(OR(COUNT(D61,Assumptions!$D$7,Assumptions!D$19)<3,Assumptions!$D$7<=0,Assumptions!D$19<=0),"",D61*Assumptions!$D$7*Assumptions!D$19) -> 4702.6087 | E64: =IF(OR(COUNT(E61,Assumptions!$D$7,Assumptions!E$19)<3,Assumptions!$D$7<=0,Assumptions!E$19<=0),"",E61*Assumptions!$D$7*Assumptions!E$19) -> 4702.6087 | F64: =IF(OR(COUNT(F61,Assumptions!$D$7,Assumptions!F$19)<3,Assumptions!$D$7<=0,Assumptions!F$19<=0),"",F61*Assumptions!$D$7*Assumptions!F$19) -> 4702.6087 | G64: =IF(OR(COUNT(G61,Assumptions!$D$7,Assumptions!G$19)<3,Assumptions!$D$7<=0,Assumptions!G$19<=0),"",G61*Assumptions!$D$7*Assumptions!G$19) -> 4702.6087 | H64: =IF(OR(COUNT(H61,Assumptions!$D$7,Assumptions!H$19)<3,Assumptions!$D$7<=0,Assumptions!H$19<=0),"",H61*Assumptions!$D$7*Assumptions!H$19) -> 4702.6087 | I64: =IF(OR(COUNT(I61,Assumptions!$D$7,Assumptions!I$19)<3,Assumptions!$D$7<=0,Assumptions!I$19<=0),"",I61*Assumptions!$D$7*Assumptions!I$19) -> 2351.3043
C65: Input status | D65: =IF(COUNTIFS('Source Data'!$C$21:$C$26,$C56)<>1,"Duplicate / missing role",IF(OR($D56="",COUNT(D57:D58)<2,COUNT(D59,D61,D63)<3),"Missing / invalid",IF(OR(D57<0,D58<0),"Invalid input",IF(D63<-0.01,"Staffing shortfall","Complete")))) -> Complete | E65: =IF(COUNTIFS('Source Data'!$C$21:$C$26,$C56)<>1,"Duplicate / missing role",IF(OR($D56="",COUNT(E57:E58)<2,COUNT(E59,E61,E63)<3),"Missing / invalid",IF(OR(E57<0,E58<0),"Invalid input",IF(E63<-0.01,"Staffing shortfall","Complete")))) -> Complete | F65: =IF(COUNTIFS('Source Data'!$C$21:$C$26,$C56)<>1,"Duplicate / missing role",IF(OR($D56="",COUNT(F57:F58)<2,COUNT(F59,F61,F63)<3),"Missing / invalid",IF(OR(F57<0,F58<0),"Invalid input",IF(F63<-0.01,"Staffing shortfall","Complete")))) -> Complete | G65: =IF(COUNTIFS('Source Data'!$C$21:$C$26,$C56)<>1,"Duplicate / missing role",IF(OR($D56="",COUNT(G57:G58)<2,COUNT(G59,G61,G63)<3),"Missing / invalid",IF(OR(G57<0,G58<0),"Invalid input",IF(G63<-0.01,"Staffing shortfall","Complete")))) -> Complete | H65: =IF(COUNTIFS('Source Data'!$C$21:$C$26,$C56)<>1,"Duplicate / missing role",IF(OR($D56="",COUNT(H57:H58)<2,COUNT(H59,H61,H63)<3),"Missing / invalid",IF(OR(H57<0,H58<0),"Invalid input",IF(H63<-0.01,"Staffing shortfall","Complete")))) -> Complete | I65: =IF(COUNTIFS('Source Data'!$C$21:$C$26,$C56)<>1,"Duplicate / missing role",IF(OR($D56="",COUNT(I57:I58)<2,COUNT(I59,I61,I63)<3),"Missing / invalid",IF(OR(I57<0,I58<0),"Invalid input",IF(I63<-0.01,"Staffing shortfall","Complete")))) -> Complete
C68: R06 | D68: =IF(COUNTIFS('Source Data'!$C$21:$C$26,$C68)<>1,"",IF(INDEX('Source Data'!$D$21:$D$26,MATCH($C68,'Source Data'!$C$21:$C$26,0))="","",INDEX('Source Data'!$D$21:$D$26,MATCH($C68,'Source Data'!$C$21:$C$26,0)))) -> Program Analyst III
C69: Requested hours | D69: =IF(COUNTIFS('Source Data'!$C$30:$C$35,$C68)<>1,"",IF(INDEX('Source Data'!$D$30:$D$35,MATCH($C68,'Source Data'!$C$30:$C$35,0))="","",INDEX('Source Data'!$D$30:$D$35,MATCH($C68,'Source Data'!$C$30:$C$35,0)))) -> 2080 | E69: =IF(COUNTIFS('Source Data'!$C$30:$C$35,$C68)<>1,"",IF(INDEX('Source Data'!$E$30:$E$35,MATCH($C68,'Source Data'!$C$30:$C$35,0))="","",INDEX('Source Data'!$E$30:$E$35,MATCH($C68,'Source Data'!$C$30:$C$35,0)))) -> 2080 | F69: =IF(COUNTIFS('Source Data'!$C$30:$C$35,$C68)<>1,"",IF(INDEX('Source Data'!$F$30:$F$35,MATCH($C68,'Source Data'!$C$30:$C$35,0))="","",INDEX('Source Data'!$F$30:$F$35,MATCH($C68,'Source Data'!$C$30:$C$35,0)))) -> 2080 | G69: =IF(COUNTIFS('Source Data'!$C$30:$C$35,$C68)<>1,"",IF(INDEX('Source Data'!$G$30:$G$35,MATCH($C68,'Source Data'!$C$30:$C$35,0))="","",INDEX('Source Data'!$G$30:$G$35,MATCH($C68,'Source Data'!$C$30:$C$35,0)))) -> 2080 | H69: =IF(COUNTIFS('Source Data'!$C$30:$C$35,$C68)<>1,"",IF(INDEX('Source Data'!$H$30:$H$35,MATCH($C68,'Source Data'!$C$30:$C$35,0))="","",INDEX('Source Data'!$H$30:$H$35,MATCH($C68,'Source Data'!$C$30:$C$35,0)))) -> 2080 | I69: =IF(COUNTIFS('Source Data'!$C$30:$C$35,$C68)<>1,"",IF(INDEX('Source Data'!$I$30:$I$35,MATCH($C68,'Source Data'!$C$30:$C$35,0))="","",INDEX('Source Data'!$I$30:$I$35,MATCH($C68,'Source Data'!$C$30:$C$35,0)))) -> 1040
C70: Estimated positions | D70: =IF(COUNTIFS('Source Data'!$C$21:$C$26,$C68)<>1,"",IF(INDEX('Source Data'!$E$21:$E$26,MATCH($C68,'Source Data'!$C$21:$C$26,0))="","",INDEX('Source Data'!$E$21:$E$26,MATCH($C68,'Source Data'!$C$21:$C$26,0)))) -> 1 | E70: =IF(COUNTIFS('Source Data'!$C$21:$C$26,$C68)<>1,"",IF(INDEX('Source Data'!$E$21:$E$26,MATCH($C68,'Source Data'!$C$21:$C$26,0))="","",INDEX('Source Data'!$E$21:$E$26,MATCH($C68,'Source Data'!$C$21:$C$26,0)))) -> 1 | F70: =IF(COUNTIFS('Source Data'!$C$21:$C$26,$C68)<>1,"",IF(INDEX('Source Data'!$E$21:$E$26,MATCH($C68,'Source Data'!$C$21:$C$26,0))="","",INDEX('Source Data'!$E$21:$E$26,MATCH($C68,'Source Data'!$C$21:$C$26,0)))) -> 1 | G70: =IF(COUNTIFS('Source Data'!$C$21:$C$26,$C68)<>1,"",IF(INDEX('Source Data'!$E$21:$E$26,MATCH($C68,'Source Data'!$C$21:$C$26,0))="","",INDEX('Source Data'!$E$21:$E$26,MATCH($C68,'Source Data'!$C$21:$C$26,0)))) -> 1 | H70: =IF(COUNTIFS('Source Data'!$C$21:$C$26,$C68)<>1,"",IF(INDEX('Source Data'!$E$21:$E$26,MATCH($C68,'Source Data'!$C$21:$C$26,0))="","",INDEX('Source Data'!$E$21:$E$26,MATCH($C68,'Source Data'!$C$21:$C$26,0)))) -> 1 | I70: =IF(COUNTIFS('Source Data'!$C$21:$C$26,$C68)<>1,"",IF(INDEX('Source Data'!$E$21:$E$26,MATCH($C68,'Source Data'!$C$21:$C$26,0))="","",INDEX('Source Data'!$E$21:$E$26,MATCH($C68,'Source Data'!$C$21:$C$26,0)))) -> 1
C71: Required paid FTE | D71: =IF(COUNT(D69,Assumptions!$D$7,Assumptions!$D$8,Assumptions!D$19)<4,"",IF(OR(D69<0,Assumptions!$D$7<=Assumptions!$D$8,Assumptions!$D$8<0,Assumptions!D$19<=0),"",D69/((Assumptions!$D$7-Assumptions!$D$8)*Assumptions!D$19))) -> 1.1304348 | E71: =IF(COUNT(E69,Assumptions!$D$7,Assumptions!$D$8,Assumptions!E$19)<4,"",IF(OR(E69<0,Assumptions!$D$7<=Assumptions!$D$8,Assumptions!$D$8<0,Assumptions!E$19<=0),"",E69/((Assumptions!$D$7-Assumptions!$D$8)*Assumptions!E$19))) -> 1.1304348 | F71: =IF(COUNT(F69,Assumptions!$D$7,Assumptions!$D$8,Assumptions!F$19)<4,"",IF(OR(F69<0,Assumptions!$D$7<=Assumptions!$D$8,Assumptions!$D$8<0,Assumptions!F$19<=0),"",F69/((Assumptions!$D$7-Assumptions!$D$8)*Assumptions!F$19))) -> 1.1304348 | G71: =IF(COUNT(G69,Assumptions!$D$7,Assumptions!$D$8,Assumptions!G$19)<4,"",IF(OR(G69<0,Assumptions!$D$7<=Assumptions!$D$8,Assumptions!$D$8<0,Assumptions!G$19<=0),"",G69/((Assumptions!$D$7-Assumptions!$D$8)*Assumptions!G$19))) -> 1.1304348 | H71: =IF(COUNT(H69,Assumptions!$D$7,Assumptions!$D$8,Assumptions!H$19)<4,"",IF(OR(H69<0,Assumptions!$D$7<=Assumptions!$D$8,Assumptions!$D$8<0,Assumptions!H$19<=0),"",H69/((Assumptions!$D$7-Assumptions!$D$8)*Assumptions!H$19))) -> 1.1304348 | I71: =IF(COUNT(I69,Assumptions!$D$7,Assumptions!$D$8,Assumptions!I$19)<4,"",IF(OR(I69<0,Assumptions!$D$7<=Assumptions!$D$8,Assumptions!$D$8<0,Assumptions!I$19<=0),"",I69/((Assumptions!$D$7-Assumptions!$D$8)*Assumptions!I$19))) -> 1.1304348
C72: Proposed FTE override
C73: Paid FTE used | D73: =IF(D72="",IF(D71="","",D71),IF(AND(ISNUMBER(D72),D72>=0),D72,"")) -> 1.1304348 | E73: =IF(E72="",IF(E71="","",E71),IF(AND(ISNUMBER(E72),E72>=0),E72,"")) -> 1.1304348 | F73: =IF(F72="",IF(F71="","",F71),IF(AND(ISNUMBER(F72),F72>=0),F72,"")) -> 1.1304348 | G73: =IF(G72="",IF(G71="","",G71),IF(AND(ISNUMBER(G72),G72>=0),G72,"")) -> 1.1304348 | H73: =IF(H72="",IF(H71="","",H71),IF(AND(ISNUMBER(H72),H72>=0),H72,"")) -> 1.1304348 | I73: =IF(I72="",IF(I71="","",I71),IF(AND(ISNUMBER(I72),I72>=0),I72,"")) -> 1.1304348
C74: Available billable hours | D74: =IF(OR(COUNT(D73,Assumptions!$D$7,Assumptions!$D$8,Assumptions!D$19)<4,Assumptions!$D$7<=Assumptions!$D$8,Assumptions!$D$8<0,Assumptions!D$19<=0),"",D73*(Assumptions!$D$7-Assumptions!$D$8)*Assumptions!D$19) -> 2080 | E74: =IF(OR(COUNT(E73,Assumptions!$D$7,Assumptions!$D$8,Assumptions!E$19)<4,Assumptions!$D$7<=Assumptions!$D$8,Assumptions!$D$8<0,Assumptions!E$19<=0),"",E73*(Assumptions!$D$7-Assumptions!$D$8)*Assumptions!E$19) -> 2080 | F74: =IF(OR(COUNT(F73,Assumptions!$D$7,Assumptions!$D$8,Assumptions!F$19)<4,Assumptions!$D$7<=Assumptions!$D$8,Assumptions!$D$8<0,Assumptions!F$19<=0),"",F73*(Assumptions!$D$7-Assumptions!$D$8)*Assumptions!F$19) -> 2080 | G74: =IF(OR(COUNT(G73,Assumptions!$D$7,Assumptions!$D$8,Assumptions!G$19)<4,Assumptions!$D$7<=Assumptions!$D$8,Assumptions!$D$8<0,Assumptions!G$19<=0),"",G73*(Assumptions!$D$7-Assumptions!$D$8)*Assumptions!G$19) -> 2080 | H74: =IF(OR(COUNT(H73,Assumptions!$D$7,Assumptions!$D$8,Assumptions!H$19)<4,Assumptions!$D$7<=Assumptions!$D$8,Assumptions!$D$8<0,Assumptions!H$19<=0),"",H73*(Assumptions!$D$7-Assumptions!$D$8)*Assumptions!H$19) -> 2080 | I74: =IF(OR(COUNT(I73,Assumptions!$D$7,Assumptions!$D$8,Assumptions!I$19)<4,Assumptions!$D$7<=Assumptions!$D$8,Assumptions!$D$8<0,Assumptions!I$19<=0),"",I73*(Assumptions!$D$7-Assumptions!$D$8)*Assumptions!I$19) -> 1040
C75: Hours above / (below) need | D75: =IF(COUNT(D74,D69)<2,"",D74-D69) -> 0 | E75: =IF(COUNT(E74,E69)<2,"",E74-E69) -> 0 | F75: =IF(COUNT(F74,F69)<2,"",F74-F69) -> 0 | G75: =IF(COUNT(G74,G69)<2,"",G74-G69) -> 0 | H75: =IF(COUNT(H74,H69)<2,"",H74-H69) -> 0 | I75: =IF(COUNT(I74,I69)<2,"",I74-I69) -> 0
C76: Paid hours for cost | D76: =IF(OR(COUNT(D73,Assumptions!$D$7,Assumptions!D$19)<3,Assumptions!$D$7<=0,Assumptions!D$19<=0),"",D73*Assumptions!$D$7*Assumptions!D$19) -> 2351.3043 | E76: =IF(OR(COUNT(E73,Assumptions!$D$7,Assumptions!E$19)<3,Assumptions!$D$7<=0,Assumptions!E$19<=0),"",E73*Assumptions!$D$7*Assumptions!E$19) -> 2351.3043 | F76: =IF(OR(COUNT(F73,Assumptions!$D$7,Assumptions!F$19)<3,Assumptions!$D$7<=0,Assumptions!F$19<=0),"",F73*Assumptions!$D$7*Assumptions!F$19) -> 2351.3043 | G76: =IF(OR(COUNT(G73,Assumptions!$D$7,Assumptions!G$19)<3,Assumptions!$D$7<=0,Assumptions!G$19<=0),"",G73*Assumptions!$D$7*Assumptions!G$19) -> 2351.3043 | H76: =IF(OR(COUNT(H73,Assumptions!$D$7,Assumptions!H$19)<3,Assumptions!$D$7<=0,Assumptions!H$19<=0),"",H73*Assumptions!$D$7*Assumptions!H$19) -> 2351.3043 | I76: =IF(OR(COUNT(I73,Assumptions!$D$7,Assumptions!I$19)<3,Assumptions!$D$7<=0,Assumptions!I$19<=0),"",I73*Assumptions!$D$7*Assumptions!I$19) -> 1175.6522
C77: Input status | D77: =IF(COUNTIFS('Source Data'!$C$21:$C$26,$C68)<>1,"Duplicate / missing role",IF(OR($D68="",COUNT(D69:D70)<2,COUNT(D71,D73,D75)<3),"Missing / invalid",IF(OR(D69<0,D70<0),"Invalid input",IF(D75<-0.01,"Staffing shortfall","Complete")))) -> Complete | E77: =IF(COUNTIFS('Source Data'!$C$21:$C$26,$C68)<>1,"Duplicate / missing role",IF(OR($D68="",COUNT(E69:E70)<2,COUNT(E71,E73,E75)<3),"Missing / invalid",IF(OR(E69<0,E70<0),"Invalid input",IF(E75<-0.01,"Staffing shortfall","Complete")))) -> Complete | F77: =IF(COUNTIFS('Source Data'!$C$21:$C$26,$C68)<>1,"Duplicate / missing role",IF(OR($D68="",COUNT(F69:F70)<2,COUNT(F71,F73,F75)<3),"Missing / invalid",IF(OR(F69<0,F70<0),"Invalid input",IF(F75<-0.01,"Staffing shortfall","Complete")))) -> Complete | G77: =IF(COUNTIFS('Source Data'!$C$21:$C$26,$C68)<>1,"Duplicate / missing role",IF(OR($D68="",COUNT(G69:G70)<2,COUNT(G71,G73,G75)<3),"Missing / invalid",IF(OR(G69<0,G70<0),"Invalid input",IF(G75<-0.01,"Staffing shortfall","Complete")))) -> Complete | H77: =IF(COUNTIFS('Source Data'!$C$21:$C$26,$C68)<>1,"Duplicate / missing role",IF(OR($D68="",COUNT(H69:H70)<2,COUNT(H71,H73,H75)<3),"Missing / invalid",IF(OR(H69<0,H70<0),"Invalid input",IF(H75<-0.01,"Staffing shortfall","Complete")))) -> Complete | I77: =IF(COUNTIFS('Source Data'!$C$21:$C$26,$C68)<>1,"Duplicate / missing role",IF(OR($D68="",COUNT(I69:I70)<2,COUNT(I71,I73,I75)<3),"Missing / invalid",IF(OR(I69<0,I70<0),"Invalid input",IF(I75<-0.01,"Staffing shortfall","Complete")))) -> Complete

Sheet Labor Rates
C2: Labor Rates
C4: Scenario | D4: =Assumptions!$D$4 -> Base
D5: Base | E5: Option 1 | F5: Option 2 | G5: Option 3 | H5: Option 4 | I5: Extension
C8: R01 | D8: =IF(COUNTIFS('Source Data'!$C$21:$C$26,$C8)<>1,"",IF(INDEX('Source Data'!$D$21:$D$26,MATCH($C8,'Source Data'!$C$21:$C$26,0))="","",INDEX('Source Data'!$D$21:$D$26,MATCH($C8,'Source Data'!$C$21:$C$26,0)))) -> On-Site Supervisor
C9: Rate basis | D9: =IF(COUNTIFS('Source Data'!$C$21:$C$26,$C8)<>1,"",IF(INDEX('Source Data'!$H$21:$H$26,MATCH($C8,'Source Data'!$C$21:$C$26,0))="","",INDEX('Source Data'!$H$21:$H$26,MATCH($C8,'Source Data'!$C$21:$C$26,0)))) -> Build from wage | E9: =IF(COUNTIFS('Source Data'!$C$21:$C$26,$C8)<>1,"",IF(INDEX('Source Data'!$H$21:$H$26,MATCH($C8,'Source Data'!$C$21:$C$26,0))="","",INDEX('Source Data'!$H$21:$H$26,MATCH($C8,'Source Data'!$C$21:$C$26,0)))) -> Build from wage | F9: =IF(COUNTIFS('Source Data'!$C$21:$C$26,$C8)<>1,"",IF(INDEX('Source Data'!$H$21:$H$26,MATCH($C8,'Source Data'!$C$21:$C$26,0))="","",INDEX('Source Data'!$H$21:$H$26,MATCH($C8,'Source Data'!$C$21:$C$26,0)))) -> Build from wage | G9: =IF(COUNTIFS('Source Data'!$C$21:$C$26,$C8)<>1,"",IF(INDEX('Source Data'!$H$21:$H$26,MATCH($C8,'Source Data'!$C$21:$C$26,0))="","",INDEX('Source Data'!$H$21:$H$26,MATCH($C8,'Source Data'!$C$21:$C$26,0)))) -> Build from wage | H9: =IF(COUNTIFS('Source Data'!$C$21:$C$26,$C8)<>1,"",IF(INDEX('Source Data'!$H$21:$H$26,MATCH($C8,'Source Data'!$C$21:$C$26,0))="","",INDEX('Source Data'!$H$21:$H$26,MATCH($C8,'Source Data'!$C$21:$C$26,0)))) -> Build from wage | I9: =IF(COUNTIFS('Source Data'!$C$21:$C$26,$C8)<>1,"",IF(INDEX('Source Data'!$H$21:$H$26,MATCH($C8,'Source Data'!$C$21:$C$26,0))="","",INDEX('Source Data'!$H$21:$H$26,MATCH($C8,'Source Data'!$C$21:$C$26,0)))) -> Build from wage
C10: Benchmark wage / hour | D10: =IF(COUNTIFS('Source Data'!$C$21:$C$26,$C8)<>1,"",IF(INDEX('Source Data'!$F$21:$F$26,MATCH($C8,'Source Data'!$C$21:$C$26,0))="","",INDEX('Source Data'!$F$21:$F$26,MATCH($C8,'Source Data'!$C$21:$C$26,0)))) -> 46.21 | E10: =IF(COUNTIFS('Source Data'!$C$21:$C$26,$C8)<>1,"",IF(INDEX('Source Data'!$F$21:$F$26,MATCH($C8,'Source Data'!$C$21:$C$26,0))="","",INDEX('Source Data'!$F$21:$F$26,MATCH($C8,'Source Data'!$C$21:$C$26,0)))) -> 46.21 | F10: =IF(COUNTIFS('Source Data'!$C$21:$C$26,$C8)<>1,"",IF(INDEX('Source Data'!$F$21:$F$26,MATCH($C8,'Source Data'!$C$21:$C$26,0))="","",INDEX('Source Data'!$F$21:$F$26,MATCH($C8,'Source Data'!$C$21:$C$26,0)))) -> 46.21 | G10: =IF(COUNTIFS('Source Data'!$C$21:$C$26,$C8)<>1,"",IF(INDEX('Source Data'!$F$21:$F$26,MATCH($C8,'Source Data'!$C$21:$C$26,0))="","",INDEX('Source Data'!$F$21:$F$26,MATCH($C8,'Source Data'!$C$21:$C$26,0)))) -> 46.21 | H10: =IF(COUNTIFS('Source Data'!$C$21:$C$26,$C8)<>1,"",IF(INDEX('Source Data'!$F$21:$F$26,MATCH($C8,'Source Data'!$C$21:$C$26,0))="","",INDEX('Source Data'!$F$21:$F$26,MATCH($C8,'Source Data'!$C$21:$C$26,0)))) -> 46.21 | I10: =IF(COUNTIFS('Source Data'!$C$21:$C$26,$C8)<>1,"",IF(INDEX('Source Data'!$F$21:$F$26,MATCH($C8,'Source Data'!$C$21:$C$26,0))="","",INDEX('Source Data'!$F$21:$F$26,MATCH($C8,'Source Data'!$C$21:$C$26,0)))) -> 46.21
C11: Benchmark year | D11: =IF(COUNTIFS('Source Data'!$C$21:$C$26,$C8)<>1,"",IF(INDEX('Source Data'!$G$21:$G$26,MATCH($C8,'Source Data'!$C$21:$C$26,0))="","",INDEX('Source Data'!$G$21:$G$26,MATCH($C8,'Source Data'!$C$21:$C$26,0)))) -> 2025 | E11: =IF(COUNTIFS('Source Data'!$C$21:$C$26,$C8)<>1,"",IF(INDEX('Source Data'!$G$21:$G$26,MATCH($C8,'Source Data'!$C$21:$C$26,0))="","",INDEX('Source Data'!$G$21:$G$26,MATCH($C8,'Source Data'!$C$21:$C$26,0)))) -> 2025 | F11: =IF(COUNTIFS('Source Data'!$C$21:$C$26,$C8)<>1,"",IF(INDEX('Source Data'!$G$21:$G$26,MATCH($C8,'Source Data'!$C$21:$C$26,0))="","",INDEX('Source Data'!$G$21:$G$26,MATCH($C8,'Source Data'!$C$21:$C$26,0)))) -> 2025 | G11: =IF(COUNTIFS('Source Data'!$C$21:$C$26,$C8)<>1,"",IF(INDEX('Source Data'!$G$21:$G$26,MATCH($C8,'Source Data'!$C$21:$C$26,0))="","",INDEX('Source Data'!$G$21:$G$26,MATCH($C8,'Source Data'!$C$21:$C$26,0)))) -> 2025 | H11: =IF(COUNTIFS('Source Data'!$C$21:$C$26,$C8)<>1,"",IF(INDEX('Source Data'!$G$21:$G$26,MATCH($C8,'Source Data'!$C$21:$C$26,0))="","",INDEX('Source Data'!$G$21:$G$26,MATCH($C8,'Source Data'!$C$21:$C$26,0)))) -> 2025 | I11: =IF(COUNTIFS('Source Data'!$C$21:$C$26,$C8)<>1,"",IF(INDEX('Source Data'!$G$21:$G$26,MATCH($C8,'Source Data'!$C$21:$C$26,0))="","",INDEX('Source Data'!$G$21:$G$26,MATCH($C8,'Source Data'!$C$21:$C$26,0)))) -> 2025
C12: Wage adjustment factor | D12: =IF(COUNT(D11,Assumptions!D$22,Assumptions!D$17)<3,"",IF(OR(Assumptions!D$22<0,Assumptions!D$22>1,YEAR(Assumptions!D$17)<D11),"",(1+Assumptions!D$22)^(YEAR(Assumptions!D$17)-D11))) -> 1.03 | E12: =IF(COUNT(E11,Assumptions!E$22,Assumptions!E$17)<3,"",IF(OR(Assumptions!E$22<0,Assumptions!E$22>1,YEAR(Assumptions!E$17)<E11),"",IF(D12="","",D12*(1+Assumptions!E$22)))) -> 1.0609 | F12: =IF(COUNT(F11,Assumptions!F$22,Assumptions!F$17)<3,"",IF(OR(Assumptions!F$22<0,Assumptions!F$22>1,YEAR(Assumptions!F$17)<F11),"",IF(E12="","",E12*(1+Assumptions!F$22)))) -> 1.092727 | G12: =IF(COUNT(G11,Assumptions!G$22,Assumptions!G$17)<3,"",IF(OR(Assumptions!G$22<0,Assumptions!G$22>1,YEAR(Assumptions!G$17)<G11),"",IF(F12="","",F12*(1+Assumptions!G$22)))) -> 1.1255088 | H12: =IF(COUNT(H11,Assumptions!H$22,Assumptions!H$17)<3,"",IF(OR(Assumptions!H$22<0,Assumptions!H$22>1,YEAR(Assumptions!H$17)<H11),"",IF(G12="","",G12*(1+Assumptions!H$22)))) -> 1.1592741 | I12: =IF(H12="","",H12) -> 1.1592741
C13: Adjusted wage / hour | D13: =IF(OR(D9<>"Build from wage",COUNT(D10,D12)<2,D10<0),"",D10*D12) -> 47.5963 | E13: =IF(OR(E9<>"Build from wage",COUNT(E10,E12)<2,E10<0),"",E10*E12) -> 49.024189 | F13: =IF(OR(F9<>"Build from wage",COUNT(F10,F12)<2,F10<0),"",F10*F12) -> 50.494915 | G13: =IF(OR(G9<>"Build from wage",COUNT(G10,G12)<2,G10<0),"",G10*G12) -> 52.009762 | H13: =IF(OR(H9<>"Build from wage",COUNT(H10,H12)<2,H10<0),"",H10*H12) -> 53.570055 | I13: =IF(OR(I9<>"Build from wage",COUNT(I10,I12)<2,I10<0),"",I10*I12) -> 53.570055
C14: Paid hours for cost | D14: =IF(Staffing!D16="","",Staffing!D16) -> 2351.3043 | E14: =IF(Staffing!E16="","",Staffing!E16) -> 2351.3043 | F14: =IF(Staffing!F16="","",Staffing!F16) -> 2351.3043 | G14: =IF(Staffing!G16="","",Staffing!G16) -> 2351.3043 | H14: =IF(Staffing!H16="","",Staffing!H16) -> 2351.3043 | I14: =IF(Staffing!I16="","",Staffing!I16) -> 1175.6522
C15: Paid labor cost | D15: =IF(COUNT(D13:D14)<2,"",D13*D14) -> 111913.39 | E15: =IF(COUNT(E13:E14)<2,"",E13*E14) -> 115270.79 | F15: =IF(COUNT(F13:F14)<2,"",F13*F14) -> 118728.91 | G15: =IF(COUNT(G13:G14)<2,"",G13*G14) -> 122290.78 | H15: =IF(COUNT(H13:H14)<2,"",H13*H14) -> 125959.5 | I15: =IF(COUNT(I13:I14)<2,"",I13*I14) -> 62979.752
C16: Fringe benefits | D16: =IF(OR(COUNT(D15,Assumptions!D$28)<2,Assumptions!D$28<0),"",D15*Assumptions!D$28) -> 27978.347 | E16: =IF(OR(COUNT(E15,Assumptions!E$28)<2,Assumptions!E$28<0),"",E15*Assumptions!E$28) -> 28817.697 | F16: =IF(OR(COUNT(F15,Assumptions!F$28)<2,Assumptions!F$28<0),"",F15*Assumptions!F$28) -> 29682.228 | G16: =IF(OR(COUNT(G15,Assumptions!G$28)<2,Assumptions!G$28<0),"",G15*Assumptions!G$28) -> 30572.695 | H16: =IF(OR(COUNT(H15,Assumptions!H$28)<2,Assumptions!H$28<0),"",H15*Assumptions!H$28) -> 31489.876 | I16: =IF(OR(COUNT(I15,Assumptions!I$28)<2,Assumptions!I$28<0),"",I15*Assumptions!I$28) -> 15744.938
C17: Additional hourly benefits | D17: =IF(OR(D9<>"Build from wage",COUNT(D14,Assumptions!$D$9)<2,Assumptions!$D$9<0),"",D14*Assumptions!$D$9) -> 0 | E17: =IF(OR(E9<>"Build from wage",COUNT(E14,Assumptions!$D$9)<2,Assumptions!$D$9<0),"",E14*Assumptions!$D$9) -> 0 | F17: =IF(OR(F9<>"Build from wage",COUNT(F14,Assumptions!$D$9)<2,Assumptions!$D$9<0),"",F14*Assumptions!$D$9) -> 0 | G17: =IF(OR(G9<>"Build from wage",COUNT(G14,Assumptions!$D$9)<2,Assumptions!$D$9<0),"",G14*Assumptions!$D$9) -> 0 | H17: =IF(OR(H9<>"Build from wage",COUNT(H14,Assumptions!$D$9)<2,Assumptions!$D$9<0),"",H14*Assumptions!$D$9) -> 0 | I17: =IF(OR(I9<>"Build from wage",COUNT(I14,Assumptions!$D$9)<2,Assumptions!$D$9<0),"",I14*Assumptions!$D$9) -> 0
C18: Labor plus benefits | D18: =IF(COUNT(D15:D17)<3,"",SUM(D15:D17)) -> 139891.73 | E18: =IF(COUNT(E15:E17)<3,"",SUM(E15:E17)) -> 144088.49 | F18: =IF(COUNT(F15:F17)<3,"",SUM(F15:F17)) -> 148411.14 | G18: =IF(COUNT(G15:G17)<3,"",SUM(G15:G17)) -> 152863.47 | H18: =IF(COUNT(H15:H17)<3,"",SUM(H15:H17)) -> 157449.38 | I18: =IF(COUNT(I15:I17)<3,"",SUM(I15:I17)) -> 78724.689
C19: Overhead | D19: =IF(OR(COUNT(D18,Assumptions!D$34)<2,Assumptions!D$34<0),"",D18*Assumptions!D$34) -> 13989.173 | E19: =IF(OR(COUNT(E18,Assumptions!E$34)<2,Assumptions!E$34<0),"",E18*Assumptions!E$34) -> 14408.849 | F19: =IF(OR(COUNT(F18,Assumptions!F$34)<2,Assumptions!F$34<0),"",F18*Assumptions!F$34) -> 14841.114 | G19: =IF(OR(COUNT(G18,Assumptions!G$34)<2,Assumptions!G$34<0),"",G18*Assumptions!G$34) -> 15286.347 | H19: =IF(OR(COUNT(H18,Assumptions!H$34)<2,Assumptions!H$34<0),"",H18*Assumptions!H$34) -> 15744.938 | I19: =IF(OR(COUNT(I18,Assumptions!I$34)<2,Assumptions!I$34<0),"",I18*Assumptions!I$34) -> 7872.4689
C20: Labor, benefits, overhead | D20: =IF(COUNT(D18:D19)<2,"",SUM(D18:D19)) -> 153880.91 | E20: =IF(COUNT(E18:E19)<2,"",SUM(E18:E19)) -> 158497.33 | F20: =IF(COUNT(F18:F19)<2,"",SUM(F18:F19)) -> 163252.25 | G20: =IF(COUNT(G18:G19)<2,"",SUM(G18:G19)) -> 168149.82 | H20: =IF(COUNT(H18:H19)<2,"",SUM(H18:H19)) -> 173194.32 | I20: =IF(COUNT(I18:I19)<2,"",SUM(I18:I19)) -> 86597.158
C21: G&A | D21: =IF(OR(COUNT(D20,Assumptions!D$40)<2,Assumptions!D$40<0),"",D20*Assumptions!D$40) -> 15388.091 | E21: =IF(OR(COUNT(E20,Assumptions!E$40)<2,Assumptions!E$40<0),"",E20*Assumptions!E$40) -> 15849.733 | F21: =IF(OR(COUNT(F20,Assumptions!F$40)<2,Assumptions!F$40<0),"",F20*Assumptions!F$40) -> 16325.225 | G21: =IF(OR(COUNT(G20,Assumptions!G$40)<2,Assumptions!G$40<0),"",G20*Assumptions!G$40) -> 16814.982 | H21: =IF(OR(COUNT(H20,Assumptions!H$40)<2,Assumptions!H$40<0),"",H20*Assumptions!H$40) -> 17319.432 | I21: =IF(OR(COUNT(I20,Assumptions!I$40)<2,Assumptions!I$40<0),"",I20*Assumptions!I$40) -> 8659.7158
C22: Total modeled cost | D22: =IF(COUNT(D20:D21)<2,"",SUM(D20:D21)) -> 169269 | E22: =IF(COUNT(E20:E21)<2,"",SUM(E20:E21)) -> 174347.07 | F22: =IF(COUNT(F20:F21)<2,"",SUM(F20:F21)) -> 179577.48 | G22: =IF(COUNT(G20:G21)<2,"",SUM(G20:G21)) -> 184964.8 | H22: =IF(COUNT(H20:H21)<2,"",SUM(H20:H21)) -> 190513.75 | I22: =IF(COUNT(I20:I21)<2,"",SUM(I20:I21)) -> 95256.874
C23: Target profit | D23: =IF(OR(COUNT(D22,Assumptions!$D$10)<2,Assumptions!$D$10<0),"",IF(Assumptions!$D$11="Profit on cost",D22*Assumptions!$D$10,IF(Assumptions!$D$11="Margin on sales",IF(Assumptions!$D$10>=1,"",D22/(1-Assumptions!$D$10)-D22),""))) -> 16926.9 | E23: =IF(OR(COUNT(E22,Assumptions!$D$10)<2,Assumptions!$D$10<0),"",IF(Assumptions!$D$11="Profit on cost",E22*Assumptions!$D$10,IF(Assumptions!$D$11="Margin on sales",IF(Assumptions!$D$10>=1,"",E22/(1-Assumptions!$D$10)-E22),""))) -> 17434.707 | F23: =IF(OR(COUNT(F22,Assumptions!$D$10)<2,Assumptions!$D$10<0),"",IF(Assumptions!$D$11="Profit on cost",F22*Assumptions!$D$10,IF(Assumptions!$D$11="Margin on sales",IF(Assumptions!$D$10>=1,"",F22/(1-Assumptions!$D$10)-F22),""))) -> 17957.748 | G23: =IF(OR(COUNT(G22,Assumptions!$D$10)<2,Assumptions!$D$10<0),"",IF(Assumptions!$D$11="Profit on cost",G22*Assumptions!$D$10,IF(Assumptions!$D$11="Margin on sales",IF(Assumptions!$D$10>=1,"",G22/(1-Assumptions!$D$10)-G22),""))) -> 18496.48 | H23: =IF(OR(COUNT(H22,Assumptions!$D$10)<2,Assumptions!$D$10<0),"",IF(Assumptions!$D$11="Profit on cost",H22*Assumptions!$D$10,IF(Assumptions!$D$11="Margin on sales",IF(Assumptions!$D$10>=1,"",H22/(1-Assumptions!$D$10)-H22),""))) -> 19051.375 | I23: =IF(OR(COUNT(I22,Assumptions!$D$10)<2,Assumptions!$D$10<0),"",IF(Assumptions!$D$11="Profit on cost",I22*Assumptions!$D$10,IF(Assumptions!$D$11="Margin on sales",IF(Assumptions!$D$10>=1,"",I22/(1-Assumptions!$D$10)-I22),""))) -> 9525.6874
C24: Calculated rate / hour | D24: =IF(D9="Use supplied loaded rate",IF(COUNTIFS('Source Data'!$C$21:$C$26,$C8)<>1,"",IF(INDEX('Source Data'!$I$21:$I$26,MATCH($C8,'Source Data'!$C$21:$C$26,0))="","",INDEX('Source Data'!$I$21:$I$26,MATCH($C8,'Source Data'!$C$21:$C$26,0)))),IF(OR(D9<>"Build from wage",COUNT(D22:D23)<2,NOT(ISNUMBER(Staffing!D9)),Staffing!D9<=0),"",SUM(D22:D23)/Staffing!D9)) -> 89.517259 | E24: =IF(E9="Use supplied loaded rate",IF(OR(COUNT(D24,Assumptions!E$46)<2,Assumptions!E$46<0,Assumptions!E$46>1),"",D24*(1+Assumptions!E$46)),IF(OR(E9<>"Build from wage",COUNT(E22:E23)<2,NOT(ISNUMBER(Staffing!E9)),Staffing!E9<=0),"",SUM(E22:E23)/Staffing!E9)) -> 92.202776 | F24: =IF(F9="Use supplied loaded rate",IF(OR(COUNT(E24,Assumptions!F$46)<2,Assumptions!F$46<0,Assumptions!F$46>1),"",E24*(1+Assumptions!F$46)),IF(OR(F9<>"Build from wage",COUNT(F22:F23)<2,NOT(ISNUMBER(Staffing!F9)),Staffing!F9<=0),"",SUM(F22:F23)/Staffing!F9)) -> 94.96886 | G24: =IF(G9="Use supplied loaded rate",IF(OR(COUNT(F24,Assumptions!G$46)<2,Assumptions!G$46<0,Assumptions!G$46>1),"",F24*(1+Assumptions!G$46)),IF(OR(G9<>"Build from wage",COUNT(G22:G23)<2,NOT(ISNUMBER(Staffing!G9)),Staffing!G9<=0),"",SUM(G22:G23)/Staffing!G9)) -> 97.817925 | H24: =IF(H9="Use supplied loaded rate",IF(OR(COUNT(G24,Assumptions!H$46)<2,Assumptions!H$46<0,Assumptions!H$46>1),"",G24*(1+Assumptions!H$46)),IF(OR(H9<>"Build from wage",COUNT(H22:H23)<2,NOT(ISNUMBER(Staffing!H9)),Staffing!H9<=0),"",SUM(H22:H23)/Staffing!H9)) -> 100.75246 | I24: =IF(I9="Use supplied loaded rate",IF(H24="","",H24),IF(OR(I9<>"Build from wage",COUNT(I22:I23)<2,NOT(ISNUMBER(Staffing!I9)),Staffing!I9<=0),"",SUM(I22:I23)/Staffing!I9)) -> 100.75246
C25: Period-rate override
C26: Selling rate / hour | D26: =IF(D25="",IF(OR(NOT(ISNUMBER(D24)),D24<0),"",ROUND(D24,4)),IF(AND(ISNUMBER(D25),D25>=0),ROUND(D25,4),"")) -> 89.5173 | E26: =IF(E25="",IF(OR(NOT(ISNUMBER(E24)),E24<0),"",ROUND(E24,4)),IF(AND(ISNUMBER(E25),E25>=0),ROUND(E25,4),"")) -> 92.2028 | F26: =IF(F25="",IF(OR(NOT(ISNUMBER(F24)),F24<0),"",ROUND(F24,4)),IF(AND(ISNUMBER(F25),F25>=0),ROUND(F25,4),"")) -> 94.9689 | G26: =IF(G25="",IF(OR(NOT(ISNUMBER(G24)),G24<0),"",ROUND(G24,4)),IF(AND(ISNUMBER(G25),G25>=0),ROUND(G25,4),"")) -> 97.8179 | H26: =IF(H25="",IF(OR(NOT(ISNUMBER(H24)),H24<0),"",ROUND(H24,4)),IF(AND(ISNUMBER(H25),H25>=0),ROUND(H25,4),"")) -> 100.7525 | I26: =IF(I25="",IF(OR(NOT(ISNUMBER(H26)),H26<0),"",ROUND(H26,4)),IF(AND(ISNUMBER(I25),I25>=0),ROUND(I25,4),"")) -> 100.7525
C27: Input status | D27: =IF(Staffing!D17<>"Complete",Staffing!D17,IF(AND(D9<>"Build from wage",D9<>"Use supplied loaded rate"),"Invalid rate basis",IF(Staffing!D9=0,"Zero hours",IF(D26="","Missing / invalid rate",IF(AND(D9="Build from wage",COUNT(D22:D23)<2),"Missing cost inputs","Complete"))))) -> Complete | E27: =IF(Staffing!E17<>"Complete",Staffing!E17,IF(AND(E9<>"Build from wage",E9<>"Use supplied loaded rate"),"Invalid rate basis",IF(Staffing!E9=0,"Zero hours",IF(E26="","Missing / invalid rate",IF(AND(E9="Build from wage",COUNT(E22:E23)<2),"Missing cost inputs","Complete"))))) -> Complete | F27: =IF(Staffing!F17<>"Complete",Staffing!F17,IF(AND(F9<>"Build from wage",F9<>"Use supplied loaded rate"),"Invalid rate basis",IF(Staffing!F9=0,"Zero hours",IF(F26="","Missing / invalid rate",IF(AND(F9="Build from wage",COUNT(F22:F23)<2),"Missing cost inputs","Complete"))))) -> Complete | G27: =IF(Staffing!G17<>"Complete",Staffing!G17,IF(AND(G9<>"Build from wage",G9<>"Use supplied loaded rate"),"Invalid rate basis",IF(Staffing!G9=0,"Zero hours",IF(G26="","Missing / invalid rate",IF(AND(G9="Build from wage",COUNT(G22:G23)<2),"Missing cost inputs","Complete"))))) -> Complete | H27: =IF(Staffing!H17<>"Complete",Staffing!H17,IF(AND(H9<>"Build from wage",H9<>"Use supplied loaded rate"),"Invalid rate basis",IF(Staffing!H9=0,"Zero hours",IF(H26="","Missing / invalid rate",IF(AND(H9="Build from wage",COUNT(H22:H23)<2),"Missing cost inputs","Complete"))))) -> Complete | I27: =IF(Staffing!I17<>"Complete",Staffing!I17,IF(AND(I9<>"Build from wage",I9<>"Use supplied loaded rate"),"Invalid rate basis",IF(Staffing!I9=0,"Zero hours",IF(I26="","Missing / invalid rate",IF(AND(I9="Build from wage",COUNT(I22:I23)<2),"Missing cost inputs","Complete"))))) -> Complete
C31: R02 | D31: =IF(COUNTIFS('Source Data'!$C$21:$C$26,$C31)<>1,"",IF(INDEX('Source Data'!$D$21:$D$26,MATCH($C31,'Source Data'!$C$21:$C$26,0))="","",INDEX('Source Data'!$D$21:$D$26,MATCH($C31,'Source Data'!$C$21:$C$26,0)))) -> Financial Analyst
C32: Rate basis | D32: =IF(COUNTIFS('Source Data'!$C$21:$C$26,$C31)<>1,"",IF(INDEX('Source Data'!$H$21:$H$26,MATCH($C31,'Source Data'!$C$21:$C$26,0))="","",INDEX('Source Data'!$H$21:$H$26,MATCH($C31,'Source Data'!$C$21:$C$26,0)))) -> Build from wage | E32: =IF(COUNTIFS('Source Data'!$C$21:$C$26,$C31)<>1,"",IF(INDEX('Source Data'!$H$21:$H$26,MATCH($C31,'Source Data'!$C$21:$C$26,0))="","",INDEX('Source Data'!$H$21:$H$26,MATCH($C31,'Source Data'!$C$21:$C$26,0)))) -> Build from wage | F32: =IF(COUNTIFS('Source Data'!$C$21:$C$26,$C31)<>1,"",IF(INDEX('Source Data'!$H$21:$H$26,MATCH($C31,'Source Data'!$C$21:$C$26,0))="","",INDEX('Source Data'!$H$21:$H$26,MATCH($C31,'Source Data'!$C$21:$C$26,0)))) -> Build from wage | G32: =IF(COUNTIFS('Source Data'!$C$21:$C$26,$C31)<>1,"",IF(INDEX('Source Data'!$H$21:$H$26,MATCH($C31,'Source Data'!$C$21:$C$26,0))="","",INDEX('Source Data'!$H$21:$H$26,MATCH($C31,'Source Data'!$C$21:$C$26,0)))) -> Build from wage | H32: =IF(COUNTIFS('Source Data'!$C$21:$C$26,$C31)<>1,"",IF(INDEX('Source Data'!$H$21:$H$26,MATCH($C31,'Source Data'!$C$21:$C$26,0))="","",INDEX('Source Data'!$H$21:$H$26,MATCH($C31,'Source Data'!$C$21:$C$26,0)))) -> Build from wage | I32: =IF(COUNTIFS('Source Data'!$C$21:$C$26,$C31)<>1,"",IF(INDEX('Source Data'!$H$21:$H$26,MATCH($C31,'Source Data'!$C$21:$C$26,0))="","",INDEX('Source Data'!$H$21:$H$26,MATCH($C31,'Source Data'!$C$21:$C$26,0)))) -> Build from wage
C33: Benchmark wage / hour | D33: =IF(COUNTIFS('Source Data'!$C$21:$C$26,$C31)<>1,"",IF(INDEX('Source Data'!$F$21:$F$26,MATCH($C31,'Source Data'!$C$21:$C$26,0))="","",INDEX('Source Data'!$F$21:$F$26,MATCH($C31,'Source Data'!$C$21:$C$26,0)))) -> 60.82 | E33: =IF(COUNTIFS('Source Data'!$C$21:$C$26,$C31)<>1,"",IF(INDEX('Source Data'!$F$21:$F$26,MATCH($C31,'Source Data'!$C$21:$C$26,0))="","",INDEX('Source Data'!$F$21:$F$26,MATCH($C31,'Source Data'!$C$21:$C$26,0)))) -> 60.82 | F33: =IF(COUNTIFS('Source Data'!$C$21:$C$26,$C31)<>1,"",IF(INDEX('Source Data'!$F$21:$F$26,MATCH($C31,'Source Data'!$C$21:$C$26,0))="","",INDEX('Source Data'!$F$21:$F$26,MATCH($C31,'Source Data'!$C$21:$C$26,0)))) -> 60.82 | G33: =IF(COUNTIFS('Source Data'!$C$21:$C$26,$C31)<>1,"",IF(INDEX('Source Data'!$F$21:$F$26,MATCH($C31,'Source Data'!$C$21:$C$26,0))="","",INDEX('Source Data'!$F$21:$F$26,MATCH($C31,'Source Data'!$C$21:$C$26,0)))) -> 60.82 | H33: =IF(COUNTIFS('Source Data'!$C$21:$C$26,$C31)<>1,"",IF(INDEX('Source Data'!$F$21:$F$26,MATCH($C31,'Source Data'!$C$21:$C$26,0))="","",INDEX('Source Data'!$F$21:$F$26,MATCH($C31,'Source Data'!$C$21:$C$26,0)))) -> 60.82 | I33: =IF(COUNTIFS('Source Data'!$C$21:$C$26,$C31)<>1,"",IF(INDEX('Source Data'!$F$21:$F$26,MATCH($C31,'Source Data'!$C$21:$C$26,0))="","",INDEX('Source Data'!$F$21:$F$26,MATCH($C31,'Source Data'!$C$21:$C$26,0)))) -> 60.82
C34: Benchmark year | D34: =IF(COUNTIFS('Source Data'!$C$21:$C$26,$C31)<>1,"",IF(INDEX('Source Data'!$G$21:$G$26,MATCH($C31,'Source Data'!$C$21:$C$26,0))="","",INDEX('Source Data'!$G$21:$G$26,MATCH($C31,'Source Data'!$C$21:$C$26,0)))) -> 2025 | E34: =IF(COUNTIFS('Source Data'!$C$21:$C$26,$C31)<>1,"",IF(INDEX('Source Data'!$G$21:$G$26,MATCH($C31,'Source Data'!$C$21:$C$26,0))="","",INDEX('Source Data'!$G$21:$G$26,MATCH($C31,'Source Data'!$C$21:$C$26,0)))) -> 2025 | F34: =IF(COUNTIFS('Source Data'!$C$21:$C$26,$C31)<>1,"",IF(INDEX('Source Data'!$G$21:$G$26,MATCH($C31,'Source Data'!$C$21:$C$26,0))="","",INDEX('Source Data'!$G$21:$G$26,MATCH($C31,'Source Data'!$C$21:$C$26,0)))) -> 2025 | G34: =IF(COUNTIFS('Source Data'!$C$21:$C$26,$C31)<>1,"",IF(INDEX('Source Data'!$G$21:$G$26,MATCH($C31,'Source Data'!$C$21:$C$26,0))="","",INDEX('Source Data'!$G$21:$G$26,MATCH($C31,'Source Data'!$C$21:$C$26,0)))) -> 2025 | H34: =IF(COUNTIFS('Source Data'!$C$21:$C$26,$C31)<>1,"",IF(INDEX('Source Data'!$G$21:$G$26,MATCH($C31,'Source Data'!$C$21:$C$26,0))="","",INDEX('Source Data'!$G$21:$G$26,MATCH($C31,'Source Data'!$C$21:$C$26,0)))) -> 2025 | I34: =IF(COUNTIFS('Source Data'!$C$21:$C$26,$C31)<>1,"",IF(INDEX('Source Data'!$G$21:$G$26,MATCH($C31,'Source Data'!$C$21:$C$26,0))="","",INDEX('Source Data'!$G$21:$G$26,MATCH($C31,'Source Data'!$C$21:$C$26,0)))) -> 2025
C35: Wage adjustment factor | D35: =IF(COUNT(D34,Assumptions!D$22,Assumptions!D$17)<3,"",IF(OR(Assumptions!D$22<0,Assumptions!D$22>1,YEAR(Assumptions!D$17)<D34),"",(1+Assumptions!D$22)^(YEAR(Assumptions!D$17)-D34))) -> 1.03 | E35: =IF(COUNT(E34,Assumptions!E$22,Assumptions!E$17)<3,"",IF(OR(Assumptions!E$22<0,Assumptions!E$22>1,YEAR(Assumptions!E$17)<E34),"",IF(D35="","",D35*(1+Assumptions!E$22)))) -> 1.0609 | F35: =IF(COUNT(F34,Assumptions!F$22,Assumptions!F$17)<3,"",IF(OR(Assumptions!F$22<0,Assumptions!F$22>1,YEAR(Assumptions!F$17)<F34),"",IF(E35="","",E35*(1+Assumptions!F$22)))) -> 1.092727 | G35: =IF(COUNT(G34,Assumptions!G$22,Assumptions!G$17)<3,"",IF(OR(Assumptions!G$22<0,Assumptions!G$22>1,YEAR(Assumptions!G$17)<G34),"",IF(F35="","",F35*(1+Assumptions!G$22)))) -> 1.1255088 | H35: =IF(COUNT(H34,Assumptions!H$22,Assumptions!H$17)<3,"",IF(OR(Assumptions!H$22<0,Assumptions!H$22>1,YEAR(Assumptions!H$17)<H34),"",IF(G35="","",G35*(1+Assumptions!H$22)))) -> 1.1592741 | I35: =IF(H35="","",H35) -> 1.1592741
C36: Adjusted wage / hour | D36: =IF(OR(D32<>"Build from wage",COUNT(D33,D35)<2,D33<0),"",D33*D35) -> 62.6446 | E36: =IF(OR(E32<>"Build from wage",COUNT(E33,E35)<2,E33<0),"",E33*E35) -> 64.523938 | F36: =IF(OR(F32<>"Build from wage",COUNT(F33,F35)<2,F33<0),"",F33*F35) -> 66.459656 | G36: =IF(OR(G32<>"Build from wage",COUNT(G33,G35)<2,G33<0),"",G33*G35) -> 68.453446 | H36: =IF(OR(H32<>"Build from wage",COUNT(H33,H35)<2,H33<0),"",H33*H35) -> 70.507049 | I36: =IF(OR(I32<>"Build from wage",COUNT(I33,I35)<2,I33<0),"",I33*I35) -> 70.507049
C37: Paid hours for cost | D37: =IF(Staffing!D28="","",Staffing!D28) -> 4702.6087 | E37: =IF(Staffing!E28="","",Staffing!E28) -> 4702.6087 | F37: =IF(Staffing!F28="","",Staffing!F28) -> 4702.6087 | G37: =IF(Staffing!G28="","",Staffing!G28) -> 4702.6087 | H37: =IF(Staffing!H28="","",Staffing!H28) -> 4702.6087 | I37: =IF(Staffing!I28="","",Staffing!I28) -> 2351.3043
C38: Paid labor cost | D38: =IF(COUNT(D36:D37)<2,"",D36*D37) -> 294593.04 | E38: =IF(COUNT(E36:E37)<2,"",E36*E37) -> 303430.83 | F38: =IF(COUNT(F36:F37)<2,"",F36*F37) -> 312533.76 | G38: =IF(COUNT(G36:G37)<2,"",G36*G37) -> 321909.77 | H38: =IF(COUNT(H36:H37)<2,"",H36*H37) -> 331567.06 | I38: =IF(COUNT(I36:I37)<2,"",I36*I37) -> 165783.53
C39: Fringe benefits | D39: =IF(OR(COUNT(D38,Assumptions!D$28)<2,Assumptions!D$28<0),"",D38*Assumptions!D$28) -> 73648.26 | E39: =IF(OR(COUNT(E38,Assumptions!E$28)<2,Assumptions!E$28<0),"",E38*Assumptions!E$28) -> 75857.708 | F39: =IF(OR(COUNT(F38,Assumptions!F$28)<2,Assumptions!F$28<0),"",F38*Assumptions!F$28) -> 78133.439 | G39: =IF(OR(COUNT(G38,Assumptions!G$28)<2,Assumptions!G$28<0),"",G38*Assumptions!G$28) -> 80477.442 | H39: =IF(OR(COUNT(H38,Assumptions!H$28)<2,Assumptions!H$28<0),"",H38*Assumptions!H$28) -> 82891.766 | I39: =IF(OR(COUNT(I38,Assumptions!I$28)<2,Assumptions!I$28<0),"",I38*Assumptions!I$28) -> 41445.883
C40: Additional hourly benefits | D40: =IF(OR(D32<>"Build from wage",COUNT(D37,Assumptions!$D$9)<2,Assumptions!$D$9<0),"",D37*Assumptions!$D$9) -> 0 | E40: =IF(OR(E32<>"Build from wage",COUNT(E37,Assumptions!$D$9)<2,Assumptions!$D$9<0),"",E37*Assumptions!$D$9) -> 0 | F40: =IF(OR(F32<>"Build from wage",COUNT(F37,Assumptions!$D$9)<2,Assumptions!$D$9<0),"",F37*Assumptions!$D$9) -> 0 | G40: =IF(OR(G32<>"Build from wage",COUNT(G37,Assumptions!$D$9)<2,Assumptions!$D$9<0),"",G37*Assumptions!$D$9) -> 0 | H40: =IF(OR(H32<>"Build from wage",COUNT(H37,Assumptions!$D$9)<2,Assumptions!$D$9<0),"",H37*Assumptions!$D$9) -> 0 | I40: =IF(OR(I32<>"Build from wage",COUNT(I37,Assumptions!$D$9)<2,Assumptions!$D$9<0),"",I37*Assumptions!$D$9) -> 0
C41: Labor plus benefits | D41: =IF(COUNT(D38:D40)<3,"",SUM(D38:D40)) -> 368241.3 | E41: =IF(COUNT(E38:E40)<3,"",SUM(E38:E40)) -> 379288.54 | F41: =IF(COUNT(F38:F40)<3,"",SUM(F38:F40)) -> 390667.2 | G41: =IF(COUNT(G38:G40)<3,"",SUM(G38:G40)) -> 402387.21 | H41: =IF(COUNT(H38:H40)<3,"",SUM(H38:H40)) -> 414458.83 | I41: =IF(COUNT(I38:I40)<3,"",SUM(I38:I40)) -> 207229.41
C42: Overhead | D42: =IF(OR(COUNT(D41,Assumptions!D$34)<2,Assumptions!D$34<0),"",D41*Assumptions!D$34) -> 36824.13 | E42: =IF(OR(COUNT(E41,Assumptions!E$34)<2,Assumptions!E$34<0),"",E41*Assumptions!E$34) -> 37928.854 | F42: =IF(OR(COUNT(F41,Assumptions!F$34)<2,Assumptions!F$34<0),"",F41*Assumptions!F$34) -> 39066.72 | G42: =IF(OR(COUNT(G41,Assumptions!G$34)<2,Assumptions!G$34<0),"",G41*Assumptions!G$34) -> 40238.721 | H42: =IF(OR(COUNT(H41,Assumptions!H$34)<2,Assumptions!H$34<0),"",H41*Assumptions!H$34) -> 41445.883 | I42: =IF(OR(COUNT(I41,Assumptions!I$34)<2,Assumptions!I$34<0),"",I41*Assumptions!I$34) -> 20722.941
C43: Labor, benefits, overhead | D43: =IF(COUNT(D41:D42)<2,"",SUM(D41:D42)) -> 405065.43 | E43: =IF(COUNT(E41:E42)<2,"",SUM(E41:E42)) -> 417217.39 | F43: =IF(COUNT(F41:F42)<2,"",SUM(F41:F42)) -> 429733.92 | G43: =IF(COUNT(G41:G42)<2,"",SUM(G41:G42)) -> 442625.93 | H43: =IF(COUNT(H41:H42)<2,"",SUM(H41:H42)) -> 455904.71 | I43: =IF(COUNT(I41:I42)<2,"",SUM(I41:I42)) -> 227952.36
C44: G&A | D44: =IF(OR(COUNT(D43,Assumptions!D$40)<2,Assumptions!D$40<0),"",D43*Assumptions!D$40) -> 40506.543 | E44: =IF(OR(COUNT(E43,Assumptions!E$40)<2,Assumptions!E$40<0),"",E43*Assumptions!E$40) -> 41721.739 | F44: =IF(OR(COUNT(F43,Assumptions!F$40)<2,Assumptions!F$40<0),"",F43*Assumptions!F$40) -> 42973.392 | G44: =IF(OR(COUNT(G43,Assumptions!G$40)<2,Assumptions!G$40<0),"",G43*Assumptions!G$40) -> 44262.593 | H44: =IF(OR(COUNT(H43,Assumptions!H$40)<2,Assumptions!H$40<0),"",H43*Assumptions!H$40) -> 45590.471 | I44: =IF(OR(COUNT(I43,Assumptions!I$40)<2,Assumptions!I$40<0),"",I43*Assumptions!I$40) -> 22795.236
C45: Total modeled cost | D45: =IF(COUNT(D43:D44)<2,"",SUM(D43:D44)) -> 445571.97 | E45: =IF(COUNT(E43:E44)<2,"",SUM(E43:E44)) -> 458939.13 | F45: =IF(COUNT(F43:F44)<2,"",SUM(F43:F44)) -> 472707.31 | G45: =IF(COUNT(G43:G44)<2,"",SUM(G43:G44)) -> 486888.53 | H45: =IF(COUNT(H43:H44)<2,"",SUM(H43:H44)) -> 501495.18 | I45: =IF(COUNT(I43:I44)<2,"",SUM(I43:I44)) -> 250747.59
C46: Target profit | D46: =IF(OR(COUNT(D45,Assumptions!$D$10)<2,Assumptions!$D$10<0),"",IF(Assumptions!$D$11="Profit on cost",D45*Assumptions!$D$10,IF(Assumptions!$D$11="Margin on sales",IF(Assumptions!$D$10>=1,"",D45/(1-Assumptions!$D$10)-D45),""))) -> 44557.197 | E46: =IF(OR(COUNT(E45,Assumptions!$D$10)<2,Assumptions!$D$10<0),"",IF(Assumptions!$D$11="Profit on cost",E45*Assumptions!$D$10,IF(Assumptions!$D$11="Margin on sales",IF(Assumptions!$D$10>=1,"",E45/(1-Assumptions!$D$10)-E45),""))) -> 45893.913 | F46: =IF(OR(COUNT(F45,Assumptions!$D$10)<2,Assumptions!$D$10<0),"",IF(Assumptions!$D$11="Profit on cost",F45*Assumptions!$D$10,IF(Assumptions!$D$11="Margin on sales",IF(Assumptions!$D$10>=1,"",F45/(1-Assumptions!$D$10)-F45),""))) -> 47270.731 | G46: =IF(OR(COUNT(G45,Assumptions!$D$10)<2,Assumptions!$D$10<0),"",IF(Assumptions!$D$11="Profit on cost",G45*Assumptions!$D$10,IF(Assumptions!$D$11="Margin on sales",IF(Assumptions!$D$10>=1,"",G45/(1-Assumptions!$D$10)-G45),""))) -> 48688.853 | H46: =IF(OR(COUNT(H45,Assumptions!$D$10)<2,Assumptions!$D$10<0),"",IF(Assumptions!$D$11="Profit on cost",H45*Assumptions!$D$10,IF(Assumptions!$D$11="Margin on sales",IF(Assumptions!$D$10>=1,"",H45/(1-Assumptions!$D$10)-H45),""))) -> 50149.518 | I46: =IF(OR(COUNT(I45,Assumptions!$D$10)<2,Assumptions!$D$10<0),"",IF(Assumptions!$D$11="Profit on cost",I45*Assumptions!$D$10,IF(Assumptions!$D$11="Margin on sales",IF(Assumptions!$D$10>=1,"",I45/(1-Assumptions!$D$10)-I45),""))) -> 25074.759
C47: Calculated rate / hour | D47: =IF(D32="Use supplied loaded rate",IF(COUNTIFS('Source Data'!$C$21:$C$26,$C31)<>1,"",IF(INDEX('Source Data'!$I$21:$I$26,MATCH($C31,'Source Data'!$C$21:$C$26,0))="","",INDEX('Source Data'!$I$21:$I$26,MATCH($C31,'Source Data'!$C$21:$C$26,0)))),IF(OR(D32<>"Build from wage",COUNT(D45:D46)<2,NOT(ISNUMBER(Staffing!D21)),Staffing!D21<=0),"",SUM(D45:D46)/Staffing!D21)) -> 117.81951 | E47: =IF(E32="Use supplied loaded rate",IF(OR(COUNT(D47,Assumptions!E$46)<2,Assumptions!E$46<0,Assumptions!E$46>1),"",D47*(1+Assumptions!E$46)),IF(OR(E32<>"Build from wage",COUNT(E45:E46)<2,NOT(ISNUMBER(Staffing!E21)),Staffing!E21<=0),"",SUM(E45:E46)/Staffing!E21)) -> 121.3541 | F47: =IF(F32="Use supplied loaded rate",IF(OR(COUNT(E47,Assumptions!F$46)<2,Assumptions!F$46<0,Assumptions!F$46>1),"",E47*(1+Assumptions!F$46)),IF(OR(F32<>"Build from wage",COUNT(F45:F46)<2,NOT(ISNUMBER(Staffing!F21)),Staffing!F21<=0),"",SUM(F45:F46)/Staffing!F21)) -> 124.99472 | G47: =IF(G32="Use supplied loaded rate",IF(OR(COUNT(F47,Assumptions!G$46)<2,Assumptions!G$46<0,Assumptions!G$46>1),"",F47*(1+Assumptions!G$46)),IF(OR(G32<>"Build from wage",COUNT(G45:G46)<2,NOT(ISNUMBER(Staffing!G21)),Staffing!G21<=0),"",SUM(G45:G46)/Staffing!G21)) -> 128.74456 | H47: =IF(H32="Use supplied loaded rate",IF(OR(COUNT(G47,Assumptions!H$46)<2,Assumptions!H$46<0,Assumptions!H$46>1),"",G47*(1+Assumptions!H$46)),IF(OR(H32<>"Build from wage",COUNT(H45:H46)<2,NOT(ISNUMBER(Staffing!H21)),Staffing!H21<=0),"",SUM(H45:H46)/Staffing!H21)) -> 132.6069 | I47: =IF(I32="Use supplied loaded rate",IF(H47="","",H47),IF(OR(I32<>"Build from wage",COUNT(I45:I46)<2,NOT(ISNUMBER(Staffing!I21)),Staffing!I21<=0),"",SUM(I45:I46)/Staffing!I21)) -> 132.6069
C48: Period-rate override
C49: Selling rate / hour | D49: =IF(D48="",IF(OR(NOT(ISNUMBER(D47)),D47<0),"",ROUND(D47,4)),IF(AND(ISNUMBER(D48),D48>=0),ROUND(D48,4),"")) -> 117.8195 | E49: =IF(E48="",IF(OR(NOT(ISNUMBER(E47)),E47<0),"",ROUND(E47,4)),IF(AND(ISNUMBER(E48),E48>=0),ROUND(E48,4),"")) -> 121.3541 | F49: =IF(F48="",IF(OR(NOT(ISNUMBER(F47)),F47<0),"",ROUND(F47,4)),IF(AND(ISNUMBER(F48),F48>=0),ROUND(F48,4),"")) -> 124.9947 | G49: =IF(G48="",IF(OR(NOT(ISNUMBER(G47)),G47<0),"",ROUND(G47,4)),IF(AND(ISNUMBER(G48),G48>=0),ROUND(G48,4),"")) -> 128.7446 | H49: =IF(H48="",IF(OR(NOT(ISNUMBER(H47)),H47<0),"",ROUND(H47,4)),IF(AND(ISNUMBER(H48),H48>=0),ROUND(H48,4),"")) -> 132.6069 | I49: =IF(I48="",IF(OR(NOT(ISNUMBER(H49)),H49<0),"",ROUND(H49,4)),IF(AND(ISNUMBER(I48),I48>=0),ROUND(I48,4),"")) -> 132.6069
C50: Input status | D50: =IF(Staffing!D29<>"Complete",Staffing!D29,IF(AND(D32<>"Build from wage",D32<>"Use supplied loaded rate"),"Invalid rate basis",IF(Staffing!D21=0,"Zero hours",IF(D49="","Missing / invalid rate",IF(AND(D32="Build from wage",COUNT(D45:D46)<2),"Missing cost inputs","Complete"))))) -> Complete | E50: =IF(Staffing!E29<>"Complete",Staffing!E29,IF(AND(E32<>"Build from wage",E32<>"Use supplied loaded rate"),"Invalid rate basis",IF(Staffing!E21=0,"Zero hours",IF(E49="","Missing / invalid rate",IF(AND(E32="Build from wage",COUNT(E45:E46)<2),"Missing cost inputs","Complete"))))) -> Complete | F50: =IF(Staffing!F29<>"Complete",Staffing!F29,IF(AND(F32<>"Build from wage",F32<>"Use supplied loaded rate"),"Invalid rate basis",IF(Staffing!F21=0,"Zero hours",IF(F49="","Missing / invalid rate",IF(AND(F32="Build from wage",COUNT(F45:F46)<2),"Missing cost inputs","Complete"))))) -> Complete | G50: =IF(Staffing!G29<>"Complete",Staffing!G29,IF(AND(G32<>"Build from wage",G32<>"Use supplied loaded rate"),"Invalid rate basis",IF(Staffing!G21=0,"Zero hours",IF(G49="","Missing / invalid rate",IF(AND(G32="Build from wage",COUNT(G45:G46)<2),"Missing cost inputs","Complete"))))) -> Complete | H50: =IF(Staffing!H29<>"Complete",Staffing!H29,IF(AND(H32<>"Build from wage",H32<>"Use supplied loaded rate"),"Invalid rate basis",IF(Staffing!H21=0,"Zero hours",IF(H49="","Missing / invalid rate",IF(AND(H32="Build from wage",COUNT(H45:H46)<2),"Missing cost inputs","Complete"))))) -> Complete | I50: =IF(Staffing!I29<>"Complete",Staffing!I29,IF(AND(I32<>"Build from wage",I32<>"Use supplied loaded rate"),"Invalid rate basis",IF(Staffing!I21=0,"Zero hours",IF(I49="","Missing / invalid rate",IF(AND(I32="Build from wage",COUNT(I45:I46)<2),"Missing cost inputs","Complete"))))) -> Complete
C54: R03 | D54: =IF(COUNTIFS('Source Data'!$C$21:$C$26,$C54)<>1,"",IF(INDEX('Source Data'!$D$21:$D$26,MATCH($C54,'Source Data'!$C$21:$C$26,0))="","",INDEX('Source Data'!$D$21:$D$26,MATCH($C54,'Source Data'!$C$21:$C$26,0)))) -> Administrative Assistant
C55: Rate basis | D55: =IF(COUNTIFS('Source Data'!$C$21:$C$26,$C54)<>1,"",IF(INDEX('Source Data'!$H$21:$H$26,MATCH($C54,'Source Data'!$C$21:$C$26,0))="","",INDEX('Source Data'!$H$21:$H$26,MATCH($C54,'Source Data'!$C$21:$C$26,0)))) -> Build from wage | E55: =IF(COUNTIFS('Source Data'!$C$21:$C$26,$C54)<>1,"",IF(INDEX('Source Data'!$H$21:$H$26,MATCH($C54,'Source Data'!$C$21:$C$26,0))="","",INDEX('Source Data'!$H$21:$H$26,MATCH($C54,'Source Data'!$C$21:$C$26,0)))) -> Build from wage | F55: =IF(COUNTIFS('Source Data'!$C$21:$C$26,$C54)<>1,"",IF(INDEX('Source Data'!$H$21:$H$26,MATCH($C54,'Source Data'!$C$21:$C$26,0))="","",INDEX('Source Data'!$H$21:$H$26,MATCH($C54,'Source Data'!$C$21:$C$26,0)))) -> Build from wage | G55: =IF(COUNTIFS('Source Data'!$C$21:$C$26,$C54)<>1,"",IF(INDEX('Source Data'!$H$21:$H$26,MATCH($C54,'Source Data'!$C$21:$C$26,0))="","",INDEX('Source Data'!$H$21:$H$26,MATCH($C54,'Source Data'!$C$21:$C$26,0)))) -> Build from wage | H55: =IF(COUNTIFS('Source Data'!$C$21:$C$26,$C54)<>1,"",IF(INDEX('Source Data'!$H$21:$H$26,MATCH($C54,'Source Data'!$C$21:$C$26,0))="","",INDEX('Source Data'!$H$21:$H$26,MATCH($C54,'Source Data'!$C$21:$C$26,0)))) -> Build from wage | I55: =IF(COUNTIFS('Source Data'!$C$21:$C$26,$C54)<>1,"",IF(INDEX('Source Data'!$H$21:$H$26,MATCH($C54,'Source Data'!$C$21:$C$26,0))="","",INDEX('Source Data'!$H$21:$H$26,MATCH($C54,'Source Data'!$C$21:$C$26,0)))) -> Build from wage
C56: Benchmark wage / hour | D56: =IF(COUNTIFS('Source Data'!$C$21:$C$26,$C54)<>1,"",IF(INDEX('Source Data'!$F$21:$F$26,MATCH($C54,'Source Data'!$C$21:$C$26,0))="","",INDEX('Source Data'!$F$21:$F$26,MATCH($C54,'Source Data'!$C$21:$C$26,0)))) -> 25.8 | E56: =IF(COUNTIFS('Source Data'!$C$21:$C$26,$C54)<>1,"",IF(INDEX('Source Data'!$F$21:$F$26,MATCH($C54,'Source Data'!$C$21:$C$26,0))="","",INDEX('Source Data'!$F$21:$F$26,MATCH($C54,'Source Data'!$C$21:$C$26,0)))) -> 25.8 | F56: =IF(COUNTIFS('Source Data'!$C$21:$C$26,$C54)<>1,"",IF(INDEX('Source Data'!$F$21:$F$26,MATCH($C54,'Source Data'!$C$21:$C$26,0))="","",INDEX('Source Data'!$F$21:$F$26,MATCH($C54,'Source Data'!$C$21:$C$26,0)))) -> 25.8 | G56: =IF(COUNTIFS('Source Data'!$C$21:$C$26,$C54)<>1,"",IF(INDEX('Source Data'!$F$21:$F$26,MATCH($C54,'Source Data'!$C$21:$C$26,0))="","",INDEX('Source Data'!$F$21:$F$26,MATCH($C54,'Source Data'!$C$21:$C$26,0)))) -> 25.8 | H56: =IF(COUNTIFS('Source Data'!$C$21:$C$26,$C54)<>1,"",IF(INDEX('Source Data'!$F$21:$F$26,MATCH($C54,'Source Data'!$C$21:$C$26,0))="","",INDEX('Source Data'!$F$21:$F$26,MATCH($C54,'Source Data'!$C$21:$C$26,0)))) -> 25.8 | I56: =IF(COUNTIFS('Source Data'!$C$21:$C$26,$C54)<>1,"",IF(INDEX('Source Data'!$F$21:$F$26,MATCH($C54,'Source Data'!$C$21:$C$26,0))="","",INDEX('Source Data'!$F$21:$F$26,MATCH($C54,'Source Data'!$C$21:$C$26,0)))) -> 25.8
C57: Benchmark year | D57: =IF(COUNTIFS('Source Data'!$C$21:$C$26,$C54)<>1,"",IF(INDEX('Source Data'!$G$21:$G$26,MATCH($C54,'Source Data'!$C$21:$C$26,0))="","",INDEX('Source Data'!$G$21:$G$26,MATCH($C54,'Source Data'!$C$21:$C$26,0)))) -> 2025 | E57: =IF(COUNTIFS('Source Data'!$C$21:$C$26,$C54)<>1,"",IF(INDEX('Source Data'!$G$21:$G$26,MATCH($C54,'Source Data'!$C$21:$C$26,0))="","",INDEX('Source Data'!$G$21:$G$26,MATCH($C54,'Source Data'!$C$21:$C$26,0)))) -> 2025 | F57: =IF(COUNTIFS('Source Data'!$C$21:$C$26,$C54)<>1,"",IF(INDEX('Source Data'!$G$21:$G$26,MATCH($C54,'Source Data'!$C$21:$C$26,0))="","",INDEX('Source Data'!$G$21:$G$26,MATCH($C54,'Source Data'!$C$21:$C$26,0)))) -> 2025 | G57: =IF(COUNTIFS('Source Data'!$C$21:$C$26,$C54)<>1,"",IF(INDEX('Source Data'!$G$21:$G$26,MATCH($C54,'Source Data'!$C$21:$C$26,0))="","",INDEX('Source Data'!$G$21:$G$26,MATCH($C54,'Source Data'!$C$21:$C$26,0)))) -> 2025 | H57: =IF(COUNTIFS('Source Data'!$C$21:$C$26,$C54)<>1,"",IF(INDEX('Source Data'!$G$21:$G$26,MATCH($C54,'Source Data'!$C$21:$C$26,0))="","",INDEX('Source Data'!$G$21:$G$26,MATCH($C54,'Source Data'!$C$21:$C$26,0)))) -> 2025 | I57: =IF(COUNTIFS('Source Data'!$C$21:$C$26,$C54)<>1,"",IF(INDEX('Source Data'!$G$21:$G$26,MATCH($C54,'Source Data'!$C$21:$C$26,0))="","",INDEX('Source Data'!$G$21:$G$26,MATCH($C54,'Source Data'!$C$21:$C$26,0)))) -> 2025
C58: Wage adjustment factor | D58: =IF(COUNT(D57,Assumptions!D$22,Assumptions!D$17)<3,"",IF(OR(Assumptions!D$22<0,Assumptions!D$22>1,YEAR(Assumptions!D$17)<D57),"",(1+Assumptions!D$22)^(YEAR(Assumptions!D$17)-D57))) -> 1.03 | E58: =IF(COUNT(E57,Assumptions!E$22,Assumptions!E$17)<3,"",IF(OR(Assumptions!E$22<0,Assumptions!E$22>1,YEAR(Assumptions!E$17)<E57),"",IF(D58="","",D58*(1+Assumptions!E$22)))) -> 1.0609 | F58: =IF(COUNT(F57,Assumptions!F$22,Assumptions!F$17)<3,"",IF(OR(Assumptions!F$22<0,Assumptions!F$22>1,YEAR(Assumptions!F$17)<F57),"",IF(E58="","",E58*(1+Assumptions!F$22)))) -> 1.092727 | G58: =IF(COUNT(G57,Assumptions!G$22,Assumptions!G$17)<3,"",IF(OR(Assumptions!G$22<0,Assumptions!G$22>1,YEAR(Assumptions!G$17)<G57),"",IF(F58="","",F58*(1+Assumptions!G$22)))) -> 1.1255088 | H58: =IF(COUNT(H57,Assumptions!H$22,Assumptions!H$17)<3,"",IF(OR(Assumptions!H$22<0,Assumptions!H$22>1,YEAR(Assumptions!H$17)<H57),"",IF(G58="","",G58*(1+Assumptions!H$22)))) -> 1.1592741 | I58: =IF(H58="","",H58) -> 1.1592741
C59: Adjusted wage / hour | D59: =IF(OR(D55<>"Build from wage",COUNT(D56,D58)<2,D56<0),"",D56*D58) -> 26.574 | E59: =IF(OR(E55<>"Build from wage",COUNT(E56,E58)<2,E56<0),"",E56*E58) -> 27.37122 | F59: =IF(OR(F55<>"Build from wage",COUNT(F56,F58)<2,F56<0),"",F56*F58) -> 28.192357 | G59: =IF(OR(G55<>"Build from wage",COUNT(G56,G58)<2,G56<0),"",G56*G58) -> 29.038127 | H59: =IF(OR(H55<>"Build from wage",COUNT(H56,H58)<2,H56<0),"",H56*H58) -> 29.909271 | I59: =IF(OR(I55<>"Build from wage",COUNT(I56,I58)<2,I56<0),"",I56*I58) -> 29.909271
C60: Paid hours for cost | D60: =IF(Staffing!D40="","",Staffing!D40) -> 2351.3043 | E60: =IF(Staffing!E40="","",Staffing!E40) -> 2351.3043 | F60: =IF(Staffing!F40="","",Staffing!F40) -> 2351.3043 | G60: =IF(Staffing!G40="","",Staffing!G40) -> 2351.3043 | H60: =IF(Staffing!H40="","",Staffing!H40) -> 2351.3043 | I60: =IF(Staffing!I40="","",Staffing!I40) -> 1175.6522
C61: Paid labor cost | D61: =IF(COUNT(D59:D60)<2,"",D59*D60) -> 62483.562 | E61: =IF(COUNT(E59:E60)<2,"",E59*E60) -> 64358.069 | F61: =IF(COUNT(F59:F60)<2,"",F59*F60) -> 66288.811 | G61: =IF(COUNT(G59:G60)<2,"",G59*G60) -> 68277.475 | H61: =IF(COUNT(H59:H60)<2,"",H59*H60) -> 70325.799 | I61: =IF(COUNT(I59:I60)<2,"",I59*I60) -> 35162.9
C62: Fringe benefits | D62: =IF(OR(COUNT(D61,Assumptions!D$28)<2,Assumptions!D$28<0),"",D61*Assumptions!D$28) -> 15620.89 | E62: =IF(OR(COUNT(E61,Assumptions!E$28)<2,Assumptions!E$28<0),"",E61*Assumptions!E$28) -> 16089.517 | F62: =IF(OR(COUNT(F61,Assumptions!F$28)<2,Assumptions!F$28<0),"",F61*Assumptions!F$28) -> 16572.203 | G62: =IF(OR(COUNT(G61,Assumptions!G$28)<2,Assumptions!G$28<0),"",G61*Assumptions!G$28) -> 17069.369 | H62: =IF(OR(COUNT(H61,Assumptions!H$28)<2,Assumptions!H$28<0),"",H61*Assumptions!H$28) -> 17581.45 | I62: =IF(OR(COUNT(I61,Assumptions!I$28)<2,Assumptions!I$28<0),"",I61*Assumptions!I$28) -> 8790.7249
C63: Additional hourly benefits | D63: =IF(OR(D55<>"Build from wage",COUNT(D60,Assumptions!$D$9)<2,Assumptions!$D$9<0),"",D60*Assumptions!$D$9) -> 0 | E63: =IF(OR(E55<>"Build from wage",COUNT(E60,Assumptions!$D$9)<2,Assumptions!$D$9<0),"",E60*Assumptions!$D$9) -> 0 | F63: =IF(OR(F55<>"Build from wage",COUNT(F60,Assumptions!$D$9)<2,Assumptions!$D$9<0),"",F60*Assumptions!$D$9) -> 0 | G63: =IF(OR(G55<>"Build from wage",COUNT(G60,Assumptions!$D$9)<2,Assumptions!$D$9<0),"",G60*Assumptions!$D$9) -> 0 | H63: =IF(OR(H55<>"Build from wage",COUNT(H60,Assumptions!$D$9)<2,Assumptions!$D$9<0),"",H60*Assumptions!$D$9) -> 0 | I63: =IF(OR(I55<>"Build from wage",COUNT(I60,Assumptions!$D$9)<2,Assumptions!$D$9<0),"",I60*Assumptions!$D$9) -> 0
C64: Labor plus benefits | D64: =IF(COUNT(D61:D63)<3,"",SUM(D61:D63)) -> 78104.452 | E64: =IF(COUNT(E61:E63)<3,"",SUM(E61:E63)) -> 80447.586 | F64: =IF(COUNT(F61:F63)<3,"",SUM(F61:F63)) -> 82861.013 | G64: =IF(COUNT(G61:G63)<3,"",SUM(G61:G63)) -> 85346.844 | H64: =IF(COUNT(H61:H63)<3,"",SUM(H61:H63)) -> 87907.249 | I64: =IF(COUNT(I61:I63)<3,"",SUM(I61:I63)) -> 43953.625
C65: Overhead | D65: =IF(OR(COUNT(D64,Assumptions!D$34)<2,Assumptions!D$34<0),"",D64*Assumptions!D$34) -> 7810.4452 | E65: =IF(OR(COUNT(E64,Assumptions!E$34)<2,Assumptions!E$34<0),"",E64*Assumptions!E$34) -> 8044.7586 | F65: =IF(OR(COUNT(F64,Assumptions!F$34)<2,Assumptions!F$34<0),"",F64*Assumptions!F$34) -> 8286.1013 | G65: =IF(OR(COUNT(G64,Assumptions!G$34)<2,Assumptions!G$34<0),"",G64*Assumptions!G$34) -> 8534.6844 | H65: =IF(OR(COUNT(H64,Assumptions!H$34)<2,Assumptions!H$34<0),"",H64*Assumptions!H$34) -> 8790.7249 | I65: =IF(OR(COUNT(I64,Assumptions!I$34)<2,Assumptions!I$34<0),"",I64*Assumptions!I$34) -> 4395.3625
C66: Labor, benefits, overhead | D66: =IF(COUNT(D64:D65)<2,"",SUM(D64:D65)) -> 85914.897 | E66: =IF(COUNT(E64:E65)<2,"",SUM(E64:E65)) -> 88492.344 | F66: =IF(COUNT(F64:F65)<2,"",SUM(F64:F65)) -> 91147.115 | G66: =IF(COUNT(G64:G65)<2,"",SUM(G64:G65)) -> 93881.528 | H66: =IF(COUNT(H64:H65)<2,"",SUM(H64:H65)) -> 96697.974 | I66: =IF(COUNT(I64:I65)<2,"",SUM(I64:I65)) -> 48348.987
C67: G&A | D67: =IF(OR(COUNT(D66,Assumptions!D$40)<2,Assumptions!D$40<0),"",D66*Assumptions!D$40) -> 8591.4897 | E67: =IF(OR(COUNT(E66,Assumptions!E$40)<2,Assumptions!E$40<0),"",E66*Assumptions!E$40) -> 8849.2344 | F67: =IF(OR(COUNT(F66,Assumptions!F$40)<2,Assumptions!F$40<0),"",F66*Assumptions!F$40) -> 9114.7115 | G67: =IF(OR(COUNT(G66,Assumptions!G$40)<2,Assumptions!G$40<0),"",G66*Assumptions!G$40) -> 9388.1528 | H67: =IF(OR(COUNT(H66,Assumptions!H$40)<2,Assumptions!H$40<0),"",H66*Assumptions!H$40) -> 9669.7974 | I67: =IF(OR(COUNT(I66,Assumptions!I$40)<2,Assumptions!I$40<0),"",I66*Assumptions!I$40) -> 4834.8987
C68: Total modeled cost | D68: =IF(COUNT(D66:D67)<2,"",SUM(D66:D67)) -> 94506.387 | E68: =IF(COUNT(E66:E67)<2,"",SUM(E66:E67)) -> 97341.579 | F68: =IF(COUNT(F66:F67)<2,"",SUM(F66:F67)) -> 100261.83 | G68: =IF(COUNT(G66:G67)<2,"",SUM(G66:G67)) -> 103269.68 | H68: =IF(COUNT(H66:H67)<2,"",SUM(H66:H67)) -> 106367.77 | I68: =IF(COUNT(I66:I67)<2,"",SUM(I66:I67)) -> 53183.886
C69: Target profit | D69: =IF(OR(COUNT(D68,Assumptions!$D$10)<2,Assumptions!$D$10<0),"",IF(Assumptions!$D$11="Profit on cost",D68*Assumptions!$D$10,IF(Assumptions!$D$11="Margin on sales",IF(Assumptions!$D$10>=1,"",D68/(1-Assumptions!$D$10)-D68),""))) -> 9450.6387 | E69: =IF(OR(COUNT(E68,Assumptions!$D$10)<2,Assumptions!$D$10<0),"",IF(Assumptions!$D$11="Profit on cost",E68*Assumptions!$D$10,IF(Assumptions!$D$11="Margin on sales",IF(Assumptions!$D$10>=1,"",E68/(1-Assumptions!$D$10)-E68),""))) -> 9734.1579 | F69: =IF(OR(COUNT(F68,Assumptions!$D$10)<2,Assumptions!$D$10<0),"",IF(Assumptions!$D$11="Profit on cost",F68*Assumptions!$D$10,IF(Assumptions!$D$11="Margin on sales",IF(Assumptions!$D$10>=1,"",F68/(1-Assumptions!$D$10)-F68),""))) -> 10026.183 | G69: =IF(OR(COUNT(G68,Assumptions!$D$10)<2,Assumptions!$D$10<0),"",IF(Assumptions!$D$11="Profit on cost",G68*Assumptions!$D$10,IF(Assumptions!$D$11="Margin on sales",IF(Assumptions!$D$10>=1,"",G68/(1-Assumptions!$D$10)-G68),""))) -> 10326.968 | H69: =IF(OR(COUNT(H68,Assumptions!$D$10)<2,Assumptions!$D$10<0),"",IF(Assumptions!$D$11="Profit on cost",H68*Assumptions!$D$10,IF(Assumptions!$D$11="Margin on sales",IF(Assumptions!$D$10>=1,"",H68/(1-Assumptions!$D$10)-H68),""))) -> 10636.777 | I69: =IF(OR(COUNT(I68,Assumptions!$D$10)<2,Assumptions!$D$10<0),"",IF(Assumptions!$D$11="Profit on cost",I68*Assumptions!$D$10,IF(Assumptions!$D$11="Margin on sales",IF(Assumptions!$D$10>=1,"",I68/(1-Assumptions!$D$10)-I68),""))) -> 5318.3886
C70: Calculated rate / hour | D70: =IF(D55="Use supplied loaded rate",IF(COUNTIFS('Source Data'!$C$21:$C$26,$C54)<>1,"",IF(INDEX('Source Data'!$I$21:$I$26,MATCH($C54,'Source Data'!$C$21:$C$26,0))="","",INDEX('Source Data'!$I$21:$I$26,MATCH($C54,'Source Data'!$C$21:$C$26,0)))),IF(OR(D55<>"Build from wage",COUNT(D68:D69)<2,NOT(ISNUMBER(Staffing!D33)),Staffing!D33<=0),"",SUM(D68:D69)/Staffing!D33)) -> 49.979339 | E70: =IF(E55="Use supplied loaded rate",IF(OR(COUNT(D70,Assumptions!E$46)<2,Assumptions!E$46<0,Assumptions!E$46>1),"",D70*(1+Assumptions!E$46)),IF(OR(E55<>"Build from wage",COUNT(E68:E69)<2,NOT(ISNUMBER(Staffing!E33)),Staffing!E33<=0),"",SUM(E68:E69)/Staffing!E33)) -> 51.47872 | F70: =IF(F55="Use supplied loaded rate",IF(OR(COUNT(E70,Assumptions!F$46)<2,Assumptions!F$46<0,Assumptions!F$46>1),"",E70*(1+Assumptions!F$46)),IF(OR(F55<>"Build from wage",COUNT(F68:F69)<2,NOT(ISNUMBER(Staffing!F33)),Staffing!F33<=0),"",SUM(F68:F69)/Staffing!F33)) -> 53.023081 | G70: =IF(G55="Use supplied loaded rate",IF(OR(COUNT(F70,Assumptions!G$46)<2,Assumptions!G$46<0,Assumptions!G$46>1),"",F70*(1+Assumptions!G$46)),IF(OR(G55<>"Build from wage",COUNT(G68:G69)<2,NOT(ISNUMBER(Staffing!G33)),Staffing!G33<=0),"",SUM(G68:G69)/Staffing!G33)) -> 54.613774 | H70: =IF(H55="Use supplied loaded rate",IF(OR(COUNT(G70,Assumptions!H$46)<2,Assumptions!H$46<0,Assumptions!H$46>1),"",G70*(1+Assumptions!H$46)),IF(OR(H55<>"Build from wage",COUNT(H68:H69)<2,NOT(ISNUMBER(Staffing!H33)),Staffing!H33<=0),"",SUM(H68:H69)/Staffing!H33)) -> 56.252187 | I70: =IF(I55="Use supplied loaded rate",IF(H70="","",H70),IF(OR(I55<>"Build from wage",COUNT(I68:I69)<2,NOT(ISNUMBER(Staffing!I33)),Staffing!I33<=0),"",SUM(I68:I69)/Staffing!I33)) -> 56.252187
C71: Period-rate override
C72: Selling rate / hour | D72: =IF(D71="",IF(OR(NOT(ISNUMBER(D70)),D70<0),"",ROUND(D70,4)),IF(AND(ISNUMBER(D71),D71>=0),ROUND(D71,4),"")) -> 49.9793 | E72: =IF(E71="",IF(OR(NOT(ISNUMBER(E70)),E70<0),"",ROUND(E70,4)),IF(AND(ISNUMBER(E71),E71>=0),ROUND(E71,4),"")) -> 51.4787 | F72: =IF(F71="",IF(OR(NOT(ISNUMBER(F70)),F70<0),"",ROUND(F70,4)),IF(AND(ISNUMBER(F71),F71>=0),ROUND(F71,4),"")) -> 53.0231 | G72: =IF(G71="",IF(OR(NOT(ISNUMBER(G70)),G70<0),"",ROUND(G70,4)),IF(AND(ISNUMBER(G71),G71>=0),ROUND(G71,4),"")) -> 54.6138 | H72: =IF(H71="",IF(OR(NOT(ISNUMBER(H70)),H70<0),"",ROUND(H70,4)),IF(AND(ISNUMBER(H71),H71>=0),ROUND(H71,4),"")) -> 56.2522 | I72: =IF(I71="",IF(OR(NOT(ISNUMBER(H72)),H72<0),"",ROUND(H72,4)),IF(AND(ISNUMBER(I71),I71>=0),ROUND(I71,4),"")) -> 56.2522
C73: Input status | D73: =IF(Staffing!D41<>"Complete",Staffing!D41,IF(AND(D55<>"Build from wage",D55<>"Use supplied loaded rate"),"Invalid rate basis",IF(Staffing!D33=0,"Zero hours",IF(D72="","Missing / invalid rate",IF(AND(D55="Build from wage",COUNT(D68:D69)<2),"Missing cost inputs","Complete"))))) -> Complete | E73: =IF(Staffing!E41<>"Complete",Staffing!E41,IF(AND(E55<>"Build from wage",E55<>"Use supplied loaded rate"),"Invalid rate basis",IF(Staffing!E33=0,"Zero hours",IF(E72="","Missing / invalid rate",IF(AND(E55="Build from wage",COUNT(E68:E69)<2),"Missing cost inputs","Complete"))))) -> Complete | F73: =IF(Staffing!F41<>"Complete",Staffing!F41,IF(AND(F55<>"Build from wage",F55<>"Use supplied loaded rate"),"Invalid rate basis",IF(Staffing!F33=0,"Zero hours",IF(F72="","Missing / invalid rate",IF(AND(F55="Build from wage",COUNT(F68:F69)<2),"Missing cost inputs","Complete"))))) -> Complete | G73: =IF(Staffing!G41<>"Complete",Staffing!G41,IF(AND(G55<>"Build from wage",G55<>"Use supplied loaded rate"),"Invalid rate basis",IF(Staffing!G33=0,"Zero hours",IF(G72="","Missing / invalid rate",IF(AND(G55="Build from wage",COUNT(G68:G69)<2),"Missing cost inputs","Complete"))))) -> Complete | H73: =IF(Staffing!H41<>"Complete",Staffing!H41,IF(AND(H55<>"Build from wage",H55<>"Use supplied loaded rate"),"Invalid rate basis",IF(Staffing!H33=0,"Zero hours",IF(H72="","Missing / invalid rate",IF(AND(H55="Build from wage",COUNT(H68:H69)<2),"Missing cost inputs","Complete"))))) -> Complete | I73: =IF(Staffing!I41<>"Complete",Staffing!I41,IF(AND(I55<>"Build from wage",I55<>"Use supplied loaded rate"),"Invalid rate basis",IF(Staffing!I33=0,"Zero hours",IF(I72="","Missing / invalid rate",IF(AND(I55="Build from wage",COUNT(I68:I69)<2),"Missing cost inputs","Complete"))))) -> Complete
C77: R04 | D77: =IF(COUNTIFS('Source Data'!$C$21:$C$26,$C77)<>1,"",IF(INDEX('Source Data'!$D$21:$D$26,MATCH($C77,'Source Data'!$C$21:$C$26,0))="","",INDEX('Source Data'!$D$21:$D$26,MATCH($C77,'Source Data'!$C$21:$C$26,0)))) -> Program Analyst I
C78: Rate basis | D78: =IF(COUNTIFS('Source Data'!$C$21:$C$26,$C77)<>1,"",IF(INDEX('Source Data'!$H$21:$H$26,MATCH($C77,'Source Data'!$C$21:$C$26,0))="","",INDEX('Source Data'!$H$21:$H$26,MATCH($C77,'Source Data'!$C$21:$C$26,0)))) -> Build from wage | E78: =IF(COUNTIFS('Source Data'!$C$21:$C$26,$C77)<>1,"",IF(INDEX('Source Data'!$H$21:$H$26,MATCH($C77,'Source Data'!$C$21:$C$26,0))="","",INDEX('Source Data'!$H$21:$H$26,MATCH($C77,'Source Data'!$C$21:$C$26,0)))) -> Build from wage | F78: =IF(COUNTIFS('Source Data'!$C$21:$C$26,$C77)<>1,"",IF(INDEX('Source Data'!$H$21:$H$26,MATCH($C77,'Source Data'!$C$21:$C$26,0))="","",INDEX('Source Data'!$H$21:$H$26,MATCH($C77,'Source Data'!$C$21:$C$26,0)))) -> Build from wage | G78: =IF(COUNTIFS('Source Data'!$C$21:$C$26,$C77)<>1,"",IF(INDEX('Source Data'!$H$21:$H$26,MATCH($C77,'Source Data'!$C$21:$C$26,0))="","",INDEX('Source Data'!$H$21:$H$26,MATCH($C77,'Source Data'!$C$21:$C$26,0)))) -> Build from wage | H78: =IF(COUNTIFS('Source Data'!$C$21:$C$26,$C77)<>1,"",IF(INDEX('Source Data'!$H$21:$H$26,MATCH($C77,'Source Data'!$C$21:$C$26,0))="","",INDEX('Source Data'!$H$21:$H$26,MATCH($C77,'Source Data'!$C$21:$C$26,0)))) -> Build from wage | I78: =IF(COUNTIFS('Source Data'!$C$21:$C$26,$C77)<>1,"",IF(INDEX('Source Data'!$H$21:$H$26,MATCH($C77,'Source Data'!$C$21:$C$26,0))="","",INDEX('Source Data'!$H$21:$H$26,MATCH($C77,'Source Data'!$C$21:$C$26,0)))) -> Build from wage
C79: Benchmark wage / hour | D79: =IF(COUNTIFS('Source Data'!$C$21:$C$26,$C77)<>1,"",IF(INDEX('Source Data'!$F$21:$F$26,MATCH($C77,'Source Data'!$C$21:$C$26,0))="","",INDEX('Source Data'!$F$21:$F$26,MATCH($C77,'Source Data'!$C$21:$C$26,0)))) -> 48.75 | E79: =IF(COUNTIFS('Source Data'!$C$21:$C$26,$C77)<>1,"",IF(INDEX('Source Data'!$F$21:$F$26,MATCH($C77,'Source Data'!$C$21:$C$26,0))="","",INDEX('Source Data'!$F$21:$F$26,MATCH($C77,'Source Data'!$C$21:$C$26,0)))) -> 48.75 | F79: =IF(COUNTIFS('Source Data'!$C$21:$C$26,$C77)<>1,"",IF(INDEX('Source Data'!$F$21:$F$26,MATCH($C77,'Source Data'!$C$21:$C$26,0))="","",INDEX('Source Data'!$F$21:$F$26,MATCH($C77,'Source Data'!$C$21:$C$26,0)))) -> 48.75 | G79: =IF(COUNTIFS('Source Data'!$C$21:$C$26,$C77)<>1,"",IF(INDEX('Source Data'!$F$21:$F$26,MATCH($C77,'Source Data'!$C$21:$C$26,0))="","",INDEX('Source Data'!$F$21:$F$26,MATCH($C77,'Source Data'!$C$21:$C$26,0)))) -> 48.75 | H79: =IF(COUNTIFS('Source Data'!$C$21:$C$26,$C77)<>1,"",IF(INDEX('Source Data'!$F$21:$F$26,MATCH($C77,'Source Data'!$C$21:$C$26,0))="","",INDEX('Source Data'!$F$21:$F$26,MATCH($C77,'Source Data'!$C$21:$C$26,0)))) -> 48.75 | I79: =IF(COUNTIFS('Source Data'!$C$21:$C$26,$C77)<>1,"",IF(INDEX('Source Data'!$F$21:$F$26,MATCH($C77,'Source Data'!$C$21:$C$26,0))="","",INDEX('Source Data'!$F$21:$F$26,MATCH($C77,'Source Data'!$C$21:$C$26,0)))) -> 48.75
C80: Benchmark year | D80: =IF(COUNTIFS('Source Data'!$C$21:$C$26,$C77)<>1,"",IF(INDEX('Source Data'!$G$21:$G$26,MATCH($C77,'Source Data'!$C$21:$C$26,0))="","",INDEX('Source Data'!$G$21:$G$26,MATCH($C77,'Source Data'!$C$21:$C$26,0)))) -> 2025 | E80: =IF(COUNTIFS('Source Data'!$C$21:$C$26,$C77)<>1,"",IF(INDEX('Source Data'!$G$21:$G$26,MATCH($C77,'Source Data'!$C$21:$C$26,0))="","",INDEX('Source Data'!$G$21:$G$26,MATCH($C77,'Source Data'!$C$21:$C$26,0)))) -> 2025 | F80: =IF(COUNTIFS('Source Data'!$C$21:$C$26,$C77)<>1,"",IF(INDEX('Source Data'!$G$21:$G$26,MATCH($C77,'Source Data'!$C$21:$C$26,0))="","",INDEX('Source Data'!$G$21:$G$26,MATCH($C77,'Source Data'!$C$21:$C$26,0)))) -> 2025 | G80: =IF(COUNTIFS('Source Data'!$C$21:$C$26,$C77)<>1,"",IF(INDEX('Source Data'!$G$21:$G$26,MATCH($C77,'Source Data'!$C$21:$C$26,0))="","",INDEX('Source Data'!$G$21:$G$26,MATCH($C77,'Source Data'!$C$21:$C$26,0)))) -> 2025 | H80: =IF(COUNTIFS('Source Data'!$C$21:$C$26,$C77)<>1,"",IF(INDEX('Source Data'!$G$21:$G$26,MATCH($C77,'Source Data'!$C$21:$C$26,0))="","",INDEX('Source Data'!$G$21:$G$26,MATCH($C77,'Source Data'!$C$21:$C$26,0)))) -> 2025 | I80: =IF(COUNTIFS('Source Data'!$C$21:$C$26,$C77)<>1,"",IF(INDEX('Source Data'!$G$21:$G$26,MATCH($C77,'Source Data'!$C$21:$C$26,0))="","",INDEX('Source Data'!$G$21:$G$26,MATCH($C77,'Source Data'!$C$21:$C$26,0)))) -> 2025
C81: Wage adjustment factor | D81: =IF(COUNT(D80,Assumptions!D$22,Assumptions!D$17)<3,"",IF(OR(Assumptions!D$22<0,Assumptions!D$22>1,YEAR(Assumptions!D$17)<D80),"",(1+Assumptions!D$22)^(YEAR(Assumptions!D$17)-D80))) -> 1.03 | E81: =IF(COUNT(E80,Assumptions!E$22,Assumptions!E$17)<3,"",IF(OR(Assumptions!E$22<0,Assumptions!E$22>1,YEAR(Assumptions!E$17)<E80),"",IF(D81="","",D81*(1+Assumptions!E$22)))) -> 1.0609 | F81: =IF(COUNT(F80,Assumptions!F$22,Assumptions!F$17)<3,"",IF(OR(Assumptions!F$22<0,Assumptions!F$22>1,YEAR(Assumptions!F$17)<F80),"",IF(E81="","",E81*(1+Assumptions!F$22)))) -> 1.092727 | G81: =IF(COUNT(G80,Assumptions!G$22,Assumptions!G$17)<3,"",IF(OR(Assumptions!G$22<0,Assumptions!G$22>1,YEAR(Assumptions!G$17)<G80),"",IF(F81="","",F81*(1+Assumptions!G$22)))) -> 1.1255088 | H81: =IF(COUNT(H80,Assumptions!H$22,Assumptions!H$17)<3,"",IF(OR(Assumptions!H$22<0,Assumptions!H$22>1,YEAR(Assumptions!H$17)<H80),"",IF(G81="","",G81*(1+Assumptions!H$22)))) -> 1.1592741 | I81: =IF(H81="","",H81) -> 1.1592741
C82: Adjusted wage / hour | D82: =IF(OR(D78<>"Build from wage",COUNT(D79,D81)<2,D79<0),"",D79*D81) -> 50.2125 | E82: =IF(OR(E78<>"Build from wage",COUNT(E79,E81)<2,E79<0),"",E79*E81) -> 51.718875 | F82: =IF(OR(F78<>"Build from wage",COUNT(F79,F81)<2,F79<0),"",F79*F81) -> 53.270441 | G82: =IF(OR(G78<>"Build from wage",COUNT(G79,G81)<2,G79<0),"",G79*G81) -> 54.868554 | H82: =IF(OR(H78<>"Build from wage",COUNT(H79,H81)<2,H79<0),"",H79*H81) -> 56.514611 | I82: =IF(OR(I78<>"Build from wage",COUNT(I79,I81)<2,I79<0),"",I79*I81) -> 56.514611
C83: Paid hours for cost | D83: =IF(Staffing!D52="","",Staffing!D52) -> 2351.3043 | E83: =IF(Staffing!E52="","",Staffing!E52) -> 2351.3043 | F83: =IF(Staffing!F52="","",Staffing!F52) -> 2351.3043 | G83: =IF(Staffing!G52="","",Staffing!G52) -> 2351.3043 | H83: =IF(Staffing!H52="","",Staffing!H52) -> 2351.3043 | I83: =IF(Staffing!I52="","",Staffing!I52) -> 1175.6522
C84: Paid labor cost | D84: =IF(COUNT(D82:D83)<2,"",D82*D83) -> 118064.87 | E84: =IF(COUNT(E82:E83)<2,"",E82*E83) -> 121606.82 | F84: =IF(COUNT(F82:F83)<2,"",F82*F83) -> 125255.02 | G84: =IF(COUNT(G82:G83)<2,"",G82*G83) -> 129012.67 | H84: =IF(COUNT(H82:H83)<2,"",H82*H83) -> 132883.05 | I84: =IF(COUNT(I82:I83)<2,"",I82*I83) -> 66441.525
C85: Fringe benefits | D85: =IF(OR(COUNT(D84,Assumptions!D$28)<2,Assumptions!D$28<0),"",D84*Assumptions!D$28) -> 29516.217 | E85: =IF(OR(COUNT(E84,Assumptions!E$28)<2,Assumptions!E$28<0),"",E84*Assumptions!E$28) -> 30401.704 | F85: =IF(OR(COUNT(F84,Assumptions!F$28)<2,Assumptions!F$28<0),"",F84*Assumptions!F$28) -> 31313.755 | G85: =IF(OR(COUNT(G84,Assumptions!G$28)<2,Assumptions!G$28<0),"",G84*Assumptions!G$28) -> 32253.168 | H85: =IF(OR(COUNT(H84,Assumptions!H$28)<2,Assumptions!H$28<0),"",H84*Assumptions!H$28) -> 33220.763 | I85: =IF(OR(COUNT(I84,Assumptions!I$28)<2,Assumptions!I$28<0),"",I84*Assumptions!I$28) -> 16610.381
C86: Additional hourly benefits | D86: =IF(OR(D78<>"Build from wage",COUNT(D83,Assumptions!$D$9)<2,Assumptions!$D$9<0),"",D83*Assumptions!$D$9) -> 0 | E86: =IF(OR(E78<>"Build from wage",COUNT(E83,Assumptions!$D$9)<2,Assumptions!$D$9<0),"",E83*Assumptions!$D$9) -> 0 | F86: =IF(OR(F78<>"Build from wage",COUNT(F83,Assumptions!$D$9)<2,Assumptions!$D$9<0),"",F83*Assumptions!$D$9) -> 0 | G86: =IF(OR(G78<>"Build from wage",COUNT(G83,Assumptions!$D$9)<2,Assumptions!$D$9<0),"",G83*Assumptions!$D$9) -> 0 | H86: =IF(OR(H78<>"Build from wage",COUNT(H83,Assumptions!$D$9)<2,Assumptions!$D$9<0),"",H83*Assumptions!$D$9) -> 0 | I86: =IF(OR(I78<>"Build from wage",COUNT(I83,Assumptions!$D$9)<2,Assumptions!$D$9<0),"",I83*Assumptions!$D$9) -> 0
C87: Labor plus benefits | D87: =IF(COUNT(D84:D86)<3,"",SUM(D84:D86)) -> 147581.09 | E87: =IF(COUNT(E84:E86)<3,"",SUM(E84:E86)) -> 152008.52 | F87: =IF(COUNT(F84:F86)<3,"",SUM(F84:F86)) -> 156568.78 | G87: =IF(COUNT(G84:G86)<3,"",SUM(G84:G86)) -> 161265.84 | H87: =IF(COUNT(H84:H86)<3,"",SUM(H84:H86)) -> 166103.81 | I87: =IF(COUNT(I84:I86)<3,"",SUM(I84:I86)) -> 83051.907
C88: Overhead | D88: =IF(OR(COUNT(D87,Assumptions!D$34)<2,Assumptions!D$34<0),"",D87*Assumptions!D$34) -> 14758.109 | E88: =IF(OR(COUNT(E87,Assumptions!E$34)<2,Assumptions!E$34<0),"",E87*Assumptions!E$34) -> 15200.852 | F88: =IF(OR(COUNT(F87,Assumptions!F$34)<2,Assumptions!F$34<0),"",F87*Assumptions!F$34) -> 15656.878 | G88: =IF(OR(COUNT(G87,Assumptions!G$34)<2,Assumptions!G$34<0),"",G87*Assumptions!G$34) -> 16126.584 | H88: =IF(OR(COUNT(H87,Assumptions!H$34)<2,Assumptions!H$34<0),"",H87*Assumptions!H$34) -> 16610.381 | I88: =IF(OR(COUNT(I87,Assumptions!I$34)<2,Assumptions!I$34<0),"",I87*Assumptions!I$34) -> 8305.1907
C89: Labor, benefits, overhead | D89: =IF(COUNT(D87:D88)<2,"",SUM(D87:D88)) -> 162339.2 | E89: =IF(COUNT(E87:E88)<2,"",SUM(E87:E88)) -> 167209.37 | F89: =IF(COUNT(F87:F88)<2,"",SUM(F87:F88)) -> 172225.65 | G89: =IF(COUNT(G87:G88)<2,"",SUM(G87:G88)) -> 177392.42 | H89: =IF(COUNT(H87:H88)<2,"",SUM(H87:H88)) -> 182714.19 | I89: =IF(COUNT(I87:I88)<2,"",SUM(I87:I88)) -> 91357.097
C90: G&A | D90: =IF(OR(COUNT(D89,Assumptions!D$40)<2,Assumptions!D$40<0),"",D89*Assumptions!D$40) -> 16233.92 | E90: =IF(OR(COUNT(E89,Assumptions!E$40)<2,Assumptions!E$40<0),"",E89*Assumptions!E$40) -> 16720.937 | F90: =IF(OR(COUNT(F89,Assumptions!F$40)<2,Assumptions!F$40<0),"",F89*Assumptions!F$40) -> 17222.565 | G90: =IF(OR(COUNT(G89,Assumptions!G$40)<2,Assumptions!G$40<0),"",G89*Assumptions!G$40) -> 17739.242 | H90: =IF(OR(COUNT(H89,Assumptions!H$40)<2,Assumptions!H$40<0),"",H89*Assumptions!H$40) -> 18271.419 | I90: =IF(OR(COUNT(I89,Assumptions!I$40)<2,Assumptions!I$40<0),"",I89*Assumptions!I$40) -> 9135.7097
C91: Total modeled cost | D91: =IF(COUNT(D89:D90)<2,"",SUM(D89:D90)) -> 178573.12 | E91: =IF(COUNT(E89:E90)<2,"",SUM(E89:E90)) -> 183930.31 | F91: =IF(COUNT(F89:F90)<2,"",SUM(F89:F90)) -> 189448.22 | G91: =IF(COUNT(G89:G90)<2,"",SUM(G89:G90)) -> 195131.66 | H91: =IF(COUNT(H89:H90)<2,"",SUM(H89:H90)) -> 200985.61 | I91: =IF(COUNT(I89:I90)<2,"",SUM(I89:I90)) -> 100492.81
C92: Target profit | D92: =IF(OR(COUNT(D91,Assumptions!$D$10)<2,Assumptions!$D$10<0),"",IF(Assumptions!$D$11="Profit on cost",D91*Assumptions!$D$10,IF(Assumptions!$D$11="Margin on sales",IF(Assumptions!$D$10>=1,"",D91/(1-Assumptions!$D$10)-D91),""))) -> 17857.312 | E92: =IF(OR(COUNT(E91,Assumptions!$D$10)<2,Assumptions!$D$10<0),"",IF(Assumptions!$D$11="Profit on cost",E91*Assumptions!$D$10,IF(Assumptions!$D$11="Margin on sales",IF(Assumptions!$D$10>=1,"",E91/(1-Assumptions!$D$10)-E91),""))) -> 18393.031 | F92: =IF(OR(COUNT(F91,Assumptions!$D$10)<2,Assumptions!$D$10<0),"",IF(Assumptions!$D$11="Profit on cost",F91*Assumptions!$D$10,IF(Assumptions!$D$11="Margin on sales",IF(Assumptions!$D$10>=1,"",F91/(1-Assumptions!$D$10)-F91),""))) -> 18944.822 | G92: =IF(OR(COUNT(G91,Assumptions!$D$10)<2,Assumptions!$D$10<0),"",IF(Assumptions!$D$11="Profit on cost",G91*Assumptions!$D$10,IF(Assumptions!$D$11="Margin on sales",IF(Assumptions!$D$10>=1,"",G91/(1-Assumptions!$D$10)-G91),""))) -> 19513.166 | H92: =IF(OR(COUNT(H91,Assumptions!$D$10)<2,Assumptions!$D$10<0),"",IF(Assumptions!$D$11="Profit on cost",H91*Assumptions!$D$10,IF(Assumptions!$D$11="Margin on sales",IF(Assumptions!$D$10>=1,"",H91/(1-Assumptions!$D$10)-H91),""))) -> 20098.561 | I92: =IF(OR(COUNT(I91,Assumptions!$D$10)<2,Assumptions!$D$10<0),"",IF(Assumptions!$D$11="Profit on cost",I91*Assumptions!$D$10,IF(Assumptions!$D$11="Margin on sales",IF(Assumptions!$D$10>=1,"",I91/(1-Assumptions!$D$10)-I91),""))) -> 10049.281
C93: Calculated rate / hour | D93: =IF(D78="Use supplied loaded rate",IF(COUNTIFS('Source Data'!$C$21:$C$26,$C77)<>1,"",IF(INDEX('Source Data'!$I$21:$I$26,MATCH($C77,'Source Data'!$C$21:$C$26,0))="","",INDEX('Source Data'!$I$21:$I$26,MATCH($C77,'Source Data'!$C$21:$C$26,0)))),IF(OR(D78<>"Build from wage",COUNT(D91:D92)<2,NOT(ISNUMBER(Staffing!D45)),Staffing!D45<=0),"",SUM(D91:D92)/Staffing!D45)) -> 94.437705 | E93: =IF(E78="Use supplied loaded rate",IF(OR(COUNT(D93,Assumptions!E$46)<2,Assumptions!E$46<0,Assumptions!E$46>1),"",D93*(1+Assumptions!E$46)),IF(OR(E78<>"Build from wage",COUNT(E91:E92)<2,NOT(ISNUMBER(Staffing!E45)),Staffing!E45<=0),"",SUM(E91:E92)/Staffing!E45)) -> 97.270836 | F93: =IF(F78="Use supplied loaded rate",IF(OR(COUNT(E93,Assumptions!F$46)<2,Assumptions!F$46<0,Assumptions!F$46>1),"",E93*(1+Assumptions!F$46)),IF(OR(F78<>"Build from wage",COUNT(F91:F92)<2,NOT(ISNUMBER(Staffing!F45)),Staffing!F45<=0),"",SUM(F91:F92)/Staffing!F45)) -> 100.18896 | G93: =IF(G78="Use supplied loaded rate",IF(OR(COUNT(F93,Assumptions!G$46)<2,Assumptions!G$46<0,Assumptions!G$46>1),"",F93*(1+Assumptions!G$46)),IF(OR(G78<>"Build from wage",COUNT(G91:G92)<2,NOT(ISNUMBER(Staffing!G45)),Staffing!G45<=0),"",SUM(G91:G92)/Staffing!G45)) -> 103.19463 | H93: =IF(H78="Use supplied loaded rate",IF(OR(COUNT(G93,Assumptions!H$46)<2,Assumptions!H$46<0,Assumptions!H$46>1),"",G93*(1+Assumptions!H$46)),IF(OR(H78<>"Build from wage",COUNT(H91:H92)<2,NOT(ISNUMBER(Staffing!H45)),Staffing!H45<=0),"",SUM(H91:H92)/Staffing!H45)) -> 106.29047 | I93: =IF(I78="Use supplied loaded rate",IF(H93="","",H93),IF(OR(I78<>"Build from wage",COUNT(I91:I92)<2,NOT(ISNUMBER(Staffing!I45)),Staffing!I45<=0),"",SUM(I91:I92)/Staffing!I45)) -> 106.29047
C94: Period-rate override
C95: Selling rate / hour | D95: =IF(D94="",IF(OR(NOT(ISNUMBER(D93)),D93<0),"",ROUND(D93,4)),IF(AND(ISNUMBER(D94),D94>=0),ROUND(D94,4),"")) -> 94.4377 | E95: =IF(E94="",IF(OR(NOT(ISNUMBER(E93)),E93<0),"",ROUND(E93,4)),IF(AND(ISNUMBER(E94),E94>=0),ROUND(E94,4),"")) -> 97.2708 | F95: =IF(F94="",IF(OR(NOT(ISNUMBER(F93)),F93<0),"",ROUND(F93,4)),IF(AND(ISNUMBER(F94),F94>=0),ROUND(F94,4),"")) -> 100.189 | G95: =IF(G94="",IF(OR(NOT(ISNUMBER(G93)),G93<0),"",ROUND(G93,4)),IF(AND(ISNUMBER(G94),G94>=0),ROUND(G94,4),"")) -> 103.1946 | H95: =IF(H94="",IF(OR(NOT(ISNUMBER(H93)),H93<0),"",ROUND(H93,4)),IF(AND(ISNUMBER(H94),H94>=0),ROUND(H94,4),"")) -> 106.2905 | I95: =IF(I94="",IF(OR(NOT(ISNUMBER(H95)),H95<0),"",ROUND(H95,4)),IF(AND(ISNUMBER(I94),I94>=0),ROUND(I94,4),"")) -> 106.2905
C96: Input status | D96: =IF(Staffing!D53<>"Complete",Staffing!D53,IF(AND(D78<>"Build from wage",D78<>"Use supplied loaded rate"),"Invalid rate basis",IF(Staffing!D45=0,"Zero hours",IF(D95="","Missing / invalid rate",IF(AND(D78="Build from wage",COUNT(D91:D92)<2),"Missing cost inputs","Complete"))))) -> Complete | E96: =IF(Staffing!E53<>"Complete",Staffing!E53,IF(AND(E78<>"Build from wage",E78<>"Use supplied loaded rate"),"Invalid rate basis",IF(Staffing!E45=0,"Zero hours",IF(E95="","Missing / invalid rate",IF(AND(E78="Build from wage",COUNT(E91:E92)<2),"Missing cost inputs","Complete"))))) -> Complete | F96: =IF(Staffing!F53<>"Complete",Staffing!F53,IF(AND(F78<>"Build from wage",F78<>"Use supplied loaded rate"),"Invalid rate basis",IF(Staffing!F45=0,"Zero hours",IF(F95="","Missing / invalid rate",IF(AND(F78="Build from wage",COUNT(F91:F92)<2),"Missing cost inputs","Complete"))))) -> Complete | G96: =IF(Staffing!G53<>"Complete",Staffing!G53,IF(AND(G78<>"Build from wage",G78<>"Use supplied loaded rate"),"Invalid rate basis",IF(Staffing!G45=0,"Zero hours",IF(G95="","Missing / invalid rate",IF(AND(G78="Build from wage",COUNT(G91:G92)<2),"Missing cost inputs","Complete"))))) -> Complete | H96: =IF(Staffing!H53<>"Complete",Staffing!H53,IF(AND(H78<>"Build from wage",H78<>"Use supplied loaded rate"),"Invalid rate basis",IF(Staffing!H45=0,"Zero hours",IF(H95="","Missing / invalid rate",IF(AND(H78="Build from wage",COUNT(H91:H92)<2),"Missing cost inputs","Complete"))))) -> Complete | I96: =IF(Staffing!I53<>"Complete",Staffing!I53,IF(AND(I78<>"Build from wage",I78<>"Use supplied loaded rate"),"Invalid rate basis",IF(Staffing!I45=0,"Zero hours",IF(I95="","Missing / invalid rate",IF(AND(I78="Build from wage",COUNT(I91:I92)<2),"Missing cost inputs","Complete"))))) -> Complete
C100: R05 | D100: =IF(COUNTIFS('Source Data'!$C$21:$C$26,$C100)<>1,"",IF(INDEX('Source Data'!$D$21:$D$26,MATCH($C100,'Source Data'!$C$21:$C$26,0))="","",INDEX('Source Data'!$D$21:$D$26,MATCH($C100,'Source Data'!$C$21:$C$26,0)))) -> Program Analyst II
C101: Rate basis | D101: =IF(COUNTIFS('Source Data'!$C$21:$C$26,$C100)<>1,"",IF(INDEX('Source Data'!$H$21:$H$26,MATCH($C100,'Source Data'!$C$21:$C$26,0))="","",INDEX('Source Data'!$H$21:$H$26,MATCH($C100,'Source Data'!$C$21:$C$26,0)))) -> Build from wage | E101: =IF(COUNTIFS('Source Data'!$C$21:$C$26,$C100)<>1,"",IF(INDEX('Source Data'!$H$21:$H$26,MATCH($C100,'Source Data'!$C$21:$C$26,0))="","",INDEX('Source Data'!$H$21:$H$26,MATCH($C100,'Source Data'!$C$21:$C$26,0)))) -> Build from wage | F101: =IF(COUNTIFS('Source Data'!$C$21:$C$26,$C100)<>1,"",IF(INDEX('Source Data'!$H$21:$H$26,MATCH($C100,'Source Data'!$C$21:$C$26,0))="","",INDEX('Source Data'!$H$21:$H$26,MATCH($C100,'Source Data'!$C$21:$C$26,0)))) -> Build from wage | G101: =IF(COUNTIFS('Source Data'!$C$21:$C$26,$C100)<>1,"",IF(INDEX('Source Data'!$H$21:$H$26,MATCH($C100,'Source Data'!$C$21:$C$26,0))="","",INDEX('Source Data'!$H$21:$H$26,MATCH($C100,'Source Data'!$C$21:$C$26,0)))) -> Build from wage | H101: =IF(COUNTIFS('Source Data'!$C$21:$C$26,$C100)<>1,"",IF(INDEX('Source Data'!$H$21:$H$26,MATCH($C100,'Source Data'!$C$21:$C$26,0))="","",INDEX('Source Data'!$H$21:$H$26,MATCH($C100,'Source Data'!$C$21:$C$26,0)))) -> Build from wage | I101: =IF(COUNTIFS('Source Data'!$C$21:$C$26,$C100)<>1,"",IF(INDEX('Source Data'!$H$21:$H$26,MATCH($C100,'Source Data'!$C$21:$C$26,0))="","",INDEX('Source Data'!$H$21:$H$26,MATCH($C100,'Source Data'!$C$21:$C$26,0)))) -> Build from wage
C102: Benchmark wage / hour | D102: =IF(COUNTIFS('Source Data'!$C$21:$C$26,$C100)<>1,"",IF(INDEX('Source Data'!$F$21:$F$26,MATCH($C100,'Source Data'!$C$21:$C$26,0))="","",INDEX('Source Data'!$F$21:$F$26,MATCH($C100,'Source Data'!$C$21:$C$26,0)))) -> 60.97 | E102: =IF(COUNTIFS('Source Data'!$C$21:$C$26,$C100)<>1,"",IF(INDEX('Source Data'!$F$21:$F$26,MATCH($C100,'Source Data'!$C$21:$C$26,0))="","",INDEX('Source Data'!$F$21:$F$26,MATCH($C100,'Source Data'!$C$21:$C$26,0)))) -> 60.97 | F102: =IF(COUNTIFS('Source Data'!$C$21:$C$26,$C100)<>1,"",IF(INDEX('Source Data'!$F$21:$F$26,MATCH($C100,'Source Data'!$C$21:$C$26,0))="","",INDEX('Source Data'!$F$21:$F$26,MATCH($C100,'Source Data'!$C$21:$C$26,0)))) -> 60.97 | G102: =IF(COUNTIFS('Source Data'!$C$21:$C$26,$C100)<>1,"",IF(INDEX('Source Data'!$F$21:$F$26,MATCH($C100,'Source Data'!$C$21:$C$26,0))="","",INDEX('Source Data'!$F$21:$F$26,MATCH($C100,'Source Data'!$C$21:$C$26,0)))) -> 60.97 | H102: =IF(COUNTIFS('Source Data'!$C$21:$C$26,$C100)<>1,"",IF(INDEX('Source Data'!$F$21:$F$26,MATCH($C100,'Source Data'!$C$21:$C$26,0))="","",INDEX('Source Data'!$F$21:$F$26,MATCH($C100,'Source Data'!$C$21:$C$26,0)))) -> 60.97 | I102: =IF(COUNTIFS('Source Data'!$C$21:$C$26,$C100)<>1,"",IF(INDEX('Source Data'!$F$21:$F$26,MATCH($C100,'Source Data'!$C$21:$C$26,0))="","",INDEX('Source Data'!$F$21:$F$26,MATCH($C100,'Source Data'!$C$21:$C$26,0)))) -> 60.97
C103: Benchmark year | D103: =IF(COUNTIFS('Source Data'!$C$21:$C$26,$C100)<>1,"",IF(INDEX('Source Data'!$G$21:$G$26,MATCH($C100,'Source Data'!$C$21:$C$26,0))="","",INDEX('Source Data'!$G$21:$G$26,MATCH($C100,'Source Data'!$C$21:$C$26,0)))) -> 2025 | E103: =IF(COUNTIFS('Source Data'!$C$21:$C$26,$C100)<>1,"",IF(INDEX('Source Data'!$G$21:$G$26,MATCH($C100,'Source Data'!$C$21:$C$26,0))="","",INDEX('Source Data'!$G$21:$G$26,MATCH($C100,'Source Data'!$C$21:$C$26,0)))) -> 2025 | F103: =IF(COUNTIFS('Source Data'!$C$21:$C$26,$C100)<>1,"",IF(INDEX('Source Data'!$G$21:$G$26,MATCH($C100,'Source Data'!$C$21:$C$26,0))="","",INDEX('Source Data'!$G$21:$G$26,MATCH($C100,'Source Data'!$C$21:$C$26,0)))) -> 2025 | G103: =IF(COUNTIFS('Source Data'!$C$21:$C$26,$C100)<>1,"",IF(INDEX('Source Data'!$G$21:$G$26,MATCH($C100,'Source Data'!$C$21:$C$26,0))="","",INDEX('Source Data'!$G$21:$G$26,MATCH($C100,'Source Data'!$C$21:$C$26,0)))) -> 2025 | H103: =IF(COUNTIFS('Source Data'!$C$21:$C$26,$C100)<>1,"",IF(INDEX('Source Data'!$G$21:$G$26,MATCH($C100,'Source Data'!$C$21:$C$26,0))="","",INDEX('Source Data'!$G$21:$G$26,MATCH($C100,'Source Data'!$C$21:$C$26,0)))) -> 2025 | I103: =IF(COUNTIFS('Source Data'!$C$21:$C$26,$C100)<>1,"",IF(INDEX('Source Data'!$G$21:$G$26,MATCH($C100,'Source Data'!$C$21:$C$26,0))="","",INDEX('Source Data'!$G$21:$G$26,MATCH($C100,'Source Data'!$C$21:$C$26,0)))) -> 2025
C104: Wage adjustment factor | D104: =IF(COUNT(D103,Assumptions!D$22,Assumptions!D$17)<3,"",IF(OR(Assumptions!D$22<0,Assumptions!D$22>1,YEAR(Assumptions!D$17)<D103),"",(1+Assumptions!D$22)^(YEAR(Assumptions!D$17)-D103))) -> 1.03 | E104: =IF(COUNT(E103,Assumptions!E$22,Assumptions!E$17)<3,"",IF(OR(Assumptions!E$22<0,Assumptions!E$22>1,YEAR(Assumptions!E$17)<E103),"",IF(D104="","",D104*(1+Assumptions!E$22)))) -> 1.0609 | F104: =IF(COUNT(F103,Assumptions!F$22,Assumptions!F$17)<3,"",IF(OR(Assumptions!F$22<0,Assumptions!F$22>1,YEAR(Assumptions!F$17)<F103),"",IF(E104="","",E104*(1+Assumptions!F$22)))) -> 1.092727 | G104: =IF(COUNT(G103,Assumptions!G$22,Assumptions!G$17)<3,"",IF(OR(Assumptions!G$22<0,Assumptions!G$22>1,YEAR(Assumptions!G$17)<G103),"",IF(F104="","",F104*(1+Assumptions!G$22)))) -> 1.1255088 | H104: =IF(COUNT(H103,Assumptions!H$22,Assumptions!H$17)<3,"",IF(OR(Assumptions!H$22<0,Assumptions!H$22>1,YEAR(Assumptions!H$17)<H103),"",IF(G104="","",G104*(1+Assumptions!H$22)))) -> 1.1592741 | I104: =IF(H104="","",H104) -> 1.1592741
C105: Adjusted wage / hour | D105: =IF(OR(D101<>"Build from wage",COUNT(D102,D104)<2,D102<0),"",D102*D104) -> 62.7991 | E105: =IF(OR(E101<>"Build from wage",COUNT(E102,E104)<2,E102<0),"",E102*E104) -> 64.683073 | F105: =IF(OR(F101<>"Build from wage",COUNT(F102,F104)<2,F102<0),"",F102*F104) -> 66.623565 | G105: =IF(OR(G101<>"Build from wage",COUNT(G102,G104)<2,G102<0),"",G102*G104) -> 68.622272 | H105: =IF(OR(H101<>"Build from wage",COUNT(H102,H104)<2,H102<0),"",H102*H104) -> 70.68094 | I105: =IF(OR(I101<>"Build from wage",COUNT(I102,I104)<2,I102<0),"",I102*I104) -> 70.68094
C106: Paid hours for cost | D106: =IF(Staffing!D64="","",Staffing!D64) -> 4702.6087 | E106: =IF(Staffing!E64="","",Staffing!E64) -> 4702.6087 | F106: =IF(Staffing!F64="","",Staffing!F64) -> 4702.6087 | G106: =IF(Staffing!G64="","",Staffing!G64) -> 4702.6087 | H106: =IF(Staffing!H64="","",Staffing!H64) -> 4702.6087 | I106: =IF(Staffing!I64="","",Staffing!I64) -> 2351.3043
C107: Paid labor cost | D107: =IF(COUNT(D105:D106)<2,"",D105*D106) -> 295319.59 | E107: =IF(COUNT(E105:E106)<2,"",E105*E106) -> 304179.18 | F107: =IF(COUNT(F105:F106)<2,"",F105*F106) -> 313304.56 | G107: =IF(COUNT(G105:G106)<2,"",G105*G106) -> 322703.69 | H107: =IF(COUNT(H105:H106)<2,"",H105*H106) -> 332384.8 | I107: =IF(COUNT(I105:I106)<2,"",I105*I106) -> 166192.4
C108: Fringe benefits | D108: =IF(OR(COUNT(D107,Assumptions!D$28)<2,Assumptions!D$28<0),"",D107*Assumptions!D$28) -> 73829.898 | E108: =IF(OR(COUNT(E107,Assumptions!E$28)<2,Assumptions!E$28<0),"",E107*Assumptions!E$28) -> 76044.795 | F108: =IF(OR(COUNT(F107,Assumptions!F$28)<2,Assumptions!F$28<0),"",F107*Assumptions!F$28) -> 78326.139 | G108: =IF(OR(COUNT(G107,Assumptions!G$28)<2,Assumptions!G$28<0),"",G107*Assumptions!G$28) -> 80675.923 | H108: =IF(OR(COUNT(H107,Assumptions!H$28)<2,Assumptions!H$28<0),"",H107*Assumptions!H$28) -> 83096.201 | I108: =IF(OR(COUNT(I107,Assumptions!I$28)<2,Assumptions!I$28<0),"",I107*Assumptions!I$28) -> 41548.101
C109: Additional hourly benefits | D109: =IF(OR(D101<>"Build from wage",COUNT(D106,Assumptions!$D$9)<2,Assumptions!$D$9<0),"",D106*Assumptions!$D$9) -> 0 | E109: =IF(OR(E101<>"Build from wage",COUNT(E106,Assumptions!$D$9)<2,Assumptions!$D$9<0),"",E106*Assumptions!$D$9) -> 0 | F109: =IF(OR(F101<>"Build from wage",COUNT(F106,Assumptions!$D$9)<2,Assumptions!$D$9<0),"",F106*Assumptions!$D$9) -> 0 | G109: =IF(OR(G101<>"Build from wage",COUNT(G106,Assumptions!$D$9)<2,Assumptions!$D$9<0),"",G106*Assumptions!$D$9) -> 0 | H109: =IF(OR(H101<>"Build from wage",COUNT(H106,Assumptions!$D$9)<2,Assumptions!$D$9<0),"",H106*Assumptions!$D$9) -> 0 | I109: =IF(OR(I101<>"Build from wage",COUNT(I106,Assumptions!$D$9)<2,Assumptions!$D$9<0),"",I106*Assumptions!$D$9) -> 0
C110: Labor plus benefits | D110: =IF(COUNT(D107:D109)<3,"",SUM(D107:D109)) -> 369149.49 | E110: =IF(COUNT(E107:E109)<3,"",SUM(E107:E109)) -> 380223.98 | F110: =IF(COUNT(F107:F109)<3,"",SUM(F107:F109)) -> 391630.7 | G110: =IF(COUNT(G107:G109)<3,"",SUM(G107:G109)) -> 403379.62 | H110: =IF(COUNT(H107:H109)<3,"",SUM(H107:H109)) -> 415481.01 | I110: =IF(COUNT(I107:I109)<3,"",SUM(I107:I109)) -> 207740.5
C111: Overhead | D111: =IF(OR(COUNT(D110,Assumptions!D$34)<2,Assumptions!D$34<0),"",D110*Assumptions!D$34) -> 36914.949 | E111: =IF(OR(COUNT(E110,Assumptions!E$34)<2,Assumptions!E$34<0),"",E110*Assumptions!E$34) -> 38022.398 | F111: =IF(OR(COUNT(F110,Assumptions!F$34)<2,Assumptions!F$34<0),"",F110*Assumptions!F$34) -> 39163.07 | G111: =IF(OR(COUNT(G110,Assumptions!G$34)<2,Assumptions!G$34<0),"",G110*Assumptions!G$34) -> 40337.962 | H111: =IF(OR(COUNT(H110,Assumptions!H$34)<2,Assumptions!H$34<0),"",H110*Assumptions!H$34) -> 41548.101 | I111: =IF(OR(COUNT(I110,Assumptions!I$34)<2,Assumptions!I$34<0),"",I110*Assumptions!I$34) -> 20774.05
C112: Labor, benefits, overhead | D112: =IF(COUNT(D110:D111)<2,"",SUM(D110:D111)) -> 406064.44 | E112: =IF(COUNT(E110:E111)<2,"",SUM(E110:E111)) -> 418246.37 | F112: =IF(COUNT(F110:F111)<2,"",SUM(F110:F111)) -> 430793.77 | G112: =IF(COUNT(G110:G111)<2,"",SUM(G110:G111)) -> 443717.58 | H112: =IF(COUNT(H110:H111)<2,"",SUM(H110:H111)) -> 457029.11 | I112: =IF(COUNT(I110:I111)<2,"",SUM(I110:I111)) -> 228514.55
C113: G&A | D113: =IF(OR(COUNT(D112,Assumptions!D$40)<2,Assumptions!D$40<0),"",D112*Assumptions!D$40) -> 40606.444 | E113: =IF(OR(COUNT(E112,Assumptions!E$40)<2,Assumptions!E$40<0),"",E112*Assumptions!E$40) -> 41824.637 | F113: =IF(OR(COUNT(F112,Assumptions!F$40)<2,Assumptions!F$40<0),"",F112*Assumptions!F$40) -> 43079.377 | G113: =IF(OR(COUNT(G112,Assumptions!G$40)<2,Assumptions!G$40<0),"",G112*Assumptions!G$40) -> 44371.758 | H113: =IF(OR(COUNT(H112,Assumptions!H$40)<2,Assumptions!H$40<0),"",H112*Assumptions!H$40) -> 45702.911 | I113: =IF(OR(COUNT(I112,Assumptions!I$40)<2,Assumptions!I$40<0),"",I112*Assumptions!I$40) -> 22851.455
C114: Total modeled cost | D114: =IF(COUNT(D112:D113)<2,"",SUM(D112:D113)) -> 446670.89 | E114: =IF(COUNT(E112:E113)<2,"",SUM(E112:E113)) -> 460071.01 | F114: =IF(COUNT(F112:F113)<2,"",SUM(F112:F113)) -> 473873.14 | G114: =IF(COUNT(G112:G113)<2,"",SUM(G112:G113)) -> 488089.34 | H114: =IF(COUNT(H112:H113)<2,"",SUM(H112:H113)) -> 502732.02 | I114: =IF(COUNT(I112:I113)<2,"",SUM(I112:I113)) -> 251366.01
C115: Target profit | D115: =IF(OR(COUNT(D114,Assumptions!$D$10)<2,Assumptions!$D$10<0),"",IF(Assumptions!$D$11="Profit on cost",D114*Assumptions!$D$10,IF(Assumptions!$D$11="Margin on sales",IF(Assumptions!$D$10>=1,"",D114/(1-Assumptions!$D$10)-D114),""))) -> 44667.089 | E115: =IF(OR(COUNT(E114,Assumptions!$D$10)<2,Assumptions!$D$10<0),"",IF(Assumptions!$D$11="Profit on cost",E114*Assumptions!$D$10,IF(Assumptions!$D$11="Margin on sales",IF(Assumptions!$D$10>=1,"",E114/(1-Assumptions!$D$10)-E114),""))) -> 46007.101 | F115: =IF(OR(COUNT(F114,Assumptions!$D$10)<2,Assumptions!$D$10<0),"",IF(Assumptions!$D$11="Profit on cost",F114*Assumptions!$D$10,IF(Assumptions!$D$11="Margin on sales",IF(Assumptions!$D$10>=1,"",F114/(1-Assumptions!$D$10)-F114),""))) -> 47387.314 | G115: =IF(OR(COUNT(G114,Assumptions!$D$10)<2,Assumptions!$D$10<0),"",IF(Assumptions!$D$11="Profit on cost",G114*Assumptions!$D$10,IF(Assumptions!$D$11="Margin on sales",IF(Assumptions!$D$10>=1,"",G114/(1-Assumptions!$D$10)-G114),""))) -> 48808.934 | H115: =IF(OR(COUNT(H114,Assumptions!$D$10)<2,Assumptions!$D$10<0),"",IF(Assumptions!$D$11="Profit on cost",H114*Assumptions!$D$10,IF(Assumptions!$D$11="Margin on sales",IF(Assumptions!$D$10>=1,"",H114/(1-Assumptions!$D$10)-H114),""))) -> 50273.202 | I115: =IF(OR(COUNT(I114,Assumptions!$D$10)<2,Assumptions!$D$10<0),"",IF(Assumptions!$D$11="Profit on cost",I114*Assumptions!$D$10,IF(Assumptions!$D$11="Margin on sales",IF(Assumptions!$D$10>=1,"",I114/(1-Assumptions!$D$10)-I114),""))) -> 25136.601
C116: Calculated rate / hour | D116: =IF(D101="Use supplied loaded rate",IF(COUNTIFS('Source Data'!$C$21:$C$26,$C100)<>1,"",IF(INDEX('Source Data'!$I$21:$I$26,MATCH($C100,'Source Data'!$C$21:$C$26,0))="","",INDEX('Source Data'!$I$21:$I$26,MATCH($C100,'Source Data'!$C$21:$C$26,0)))),IF(OR(D101<>"Build from wage",COUNT(D114:D115)<2,NOT(ISNUMBER(Staffing!D57)),Staffing!D57<=0),"",SUM(D114:D115)/Staffing!D57)) -> 118.11009 | E116: =IF(E101="Use supplied loaded rate",IF(OR(COUNT(D116,Assumptions!E$46)<2,Assumptions!E$46<0,Assumptions!E$46>1),"",D116*(1+Assumptions!E$46)),IF(OR(E101<>"Build from wage",COUNT(E114:E115)<2,NOT(ISNUMBER(Staffing!E57)),Staffing!E57<=0),"",SUM(E114:E115)/Staffing!E57)) -> 121.65339 | F116: =IF(F101="Use supplied loaded rate",IF(OR(COUNT(E116,Assumptions!F$46)<2,Assumptions!F$46<0,Assumptions!F$46>1),"",E116*(1+Assumptions!F$46)),IF(OR(F101<>"Build from wage",COUNT(F114:F115)<2,NOT(ISNUMBER(Staffing!F57)),Staffing!F57<=0),"",SUM(F114:F115)/Staffing!F57)) -> 125.30299 | G116: =IF(G101="Use supplied loaded rate",IF(OR(COUNT(F116,Assumptions!G$46)<2,Assumptions!G$46<0,Assumptions!G$46>1),"",F116*(1+Assumptions!G$46)),IF(OR(G101<>"Build from wage",COUNT(G114:G115)<2,NOT(ISNUMBER(Staffing!G57)),Staffing!G57<=0),"",SUM(G114:G115)/Staffing!G57)) -> 129.06208 | H116: =IF(H101="Use supplied loaded rate",IF(OR(COUNT(G116,Assumptions!H$46)<2,Assumptions!H$46<0,Assumptions!H$46>1),"",G116*(1+Assumptions!H$46)),IF(OR(H101<>"Build from wage",COUNT(H114:H115)<2,NOT(ISNUMBER(Staffing!H57)),Staffing!H57<=0),"",SUM(H114:H115)/Staffing!H57)) -> 132.93395 | I116: =IF(I101="Use supplied loaded rate",IF(H116="","",H116),IF(OR(I101<>"Build from wage",COUNT(I114:I115)<2,NOT(ISNUMBER(Staffing!I57)),Staffing!I57<=0),"",SUM(I114:I115)/Staffing!I57)) -> 132.93395
...

Sheet Pricing
C2: Pricing
C4: Scenario | D4: =Assumptions!$D$4 -> Base
C8: Base
C9: Role ID | D9: Labor category | E9: Hours | F9: Rate / hour | G9: Price | H9: Modeled cost | I9: Profit
C10: R01 | D10: =IF(COUNTIFS('Source Data'!$C$21:$C$26,$C10)<>1,"",IF(INDEX('Source Data'!$D$21:$D$26,MATCH($C10,'Source Data'!$C$21:$C$26,0))="","",INDEX('Source Data'!$D$21:$D$26,MATCH($C10,'Source Data'!$C$21:$C$26,0)))) -> On-Site Supervisor | E10: =IF(Staffing!D9="","",Staffing!D9) -> 2080 | F10: =IF('Labor Rates'!D26="","",'Labor Rates'!D26) -> 89.5173 | G10: =IF(E10="","",IF(E10=0,0,IF(COUNT(E10:F10)<2,"",ROUND(E10*F10,2)))) -> 186195.98 | H10: =IF(E10="","",IF('Labor Rates'!D22="","n.a.",ROUND('Labor Rates'!D22,2))) -> 169269 | I10: =IF(G10="","",IF(ISNUMBER(H10),G10-H10,"n.a.")) -> 16926.98
C11: R02 | D11: =IF(COUNTIFS('Source Data'!$C$21:$C$26,$C11)<>1,"",IF(INDEX('Source Data'!$D$21:$D$26,MATCH($C11,'Source Data'!$C$21:$C$26,0))="","",INDEX('Source Data'!$D$21:$D$26,MATCH($C11,'Source Data'!$C$21:$C$26,0)))) -> Financial Analyst | E11: =IF(Staffing!D21="","",Staffing!D21) -> 4160 | F11: =IF('Labor Rates'!D49="","",'Labor Rates'!D49) -> 117.8195 | G11: =IF(E11="","",IF(E11=0,0,IF(COUNT(E11:F11)<2,"",ROUND(E11*F11,2)))) -> 490129.12 | H11: =IF(E11="","",IF('Labor Rates'!D45="","n.a.",ROUND('Labor Rates'!D45,2))) -> 445571.97 | I11: =IF(G11="","",IF(ISNUMBER(H11),G11-H11,"n.a.")) -> 44557.15
C12: R03 | D12: =IF(COUNTIFS('Source Data'!$C$21:$C$26,$C12)<>1,"",IF(INDEX('Source Data'!$D$21:$D$26,MATCH($C12,'Source Data'!$C$21:$C$26,0))="","",INDEX('Source Data'!$D$21:$D$26,MATCH($C12,'Source Data'!$C$21:$C$26,0)))) -> Administrative Assistant | E12: =IF(Staffing!D33="","",Staffing!D33) -> 2080 | F12: =IF('Labor Rates'!D72="","",'Labor Rates'!D72) -> 49.9793 | G12: =IF(E12="","",IF(E12=0,0,IF(COUNT(E12:F12)<2,"",ROUND(E12*F12,2)))) -> 103956.94 | H12: =IF(E12="","",IF('Labor Rates'!D68="","n.a.",ROUND('Labor Rates'!D68,2))) -> 94506.39 | I12: =IF(G12="","",IF(ISNUMBER(H12),G12-H12,"n.a.")) -> 9450.55
C13: R04 | D13: =IF(COUNTIFS('Source Data'!$C$21:$C$26,$C13)<>1,"",IF(INDEX('Source Data'!$D$21:$D$26,MATCH($C13,'Source Data'!$C$21:$C$26,0))="","",INDEX('Source Data'!$D$21:$D$26,MATCH($C13,'Source Data'!$C$21:$C$26,0)))) -> Program Analyst I | E13: =IF(Staffing!D45="","",Staffing!D45) -> 2080 | F13: =IF('Labor Rates'!D95="","",'Labor Rates'!D95) -> 94.4377 | G13: =IF(E13="","",IF(E13=0,0,IF(COUNT(E13:F13)<2,"",ROUND(E13*F13,2)))) -> 196430.42 | H13: =IF(E13="","",IF('Labor Rates'!D91="","n.a.",ROUND('Labor Rates'!D91,2))) -> 178573.12 | I13: =IF(G13="","",IF(ISNUMBER(H13),G13-H13,"n.a.")) -> 17857.3
C14: R05 | D14: =IF(COUNTIFS('Source Data'!$C$21:$C$26,$C14)<>1,"",IF(INDEX('Source Data'!$D$21:$D$26,MATCH($C14,'Source Data'!$C$21:$C$26,0))="","",INDEX('Source Data'!$D$21:$D$26,MATCH($C14,'Source Data'!$C$21:$C$26,0)))) -> Program Analyst II | E14: =IF(Staffing!D57="","",Staffing!D57) -> 4160 | F14: =IF('Labor Rates'!D118="","",'Labor Rates'!D118) -> 118.1101 | G14: =IF(E14="","",IF(E14=0,0,IF(COUNT(E14:F14)<2,"",ROUND(E14*F14,2)))) -> 491338.02 | H14: =IF(E14="","",IF('Labor Rates'!D114="","n.a.",ROUND('Labor Rates'!D114,2))) -> 446670.89 | I14: =IF(G14="","",IF(ISNUMBER(H14),G14-H14,"n.a.")) -> 44667.13
C15: R06 | D15: =IF(COUNTIFS('Source Data'!$C$21:$C$26,$C15)<>1,"",IF(INDEX('Source Data'!$D$21:$D$26,MATCH($C15,'Source Data'!$C$21:$C$26,0))="","",INDEX('Source Data'!$D$21:$D$26,MATCH($C15,'Source Data'!$C$21:$C$26,0)))) -> Program Analyst III | E15: =IF(Staffing!D69="","",Staffing!D69) -> 2080 | F15: =IF('Labor Rates'!D141="","",'Labor Rates'!D141) -> 145.9862 | G15: =IF(E15="","",IF(E15=0,0,IF(COUNT(E15:F15)<2,"",ROUND(E15*F15,2)))) -> 303651.3 | H15: =IF(E15="","",IF('Labor Rates'!D137="","n.a.",ROUND('Labor Rates'!D137,2))) -> 276046.56 | I15: =IF(G15="","",IF(ISNUMBER(H15),G15-H15,"n.a.")) -> 27604.74
D16: Total | E16: =IF(COUNT(E10:E15)<6,"",SUM(E10:E15)) -> 16640 | G16: =IF(COUNT(G10:G15)<6,"",SUM(G10:G15)) -> 1771701.8 | H16: =IF(COUNT(H10:H15)<6,"n.a.",SUM(H10:H15)) -> 1610637.9 | I16: =IF(COUNT(I10:I15)<6,"n.a.",SUM(I10:I15)) -> 161063.85
C19: Option 1
C20: Role ID | D20: Labor category | E20: Hours | F20: Rate / hour | G20: Price | H20: Modeled cost | I20: Profit
C21: R01 | D21: =IF(COUNTIFS('Source Data'!$C$21:$C$26,$C21)<>1,"",IF(INDEX('Source Data'!$D$21:$D$26,MATCH($C21,'Source Data'!$C$21:$C$26,0))="","",INDEX('Source Data'!$D$21:$D$26,MATCH($C21,'Source Data'!$C$21:$C$26,0)))) -> On-Site Supervisor | E21: =IF(Staffing!E9="","",Staffing!E9) -> 2080 | F21: =IF('Labor Rates'!E26="","",'Labor Rates'!E26) -> 92.2028 | G21: =IF(E21="","",IF(E21=0,0,IF(COUNT(E21:F21)<2,"",ROUND(E21*F21,2)))) -> 191781.82 | H21: =IF(E21="","",IF('Labor Rates'!E22="","n.a.",ROUND('Labor Rates'!E22,2))) -> 174347.07 | I21: =IF(G21="","",IF(ISNUMBER(H21),G21-H21,"n.a.")) -> 17434.75
C22: R02 | D22: =IF(COUNTIFS('Source Data'!$C$21:$C$26,$C22)<>1,"",IF(INDEX('Source Data'!$D$21:$D$26,MATCH($C22,'Source Data'!$C$21:$C$26,0))="","",INDEX('Source Data'!$D$21:$D$26,MATCH($C22,'Source Data'!$C$21:$C$26,0)))) -> Financial Analyst | E22: =IF(Staffing!E21="","",Staffing!E21) -> 4160 | F22: =IF('Labor Rates'!E49="","",'Labor Rates'!E49) -> 121.3541 | G22: =IF(E22="","",IF(E22=0,0,IF(COUNT(E22:F22)<2,"",ROUND(E22*F22,2)))) -> 504833.06 | H22: =IF(E22="","",IF('Labor Rates'!E45="","n.a.",ROUND('Labor Rates'!E45,2))) -> 458939.13 | I22: =IF(G22="","",IF(ISNUMBER(H22),G22-H22,"n.a.")) -> 45893.93
C23: R03 | D23: =IF(COUNTIFS('Source Data'!$C$21:$C$26,$C23)<>1,"",IF(INDEX('Source Data'!$D$21:$D$26,MATCH($C23,'Source Data'!$C$21:$C$26,0))="","",INDEX('Source Data'!$D$21:$D$26,MATCH($C23,'Source Data'!$C$21:$C$26,0)))) -> Administrative Assistant | E23: =IF(Staffing!E33="","",Staffing!E33) -> 2080 | F23: =IF('Labor Rates'!E72="","",'Labor Rates'!E72) -> 51.4787 | G23: =IF(E23="","",IF(E23=0,0,IF(COUNT(E23:F23)<2,"",ROUND(E23*F23,2)))) -> 107075.7 | H23: =IF(E23="","",IF('Labor Rates'!E68="","n.a.",ROUND('Labor Rates'!E68,2))) -> 97341.58 | I23: =IF(G23="","",IF(ISNUMBER(H23),G23-H23,"n.a.")) -> 9734.12
C24: R04 | D24: =IF(COUNTIFS('Source Data'!$C$21:$C$26,$C24)<>1,"",IF(INDEX('Source Data'!$D$21:$D$26,MATCH($C24,'Source Data'!$C$21:$C$26,0))="","",INDEX('Source Data'!$D$21:$D$26,MATCH($C24,'Source Data'!$C$21:$C$26,0)))) -> Program Analyst I | E24: =IF(Staffing!E45="","",Staffing!E45) -> 2080 | F24: =IF('Labor Rates'!E95="","",'Labor Rates'!E95) -> 97.2708 | G24: =IF(E24="","",IF(E24=0,0,IF(COUNT(E24:F24)<2,"",ROUND(E24*F24,2)))) -> 202323.26 | H24: =IF(E24="","",IF('Labor Rates'!E91="","n.a.",ROUND('Labor Rates'!E91,2))) -> 183930.31 | I24: =IF(G24="","",IF(ISNUMBER(H24),G24-H24,"n.a.")) -> 18392.95
C25: R05 | D25: =IF(COUNTIFS('Source Data'!$C$21:$C$26,$C25)<>1,"",IF(INDEX('Source Data'!$D$21:$D$26,MATCH($C25,'Source Data'!$C$21:$C$26,0))="","",INDEX('Source Data'!$D$21:$D$26,MATCH($C25,'Source Data'!$C$21:$C$26,0)))) -> Program Analyst II | E25: =IF(Staffing!E57="","",Staffing!E57) -> 4160 | F25: =IF('Labor Rates'!E118="","",'Labor Rates'!E118) -> 121.6534 | G25: =IF(E25="","",IF(E25=0,0,IF(COUNT(E25:F25)<2,"",ROUND(E25*F25,2)))) -> 506078.14 | H25: =IF(E25="","",IF('Labor Rates'!E114="","n.a.",ROUND('Labor Rates'!E114,2))) -> 460071.01 | I25: =IF(G25="","",IF(ISNUMBER(H25),G25-H25,"n.a.")) -> 46007.13
C26: R06 | D26: =IF(COUNTIFS('Source Data'!$C$21:$C$26,$C26)<>1,"",IF(INDEX('Source Data'!$D$21:$D$26,MATCH($C26,'Source Data'!$C$21:$C$26,0))="","",INDEX('Source Data'!$D$21:$D$26,MATCH($C26,'Source Data'!$C$21:$C$26,0)))) -> Program Analyst III | E26: =IF(Staffing!E69="","",Staffing!E69) -> 2080 | F26: =IF('Labor Rates'!E141="","",'Labor Rates'!E141) -> 150.3657 | G26: =IF(E26="","",IF(E26=0,0,IF(COUNT(E26:F26)<2,"",ROUND(E26*F26,2)))) -> 312760.66 | H26: =IF(E26="","",IF('Labor Rates'!E137="","n.a.",ROUND('Labor Rates'!E137,2))) -> 284327.96 | I26: =IF(G26="","",IF(ISNUMBER(H26),G26-H26,"n.a.")) -> 28432.7
D27: Total | E27: =IF(COUNT(E21:E26)<6,"",SUM(E21:E26)) -> 16640 | G27: =IF(COUNT(G21:G26)<6,"",SUM(G21:G26)) -> 1824852.6 | H27: =IF(COUNT(H21:H26)<6,"n.a.",SUM(H21:H26)) -> 1658957.1 | I27: =IF(COUNT(I21:I26)<6,"n.a.",SUM(I21:I26)) -> 165895.58
C30: Option 2
C31: Role ID | D31: Labor category | E31: Hours | F31: Rate / hour | G31: Price | H31: Modeled cost | I31: Profit
C32: R01 | D32: =IF(COUNTIFS('Source Data'!$C$21:$C$26,$C32)<>1,"",IF(INDEX('Source Data'!$D$21:$D$26,MATCH($C32,'Source Data'!$C$21:$C$26,0))="","",INDEX('Source Data'!$D$21:$D$26,MATCH($C32,'Source Data'!$C$21:$C$26,0)))) -> On-Site Supervisor | E32: =IF(Staffing!F9="","",Staffing!F9) -> 2080 | F32: =IF('Labor Rates'!F26="","",'Labor Rates'!F26) -> 94.9689 | G32: =IF(E32="","",IF(E32=0,0,IF(COUNT(E32:F32)<2,"",ROUND(E32*F32,2)))) -> 197535.31 | H32: =IF(E32="","",IF('Labor Rates'!F22="","n.a.",ROUND('Labor Rates'!F22,2))) -> 179577.48 | I32: =IF(G32="","",IF(ISNUMBER(H32),G32-H32,"n.a.")) -> 17957.83
C33: R02 | D33: =IF(COUNTIFS('Source Data'!$C$21:$C$26,$C33)<>1,"",IF(INDEX('Source Data'!$D$21:$D$26,MATCH($C33,'Source Data'!$C$21:$C$26,0))="","",INDEX('Source Data'!$D$21:$D$26,MATCH($C33,'Source Data'!$C$21:$C$26,0)))) -> Financial Analyst | E33: =IF(Staffing!F21="","",Staffing!F21) -> 4160 | F33: =IF('Labor Rates'!F49="","",'Labor Rates'!F49) -> 124.9947 | G33: =IF(E33="","",IF(E33=0,0,IF(COUNT(E33:F33)<2,"",ROUND(E33*F33,2)))) -> 519977.95 | H33: =IF(E33="","",IF('Labor Rates'!F45="","n.a.",ROUND('Labor Rates'!F45,2))) -> 472707.31 | I33: =IF(G33="","",IF(ISNUMBER(H33),G33-H33,"n.a.")) -> 47270.64
C34: R03 | D34: =IF(COUNTIFS('Source Data'!$C$21:$C$26,$C34)<>1,"",IF(INDEX('Source Data'!$D$21:$D$26,MATCH($C34,'Source Data'!$C$21:$C$26,0))="","",INDEX('Source Data'!$D$21:$D$26,MATCH($C34,'Source Data'!$C$21:$C$26,0)))) -> Administrative Assistant | E34: =IF(Staffing!F33="","",Staffing!F33) -> 2080 | F34: =IF('Labor Rates'!F72="","",'Labor Rates'!F72) -> 53.0231 | G34: =IF(E34="","",IF(E34=0,0,IF(COUNT(E34:F34)<2,"",ROUND(E34*F34,2)))) -> 110288.05 | H34: =IF(E34="","",IF('Labor Rates'!F68="","n.a.",ROUND('Labor Rates'!F68,2))) -> 100261.83 | I34: =IF(G34="","",IF(ISNUMBER(H34),G34-H34,"n.a.")) -> 10026.22
C35: R04 | D35: =IF(COUNTIFS('Source Data'!$C$21:$C$26,$C35)<>1,"",IF(INDEX('Source Data'!$D$21:$D$26,MATCH($C35,'Source Data'!$C$21:$C$26,0))="","",INDEX('Source Data'!$D$21:$D$26,MATCH($C35,'Source Data'!$C$21:$C$26,0)))) -> Program Analyst I | E35: =IF(Staffing!F45="","",Staffing!F45) -> 2080 | F35: =IF('Labor Rates'!F95="","",'Labor Rates'!F95) -> 100.189 | G35: =IF(E35="","",IF(E35=0,0,IF(COUNT(E35:F35)<2,"",ROUND(E35*F35,2)))) -> 208393.12 | H35: =IF(E35="","",IF('Labor Rates'!F91="","n.a.",ROUND('Labor Rates'!F91,2))) -> 189448.22 | I35: =IF(G35="","",IF(ISNUMBER(H35),G35-H35,"n.a.")) -> 18944.9
C36: R05 | D36: =IF(COUNTIFS('Source Data'!$C$21:$C$26,$C36)<>1,"",IF(INDEX('Source Data'!$D$21:$D$26,MATCH($C36,'Source Data'!$C$21:$C$26,0))="","",INDEX('Source Data'!$D$21:$D$26,MATCH($C36,'Source Data'!$C$21:$C$26,0)))) -> Program Analyst II | E36: =IF(Staffing!F57="","",Staffing!F57) -> 4160 | F36: =IF('Labor Rates'!F118="","",'Labor Rates'!F118) -> 125.303 | G36: =IF(E36="","",IF(E36=0,0,IF(COUNT(E36:F36)<2,"",ROUND(E36*F36,2)))) -> 521260.48 | H36: =IF(E36="","",IF('Labor Rates'!F114="","n.a.",ROUND('Labor Rates'!F114,2))) -> 473873.14 | I36: =IF(G36="","",IF(ISNUMBER(H36),G36-H36,"n.a.")) -> 47387.34
C37: R06 | D37: =IF(COUNTIFS('Source Data'!$C$21:$C$26,$C37)<>1,"",IF(INDEX('Source Data'!$D$21:$D$26,MATCH($C37,'Source Data'!$C$21:$C$26,0))="","",INDEX('Source Data'!$D$21:$D$26,MATCH($C37,'Source Data'!$C$21:$C$26,0)))) -> Program Analyst III | E37: =IF(Staffing!F69="","",Staffing!F69) -> 2080 | F37: =IF('Labor Rates'!F141="","",'Labor Rates'!F141) -> 154.8767 | G37: =IF(E37="","",IF(E37=0,0,IF(COUNT(E37:F37)<2,"",ROUND(E37*F37,2)))) -> 322143.54 | H37: =IF(E37="","",IF('Labor Rates'!F137="","n.a.",ROUND('Labor Rates'!F137,2))) -> 292857.8 | I37: =IF(G37="","",IF(ISNUMBER(H37),G37-H37,"n.a.")) -> 29285.74
D38: Total | E38: =IF(COUNT(E32:E37)<6,"",SUM(E32:E37)) -> 16640 | G38: =IF(COUNT(G32:G37)<6,"",SUM(G32:G37)) -> 1879598.4 | H38: =IF(COUNT(H32:H37)<6,"n.a.",SUM(H32:H37)) -> 1708725.8 | I38: =IF(COUNT(I32:I37)<6,"n.a.",SUM(I32:I37)) -> 170872.67
C41: Option 3
C42: Role ID | D42: Labor category | E42: Hours | F42: Rate / hour | G42: Price | H42: Modeled cost | I42: Profit
C43: R01 | D43: =IF(COUNTIFS('Source Data'!$C$21:$C$26,$C43)<>1,"",IF(INDEX('Source Data'!$D$21:$D$26,MATCH($C43,'Source Data'!$C$21:$C$26,0))="","",INDEX('Source Data'!$D$21:$D$26,MATCH($C43,'Source Data'!$C$21:$C$26,0)))) -> On-Site Supervisor | E43: =IF(Staffing!G9="","",Staffing!G9) -> 2080 | F43: =IF('Labor Rates'!G26="","",'Labor Rates'!G26) -> 97.8179 | G43: =IF(E43="","",IF(E43=0,0,IF(COUNT(E43:F43)<2,"",ROUND(E43*F43,2)))) -> 203461.23 | H43: =IF(E43="","",IF('Labor Rates'!G22="","n.a.",ROUND('Labor Rates'!G22,2))) -> 184964.8 | I43: =IF(G43="","",IF(ISNUMBER(H43),G43-H43,"n.a.")) -> 18496.43
C44: R02 | D44: =IF(COUNTIFS('Source Data'!$C$21:$C$26,$C44)<>1,"",IF(INDEX('Source Data'!$D$21:$D$26,MATCH($C44,'Source Data'!$C$21:$C$26,0))="","",INDEX('Source Data'!$D$21:$D$26,MATCH($C44,'Source Data'!$C$21:$C$26,0)))) -> Financial Analyst | E44: =IF(Staffing!G21="","",Staffing!G21) -> 4160 | F44: =IF('Labor Rates'!G49="","",'Labor Rates'!G49) -> 128.7446 | G44: =IF(E44="","",IF(E44=0,0,IF(COUNT(E44:F44)<2,"",ROUND(E44*F44,2)))) -> 535577.54 | H44: =IF(E44="","",IF('Labor Rates'!G45="","n.a.",ROUND('Labor Rates'!G45,2))) -> 486888.53 | I44: =IF(G44="","",IF(ISNUMBER(H44),G44-H44,"n.a.")) -> 48689.01
C45: R03 | D45: =IF(COUNTIFS('Source Data'!$C$21:$C$26,$C45)<>1,"",IF(INDEX('Source Data'!$D$21:$D$26,MATCH($C45,'Source Data'!$C$21:$C$26,0))="","",INDEX('Source Data'!$D$21:$D$26,MATCH($C45,'Source Data'!$C$21:$C$26,0)))) -> Administrative Assistant | E45: =IF(Staffing!G33="","",Staffing!G33) -> 2080 | F45: =IF('Labor Rates'!G72="","",'Labor Rates'!G72) -> 54.6138 | G45: =IF(E45="","",IF(E45=0,0,IF(COUNT(E45:F45)<2,"",ROUND(E45*F45,2)))) -> 113596.7 | H45: =IF(E45="","",IF('Labor Rates'!G68="","n.a.",ROUND('Labor Rates'!G68,2))) -> 103269.68 | I45: =IF(G45="","",IF(ISNUMBER(H45),G45-H45,"n.a.")) -> 10327.02
C46: R04 | D46: =IF(COUNTIFS('Source Data'!$C$21:$C$26,$C46)<>1,"",IF(INDEX('Source Data'!$D$21:$D$26,MATCH($C46,'Source Data'!$C$21:$C$26,0))="","",INDEX('Source Data'!$D$21:$D$26,MATCH($C46,'Source Data'!$C$21:$C$26,0)))) -> Program Analyst I | E46: =IF(Staffing!G45="","",Staffing!G45) -> 2080 | F46: =IF('Labor Rates'!G95="","",'Labor Rates'!G95) -> 103.1946 | G46: =IF(E46="","",IF(E46=0,0,IF(COUNT(E46:F46)<2,"",ROUND(E46*F46,2)))) -> 214644.77 | H46: =IF(E46="","",IF('Labor Rates'!G91="","n.a.",ROUND('Labor Rates'!G91,2))) -> 195131.66 | I46: =IF(G46="","",IF(ISNUMBER(H46),G46-H46,"n.a.")) -> 19513.11
C47: R05 | D47: =IF(COUNTIFS('Source Data'!$C$21:$C$26,$C47)<>1,"",IF(INDEX('Source Data'!$D$21:$D$26,MATCH($C47,'Source Data'!$C$21:$C$26,0))="","",INDEX('Source Data'!$D$21:$D$26,MATCH($C47,'Source Data'!$C$21:$C$26,0)))) -> Program Analyst II | E47: =IF(Staffing!G57="","",Staffing!G57) -> 4160 | F47: =IF('Labor Rates'!G118="","",'Labor Rates'!G118) -> 129.0621 | G47: =IF(E47="","",IF(E47=0,0,IF(COUNT(E47:F47)<2,"",ROUND(E47*F47,2)))) -> 536898.34 | H47: =IF(E47="","",IF('Labor Rates'!G114="","n.a.",ROUND('Labor Rates'!G114,2))) -> 488089.34 | I47: =IF(G47="","",IF(ISNUMBER(H47),G47-H47,"n.a.")) -> 48809
C48: R06 | D48: =IF(COUNTIFS('Source Data'!$C$21:$C$26,$C48)<>1,"",IF(INDEX('Source Data'!$D$21:$D$26,MATCH($C48,'Source Data'!$C$21:$C$26,0))="","",INDEX('Source Data'!$D$21:$D$26,MATCH($C48,'Source Data'!$C$21:$C$26,0)))) -> Program Analyst III | E48: =IF(Staffing!G69="","",Staffing!G69) -> 2080 | F48: =IF('Labor Rates'!G141="","",'Labor Rates'!G141) -> 159.523 | G48: =IF(E48="","",IF(E48=0,0,IF(COUNT(E48:F48)<2,"",ROUND(E48*F48,2)))) -> 331807.84 | H48: =IF(E48="","",IF('Labor Rates'!G137="","n.a.",ROUND('Labor Rates'!G137,2))) -> 301643.53 | I48: =IF(G48="","",IF(ISNUMBER(H48),G48-H48,"n.a.")) -> 30164.31
D49: Total | E49: =IF(COUNT(E43:E48)<6,"",SUM(E43:E48)) -> 16640 | G49: =IF(COUNT(G43:G48)<6,"",SUM(G43:G48)) -> 1935986.4 | H49: =IF(COUNT(H43:H48)<6,"n.a.",SUM(H43:H48)) -> 1759987.5 | I49: =IF(COUNT(I43:I48)<6,"n.a.",SUM(I43:I48)) -> 175998.88
C52: Option 4
C53: Role ID | D53: Labor category | E53: Hours | F53: Rate / hour | G53: Price | H53: Modeled cost | I53: Profit
C54: R01 | D54: =IF(COUNTIFS('Source Data'!$C$21:$C$26,$C54)<>1,"",IF(INDEX('Source Data'!$D$21:$D$26,MATCH($C54,'Source Data'!$C$21:$C$26,0))="","",INDEX('Source Data'!$D$21:$D$26,MATCH($C54,'Source Data'!$C$21:$C$26,0)))) -> On-Site Supervisor | E54: =IF(Staffing!H9="","",Staffing!H9) -> 2080 | F54: =IF('Labor Rates'!H26="","",'Labor Rates'!H26) -> 100.7525 | G54: =IF(E54="","",IF(E54=0,0,IF(COUNT(E54:F54)<2,"",ROUND(E54*F54,2)))) -> 209565.2 | H54: =IF(E54="","",IF('Labor Rates'!H22="","n.a.",ROUND('Labor Rates'!H22,2))) -> 190513.75 | I54: =IF(G54="","",IF(ISNUMBER(H54),G54-H54,"n.a.")) -> 19051.45
C55: R02 | D55: =IF(COUNTIFS('Source Data'!$C$21:$C$26,$C55)<>1,"",IF(INDEX('Source Data'!$D$21:$D$26,MATCH($C55,'Source Data'!$C$21:$C$26,0))="","",INDEX('Source Data'!$D$21:$D$26,MATCH($C55,'Source Data'!$C$21:$C$26,0)))) -> Financial Analyst | E55: =IF(Staffing!H21="","",Staffing!H21) -> 4160 | F55: =IF('Labor Rates'!H49="","",'Labor Rates'!H49) -> 132.6069 | G55: =IF(E55="","",IF(E55=0,0,IF(COUNT(E55:F55)<2,"",ROUND(E55*F55,2)))) -> 551644.7 | H55: =IF(E55="","",IF('Labor Rates'!H45="","n.a.",ROUND('Labor Rates'!H45,2))) -> 501495.18 | I55: =IF(G55="","",IF(ISNUMBER(H55),G55-H55,"n.a.")) -> 50149.52
C56: R03 | D56: =IF(COUNTIFS('Source Data'!$C$21:$C$26,$C56)<>1,"",IF(INDEX('Source Data'!$D$21:$D$26,MATCH($C56,'Source Data'!$C$21:$C$26,0))="","",INDEX('Source Data'!$D$21:$D$26,MATCH($C56,'Source Data'!$C$21:$C$26,0)))) -> Administrative Assistant | E56: =IF(Staffing!H33="","",Staffing!H33) -> 2080 | F56: =IF('Labor Rates'!H72="","",'Labor Rates'!H72) -> 56.2522 | G56: =IF(E56="","",IF(E56=0,0,IF(COUNT(E56:F56)<2,"",ROUND(E56*F56,2)))) -> 117004.58 | H56: =IF(E56="","",IF('Labor Rates'!H68="","n.a.",ROUND('Labor Rates'!H68,2))) -> 106367.77 | I56: =IF(G56="","",IF(ISNUMBER(H56),G56-H56,"n.a.")) -> 10636.81
C57: R04 | D57: =IF(COUNTIFS('Source Data'!$C$21:$C$26,$C57)<>1,"",IF(INDEX('Source Data'!$D$21:$D$26,MATCH($C57,'Source Data'!$C$21:$C$26,0))="","",INDEX('Source Data'!$D$21:$D$26,MATCH($C57,'Source Data'!$C$21:$C$26,0)))) -> Program Analyst I | E57: =IF(Staffing!H45="","",Staffing!H45) -> 2080 | F57: =IF('Labor Rates'!H95="","",'Labor Rates'!H95) -> 106.2905 | G57: =IF(E57="","",IF(E57=0,0,IF(COUNT(E57:F57)<2,"",ROUND(E57*F57,2)))) -> 221084.24 | H57: =IF(E57="","",IF('Labor Rates'!H91="","n.a.",ROUND('Labor Rates'!H91,2))) -> 200985.61 | I57: =IF(G57="","",IF(ISNUMBER(H57),G57-H57,"n.a.")) -> 20098.63
C58: R05 | D58: =IF(COUNTIFS('Source Data'!$C$21:$C$26,$C58)<>1,"",IF(INDEX('Source Data'!$D$21:$D$26,MATCH($C58,'Source Data'!$C$21:$C$26,0))="","",INDEX('Source Data'!$D$21:$D$26,MATCH($C58,'Source Data'!$C$21:$C$26,0)))) -> Program Analyst II | E58: =IF(Staffing!H57="","",Staffing!H57) -> 4160 | F58: =IF('Labor Rates'!H118="","",'Labor Rates'!H118) -> 132.9339 | G58: =IF(E58="","",IF(E58=0,0,IF(COUNT(E58:F58)<2,"",ROUND(E58*F58,2)))) -> 553005.02 | H58: =IF(E58="","",IF('Labor Rates'!H114="","n.a.",ROUND('Labor Rates'!H114,2))) -> 502732.02 | I58: =IF(G58="","",IF(ISNUMBER(H58),G58-H58,"n.a.")) -> 50273
C59: R06 | D59: =IF(COUNTIFS('Source Data'!$C$21:$C$26,$C59)<>1,"",IF(INDEX('Source Data'!$D$21:$D$26,MATCH($C59,'Source Data'!$C$21:$C$26,0))="","",INDEX('Source Data'!$D$21:$D$26,MATCH($C59,'Source Data'!$C$21:$C$26,0)))) -> Program Analyst III | E59: =IF(Staffing!H69="","",Staffing!H69) -> 2080 | F59: =IF('Labor Rates'!H141="","",'Labor Rates'!H141) -> 164.3087 | G59: =IF(E59="","",IF(E59=0,0,IF(COUNT(E59:F59)<2,"",ROUND(E59*F59,2)))) -> 341762.1 | H59: =IF(E59="","",IF('Labor Rates'!H137="","n.a.",ROUND('Labor Rates'!H137,2))) -> 310692.84 | I59: =IF(G59="","",IF(ISNUMBER(H59),G59-H59,"n.a.")) -> 31069.26
D60: Total | E60: =IF(COUNT(E54:E59)<6,"",SUM(E54:E59)) -> 16640 | G60: =IF(COUNT(G54:G59)<6,"",SUM(G54:G59)) -> 1994065.8 | H60: =IF(COUNT(H54:H59)<6,"n.a.",SUM(H54:H59)) -> 1812787.2 | I60: =IF(COUNT(I54:I59)<6,"n.a.",SUM(I54:I59)) -> 181278.67
C63: Extension
C64: Role ID | D64: Labor category | E64: Hours | F64: Rate / hour | G64: Price | H64: Modeled cost | I64: Profit
C65: R01 | D65: =IF(COUNTIFS('Source Data'!$C$21:$C$26,$C65)<>1,"",IF(INDEX('Source Data'!$D$21:$D$26,MATCH($C65,'Source Data'!$C$21:$C$26,0))="","",INDEX('Source Data'!$D$21:$D$26,MATCH($C65,'Source Data'!$C$21:$C$26,0)))) -> On-Site Supervisor | E65: =IF(Staffing!I9="","",Staffing!I9) -> 1040 | F65: =IF('Labor Rates'!I26="","",'Labor Rates'!I26) -> 100.7525 | G65: =IF(E65="","",IF(E65=0,0,IF(COUNT(E65:F65)<2,"",ROUND(E65*F65,2)))) -> 104782.6 | H65: =IF(E65="","",IF('Labor Rates'!I22="","n.a.",ROUND('Labor Rates'!I22,2))) -> 95256.87 | I65: =IF(G65="","",IF(ISNUMBER(H65),G65-H65,"n.a.")) -> 9525.73
C66: R02 | D66: =IF(COUNTIFS('Source Data'!$C$21:$C$26,$C66)<>1,"",IF(INDEX('Source Data'!$D$21:$D$26,MATCH($C66,'Source Data'!$C$21:$C$26,0))="","",INDEX('Source Data'!$D$21:$D$26,MATCH($C66,'Source Data'!$C$21:$C$26,0)))) -> Financial Analyst | E66: =IF(Staffing!I21="","",Staffing!I21) -> 2080 | F66: =IF('Labor Rates'!I49="","",'Labor Rates'!I49) -> 132.6069 | G66: =IF(E66="","",IF(E66=0,0,IF(COUNT(E66:F66)<2,"",ROUND(E66*F66,2)))) -> 275822.35 | H66: =IF(E66="","",IF('Labor Rates'!I45="","n.a.",ROUND('Labor Rates'!I45,2))) -> 250747.59 | I66: =IF(G66="","",IF(ISNUMBER(H66),G66-H66,"n.a.")) -> 25074.76
C67: R03 | D67: =IF(COUNTIFS('Source Data'!$C$21:$C$26,$C67)<>1,"",IF(INDEX('Source Data'!$D$21:$D$26,MATCH($C67,'Source Data'!$C$21:$C$26,0))="","",INDEX('Source Data'!$D$21:$D$26,MATCH($C67,'Source Data'!$C$21:$C$26,0)))) -> Administrative Assistant | E67: =IF(Staffing!I33="","",Staffing!I33) -> 1040 | F67: =IF('Labor Rates'!I72="","",'Labor Rates'!I72) -> 56.2522 | G67: =IF(E67="","",IF(E67=0,0,IF(COUNT(E67:F67)<2,"",ROUND(E67*F67,2)))) -> 58502.29 | H67: =IF(E67="","",IF('Labor Rates'!I68="","n.a.",ROUND('Labor Rates'!I68,2))) -> 53183.89 | I67: =IF(G67="","",IF(ISNUMBER(H67),G67-H67,"n.a.")) -> 5318.4
C68: R04 | D68: =IF(COUNTIFS('Source Data'!$C$21:$C$26,$C68)<>1,"",IF(INDEX('Source Data'!$D$21:$D$26,MATCH($C68,'Source Data'!$C$21:$C$26,0))="","",INDEX('Source Data'!$D$21:$D$26,MATCH($C68,'Source Data'!$C$21:$C$26,0)))) -> Program Analyst I | E68: =IF(Staffing!I45="","",Staffing!I45) -> 1040 | F68: =IF('Labor Rates'!I95="","",'Labor Rates'!I95) -> 106.2905 | G68: =IF(E68="","",IF(E68=0,0,IF(COUNT(E68:F68)<2,"",ROUND(E68*F68,2)))) -> 110542.12 | H68: =IF(E68="","",IF('Labor Rates'!I91="","n.a.",ROUND('Labor Rates'!I91,2))) -> 100492.81 | I68: =IF(G68="","",IF(ISNUMBER(H68),G68-H68,"n.a.")) -> 10049.31
C69: R05 | D69: =IF(COUNTIFS('Source Data'!$C$21:$C$26,$C69)<>1,"",IF(INDEX('Source Data'!$D$21:$D$26,MATCH($C69,'Source Data'!$C$21:$C$26,0))="","",INDEX('Source Data'!$D$21:$D$26,MATCH($C69,'Source Data'!$C$21:$C$26,0)))) -> Program Analyst II | E69: =IF(Staffing!I57="","",Staffing!I57) -> 2080 | F69: =IF('Labor Rates'!I118="","",'Labor Rates'!I118) -> 132.9339 | G69: =IF(E69="","",IF(E69=0,0,IF(COUNT(E69:F69)<2,"",ROUND(E69*F69,2)))) -> 276502.51 | H69: =IF(E69="","",IF('Labor Rates'!I114="","n.a.",ROUND('Labor Rates'!I114,2))) -> 251366.01 | I69: =IF(G69="","",IF(ISNUMBER(H69),G69-H69,"n.a.")) -> 25136.5
C70: R06 | D70: =IF(COUNTIFS('Source Data'!$C$21:$C$26,$C70)<>1,"",IF(INDEX('Source Data'!$D$21:$D$26,MATCH($C70,'Source Data'!$C$21:$C$26,0))="","",INDEX('Source Data'!$D$21:$D$26,MATCH($C70,'Source Data'!$C$21:$C$26,0)))) -> Program Analyst III | E70: =IF(Staffing!I69="","",Staffing!I69) -> 1040 | F70: =IF('Labor Rates'!I141="","",'Labor Rates'!I141) -> 164.3087 | G70: =IF(E70="","",IF(E70=0,0,IF(COUNT(E70:F70)<2,"",ROUND(E70*F70,2)))) -> 170881.05 | H70: =IF(E70="","",IF('Labor Rates'!I137="","n.a.",ROUND('Labor Rates'!I137,2))) -> 155346.42 | I70: =IF(G70="","",IF(ISNUMBER(H70),G70-H70,"n.a.")) -> 15534.63
D71: Total | E71: =IF(COUNT(E65:E70)<6,"",SUM(E65:E70)) -> 8320 | G71: =IF(COUNT(G65:G70)<6,"",SUM(G65:G70)) -> 997032.92 | H71: =IF(COUNT(H65:H70)<6,"n.a.",SUM(H65:H70)) -> 906393.59 | I71: =IF(COUNT(I65:I70)<6,"n.a.",SUM(I65:I70)) -> 90639.33

Sheet Source Data
C2: Source Data
C4: Scenario | D4: =Assumptions!$D$4 -> Base
C6: Buyer | D6: Federal Enterprise Finance Office
C7: Project | D7: Financial Oversight and Program Support
C8: Solicitation | D8: DEMO-LABOR-001
C9: Location | D9: Washington, DC
C10: As of | D10: 46276
D14: Base | E14: Option 1 | F14: Option 2 | G14: Option 3 | H14: Option 4 | I14: Extension
C15: Starts | D15: 46296 | E15: 46661 | F15: 47027 | G15: 47392 | H15: 47757 | I15: 48122
C16: Ends | D16: 46660 | E16: 47026 | F16: 47391 | G16: 47756 | H16: 48121 | I16: 48304
C20: Role ID | D20: Labor category | E20: Positions | F20: Wage / hr | G20: Wage year | H20: Rate basis | I20: Loaded rate / hr
C21: R01 | D21: On-Site Supervisor | E21: 1 | F21: 46.21 | G21: 2025 | H21: Build from wage
C22: R02 | D22: Financial Analyst | E22: 2 | F22: 60.82 | G22: 2025 | H22: Build from wage
C23: R03 | D23: Administrative Assistant | E23: 1 | F23: 25.8 | G23: 2025 | H23: Build from wage
C24: R04 | D24: Program Analyst I | E24: 1 | F24: 48.75 | G24: 2025 | H24: Build from wage
C25: R05 | D25: Program Analyst II | E25: 2 | F25: 60.97 | G25: 2025 | H25: Build from wage
C26: R06 | D26: Program Analyst III | E26: 1 | F26: 75.36 | G26: 2025 | H26: Build from wage
C28: Requested pricing hours
C29: Role ID | D29: Base | E29: Option 1 | F29: Option 2 | G29: Option 3 | H29: Option 4 | I29: Extension
C30: R01 | D30: 2080 | E30: 2080 | F30: 2080 | G30: 2080 | H30: 2080 | I30: 1040
C31: R02 | D31: 4160 | E31: 4160 | F31: 4160 | G31: 4160 | H31: 4160 | I31: 2080
C32: R03 | D32: 2080 | E32: 2080 | F32: 2080 | G32: 2080 | H32: 2080 | I32: 1040
C33: R04 | D33: 2080 | E33: 2080 | F33: 2080 | G33: 2080 | H33: 2080 | I33: 1040
C34: R05 | D34: 4160 | E34: 4160 | F34: 4160 | G34: 4160 | H34: 4160 | I34: 2080
C35: R06 | D35: 2080 | E35: 2080 | F35: 2080 | G35: 2080 | H35: 2080 | I35: 1040
C39: Role definitions and wage evidence
C40: R01 | D40: =IF(COUNTIF($C$21:$C$26,C40)<>1,"",IF(INDEX($D$21:$D$26,MATCH(C40,$C$21:$C$26,0))="","",INDEX($D$21:$D$26,MATCH(C40,$C$21:$C$26,0)))) -> On-Site Supervisor
C41: Qualifications | D41: Supervises an administrative and analytical team; coordinates staffing, schedules and quality checks.
C42: Wage source | D42: First-Line Supervisors of Office and Administrative Support Workers (431011), Senior; 2025. Washington-Arlington-Alexandria, DC-VA-MD-WV.
C43: Limits | D43: Administrative-supervisor wage proxy; does not establish a financial-management salary.
C45: R02 | D45: =IF(COUNTIF($C$21:$C$26,C45)<>1,"",IF(INDEX($D$21:$D$26,MATCH(C45,$C$21:$C$26,0))="","",INDEX($D$21:$D$26,MATCH(C45,$C$21:$C$26,0)))) -> Financial Analyst
C46: Qualifications | D46: Bachelor’s degree in finance, accounting or related field; evaluates financial statements, credit exposure and risk.
C47: Wage source | D47: Financial Risk Specialists (132054), Journeyman; 2025. Washington-Arlington-Alexandria, DC-VA-MD-WV.
C48: Limits | D48: Financial-risk occupation is a proxy for the proposed oversight duties, not a buyer-mandated classification.
C50: R03 | D50: =IF(COUNTIF($C$21:$C$26,C50)<>1,"",IF(INDEX($D$21:$D$26,MATCH(C50,$C$21:$C$26,0))="","",INDEX($D$21:$D$26,MATCH(C50,$C$21:$C$26,0)))) -> Administrative Assistant
C51: Qualifications | D51: High school diploma and office-support experience; scheduling, correspondence, document preparation and records.
C52: Wage source | D52: Secretaries and Administrative Assistants, Except Legal, Medical, and Executive (436014), Journeyman; 2025. Washington-Arlington-Alexandria, DC-VA-MD-WV.
C53: Limits | D53: General administrative-support occupation; no executive, legal or medical specialization assumed.
C55: R04 | D55: =IF(COUNTIF($C$21:$C$26,C55)<>1,"",IF(INDEX($D$21:$D$26,MATCH(C55,$C$21:$C$26,0))="","",INDEX($D$21:$D$26,MATCH(C55,$C$21:$C$26,0)))) -> Program Analyst I
C56: Qualifications | D56: Bachelor’s degree or equivalent; 1–2 years of analysis, reporting or project-support experience.
C57: Wage source | D57: Management Analysts (131111), Junior; 2025. Washington-Arlington-Alexandria, DC-VA-MD-WV.
C58: Limits | D58: Management-analyst wage proxy at the Junior level (25th percentile).
C60: R05 | D60: =IF(COUNTIF($C$21:$C$26,C60)<>1,"",IF(INDEX($D$21:$D$26,MATCH(C60,$C$21:$C$26,0))="","",INDEX($D$21:$D$26,MATCH(C60,$C$21:$C$26,0)))) -> Program Analyst II
C61: Qualifications | D61: Bachelor’s degree or equivalent; 2–3 years of experience independently preparing analyses and program reports.
C62: Wage source | D62: Management Analysts (131111), Journeyman; 2025. Washington-Arlington-Alexandria, DC-VA-MD-WV.
C63: Limits | D63: Management-analyst wage proxy at the Journeyman level (50th percentile).
C65: R06 | D65: =IF(COUNTIF($C$21:$C$26,C65)<>1,"",IF(INDEX($D$21:$D$26,MATCH(C65,$C$21:$C$26,0))="","",INDEX($D$21:$D$26,MATCH(C65,$C$21:$C$26,0)))) -> Program Analyst III
C66: Qualifications | D66: Bachelor’s degree or equivalent; 3+ years of progressive experience leading complex program analyses.
C67: Wage source | D67: Management Analysts (131111), Senior; 2025. Washington-Arlington-Alexandria, DC-VA-MD-WV.
C68: Limits | D68: Management-analyst wage proxy at the Senior level (75th percentile).
C71: References
C72: Wages: 2025 BLS series, retrieved through GovTribe / GSA CALC+ on September 11, 2026. All Industries. Levels: Junior 25th percentile; Journeyman 50th; Senior 75th.
C73: Wages | D73: =HYPERLINK("https://buy.gsa.gov/pricing/qr/bls","GSA CALC+ BLS wage data") -> GSA CALC+ BLS wage data
C74: Staffing quantities are adapted from SBA solicitation 47QACA26R0306, Attachment B, Cost Estimate rows 6–11 and 55–60. The buyer, project, dates and solicitation shown here are fictional.
C75: Staffing | D75: =HYPERLINK("https://govtribe.com/file/government-file/attachment-b-pricing-sheet-for-risk-management-2026-09-10-dot-xlsx","Source pricing worksheet — structural inspiration") -> Source pricing worksheet — structural inspiration
C76: Company benefits, indirect costs, profit, nonbillable time and escalation are editable assumptions. Wages are not selling prices or proof of wage-determination compliance.
C77: Structure | D77: =HYPERLINK("https://coe.gsa.gov/docs/CloudMigration/SampleIGCE.xlsx","GSA cost-estimate sample") -> GSA cost-estimate sample
C78: Definitions | D78: =HYPERLINK("https://www.gsa.gov/system/files/FCP_Services_Plus_File_Refresh_32_TDR_EDIT_060126.xlsx","GSA Services Plus template") -> GSA Services Plus template
